package com.google.android.gms.internal;

import android.os.Binder;
import android.os.IBinder;
import android.os.IInterface;
import android.os.Parcel;
import android.os.Parcelable.Creator;
import android.os.RemoteException;
import com.google.android.gms.fitness.request.ClaimBleDeviceRequest;
import com.google.android.gms.fitness.request.ListClaimedBleDevicesRequest;
import com.google.android.gms.fitness.request.StartBleScanRequest;
import com.google.android.gms.fitness.request.StopBleScanRequest;
import com.google.android.gms.fitness.request.UnclaimBleDeviceRequest;

public abstract interface zzok
  extends IInterface
{
  public abstract void zza(ClaimBleDeviceRequest paramClaimBleDeviceRequest)
    throws RemoteException;
  
  public abstract void zza(ListClaimedBleDevicesRequest paramListClaimedBleDevicesRequest)
    throws RemoteException;
  
  public abstract void zza(StartBleScanRequest paramStartBleScanRequest)
    throws RemoteException;
  
  public abstract void zza(StopBleScanRequest paramStopBleScanRequest)
    throws RemoteException;
  
  public abstract void zza(UnclaimBleDeviceRequest paramUnclaimBleDeviceRequest)
    throws RemoteException;
  
  public static abstract class zza
    extends Binder
    implements zzok
  {
    public static zzok zzbF(IBinder paramIBinder)
    {
      if (paramIBinder == null) {
        return null;
      }
      IInterface localIInterface = paramIBinder.queryLocalInterface("com.google.android.gms.fitness.internal.IGoogleFitBleApi");
      if ((localIInterface != null) && ((localIInterface instanceof zzok))) {
        return (zzok)localIInterface;
      }
      return new zza(paramIBinder);
    }
    
    public boolean onTransact(int paramInt1, Parcel paramParcel1, Parcel paramParcel2, int paramInt2)
      throws RemoteException
    {
      Object localObject2 = null;
      Object localObject3 = null;
      Object localObject4 = null;
      Object localObject5 = null;
      Object localObject1 = null;
      switch (paramInt1)
      {
      default: 
        return super.onTransact(paramInt1, paramParcel1, paramParcel2, paramInt2);
      case 1598968902: 
        paramParcel2.writeString("com.google.android.gms.fitness.internal.IGoogleFitBleApi");
        return true;
      case 1: 
        paramParcel1.enforceInterface("com.google.android.gms.fitness.internal.IGoogleFitBleApi");
        if (paramParcel1.readInt() != 0) {
          localObject1 = (StartBleScanRequest)StartBleScanRequest.CREATOR.createFromParcel(paramParcel1);
        }
        zza((StartBleScanRequest)localObject1);
        paramParcel2.writeNoException();
        return true;
      case 2: 
        paramParcel1.enforceInterface("com.google.android.gms.fitness.internal.IGoogleFitBleApi");
        localObject1 = localObject2;
        if (paramParcel1.readInt() != 0) {
          localObject1 = (StopBleScanRequest)StopBleScanRequest.CREATOR.createFromParcel(paramParcel1);
        }
        zza((StopBleScanRequest)localObject1);
        paramParcel2.writeNoException();
        return true;
      case 3: 
        paramParcel1.enforceInterface("com.google.android.gms.fitness.internal.IGoogleFitBleApi");
        localObject1 = localObject3;
        if (paramParcel1.readInt() != 0) {
          localObject1 = (ClaimBleDeviceRequest)ClaimBleDeviceRequest.CREATOR.createFromParcel(paramParcel1);
        }
        zza((ClaimBleDeviceRequest)localObject1);
        paramParcel2.writeNoException();
        return true;
      case 4: 
        paramParcel1.enforceInterface("com.google.android.gms.fitness.internal.IGoogleFitBleApi");
        localObject1 = localObject4;
        if (paramParcel1.readInt() != 0) {
          localObject1 = (UnclaimBleDeviceRequest)UnclaimBleDeviceRequest.CREATOR.createFromParcel(paramParcel1);
        }
        zza((UnclaimBleDeviceRequest)localObject1);
        paramParcel2.writeNoException();
        return true;
      }
      paramParcel1.enforceInterface("com.google.android.gms.fitness.internal.IGoogleFitBleApi");
      localObject1 = localObject5;
      if (paramParcel1.readInt() != 0) {
        localObject1 = (ListClaimedBleDevicesRequest)ListClaimedBleDevicesRequest.CREATOR.createFromParcel(paramParcel1);
      }
      zza((ListClaimedBleDevicesRequest)localObject1);
      paramParcel2.writeNoException();
      return true;
    }
    
    private static class zza
      implements zzok
    {
      private IBinder zzoz;
      
      zza(IBinder paramIBinder)
      {
        this.zzoz = paramIBinder;
      }
      
      public IBinder asBinder()
      {
        return this.zzoz;
      }
      
      /* Error */
      public void zza(ClaimBleDeviceRequest paramClaimBleDeviceRequest)
        throws RemoteException
      {
        // Byte code:
        //   0: invokestatic 30	android/os/Parcel:obtain	()Landroid/os/Parcel;
        //   3: astore_2
        //   4: invokestatic 30	android/os/Parcel:obtain	()Landroid/os/Parcel;
        //   7: astore_3
        //   8: aload_2
        //   9: ldc 32
        //   11: invokevirtual 36	android/os/Parcel:writeInterfaceToken	(Ljava/lang/String;)V
        //   14: aload_1
        //   15: ifnull +41 -> 56
        //   18: aload_2
        //   19: iconst_1
        //   20: invokevirtual 40	android/os/Parcel:writeInt	(I)V
        //   23: aload_1
        //   24: aload_2
        //   25: iconst_0
        //   26: invokevirtual 46	com/google/android/gms/fitness/request/ClaimBleDeviceRequest:writeToParcel	(Landroid/os/Parcel;I)V
        //   29: aload_0
        //   30: getfield 18	com/google/android/gms/internal/zzok$zza$zza:zzoz	Landroid/os/IBinder;
        //   33: iconst_3
        //   34: aload_2
        //   35: aload_3
        //   36: iconst_0
        //   37: invokeinterface 52 5 0
        //   42: pop
        //   43: aload_3
        //   44: invokevirtual 55	android/os/Parcel:readException	()V
        //   47: aload_3
        //   48: invokevirtual 58	android/os/Parcel:recycle	()V
        //   51: aload_2
        //   52: invokevirtual 58	android/os/Parcel:recycle	()V
        //   55: return
        //   56: aload_2
        //   57: iconst_0
        //   58: invokevirtual 40	android/os/Parcel:writeInt	(I)V
        //   61: goto -32 -> 29
        //   64: astore_1
        //   65: aload_3
        //   66: invokevirtual 58	android/os/Parcel:recycle	()V
        //   69: aload_2
        //   70: invokevirtual 58	android/os/Parcel:recycle	()V
        //   73: aload_1
        //   74: athrow
        // Local variable table:
        //   start	length	slot	name	signature
        //   0	75	0	this	zza
        //   0	75	1	paramClaimBleDeviceRequest	ClaimBleDeviceRequest
        //   3	67	2	localParcel1	Parcel
        //   7	59	3	localParcel2	Parcel
        // Exception table:
        //   from	to	target	type
        //   8	14	64	finally
        //   18	29	64	finally
        //   29	47	64	finally
        //   56	61	64	finally
      }
      
      /* Error */
      public void zza(ListClaimedBleDevicesRequest paramListClaimedBleDevicesRequest)
        throws RemoteException
      {
        // Byte code:
        //   0: invokestatic 30	android/os/Parcel:obtain	()Landroid/os/Parcel;
        //   3: astore_2
        //   4: invokestatic 30	android/os/Parcel:obtain	()Landroid/os/Parcel;
        //   7: astore_3
        //   8: aload_2
        //   9: ldc 32
        //   11: invokevirtual 36	android/os/Parcel:writeInterfaceToken	(Ljava/lang/String;)V
        //   14: aload_1
        //   15: ifnull +41 -> 56
        //   18: aload_2
        //   19: iconst_1
        //   20: invokevirtual 40	android/os/Parcel:writeInt	(I)V
        //   23: aload_1
        //   24: aload_2
        //   25: iconst_0
        //   26: invokevirtual 63	com/google/android/gms/fitness/request/ListClaimedBleDevicesRequest:writeToParcel	(Landroid/os/Parcel;I)V
        //   29: aload_0
        //   30: getfield 18	com/google/android/gms/internal/zzok$zza$zza:zzoz	Landroid/os/IBinder;
        //   33: iconst_5
        //   34: aload_2
        //   35: aload_3
        //   36: iconst_0
        //   37: invokeinterface 52 5 0
        //   42: pop
        //   43: aload_3
        //   44: invokevirtual 55	android/os/Parcel:readException	()V
        //   47: aload_3
        //   48: invokevirtual 58	android/os/Parcel:recycle	()V
        //   51: aload_2
        //   52: invokevirtual 58	android/os/Parcel:recycle	()V
        //   55: return
        //   56: aload_2
        //   57: iconst_0
        //   58: invokevirtual 40	android/os/Parcel:writeInt	(I)V
        //   61: goto -32 -> 29
        //   64: astore_1
        //   65: aload_3
        //   66: invokevirtual 58	android/os/Parcel:recycle	()V
        //   69: aload_2
        //   70: invokevirtual 58	android/os/Parcel:recycle	()V
        //   73: aload_1
        //   74: athrow
        // Local variable table:
        //   start	length	slot	name	signature
        //   0	75	0	this	zza
        //   0	75	1	paramListClaimedBleDevicesRequest	ListClaimedBleDevicesRequest
        //   3	67	2	localParcel1	Parcel
        //   7	59	3	localParcel2	Parcel
        // Exception table:
        //   from	to	target	type
        //   8	14	64	finally
        //   18	29	64	finally
        //   29	47	64	finally
        //   56	61	64	finally
      }
      
      /* Error */
      public void zza(StartBleScanRequest paramStartBleScanRequest)
        throws RemoteException
      {
        // Byte code:
        //   0: invokestatic 30	android/os/Parcel:obtain	()Landroid/os/Parcel;
        //   3: astore_2
        //   4: invokestatic 30	android/os/Parcel:obtain	()Landroid/os/Parcel;
        //   7: astore_3
        //   8: aload_2
        //   9: ldc 32
        //   11: invokevirtual 36	android/os/Parcel:writeInterfaceToken	(Ljava/lang/String;)V
        //   14: aload_1
        //   15: ifnull +41 -> 56
        //   18: aload_2
        //   19: iconst_1
        //   20: invokevirtual 40	android/os/Parcel:writeInt	(I)V
        //   23: aload_1
        //   24: aload_2
        //   25: iconst_0
        //   26: invokevirtual 67	com/google/android/gms/fitness/request/StartBleScanRequest:writeToParcel	(Landroid/os/Parcel;I)V
        //   29: aload_0
        //   30: getfield 18	com/google/android/gms/internal/zzok$zza$zza:zzoz	Landroid/os/IBinder;
        //   33: iconst_1
        //   34: aload_2
        //   35: aload_3
        //   36: iconst_0
        //   37: invokeinterface 52 5 0
        //   42: pop
        //   43: aload_3
        //   44: invokevirtual 55	android/os/Parcel:readException	()V
        //   47: aload_3
        //   48: invokevirtual 58	android/os/Parcel:recycle	()V
        //   51: aload_2
        //   52: invokevirtual 58	android/os/Parcel:recycle	()V
        //   55: return
        //   56: aload_2
        //   57: iconst_0
        //   58: invokevirtual 40	android/os/Parcel:writeInt	(I)V
        //   61: goto -32 -> 29
        //   64: astore_1
        //   65: aload_3
        //   66: invokevirtual 58	android/os/Parcel:recycle	()V
        //   69: aload_2
        //   70: invokevirtual 58	android/os/Parcel:recycle	()V
        //   73: aload_1
        //   74: athrow
        // Local variable table:
        //   start	length	slot	name	signature
        //   0	75	0	this	zza
        //   0	75	1	paramStartBleScanRequest	StartBleScanRequest
        //   3	67	2	localParcel1	Parcel
        //   7	59	3	localParcel2	Parcel
        // Exception table:
        //   from	to	target	type
        //   8	14	64	finally
        //   18	29	64	finally
        //   29	47	64	finally
        //   56	61	64	finally
      }
      
      /* Error */
      public void zza(StopBleScanRequest paramStopBleScanRequest)
        throws RemoteException
      {
        // Byte code:
        //   0: invokestatic 30	android/os/Parcel:obtain	()Landroid/os/Parcel;
        //   3: astore_2
        //   4: invokestatic 30	android/os/Parcel:obtain	()Landroid/os/Parcel;
        //   7: astore_3
        //   8: aload_2
        //   9: ldc 32
        //   11: invokevirtual 36	android/os/Parcel:writeInterfaceToken	(Ljava/lang/String;)V
        //   14: aload_1
        //   15: ifnull +41 -> 56
        //   18: aload_2
        //   19: iconst_1
        //   20: invokevirtual 40	android/os/Parcel:writeInt	(I)V
        //   23: aload_1
        //   24: aload_2
        //   25: iconst_0
        //   26: invokevirtual 71	com/google/android/gms/fitness/request/StopBleScanRequest:writeToParcel	(Landroid/os/Parcel;I)V
        //   29: aload_0
        //   30: getfield 18	com/google/android/gms/internal/zzok$zza$zza:zzoz	Landroid/os/IBinder;
        //   33: iconst_2
        //   34: aload_2
        //   35: aload_3
        //   36: iconst_0
        //   37: invokeinterface 52 5 0
        //   42: pop
        //   43: aload_3
        //   44: invokevirtual 55	android/os/Parcel:readException	()V
        //   47: aload_3
        //   48: invokevirtual 58	android/os/Parcel:recycle	()V
        //   51: aload_2
        //   52: invokevirtual 58	android/os/Parcel:recycle	()V
        //   55: return
        //   56: aload_2
        //   57: iconst_0
        //   58: invokevirtual 40	android/os/Parcel:writeInt	(I)V
        //   61: goto -32 -> 29
        //   64: astore_1
        //   65: aload_3
        //   66: invokevirtual 58	android/os/Parcel:recycle	()V
        //   69: aload_2
        //   70: invokevirtual 58	android/os/Parcel:recycle	()V
        //   73: aload_1
        //   74: athrow
        // Local variable table:
        //   start	length	slot	name	signature
        //   0	75	0	this	zza
        //   0	75	1	paramStopBleScanRequest	StopBleScanRequest
        //   3	67	2	localParcel1	Parcel
        //   7	59	3	localParcel2	Parcel
        // Exception table:
        //   from	to	target	type
        //   8	14	64	finally
        //   18	29	64	finally
        //   29	47	64	finally
        //   56	61	64	finally
      }
      
      /* Error */
      public void zza(UnclaimBleDeviceRequest paramUnclaimBleDeviceRequest)
        throws RemoteException
      {
        // Byte code:
        //   0: invokestatic 30	android/os/Parcel:obtain	()Landroid/os/Parcel;
        //   3: astore_2
        //   4: invokestatic 30	android/os/Parcel:obtain	()Landroid/os/Parcel;
        //   7: astore_3
        //   8: aload_2
        //   9: ldc 32
        //   11: invokevirtual 36	android/os/Parcel:writeInterfaceToken	(Ljava/lang/String;)V
        //   14: aload_1
        //   15: ifnull +41 -> 56
        //   18: aload_2
        //   19: iconst_1
        //   20: invokevirtual 40	android/os/Parcel:writeInt	(I)V
        //   23: aload_1
        //   24: aload_2
        //   25: iconst_0
        //   26: invokevirtual 75	com/google/android/gms/fitness/request/UnclaimBleDeviceRequest:writeToParcel	(Landroid/os/Parcel;I)V
        //   29: aload_0
        //   30: getfield 18	com/google/android/gms/internal/zzok$zza$zza:zzoz	Landroid/os/IBinder;
        //   33: iconst_4
        //   34: aload_2
        //   35: aload_3
        //   36: iconst_0
        //   37: invokeinterface 52 5 0
        //   42: pop
        //   43: aload_3
        //   44: invokevirtual 55	android/os/Parcel:readException	()V
        //   47: aload_3
        //   48: invokevirtual 58	android/os/Parcel:recycle	()V
        //   51: aload_2
        //   52: invokevirtual 58	android/os/Parcel:recycle	()V
        //   55: return
        //   56: aload_2
        //   57: iconst_0
        //   58: invokevirtual 40	android/os/Parcel:writeInt	(I)V
        //   61: goto -32 -> 29
        //   64: astore_1
        //   65: aload_3
        //   66: invokevirtual 58	android/os/Parcel:recycle	()V
        //   69: aload_2
        //   70: invokevirtual 58	android/os/Parcel:recycle	()V
        //   73: aload_1
        //   74: athrow
        // Local variable table:
        //   start	length	slot	name	signature
        //   0	75	0	this	zza
        //   0	75	1	paramUnclaimBleDeviceRequest	UnclaimBleDeviceRequest
        //   3	67	2	localParcel1	Parcel
        //   7	59	3	localParcel2	Parcel
        // Exception table:
        //   from	to	target	type
        //   8	14	64	finally
        //   18	29	64	finally
        //   29	47	64	finally
        //   56	61	64	finally
      }
    }
  }
}


/* Location:              C:\Users\Genbu Hase\ÉhÉLÉÖÉÅÉìÉg\Genbu\Tool\Programing\Jad\BlockLauncher 1.13.1.jar!\com\google\android\gms\internal\zzok.class
 * Java compiler version: 6 (50.0)
 * JD-Core Version:       0.7.1-SNAPSHOT-20140817
 */