package com.google.android.gms.drive.internal;

import android.os.Binder;
import android.os.IBinder;
import android.os.IInterface;
import android.os.Parcel;
import android.os.Parcelable.Creator;
import android.os.RemoteException;
import com.google.android.gms.common.api.Status;
import com.google.android.gms.drive.ChangeSequenceNumber;
import com.google.android.gms.drive.realtime.internal.zzm;
import com.google.android.gms.drive.realtime.internal.zzm.zza;

public abstract interface zzan
  extends IInterface
{
  public abstract void onError(Status paramStatus)
    throws RemoteException;
  
  public abstract void onSuccess()
    throws RemoteException;
  
  public abstract void zza(ChangeSequenceNumber paramChangeSequenceNumber)
    throws RemoteException;
  
  public abstract void zza(GetPermissionsResponse paramGetPermissionsResponse)
    throws RemoteException;
  
  public abstract void zza(OnChangesResponse paramOnChangesResponse)
    throws RemoteException;
  
  public abstract void zza(OnContentsResponse paramOnContentsResponse)
    throws RemoteException;
  
  public abstract void zza(OnDeviceUsagePreferenceResponse paramOnDeviceUsagePreferenceResponse)
    throws RemoteException;
  
  public abstract void zza(OnDownloadProgressResponse paramOnDownloadProgressResponse)
    throws RemoteException;
  
  public abstract void zza(OnDriveIdResponse paramOnDriveIdResponse)
    throws RemoteException;
  
  public abstract void zza(OnFetchThumbnailResponse paramOnFetchThumbnailResponse)
    throws RemoteException;
  
  public abstract void zza(OnListEntriesResponse paramOnListEntriesResponse)
    throws RemoteException;
  
  public abstract void zza(OnListParentsResponse paramOnListParentsResponse)
    throws RemoteException;
  
  public abstract void zza(OnLoadRealtimeResponse paramOnLoadRealtimeResponse, zzm paramzzm)
    throws RemoteException;
  
  public abstract void zza(OnMetadataResponse paramOnMetadataResponse)
    throws RemoteException;
  
  public abstract void zza(OnPinnedDownloadPreferencesResponse paramOnPinnedDownloadPreferencesResponse)
    throws RemoteException;
  
  public abstract void zza(OnResourceIdSetResponse paramOnResourceIdSetResponse)
    throws RemoteException;
  
  public abstract void zza(OnStartStreamSession paramOnStartStreamSession)
    throws RemoteException;
  
  public abstract void zza(OnSyncMoreResponse paramOnSyncMoreResponse)
    throws RemoteException;
  
  public abstract void zza(StringListResponse paramStringListResponse)
    throws RemoteException;
  
  public abstract void zzaf(boolean paramBoolean)
    throws RemoteException;
  
  public static abstract class zza
    extends Binder
    implements zzan
  {
    public zza()
    {
      attachInterface(this, "com.google.android.gms.drive.internal.IDriveServiceCallbacks");
    }
    
    public static zzan zzbb(IBinder paramIBinder)
    {
      if (paramIBinder == null) {
        return null;
      }
      IInterface localIInterface = paramIBinder.queryLocalInterface("com.google.android.gms.drive.internal.IDriveServiceCallbacks");
      if ((localIInterface != null) && ((localIInterface instanceof zzan))) {
        return (zzan)localIInterface;
      }
      return new zza(paramIBinder);
    }
    
    public IBinder asBinder()
    {
      return this;
    }
    
    public boolean onTransact(int paramInt1, Parcel paramParcel1, Parcel paramParcel2, int paramInt2)
      throws RemoteException
    {
      Object localObject2 = null;
      Object localObject3 = null;
      Object localObject4 = null;
      Object localObject5 = null;
      Object localObject6 = null;
      Object localObject7 = null;
      Object localObject8 = null;
      Object localObject9 = null;
      Object localObject10 = null;
      Object localObject11 = null;
      Object localObject12 = null;
      Object localObject13 = null;
      Object localObject14 = null;
      Object localObject15 = null;
      Object localObject16 = null;
      Object localObject17 = null;
      Object localObject18 = null;
      Object localObject1 = null;
      switch (paramInt1)
      {
      default: 
        return super.onTransact(paramInt1, paramParcel1, paramParcel2, paramInt2);
      case 1598968902: 
        paramParcel2.writeString("com.google.android.gms.drive.internal.IDriveServiceCallbacks");
        return true;
      case 1: 
        paramParcel1.enforceInterface("com.google.android.gms.drive.internal.IDriveServiceCallbacks");
        if (paramParcel1.readInt() != 0) {
          localObject1 = (OnDownloadProgressResponse)OnDownloadProgressResponse.CREATOR.createFromParcel(paramParcel1);
        }
        zza((OnDownloadProgressResponse)localObject1);
        paramParcel2.writeNoException();
        return true;
      case 2: 
        paramParcel1.enforceInterface("com.google.android.gms.drive.internal.IDriveServiceCallbacks");
        localObject1 = localObject2;
        if (paramParcel1.readInt() != 0) {
          localObject1 = (OnListEntriesResponse)OnListEntriesResponse.CREATOR.createFromParcel(paramParcel1);
        }
        zza((OnListEntriesResponse)localObject1);
        paramParcel2.writeNoException();
        return true;
      case 3: 
        paramParcel1.enforceInterface("com.google.android.gms.drive.internal.IDriveServiceCallbacks");
        localObject1 = localObject3;
        if (paramParcel1.readInt() != 0) {
          localObject1 = (OnDriveIdResponse)OnDriveIdResponse.CREATOR.createFromParcel(paramParcel1);
        }
        zza((OnDriveIdResponse)localObject1);
        paramParcel2.writeNoException();
        return true;
      case 4: 
        paramParcel1.enforceInterface("com.google.android.gms.drive.internal.IDriveServiceCallbacks");
        localObject1 = localObject4;
        if (paramParcel1.readInt() != 0) {
          localObject1 = (OnMetadataResponse)OnMetadataResponse.CREATOR.createFromParcel(paramParcel1);
        }
        zza((OnMetadataResponse)localObject1);
        paramParcel2.writeNoException();
        return true;
      case 5: 
        paramParcel1.enforceInterface("com.google.android.gms.drive.internal.IDriveServiceCallbacks");
        localObject1 = localObject5;
        if (paramParcel1.readInt() != 0) {
          localObject1 = (OnContentsResponse)OnContentsResponse.CREATOR.createFromParcel(paramParcel1);
        }
        zza((OnContentsResponse)localObject1);
        paramParcel2.writeNoException();
        return true;
      case 6: 
        paramParcel1.enforceInterface("com.google.android.gms.drive.internal.IDriveServiceCallbacks");
        localObject1 = localObject6;
        if (paramParcel1.readInt() != 0) {
          localObject1 = (Status)Status.CREATOR.createFromParcel(paramParcel1);
        }
        onError((Status)localObject1);
        paramParcel2.writeNoException();
        return true;
      case 7: 
        paramParcel1.enforceInterface("com.google.android.gms.drive.internal.IDriveServiceCallbacks");
        onSuccess();
        paramParcel2.writeNoException();
        return true;
      case 8: 
        paramParcel1.enforceInterface("com.google.android.gms.drive.internal.IDriveServiceCallbacks");
        localObject1 = localObject7;
        if (paramParcel1.readInt() != 0) {
          localObject1 = (OnListParentsResponse)OnListParentsResponse.CREATOR.createFromParcel(paramParcel1);
        }
        zza((OnListParentsResponse)localObject1);
        paramParcel2.writeNoException();
        return true;
      case 9: 
        paramParcel1.enforceInterface("com.google.android.gms.drive.internal.IDriveServiceCallbacks");
        localObject1 = localObject8;
        if (paramParcel1.readInt() != 0) {
          localObject1 = (OnSyncMoreResponse)OnSyncMoreResponse.CREATOR.createFromParcel(paramParcel1);
        }
        zza((OnSyncMoreResponse)localObject1);
        paramParcel2.writeNoException();
        return true;
      case 11: 
        paramParcel1.enforceInterface("com.google.android.gms.drive.internal.IDriveServiceCallbacks");
        localObject1 = localObject9;
        if (paramParcel1.readInt() != 0) {
          localObject1 = (OnLoadRealtimeResponse)OnLoadRealtimeResponse.CREATOR.createFromParcel(paramParcel1);
        }
        zza((OnLoadRealtimeResponse)localObject1, zzm.zza.zzbo(paramParcel1.readStrongBinder()));
        paramParcel2.writeNoException();
        return true;
      case 12: 
        paramParcel1.enforceInterface("com.google.android.gms.drive.internal.IDriveServiceCallbacks");
        localObject1 = localObject10;
        if (paramParcel1.readInt() != 0) {
          localObject1 = (OnResourceIdSetResponse)OnResourceIdSetResponse.CREATOR.createFromParcel(paramParcel1);
        }
        zza((OnResourceIdSetResponse)localObject1);
        paramParcel2.writeNoException();
        return true;
      case 13: 
        paramParcel1.enforceInterface("com.google.android.gms.drive.internal.IDriveServiceCallbacks");
        localObject1 = localObject11;
        if (paramParcel1.readInt() != 0) {
          localObject1 = (OnPinnedDownloadPreferencesResponse)OnPinnedDownloadPreferencesResponse.CREATOR.createFromParcel(paramParcel1);
        }
        zza((OnPinnedDownloadPreferencesResponse)localObject1);
        paramParcel2.writeNoException();
        return true;
      case 14: 
        paramParcel1.enforceInterface("com.google.android.gms.drive.internal.IDriveServiceCallbacks");
        localObject1 = localObject12;
        if (paramParcel1.readInt() != 0) {
          localObject1 = (OnDeviceUsagePreferenceResponse)OnDeviceUsagePreferenceResponse.CREATOR.createFromParcel(paramParcel1);
        }
        zza((OnDeviceUsagePreferenceResponse)localObject1);
        paramParcel2.writeNoException();
        return true;
      case 15: 
        paramParcel1.enforceInterface("com.google.android.gms.drive.internal.IDriveServiceCallbacks");
        if (paramParcel1.readInt() != 0) {}
        for (boolean bool = true;; bool = false)
        {
          zzaf(bool);
          paramParcel2.writeNoException();
          return true;
        }
      case 16: 
        paramParcel1.enforceInterface("com.google.android.gms.drive.internal.IDriveServiceCallbacks");
        localObject1 = localObject13;
        if (paramParcel1.readInt() != 0) {
          localObject1 = (OnFetchThumbnailResponse)OnFetchThumbnailResponse.CREATOR.createFromParcel(paramParcel1);
        }
        zza((OnFetchThumbnailResponse)localObject1);
        paramParcel2.writeNoException();
        return true;
      case 17: 
        paramParcel1.enforceInterface("com.google.android.gms.drive.internal.IDriveServiceCallbacks");
        localObject1 = localObject14;
        if (paramParcel1.readInt() != 0) {
          localObject1 = (ChangeSequenceNumber)ChangeSequenceNumber.CREATOR.createFromParcel(paramParcel1);
        }
        zza((ChangeSequenceNumber)localObject1);
        paramParcel2.writeNoException();
        return true;
      case 18: 
        paramParcel1.enforceInterface("com.google.android.gms.drive.internal.IDriveServiceCallbacks");
        localObject1 = localObject15;
        if (paramParcel1.readInt() != 0) {
          localObject1 = (OnChangesResponse)OnChangesResponse.CREATOR.createFromParcel(paramParcel1);
        }
        zza((OnChangesResponse)localObject1);
        paramParcel2.writeNoException();
        return true;
      case 20: 
        paramParcel1.enforceInterface("com.google.android.gms.drive.internal.IDriveServiceCallbacks");
        localObject1 = localObject16;
        if (paramParcel1.readInt() != 0) {
          localObject1 = (GetPermissionsResponse)GetPermissionsResponse.CREATOR.createFromParcel(paramParcel1);
        }
        zza((GetPermissionsResponse)localObject1);
        paramParcel2.writeNoException();
        return true;
      case 21: 
        paramParcel1.enforceInterface("com.google.android.gms.drive.internal.IDriveServiceCallbacks");
        localObject1 = localObject17;
        if (paramParcel1.readInt() != 0) {
          localObject1 = (StringListResponse)StringListResponse.CREATOR.createFromParcel(paramParcel1);
        }
        zza((StringListResponse)localObject1);
        paramParcel2.writeNoException();
        return true;
      }
      paramParcel1.enforceInterface("com.google.android.gms.drive.internal.IDriveServiceCallbacks");
      localObject1 = localObject18;
      if (paramParcel1.readInt() != 0) {
        localObject1 = (OnStartStreamSession)OnStartStreamSession.CREATOR.createFromParcel(paramParcel1);
      }
      zza((OnStartStreamSession)localObject1);
      paramParcel2.writeNoException();
      return true;
    }
    
    private static class zza
      implements zzan
    {
      private IBinder zzoz;
      
      zza(IBinder paramIBinder)
      {
        this.zzoz = paramIBinder;
      }
      
      public IBinder asBinder()
      {
        return this.zzoz;
      }
      
      /* Error */
      public void onError(Status paramStatus)
        throws RemoteException
      {
        // Byte code:
        //   0: invokestatic 31	android/os/Parcel:obtain	()Landroid/os/Parcel;
        //   3: astore_2
        //   4: invokestatic 31	android/os/Parcel:obtain	()Landroid/os/Parcel;
        //   7: astore_3
        //   8: aload_2
        //   9: ldc 33
        //   11: invokevirtual 37	android/os/Parcel:writeInterfaceToken	(Ljava/lang/String;)V
        //   14: aload_1
        //   15: ifnull +42 -> 57
        //   18: aload_2
        //   19: iconst_1
        //   20: invokevirtual 41	android/os/Parcel:writeInt	(I)V
        //   23: aload_1
        //   24: aload_2
        //   25: iconst_0
        //   26: invokevirtual 47	com/google/android/gms/common/api/Status:writeToParcel	(Landroid/os/Parcel;I)V
        //   29: aload_0
        //   30: getfield 18	com/google/android/gms/drive/internal/zzan$zza$zza:zzoz	Landroid/os/IBinder;
        //   33: bipush 6
        //   35: aload_2
        //   36: aload_3
        //   37: iconst_0
        //   38: invokeinterface 53 5 0
        //   43: pop
        //   44: aload_3
        //   45: invokevirtual 56	android/os/Parcel:readException	()V
        //   48: aload_3
        //   49: invokevirtual 59	android/os/Parcel:recycle	()V
        //   52: aload_2
        //   53: invokevirtual 59	android/os/Parcel:recycle	()V
        //   56: return
        //   57: aload_2
        //   58: iconst_0
        //   59: invokevirtual 41	android/os/Parcel:writeInt	(I)V
        //   62: goto -33 -> 29
        //   65: astore_1
        //   66: aload_3
        //   67: invokevirtual 59	android/os/Parcel:recycle	()V
        //   70: aload_2
        //   71: invokevirtual 59	android/os/Parcel:recycle	()V
        //   74: aload_1
        //   75: athrow
        // Local variable table:
        //   start	length	slot	name	signature
        //   0	76	0	this	zza
        //   0	76	1	paramStatus	Status
        //   3	68	2	localParcel1	Parcel
        //   7	60	3	localParcel2	Parcel
        // Exception table:
        //   from	to	target	type
        //   8	14	65	finally
        //   18	29	65	finally
        //   29	48	65	finally
        //   57	62	65	finally
      }
      
      public void onSuccess()
        throws RemoteException
      {
        Parcel localParcel1 = Parcel.obtain();
        Parcel localParcel2 = Parcel.obtain();
        try
        {
          localParcel1.writeInterfaceToken("com.google.android.gms.drive.internal.IDriveServiceCallbacks");
          this.zzoz.transact(7, localParcel1, localParcel2, 0);
          localParcel2.readException();
          return;
        }
        finally
        {
          localParcel2.recycle();
          localParcel1.recycle();
        }
      }
      
      /* Error */
      public void zza(ChangeSequenceNumber paramChangeSequenceNumber)
        throws RemoteException
      {
        // Byte code:
        //   0: invokestatic 31	android/os/Parcel:obtain	()Landroid/os/Parcel;
        //   3: astore_2
        //   4: invokestatic 31	android/os/Parcel:obtain	()Landroid/os/Parcel;
        //   7: astore_3
        //   8: aload_2
        //   9: ldc 33
        //   11: invokevirtual 37	android/os/Parcel:writeInterfaceToken	(Ljava/lang/String;)V
        //   14: aload_1
        //   15: ifnull +42 -> 57
        //   18: aload_2
        //   19: iconst_1
        //   20: invokevirtual 41	android/os/Parcel:writeInt	(I)V
        //   23: aload_1
        //   24: aload_2
        //   25: iconst_0
        //   26: invokevirtual 65	com/google/android/gms/drive/ChangeSequenceNumber:writeToParcel	(Landroid/os/Parcel;I)V
        //   29: aload_0
        //   30: getfield 18	com/google/android/gms/drive/internal/zzan$zza$zza:zzoz	Landroid/os/IBinder;
        //   33: bipush 17
        //   35: aload_2
        //   36: aload_3
        //   37: iconst_0
        //   38: invokeinterface 53 5 0
        //   43: pop
        //   44: aload_3
        //   45: invokevirtual 56	android/os/Parcel:readException	()V
        //   48: aload_3
        //   49: invokevirtual 59	android/os/Parcel:recycle	()V
        //   52: aload_2
        //   53: invokevirtual 59	android/os/Parcel:recycle	()V
        //   56: return
        //   57: aload_2
        //   58: iconst_0
        //   59: invokevirtual 41	android/os/Parcel:writeInt	(I)V
        //   62: goto -33 -> 29
        //   65: astore_1
        //   66: aload_3
        //   67: invokevirtual 59	android/os/Parcel:recycle	()V
        //   70: aload_2
        //   71: invokevirtual 59	android/os/Parcel:recycle	()V
        //   74: aload_1
        //   75: athrow
        // Local variable table:
        //   start	length	slot	name	signature
        //   0	76	0	this	zza
        //   0	76	1	paramChangeSequenceNumber	ChangeSequenceNumber
        //   3	68	2	localParcel1	Parcel
        //   7	60	3	localParcel2	Parcel
        // Exception table:
        //   from	to	target	type
        //   8	14	65	finally
        //   18	29	65	finally
        //   29	48	65	finally
        //   57	62	65	finally
      }
      
      /* Error */
      public void zza(GetPermissionsResponse paramGetPermissionsResponse)
        throws RemoteException
      {
        // Byte code:
        //   0: invokestatic 31	android/os/Parcel:obtain	()Landroid/os/Parcel;
        //   3: astore_2
        //   4: invokestatic 31	android/os/Parcel:obtain	()Landroid/os/Parcel;
        //   7: astore_3
        //   8: aload_2
        //   9: ldc 33
        //   11: invokevirtual 37	android/os/Parcel:writeInterfaceToken	(Ljava/lang/String;)V
        //   14: aload_1
        //   15: ifnull +42 -> 57
        //   18: aload_2
        //   19: iconst_1
        //   20: invokevirtual 41	android/os/Parcel:writeInt	(I)V
        //   23: aload_1
        //   24: aload_2
        //   25: iconst_0
        //   26: invokevirtual 69	com/google/android/gms/drive/internal/GetPermissionsResponse:writeToParcel	(Landroid/os/Parcel;I)V
        //   29: aload_0
        //   30: getfield 18	com/google/android/gms/drive/internal/zzan$zza$zza:zzoz	Landroid/os/IBinder;
        //   33: bipush 20
        //   35: aload_2
        //   36: aload_3
        //   37: iconst_0
        //   38: invokeinterface 53 5 0
        //   43: pop
        //   44: aload_3
        //   45: invokevirtual 56	android/os/Parcel:readException	()V
        //   48: aload_3
        //   49: invokevirtual 59	android/os/Parcel:recycle	()V
        //   52: aload_2
        //   53: invokevirtual 59	android/os/Parcel:recycle	()V
        //   56: return
        //   57: aload_2
        //   58: iconst_0
        //   59: invokevirtual 41	android/os/Parcel:writeInt	(I)V
        //   62: goto -33 -> 29
        //   65: astore_1
        //   66: aload_3
        //   67: invokevirtual 59	android/os/Parcel:recycle	()V
        //   70: aload_2
        //   71: invokevirtual 59	android/os/Parcel:recycle	()V
        //   74: aload_1
        //   75: athrow
        // Local variable table:
        //   start	length	slot	name	signature
        //   0	76	0	this	zza
        //   0	76	1	paramGetPermissionsResponse	GetPermissionsResponse
        //   3	68	2	localParcel1	Parcel
        //   7	60	3	localParcel2	Parcel
        // Exception table:
        //   from	to	target	type
        //   8	14	65	finally
        //   18	29	65	finally
        //   29	48	65	finally
        //   57	62	65	finally
      }
      
      /* Error */
      public void zza(OnChangesResponse paramOnChangesResponse)
        throws RemoteException
      {
        // Byte code:
        //   0: invokestatic 31	android/os/Parcel:obtain	()Landroid/os/Parcel;
        //   3: astore_2
        //   4: invokestatic 31	android/os/Parcel:obtain	()Landroid/os/Parcel;
        //   7: astore_3
        //   8: aload_2
        //   9: ldc 33
        //   11: invokevirtual 37	android/os/Parcel:writeInterfaceToken	(Ljava/lang/String;)V
        //   14: aload_1
        //   15: ifnull +42 -> 57
        //   18: aload_2
        //   19: iconst_1
        //   20: invokevirtual 41	android/os/Parcel:writeInt	(I)V
        //   23: aload_1
        //   24: aload_2
        //   25: iconst_0
        //   26: invokevirtual 73	com/google/android/gms/drive/internal/OnChangesResponse:writeToParcel	(Landroid/os/Parcel;I)V
        //   29: aload_0
        //   30: getfield 18	com/google/android/gms/drive/internal/zzan$zza$zza:zzoz	Landroid/os/IBinder;
        //   33: bipush 18
        //   35: aload_2
        //   36: aload_3
        //   37: iconst_0
        //   38: invokeinterface 53 5 0
        //   43: pop
        //   44: aload_3
        //   45: invokevirtual 56	android/os/Parcel:readException	()V
        //   48: aload_3
        //   49: invokevirtual 59	android/os/Parcel:recycle	()V
        //   52: aload_2
        //   53: invokevirtual 59	android/os/Parcel:recycle	()V
        //   56: return
        //   57: aload_2
        //   58: iconst_0
        //   59: invokevirtual 41	android/os/Parcel:writeInt	(I)V
        //   62: goto -33 -> 29
        //   65: astore_1
        //   66: aload_3
        //   67: invokevirtual 59	android/os/Parcel:recycle	()V
        //   70: aload_2
        //   71: invokevirtual 59	android/os/Parcel:recycle	()V
        //   74: aload_1
        //   75: athrow
        // Local variable table:
        //   start	length	slot	name	signature
        //   0	76	0	this	zza
        //   0	76	1	paramOnChangesResponse	OnChangesResponse
        //   3	68	2	localParcel1	Parcel
        //   7	60	3	localParcel2	Parcel
        // Exception table:
        //   from	to	target	type
        //   8	14	65	finally
        //   18	29	65	finally
        //   29	48	65	finally
        //   57	62	65	finally
      }
      
      /* Error */
      public void zza(OnContentsResponse paramOnContentsResponse)
        throws RemoteException
      {
        // Byte code:
        //   0: invokestatic 31	android/os/Parcel:obtain	()Landroid/os/Parcel;
        //   3: astore_2
        //   4: invokestatic 31	android/os/Parcel:obtain	()Landroid/os/Parcel;
        //   7: astore_3
        //   8: aload_2
        //   9: ldc 33
        //   11: invokevirtual 37	android/os/Parcel:writeInterfaceToken	(Ljava/lang/String;)V
        //   14: aload_1
        //   15: ifnull +41 -> 56
        //   18: aload_2
        //   19: iconst_1
        //   20: invokevirtual 41	android/os/Parcel:writeInt	(I)V
        //   23: aload_1
        //   24: aload_2
        //   25: iconst_0
        //   26: invokevirtual 77	com/google/android/gms/drive/internal/OnContentsResponse:writeToParcel	(Landroid/os/Parcel;I)V
        //   29: aload_0
        //   30: getfield 18	com/google/android/gms/drive/internal/zzan$zza$zza:zzoz	Landroid/os/IBinder;
        //   33: iconst_5
        //   34: aload_2
        //   35: aload_3
        //   36: iconst_0
        //   37: invokeinterface 53 5 0
        //   42: pop
        //   43: aload_3
        //   44: invokevirtual 56	android/os/Parcel:readException	()V
        //   47: aload_3
        //   48: invokevirtual 59	android/os/Parcel:recycle	()V
        //   51: aload_2
        //   52: invokevirtual 59	android/os/Parcel:recycle	()V
        //   55: return
        //   56: aload_2
        //   57: iconst_0
        //   58: invokevirtual 41	android/os/Parcel:writeInt	(I)V
        //   61: goto -32 -> 29
        //   64: astore_1
        //   65: aload_3
        //   66: invokevirtual 59	android/os/Parcel:recycle	()V
        //   69: aload_2
        //   70: invokevirtual 59	android/os/Parcel:recycle	()V
        //   73: aload_1
        //   74: athrow
        // Local variable table:
        //   start	length	slot	name	signature
        //   0	75	0	this	zza
        //   0	75	1	paramOnContentsResponse	OnContentsResponse
        //   3	67	2	localParcel1	Parcel
        //   7	59	3	localParcel2	Parcel
        // Exception table:
        //   from	to	target	type
        //   8	14	64	finally
        //   18	29	64	finally
        //   29	47	64	finally
        //   56	61	64	finally
      }
      
      /* Error */
      public void zza(OnDeviceUsagePreferenceResponse paramOnDeviceUsagePreferenceResponse)
        throws RemoteException
      {
        // Byte code:
        //   0: invokestatic 31	android/os/Parcel:obtain	()Landroid/os/Parcel;
        //   3: astore_2
        //   4: invokestatic 31	android/os/Parcel:obtain	()Landroid/os/Parcel;
        //   7: astore_3
        //   8: aload_2
        //   9: ldc 33
        //   11: invokevirtual 37	android/os/Parcel:writeInterfaceToken	(Ljava/lang/String;)V
        //   14: aload_1
        //   15: ifnull +42 -> 57
        //   18: aload_2
        //   19: iconst_1
        //   20: invokevirtual 41	android/os/Parcel:writeInt	(I)V
        //   23: aload_1
        //   24: aload_2
        //   25: iconst_0
        //   26: invokevirtual 81	com/google/android/gms/drive/internal/OnDeviceUsagePreferenceResponse:writeToParcel	(Landroid/os/Parcel;I)V
        //   29: aload_0
        //   30: getfield 18	com/google/android/gms/drive/internal/zzan$zza$zza:zzoz	Landroid/os/IBinder;
        //   33: bipush 14
        //   35: aload_2
        //   36: aload_3
        //   37: iconst_0
        //   38: invokeinterface 53 5 0
        //   43: pop
        //   44: aload_3
        //   45: invokevirtual 56	android/os/Parcel:readException	()V
        //   48: aload_3
        //   49: invokevirtual 59	android/os/Parcel:recycle	()V
        //   52: aload_2
        //   53: invokevirtual 59	android/os/Parcel:recycle	()V
        //   56: return
        //   57: aload_2
        //   58: iconst_0
        //   59: invokevirtual 41	android/os/Parcel:writeInt	(I)V
        //   62: goto -33 -> 29
        //   65: astore_1
        //   66: aload_3
        //   67: invokevirtual 59	android/os/Parcel:recycle	()V
        //   70: aload_2
        //   71: invokevirtual 59	android/os/Parcel:recycle	()V
        //   74: aload_1
        //   75: athrow
        // Local variable table:
        //   start	length	slot	name	signature
        //   0	76	0	this	zza
        //   0	76	1	paramOnDeviceUsagePreferenceResponse	OnDeviceUsagePreferenceResponse
        //   3	68	2	localParcel1	Parcel
        //   7	60	3	localParcel2	Parcel
        // Exception table:
        //   from	to	target	type
        //   8	14	65	finally
        //   18	29	65	finally
        //   29	48	65	finally
        //   57	62	65	finally
      }
      
      /* Error */
      public void zza(OnDownloadProgressResponse paramOnDownloadProgressResponse)
        throws RemoteException
      {
        // Byte code:
        //   0: invokestatic 31	android/os/Parcel:obtain	()Landroid/os/Parcel;
        //   3: astore_2
        //   4: invokestatic 31	android/os/Parcel:obtain	()Landroid/os/Parcel;
        //   7: astore_3
        //   8: aload_2
        //   9: ldc 33
        //   11: invokevirtual 37	android/os/Parcel:writeInterfaceToken	(Ljava/lang/String;)V
        //   14: aload_1
        //   15: ifnull +41 -> 56
        //   18: aload_2
        //   19: iconst_1
        //   20: invokevirtual 41	android/os/Parcel:writeInt	(I)V
        //   23: aload_1
        //   24: aload_2
        //   25: iconst_0
        //   26: invokevirtual 85	com/google/android/gms/drive/internal/OnDownloadProgressResponse:writeToParcel	(Landroid/os/Parcel;I)V
        //   29: aload_0
        //   30: getfield 18	com/google/android/gms/drive/internal/zzan$zza$zza:zzoz	Landroid/os/IBinder;
        //   33: iconst_1
        //   34: aload_2
        //   35: aload_3
        //   36: iconst_0
        //   37: invokeinterface 53 5 0
        //   42: pop
        //   43: aload_3
        //   44: invokevirtual 56	android/os/Parcel:readException	()V
        //   47: aload_3
        //   48: invokevirtual 59	android/os/Parcel:recycle	()V
        //   51: aload_2
        //   52: invokevirtual 59	android/os/Parcel:recycle	()V
        //   55: return
        //   56: aload_2
        //   57: iconst_0
        //   58: invokevirtual 41	android/os/Parcel:writeInt	(I)V
        //   61: goto -32 -> 29
        //   64: astore_1
        //   65: aload_3
        //   66: invokevirtual 59	android/os/Parcel:recycle	()V
        //   69: aload_2
        //   70: invokevirtual 59	android/os/Parcel:recycle	()V
        //   73: aload_1
        //   74: athrow
        // Local variable table:
        //   start	length	slot	name	signature
        //   0	75	0	this	zza
        //   0	75	1	paramOnDownloadProgressResponse	OnDownloadProgressResponse
        //   3	67	2	localParcel1	Parcel
        //   7	59	3	localParcel2	Parcel
        // Exception table:
        //   from	to	target	type
        //   8	14	64	finally
        //   18	29	64	finally
        //   29	47	64	finally
        //   56	61	64	finally
      }
      
      /* Error */
      public void zza(OnDriveIdResponse paramOnDriveIdResponse)
        throws RemoteException
      {
        // Byte code:
        //   0: invokestatic 31	android/os/Parcel:obtain	()Landroid/os/Parcel;
        //   3: astore_2
        //   4: invokestatic 31	android/os/Parcel:obtain	()Landroid/os/Parcel;
        //   7: astore_3
        //   8: aload_2
        //   9: ldc 33
        //   11: invokevirtual 37	android/os/Parcel:writeInterfaceToken	(Ljava/lang/String;)V
        //   14: aload_1
        //   15: ifnull +41 -> 56
        //   18: aload_2
        //   19: iconst_1
        //   20: invokevirtual 41	android/os/Parcel:writeInt	(I)V
        //   23: aload_1
        //   24: aload_2
        //   25: iconst_0
        //   26: invokevirtual 89	com/google/android/gms/drive/internal/OnDriveIdResponse:writeToParcel	(Landroid/os/Parcel;I)V
        //   29: aload_0
        //   30: getfield 18	com/google/android/gms/drive/internal/zzan$zza$zza:zzoz	Landroid/os/IBinder;
        //   33: iconst_3
        //   34: aload_2
        //   35: aload_3
        //   36: iconst_0
        //   37: invokeinterface 53 5 0
        //   42: pop
        //   43: aload_3
        //   44: invokevirtual 56	android/os/Parcel:readException	()V
        //   47: aload_3
        //   48: invokevirtual 59	android/os/Parcel:recycle	()V
        //   51: aload_2
        //   52: invokevirtual 59	android/os/Parcel:recycle	()V
        //   55: return
        //   56: aload_2
        //   57: iconst_0
        //   58: invokevirtual 41	android/os/Parcel:writeInt	(I)V
        //   61: goto -32 -> 29
        //   64: astore_1
        //   65: aload_3
        //   66: invokevirtual 59	android/os/Parcel:recycle	()V
        //   69: aload_2
        //   70: invokevirtual 59	android/os/Parcel:recycle	()V
        //   73: aload_1
        //   74: athrow
        // Local variable table:
        //   start	length	slot	name	signature
        //   0	75	0	this	zza
        //   0	75	1	paramOnDriveIdResponse	OnDriveIdResponse
        //   3	67	2	localParcel1	Parcel
        //   7	59	3	localParcel2	Parcel
        // Exception table:
        //   from	to	target	type
        //   8	14	64	finally
        //   18	29	64	finally
        //   29	47	64	finally
        //   56	61	64	finally
      }
      
      /* Error */
      public void zza(OnFetchThumbnailResponse paramOnFetchThumbnailResponse)
        throws RemoteException
      {
        // Byte code:
        //   0: invokestatic 31	android/os/Parcel:obtain	()Landroid/os/Parcel;
        //   3: astore_2
        //   4: invokestatic 31	android/os/Parcel:obtain	()Landroid/os/Parcel;
        //   7: astore_3
        //   8: aload_2
        //   9: ldc 33
        //   11: invokevirtual 37	android/os/Parcel:writeInterfaceToken	(Ljava/lang/String;)V
        //   14: aload_1
        //   15: ifnull +42 -> 57
        //   18: aload_2
        //   19: iconst_1
        //   20: invokevirtual 41	android/os/Parcel:writeInt	(I)V
        //   23: aload_1
        //   24: aload_2
        //   25: iconst_0
        //   26: invokevirtual 93	com/google/android/gms/drive/internal/OnFetchThumbnailResponse:writeToParcel	(Landroid/os/Parcel;I)V
        //   29: aload_0
        //   30: getfield 18	com/google/android/gms/drive/internal/zzan$zza$zza:zzoz	Landroid/os/IBinder;
        //   33: bipush 16
        //   35: aload_2
        //   36: aload_3
        //   37: iconst_0
        //   38: invokeinterface 53 5 0
        //   43: pop
        //   44: aload_3
        //   45: invokevirtual 56	android/os/Parcel:readException	()V
        //   48: aload_3
        //   49: invokevirtual 59	android/os/Parcel:recycle	()V
        //   52: aload_2
        //   53: invokevirtual 59	android/os/Parcel:recycle	()V
        //   56: return
        //   57: aload_2
        //   58: iconst_0
        //   59: invokevirtual 41	android/os/Parcel:writeInt	(I)V
        //   62: goto -33 -> 29
        //   65: astore_1
        //   66: aload_3
        //   67: invokevirtual 59	android/os/Parcel:recycle	()V
        //   70: aload_2
        //   71: invokevirtual 59	android/os/Parcel:recycle	()V
        //   74: aload_1
        //   75: athrow
        // Local variable table:
        //   start	length	slot	name	signature
        //   0	76	0	this	zza
        //   0	76	1	paramOnFetchThumbnailResponse	OnFetchThumbnailResponse
        //   3	68	2	localParcel1	Parcel
        //   7	60	3	localParcel2	Parcel
        // Exception table:
        //   from	to	target	type
        //   8	14	65	finally
        //   18	29	65	finally
        //   29	48	65	finally
        //   57	62	65	finally
      }
      
      /* Error */
      public void zza(OnListEntriesResponse paramOnListEntriesResponse)
        throws RemoteException
      {
        // Byte code:
        //   0: invokestatic 31	android/os/Parcel:obtain	()Landroid/os/Parcel;
        //   3: astore_2
        //   4: invokestatic 31	android/os/Parcel:obtain	()Landroid/os/Parcel;
        //   7: astore_3
        //   8: aload_2
        //   9: ldc 33
        //   11: invokevirtual 37	android/os/Parcel:writeInterfaceToken	(Ljava/lang/String;)V
        //   14: aload_1
        //   15: ifnull +41 -> 56
        //   18: aload_2
        //   19: iconst_1
        //   20: invokevirtual 41	android/os/Parcel:writeInt	(I)V
        //   23: aload_1
        //   24: aload_2
        //   25: iconst_0
        //   26: invokevirtual 97	com/google/android/gms/drive/internal/OnListEntriesResponse:writeToParcel	(Landroid/os/Parcel;I)V
        //   29: aload_0
        //   30: getfield 18	com/google/android/gms/drive/internal/zzan$zza$zza:zzoz	Landroid/os/IBinder;
        //   33: iconst_2
        //   34: aload_2
        //   35: aload_3
        //   36: iconst_0
        //   37: invokeinterface 53 5 0
        //   42: pop
        //   43: aload_3
        //   44: invokevirtual 56	android/os/Parcel:readException	()V
        //   47: aload_3
        //   48: invokevirtual 59	android/os/Parcel:recycle	()V
        //   51: aload_2
        //   52: invokevirtual 59	android/os/Parcel:recycle	()V
        //   55: return
        //   56: aload_2
        //   57: iconst_0
        //   58: invokevirtual 41	android/os/Parcel:writeInt	(I)V
        //   61: goto -32 -> 29
        //   64: astore_1
        //   65: aload_3
        //   66: invokevirtual 59	android/os/Parcel:recycle	()V
        //   69: aload_2
        //   70: invokevirtual 59	android/os/Parcel:recycle	()V
        //   73: aload_1
        //   74: athrow
        // Local variable table:
        //   start	length	slot	name	signature
        //   0	75	0	this	zza
        //   0	75	1	paramOnListEntriesResponse	OnListEntriesResponse
        //   3	67	2	localParcel1	Parcel
        //   7	59	3	localParcel2	Parcel
        // Exception table:
        //   from	to	target	type
        //   8	14	64	finally
        //   18	29	64	finally
        //   29	47	64	finally
        //   56	61	64	finally
      }
      
      /* Error */
      public void zza(OnListParentsResponse paramOnListParentsResponse)
        throws RemoteException
      {
        // Byte code:
        //   0: invokestatic 31	android/os/Parcel:obtain	()Landroid/os/Parcel;
        //   3: astore_2
        //   4: invokestatic 31	android/os/Parcel:obtain	()Landroid/os/Parcel;
        //   7: astore_3
        //   8: aload_2
        //   9: ldc 33
        //   11: invokevirtual 37	android/os/Parcel:writeInterfaceToken	(Ljava/lang/String;)V
        //   14: aload_1
        //   15: ifnull +42 -> 57
        //   18: aload_2
        //   19: iconst_1
        //   20: invokevirtual 41	android/os/Parcel:writeInt	(I)V
        //   23: aload_1
        //   24: aload_2
        //   25: iconst_0
        //   26: invokevirtual 101	com/google/android/gms/drive/internal/OnListParentsResponse:writeToParcel	(Landroid/os/Parcel;I)V
        //   29: aload_0
        //   30: getfield 18	com/google/android/gms/drive/internal/zzan$zza$zza:zzoz	Landroid/os/IBinder;
        //   33: bipush 8
        //   35: aload_2
        //   36: aload_3
        //   37: iconst_0
        //   38: invokeinterface 53 5 0
        //   43: pop
        //   44: aload_3
        //   45: invokevirtual 56	android/os/Parcel:readException	()V
        //   48: aload_3
        //   49: invokevirtual 59	android/os/Parcel:recycle	()V
        //   52: aload_2
        //   53: invokevirtual 59	android/os/Parcel:recycle	()V
        //   56: return
        //   57: aload_2
        //   58: iconst_0
        //   59: invokevirtual 41	android/os/Parcel:writeInt	(I)V
        //   62: goto -33 -> 29
        //   65: astore_1
        //   66: aload_3
        //   67: invokevirtual 59	android/os/Parcel:recycle	()V
        //   70: aload_2
        //   71: invokevirtual 59	android/os/Parcel:recycle	()V
        //   74: aload_1
        //   75: athrow
        // Local variable table:
        //   start	length	slot	name	signature
        //   0	76	0	this	zza
        //   0	76	1	paramOnListParentsResponse	OnListParentsResponse
        //   3	68	2	localParcel1	Parcel
        //   7	60	3	localParcel2	Parcel
        // Exception table:
        //   from	to	target	type
        //   8	14	65	finally
        //   18	29	65	finally
        //   29	48	65	finally
        //   57	62	65	finally
      }
      
      public void zza(OnLoadRealtimeResponse paramOnLoadRealtimeResponse, zzm paramzzm)
        throws RemoteException
      {
        Parcel localParcel1 = Parcel.obtain();
        Parcel localParcel2 = Parcel.obtain();
        for (;;)
        {
          try
          {
            localParcel1.writeInterfaceToken("com.google.android.gms.drive.internal.IDriveServiceCallbacks");
            if (paramOnLoadRealtimeResponse != null)
            {
              localParcel1.writeInt(1);
              paramOnLoadRealtimeResponse.writeToParcel(localParcel1, 0);
              if (paramzzm != null)
              {
                paramOnLoadRealtimeResponse = paramzzm.asBinder();
                localParcel1.writeStrongBinder(paramOnLoadRealtimeResponse);
                this.zzoz.transact(11, localParcel1, localParcel2, 0);
                localParcel2.readException();
              }
            }
            else
            {
              localParcel1.writeInt(0);
              continue;
            }
            paramOnLoadRealtimeResponse = null;
          }
          finally
          {
            localParcel2.recycle();
            localParcel1.recycle();
          }
        }
      }
      
      /* Error */
      public void zza(OnMetadataResponse paramOnMetadataResponse)
        throws RemoteException
      {
        // Byte code:
        //   0: invokestatic 31	android/os/Parcel:obtain	()Landroid/os/Parcel;
        //   3: astore_2
        //   4: invokestatic 31	android/os/Parcel:obtain	()Landroid/os/Parcel;
        //   7: astore_3
        //   8: aload_2
        //   9: ldc 33
        //   11: invokevirtual 37	android/os/Parcel:writeInterfaceToken	(Ljava/lang/String;)V
        //   14: aload_1
        //   15: ifnull +41 -> 56
        //   18: aload_2
        //   19: iconst_1
        //   20: invokevirtual 41	android/os/Parcel:writeInt	(I)V
        //   23: aload_1
        //   24: aload_2
        //   25: iconst_0
        //   26: invokevirtual 116	com/google/android/gms/drive/internal/OnMetadataResponse:writeToParcel	(Landroid/os/Parcel;I)V
        //   29: aload_0
        //   30: getfield 18	com/google/android/gms/drive/internal/zzan$zza$zza:zzoz	Landroid/os/IBinder;
        //   33: iconst_4
        //   34: aload_2
        //   35: aload_3
        //   36: iconst_0
        //   37: invokeinterface 53 5 0
        //   42: pop
        //   43: aload_3
        //   44: invokevirtual 56	android/os/Parcel:readException	()V
        //   47: aload_3
        //   48: invokevirtual 59	android/os/Parcel:recycle	()V
        //   51: aload_2
        //   52: invokevirtual 59	android/os/Parcel:recycle	()V
        //   55: return
        //   56: aload_2
        //   57: iconst_0
        //   58: invokevirtual 41	android/os/Parcel:writeInt	(I)V
        //   61: goto -32 -> 29
        //   64: astore_1
        //   65: aload_3
        //   66: invokevirtual 59	android/os/Parcel:recycle	()V
        //   69: aload_2
        //   70: invokevirtual 59	android/os/Parcel:recycle	()V
        //   73: aload_1
        //   74: athrow
        // Local variable table:
        //   start	length	slot	name	signature
        //   0	75	0	this	zza
        //   0	75	1	paramOnMetadataResponse	OnMetadataResponse
        //   3	67	2	localParcel1	Parcel
        //   7	59	3	localParcel2	Parcel
        // Exception table:
        //   from	to	target	type
        //   8	14	64	finally
        //   18	29	64	finally
        //   29	47	64	finally
        //   56	61	64	finally
      }
      
      /* Error */
      public void zza(OnPinnedDownloadPreferencesResponse paramOnPinnedDownloadPreferencesResponse)
        throws RemoteException
      {
        // Byte code:
        //   0: invokestatic 31	android/os/Parcel:obtain	()Landroid/os/Parcel;
        //   3: astore_2
        //   4: invokestatic 31	android/os/Parcel:obtain	()Landroid/os/Parcel;
        //   7: astore_3
        //   8: aload_2
        //   9: ldc 33
        //   11: invokevirtual 37	android/os/Parcel:writeInterfaceToken	(Ljava/lang/String;)V
        //   14: aload_1
        //   15: ifnull +42 -> 57
        //   18: aload_2
        //   19: iconst_1
        //   20: invokevirtual 41	android/os/Parcel:writeInt	(I)V
        //   23: aload_1
        //   24: aload_2
        //   25: iconst_0
        //   26: invokevirtual 120	com/google/android/gms/drive/internal/OnPinnedDownloadPreferencesResponse:writeToParcel	(Landroid/os/Parcel;I)V
        //   29: aload_0
        //   30: getfield 18	com/google/android/gms/drive/internal/zzan$zza$zza:zzoz	Landroid/os/IBinder;
        //   33: bipush 13
        //   35: aload_2
        //   36: aload_3
        //   37: iconst_0
        //   38: invokeinterface 53 5 0
        //   43: pop
        //   44: aload_3
        //   45: invokevirtual 56	android/os/Parcel:readException	()V
        //   48: aload_3
        //   49: invokevirtual 59	android/os/Parcel:recycle	()V
        //   52: aload_2
        //   53: invokevirtual 59	android/os/Parcel:recycle	()V
        //   56: return
        //   57: aload_2
        //   58: iconst_0
        //   59: invokevirtual 41	android/os/Parcel:writeInt	(I)V
        //   62: goto -33 -> 29
        //   65: astore_1
        //   66: aload_3
        //   67: invokevirtual 59	android/os/Parcel:recycle	()V
        //   70: aload_2
        //   71: invokevirtual 59	android/os/Parcel:recycle	()V
        //   74: aload_1
        //   75: athrow
        // Local variable table:
        //   start	length	slot	name	signature
        //   0	76	0	this	zza
        //   0	76	1	paramOnPinnedDownloadPreferencesResponse	OnPinnedDownloadPreferencesResponse
        //   3	68	2	localParcel1	Parcel
        //   7	60	3	localParcel2	Parcel
        // Exception table:
        //   from	to	target	type
        //   8	14	65	finally
        //   18	29	65	finally
        //   29	48	65	finally
        //   57	62	65	finally
      }
      
      /* Error */
      public void zza(OnResourceIdSetResponse paramOnResourceIdSetResponse)
        throws RemoteException
      {
        // Byte code:
        //   0: invokestatic 31	android/os/Parcel:obtain	()Landroid/os/Parcel;
        //   3: astore_2
        //   4: invokestatic 31	android/os/Parcel:obtain	()Landroid/os/Parcel;
        //   7: astore_3
        //   8: aload_2
        //   9: ldc 33
        //   11: invokevirtual 37	android/os/Parcel:writeInterfaceToken	(Ljava/lang/String;)V
        //   14: aload_1
        //   15: ifnull +42 -> 57
        //   18: aload_2
        //   19: iconst_1
        //   20: invokevirtual 41	android/os/Parcel:writeInt	(I)V
        //   23: aload_1
        //   24: aload_2
        //   25: iconst_0
        //   26: invokevirtual 124	com/google/android/gms/drive/internal/OnResourceIdSetResponse:writeToParcel	(Landroid/os/Parcel;I)V
        //   29: aload_0
        //   30: getfield 18	com/google/android/gms/drive/internal/zzan$zza$zza:zzoz	Landroid/os/IBinder;
        //   33: bipush 12
        //   35: aload_2
        //   36: aload_3
        //   37: iconst_0
        //   38: invokeinterface 53 5 0
        //   43: pop
        //   44: aload_3
        //   45: invokevirtual 56	android/os/Parcel:readException	()V
        //   48: aload_3
        //   49: invokevirtual 59	android/os/Parcel:recycle	()V
        //   52: aload_2
        //   53: invokevirtual 59	android/os/Parcel:recycle	()V
        //   56: return
        //   57: aload_2
        //   58: iconst_0
        //   59: invokevirtual 41	android/os/Parcel:writeInt	(I)V
        //   62: goto -33 -> 29
        //   65: astore_1
        //   66: aload_3
        //   67: invokevirtual 59	android/os/Parcel:recycle	()V
        //   70: aload_2
        //   71: invokevirtual 59	android/os/Parcel:recycle	()V
        //   74: aload_1
        //   75: athrow
        // Local variable table:
        //   start	length	slot	name	signature
        //   0	76	0	this	zza
        //   0	76	1	paramOnResourceIdSetResponse	OnResourceIdSetResponse
        //   3	68	2	localParcel1	Parcel
        //   7	60	3	localParcel2	Parcel
        // Exception table:
        //   from	to	target	type
        //   8	14	65	finally
        //   18	29	65	finally
        //   29	48	65	finally
        //   57	62	65	finally
      }
      
      /* Error */
      public void zza(OnStartStreamSession paramOnStartStreamSession)
        throws RemoteException
      {
        // Byte code:
        //   0: invokestatic 31	android/os/Parcel:obtain	()Landroid/os/Parcel;
        //   3: astore_2
        //   4: invokestatic 31	android/os/Parcel:obtain	()Landroid/os/Parcel;
        //   7: astore_3
        //   8: aload_2
        //   9: ldc 33
        //   11: invokevirtual 37	android/os/Parcel:writeInterfaceToken	(Ljava/lang/String;)V
        //   14: aload_1
        //   15: ifnull +42 -> 57
        //   18: aload_2
        //   19: iconst_1
        //   20: invokevirtual 41	android/os/Parcel:writeInt	(I)V
        //   23: aload_1
        //   24: aload_2
        //   25: iconst_0
        //   26: invokevirtual 128	com/google/android/gms/drive/internal/OnStartStreamSession:writeToParcel	(Landroid/os/Parcel;I)V
        //   29: aload_0
        //   30: getfield 18	com/google/android/gms/drive/internal/zzan$zza$zza:zzoz	Landroid/os/IBinder;
        //   33: bipush 22
        //   35: aload_2
        //   36: aload_3
        //   37: iconst_0
        //   38: invokeinterface 53 5 0
        //   43: pop
        //   44: aload_3
        //   45: invokevirtual 56	android/os/Parcel:readException	()V
        //   48: aload_3
        //   49: invokevirtual 59	android/os/Parcel:recycle	()V
        //   52: aload_2
        //   53: invokevirtual 59	android/os/Parcel:recycle	()V
        //   56: return
        //   57: aload_2
        //   58: iconst_0
        //   59: invokevirtual 41	android/os/Parcel:writeInt	(I)V
        //   62: goto -33 -> 29
        //   65: astore_1
        //   66: aload_3
        //   67: invokevirtual 59	android/os/Parcel:recycle	()V
        //   70: aload_2
        //   71: invokevirtual 59	android/os/Parcel:recycle	()V
        //   74: aload_1
        //   75: athrow
        // Local variable table:
        //   start	length	slot	name	signature
        //   0	76	0	this	zza
        //   0	76	1	paramOnStartStreamSession	OnStartStreamSession
        //   3	68	2	localParcel1	Parcel
        //   7	60	3	localParcel2	Parcel
        // Exception table:
        //   from	to	target	type
        //   8	14	65	finally
        //   18	29	65	finally
        //   29	48	65	finally
        //   57	62	65	finally
      }
      
      /* Error */
      public void zza(OnSyncMoreResponse paramOnSyncMoreResponse)
        throws RemoteException
      {
        // Byte code:
        //   0: invokestatic 31	android/os/Parcel:obtain	()Landroid/os/Parcel;
        //   3: astore_2
        //   4: invokestatic 31	android/os/Parcel:obtain	()Landroid/os/Parcel;
        //   7: astore_3
        //   8: aload_2
        //   9: ldc 33
        //   11: invokevirtual 37	android/os/Parcel:writeInterfaceToken	(Ljava/lang/String;)V
        //   14: aload_1
        //   15: ifnull +42 -> 57
        //   18: aload_2
        //   19: iconst_1
        //   20: invokevirtual 41	android/os/Parcel:writeInt	(I)V
        //   23: aload_1
        //   24: aload_2
        //   25: iconst_0
        //   26: invokevirtual 132	com/google/android/gms/drive/internal/OnSyncMoreResponse:writeToParcel	(Landroid/os/Parcel;I)V
        //   29: aload_0
        //   30: getfield 18	com/google/android/gms/drive/internal/zzan$zza$zza:zzoz	Landroid/os/IBinder;
        //   33: bipush 9
        //   35: aload_2
        //   36: aload_3
        //   37: iconst_0
        //   38: invokeinterface 53 5 0
        //   43: pop
        //   44: aload_3
        //   45: invokevirtual 56	android/os/Parcel:readException	()V
        //   48: aload_3
        //   49: invokevirtual 59	android/os/Parcel:recycle	()V
        //   52: aload_2
        //   53: invokevirtual 59	android/os/Parcel:recycle	()V
        //   56: return
        //   57: aload_2
        //   58: iconst_0
        //   59: invokevirtual 41	android/os/Parcel:writeInt	(I)V
        //   62: goto -33 -> 29
        //   65: astore_1
        //   66: aload_3
        //   67: invokevirtual 59	android/os/Parcel:recycle	()V
        //   70: aload_2
        //   71: invokevirtual 59	android/os/Parcel:recycle	()V
        //   74: aload_1
        //   75: athrow
        // Local variable table:
        //   start	length	slot	name	signature
        //   0	76	0	this	zza
        //   0	76	1	paramOnSyncMoreResponse	OnSyncMoreResponse
        //   3	68	2	localParcel1	Parcel
        //   7	60	3	localParcel2	Parcel
        // Exception table:
        //   from	to	target	type
        //   8	14	65	finally
        //   18	29	65	finally
        //   29	48	65	finally
        //   57	62	65	finally
      }
      
      /* Error */
      public void zza(StringListResponse paramStringListResponse)
        throws RemoteException
      {
        // Byte code:
        //   0: invokestatic 31	android/os/Parcel:obtain	()Landroid/os/Parcel;
        //   3: astore_2
        //   4: invokestatic 31	android/os/Parcel:obtain	()Landroid/os/Parcel;
        //   7: astore_3
        //   8: aload_2
        //   9: ldc 33
        //   11: invokevirtual 37	android/os/Parcel:writeInterfaceToken	(Ljava/lang/String;)V
        //   14: aload_1
        //   15: ifnull +42 -> 57
        //   18: aload_2
        //   19: iconst_1
        //   20: invokevirtual 41	android/os/Parcel:writeInt	(I)V
        //   23: aload_1
        //   24: aload_2
        //   25: iconst_0
        //   26: invokevirtual 136	com/google/android/gms/drive/internal/StringListResponse:writeToParcel	(Landroid/os/Parcel;I)V
        //   29: aload_0
        //   30: getfield 18	com/google/android/gms/drive/internal/zzan$zza$zza:zzoz	Landroid/os/IBinder;
        //   33: bipush 21
        //   35: aload_2
        //   36: aload_3
        //   37: iconst_0
        //   38: invokeinterface 53 5 0
        //   43: pop
        //   44: aload_3
        //   45: invokevirtual 56	android/os/Parcel:readException	()V
        //   48: aload_3
        //   49: invokevirtual 59	android/os/Parcel:recycle	()V
        //   52: aload_2
        //   53: invokevirtual 59	android/os/Parcel:recycle	()V
        //   56: return
        //   57: aload_2
        //   58: iconst_0
        //   59: invokevirtual 41	android/os/Parcel:writeInt	(I)V
        //   62: goto -33 -> 29
        //   65: astore_1
        //   66: aload_3
        //   67: invokevirtual 59	android/os/Parcel:recycle	()V
        //   70: aload_2
        //   71: invokevirtual 59	android/os/Parcel:recycle	()V
        //   74: aload_1
        //   75: athrow
        // Local variable table:
        //   start	length	slot	name	signature
        //   0	76	0	this	zza
        //   0	76	1	paramStringListResponse	StringListResponse
        //   3	68	2	localParcel1	Parcel
        //   7	60	3	localParcel2	Parcel
        // Exception table:
        //   from	to	target	type
        //   8	14	65	finally
        //   18	29	65	finally
        //   29	48	65	finally
        //   57	62	65	finally
      }
      
      public void zzaf(boolean paramBoolean)
        throws RemoteException
      {
        int i = 0;
        Parcel localParcel1 = Parcel.obtain();
        Parcel localParcel2 = Parcel.obtain();
        try
        {
          localParcel1.writeInterfaceToken("com.google.android.gms.drive.internal.IDriveServiceCallbacks");
          if (paramBoolean) {
            i = 1;
          }
          localParcel1.writeInt(i);
          this.zzoz.transact(15, localParcel1, localParcel2, 0);
          localParcel2.readException();
          return;
        }
        finally
        {
          localParcel2.recycle();
          localParcel1.recycle();
        }
      }
    }
  }
}


/* Location:              C:\Users\Genbu Hase\hLg\Genbu\Tool\Programing\Jad\BlockLauncher 1.12.8.jar!\com\google\android\gms\drive\internal\zzan.class
 * Java compiler version: 6 (50.0)
 * JD-Core Version:       0.7.1-SNAPSHOT-20140817
 */