package com.google.android.gms.internal;

import android.os.Binder;
import android.os.IBinder;
import android.os.IInterface;
import android.os.Parcel;
import android.os.Parcelable.Creator;
import android.os.RemoteException;
import com.google.android.gms.fitness.request.SessionInsertRequest;
import com.google.android.gms.fitness.request.SessionReadRequest;
import com.google.android.gms.fitness.request.SessionRegistrationRequest;
import com.google.android.gms.fitness.request.SessionStartRequest;
import com.google.android.gms.fitness.request.SessionStopRequest;
import com.google.android.gms.fitness.request.SessionUnregistrationRequest;

public abstract interface zzoq
  extends IInterface
{
  public abstract void zza(SessionInsertRequest paramSessionInsertRequest)
    throws RemoteException;
  
  public abstract void zza(SessionReadRequest paramSessionReadRequest)
    throws RemoteException;
  
  public abstract void zza(SessionRegistrationRequest paramSessionRegistrationRequest)
    throws RemoteException;
  
  public abstract void zza(SessionStartRequest paramSessionStartRequest)
    throws RemoteException;
  
  public abstract void zza(SessionStopRequest paramSessionStopRequest)
    throws RemoteException;
  
  public abstract void zza(SessionUnregistrationRequest paramSessionUnregistrationRequest)
    throws RemoteException;
  
  public static abstract class zza
    extends Binder
    implements zzoq
  {
    public static zzoq zzbL(IBinder paramIBinder)
    {
      if (paramIBinder == null) {
        return null;
      }
      IInterface localIInterface = paramIBinder.queryLocalInterface("com.google.android.gms.fitness.internal.IGoogleFitSessionsApi");
      if ((localIInterface != null) && ((localIInterface instanceof zzoq))) {
        return (zzoq)localIInterface;
      }
      return new zza(paramIBinder);
    }
    
    public boolean onTransact(int paramInt1, Parcel paramParcel1, Parcel paramParcel2, int paramInt2)
      throws RemoteException
    {
      Object localObject2 = null;
      Object localObject3 = null;
      Object localObject4 = null;
      Object localObject5 = null;
      Object localObject6 = null;
      Object localObject1 = null;
      switch (paramInt1)
      {
      default: 
        return super.onTransact(paramInt1, paramParcel1, paramParcel2, paramInt2);
      case 1598968902: 
        paramParcel2.writeString("com.google.android.gms.fitness.internal.IGoogleFitSessionsApi");
        return true;
      case 1: 
        paramParcel1.enforceInterface("com.google.android.gms.fitness.internal.IGoogleFitSessionsApi");
        if (paramParcel1.readInt() != 0) {
          localObject1 = (SessionStartRequest)SessionStartRequest.CREATOR.createFromParcel(paramParcel1);
        }
        zza((SessionStartRequest)localObject1);
        paramParcel2.writeNoException();
        return true;
      case 2: 
        paramParcel1.enforceInterface("com.google.android.gms.fitness.internal.IGoogleFitSessionsApi");
        localObject1 = localObject2;
        if (paramParcel1.readInt() != 0) {
          localObject1 = (SessionStopRequest)SessionStopRequest.CREATOR.createFromParcel(paramParcel1);
        }
        zza((SessionStopRequest)localObject1);
        paramParcel2.writeNoException();
        return true;
      case 3: 
        paramParcel1.enforceInterface("com.google.android.gms.fitness.internal.IGoogleFitSessionsApi");
        localObject1 = localObject3;
        if (paramParcel1.readInt() != 0) {
          localObject1 = (SessionInsertRequest)SessionInsertRequest.CREATOR.createFromParcel(paramParcel1);
        }
        zza((SessionInsertRequest)localObject1);
        paramParcel2.writeNoException();
        return true;
      case 4: 
        paramParcel1.enforceInterface("com.google.android.gms.fitness.internal.IGoogleFitSessionsApi");
        localObject1 = localObject4;
        if (paramParcel1.readInt() != 0) {
          localObject1 = (SessionReadRequest)SessionReadRequest.CREATOR.createFromParcel(paramParcel1);
        }
        zza((SessionReadRequest)localObject1);
        paramParcel2.writeNoException();
        return true;
      case 5: 
        paramParcel1.enforceInterface("com.google.android.gms.fitness.internal.IGoogleFitSessionsApi");
        localObject1 = localObject5;
        if (paramParcel1.readInt() != 0) {
          localObject1 = (SessionRegistrationRequest)SessionRegistrationRequest.CREATOR.createFromParcel(paramParcel1);
        }
        zza((SessionRegistrationRequest)localObject1);
        paramParcel2.writeNoException();
        return true;
      }
      paramParcel1.enforceInterface("com.google.android.gms.fitness.internal.IGoogleFitSessionsApi");
      localObject1 = localObject6;
      if (paramParcel1.readInt() != 0) {
        localObject1 = (SessionUnregistrationRequest)SessionUnregistrationRequest.CREATOR.createFromParcel(paramParcel1);
      }
      zza((SessionUnregistrationRequest)localObject1);
      paramParcel2.writeNoException();
      return true;
    }
    
    private static class zza
      implements zzoq
    {
      private IBinder zzoz;
      
      zza(IBinder paramIBinder)
      {
        this.zzoz = paramIBinder;
      }
      
      public IBinder asBinder()
      {
        return this.zzoz;
      }
      
      /* Error */
      public void zza(SessionInsertRequest paramSessionInsertRequest)
        throws RemoteException
      {
        // Byte code:
        //   0: invokestatic 30	android/os/Parcel:obtain	()Landroid/os/Parcel;
        //   3: astore_2
        //   4: invokestatic 30	android/os/Parcel:obtain	()Landroid/os/Parcel;
        //   7: astore_3
        //   8: aload_2
        //   9: ldc 32
        //   11: invokevirtual 36	android/os/Parcel:writeInterfaceToken	(Ljava/lang/String;)V
        //   14: aload_1
        //   15: ifnull +41 -> 56
        //   18: aload_2
        //   19: iconst_1
        //   20: invokevirtual 40	android/os/Parcel:writeInt	(I)V
        //   23: aload_1
        //   24: aload_2
        //   25: iconst_0
        //   26: invokevirtual 46	com/google/android/gms/fitness/request/SessionInsertRequest:writeToParcel	(Landroid/os/Parcel;I)V
        //   29: aload_0
        //   30: getfield 18	com/google/android/gms/internal/zzoq$zza$zza:zzoz	Landroid/os/IBinder;
        //   33: iconst_3
        //   34: aload_2
        //   35: aload_3
        //   36: iconst_0
        //   37: invokeinterface 52 5 0
        //   42: pop
        //   43: aload_3
        //   44: invokevirtual 55	android/os/Parcel:readException	()V
        //   47: aload_3
        //   48: invokevirtual 58	android/os/Parcel:recycle	()V
        //   51: aload_2
        //   52: invokevirtual 58	android/os/Parcel:recycle	()V
        //   55: return
        //   56: aload_2
        //   57: iconst_0
        //   58: invokevirtual 40	android/os/Parcel:writeInt	(I)V
        //   61: goto -32 -> 29
        //   64: astore_1
        //   65: aload_3
        //   66: invokevirtual 58	android/os/Parcel:recycle	()V
        //   69: aload_2
        //   70: invokevirtual 58	android/os/Parcel:recycle	()V
        //   73: aload_1
        //   74: athrow
        // Local variable table:
        //   start	length	slot	name	signature
        //   0	75	0	this	zza
        //   0	75	1	paramSessionInsertRequest	SessionInsertRequest
        //   3	67	2	localParcel1	Parcel
        //   7	59	3	localParcel2	Parcel
        // Exception table:
        //   from	to	target	type
        //   8	14	64	finally
        //   18	29	64	finally
        //   29	47	64	finally
        //   56	61	64	finally
      }
      
      /* Error */
      public void zza(SessionReadRequest paramSessionReadRequest)
        throws RemoteException
      {
        // Byte code:
        //   0: invokestatic 30	android/os/Parcel:obtain	()Landroid/os/Parcel;
        //   3: astore_2
        //   4: invokestatic 30	android/os/Parcel:obtain	()Landroid/os/Parcel;
        //   7: astore_3
        //   8: aload_2
        //   9: ldc 32
        //   11: invokevirtual 36	android/os/Parcel:writeInterfaceToken	(Ljava/lang/String;)V
        //   14: aload_1
        //   15: ifnull +41 -> 56
        //   18: aload_2
        //   19: iconst_1
        //   20: invokevirtual 40	android/os/Parcel:writeInt	(I)V
        //   23: aload_1
        //   24: aload_2
        //   25: iconst_0
        //   26: invokevirtual 63	com/google/android/gms/fitness/request/SessionReadRequest:writeToParcel	(Landroid/os/Parcel;I)V
        //   29: aload_0
        //   30: getfield 18	com/google/android/gms/internal/zzoq$zza$zza:zzoz	Landroid/os/IBinder;
        //   33: iconst_4
        //   34: aload_2
        //   35: aload_3
        //   36: iconst_0
        //   37: invokeinterface 52 5 0
        //   42: pop
        //   43: aload_3
        //   44: invokevirtual 55	android/os/Parcel:readException	()V
        //   47: aload_3
        //   48: invokevirtual 58	android/os/Parcel:recycle	()V
        //   51: aload_2
        //   52: invokevirtual 58	android/os/Parcel:recycle	()V
        //   55: return
        //   56: aload_2
        //   57: iconst_0
        //   58: invokevirtual 40	android/os/Parcel:writeInt	(I)V
        //   61: goto -32 -> 29
        //   64: astore_1
        //   65: aload_3
        //   66: invokevirtual 58	android/os/Parcel:recycle	()V
        //   69: aload_2
        //   70: invokevirtual 58	android/os/Parcel:recycle	()V
        //   73: aload_1
        //   74: athrow
        // Local variable table:
        //   start	length	slot	name	signature
        //   0	75	0	this	zza
        //   0	75	1	paramSessionReadRequest	SessionReadRequest
        //   3	67	2	localParcel1	Parcel
        //   7	59	3	localParcel2	Parcel
        // Exception table:
        //   from	to	target	type
        //   8	14	64	finally
        //   18	29	64	finally
        //   29	47	64	finally
        //   56	61	64	finally
      }
      
      /* Error */
      public void zza(SessionRegistrationRequest paramSessionRegistrationRequest)
        throws RemoteException
      {
        // Byte code:
        //   0: invokestatic 30	android/os/Parcel:obtain	()Landroid/os/Parcel;
        //   3: astore_2
        //   4: invokestatic 30	android/os/Parcel:obtain	()Landroid/os/Parcel;
        //   7: astore_3
        //   8: aload_2
        //   9: ldc 32
        //   11: invokevirtual 36	android/os/Parcel:writeInterfaceToken	(Ljava/lang/String;)V
        //   14: aload_1
        //   15: ifnull +41 -> 56
        //   18: aload_2
        //   19: iconst_1
        //   20: invokevirtual 40	android/os/Parcel:writeInt	(I)V
        //   23: aload_1
        //   24: aload_2
        //   25: iconst_0
        //   26: invokevirtual 67	com/google/android/gms/fitness/request/SessionRegistrationRequest:writeToParcel	(Landroid/os/Parcel;I)V
        //   29: aload_0
        //   30: getfield 18	com/google/android/gms/internal/zzoq$zza$zza:zzoz	Landroid/os/IBinder;
        //   33: iconst_5
        //   34: aload_2
        //   35: aload_3
        //   36: iconst_0
        //   37: invokeinterface 52 5 0
        //   42: pop
        //   43: aload_3
        //   44: invokevirtual 55	android/os/Parcel:readException	()V
        //   47: aload_3
        //   48: invokevirtual 58	android/os/Parcel:recycle	()V
        //   51: aload_2
        //   52: invokevirtual 58	android/os/Parcel:recycle	()V
        //   55: return
        //   56: aload_2
        //   57: iconst_0
        //   58: invokevirtual 40	android/os/Parcel:writeInt	(I)V
        //   61: goto -32 -> 29
        //   64: astore_1
        //   65: aload_3
        //   66: invokevirtual 58	android/os/Parcel:recycle	()V
        //   69: aload_2
        //   70: invokevirtual 58	android/os/Parcel:recycle	()V
        //   73: aload_1
        //   74: athrow
        // Local variable table:
        //   start	length	slot	name	signature
        //   0	75	0	this	zza
        //   0	75	1	paramSessionRegistrationRequest	SessionRegistrationRequest
        //   3	67	2	localParcel1	Parcel
        //   7	59	3	localParcel2	Parcel
        // Exception table:
        //   from	to	target	type
        //   8	14	64	finally
        //   18	29	64	finally
        //   29	47	64	finally
        //   56	61	64	finally
      }
      
      /* Error */
      public void zza(SessionStartRequest paramSessionStartRequest)
        throws RemoteException
      {
        // Byte code:
        //   0: invokestatic 30	android/os/Parcel:obtain	()Landroid/os/Parcel;
        //   3: astore_2
        //   4: invokestatic 30	android/os/Parcel:obtain	()Landroid/os/Parcel;
        //   7: astore_3
        //   8: aload_2
        //   9: ldc 32
        //   11: invokevirtual 36	android/os/Parcel:writeInterfaceToken	(Ljava/lang/String;)V
        //   14: aload_1
        //   15: ifnull +41 -> 56
        //   18: aload_2
        //   19: iconst_1
        //   20: invokevirtual 40	android/os/Parcel:writeInt	(I)V
        //   23: aload_1
        //   24: aload_2
        //   25: iconst_0
        //   26: invokevirtual 71	com/google/android/gms/fitness/request/SessionStartRequest:writeToParcel	(Landroid/os/Parcel;I)V
        //   29: aload_0
        //   30: getfield 18	com/google/android/gms/internal/zzoq$zza$zza:zzoz	Landroid/os/IBinder;
        //   33: iconst_1
        //   34: aload_2
        //   35: aload_3
        //   36: iconst_0
        //   37: invokeinterface 52 5 0
        //   42: pop
        //   43: aload_3
        //   44: invokevirtual 55	android/os/Parcel:readException	()V
        //   47: aload_3
        //   48: invokevirtual 58	android/os/Parcel:recycle	()V
        //   51: aload_2
        //   52: invokevirtual 58	android/os/Parcel:recycle	()V
        //   55: return
        //   56: aload_2
        //   57: iconst_0
        //   58: invokevirtual 40	android/os/Parcel:writeInt	(I)V
        //   61: goto -32 -> 29
        //   64: astore_1
        //   65: aload_3
        //   66: invokevirtual 58	android/os/Parcel:recycle	()V
        //   69: aload_2
        //   70: invokevirtual 58	android/os/Parcel:recycle	()V
        //   73: aload_1
        //   74: athrow
        // Local variable table:
        //   start	length	slot	name	signature
        //   0	75	0	this	zza
        //   0	75	1	paramSessionStartRequest	SessionStartRequest
        //   3	67	2	localParcel1	Parcel
        //   7	59	3	localParcel2	Parcel
        // Exception table:
        //   from	to	target	type
        //   8	14	64	finally
        //   18	29	64	finally
        //   29	47	64	finally
        //   56	61	64	finally
      }
      
      /* Error */
      public void zza(SessionStopRequest paramSessionStopRequest)
        throws RemoteException
      {
        // Byte code:
        //   0: invokestatic 30	android/os/Parcel:obtain	()Landroid/os/Parcel;
        //   3: astore_2
        //   4: invokestatic 30	android/os/Parcel:obtain	()Landroid/os/Parcel;
        //   7: astore_3
        //   8: aload_2
        //   9: ldc 32
        //   11: invokevirtual 36	android/os/Parcel:writeInterfaceToken	(Ljava/lang/String;)V
        //   14: aload_1
        //   15: ifnull +41 -> 56
        //   18: aload_2
        //   19: iconst_1
        //   20: invokevirtual 40	android/os/Parcel:writeInt	(I)V
        //   23: aload_1
        //   24: aload_2
        //   25: iconst_0
        //   26: invokevirtual 75	com/google/android/gms/fitness/request/SessionStopRequest:writeToParcel	(Landroid/os/Parcel;I)V
        //   29: aload_0
        //   30: getfield 18	com/google/android/gms/internal/zzoq$zza$zza:zzoz	Landroid/os/IBinder;
        //   33: iconst_2
        //   34: aload_2
        //   35: aload_3
        //   36: iconst_0
        //   37: invokeinterface 52 5 0
        //   42: pop
        //   43: aload_3
        //   44: invokevirtual 55	android/os/Parcel:readException	()V
        //   47: aload_3
        //   48: invokevirtual 58	android/os/Parcel:recycle	()V
        //   51: aload_2
        //   52: invokevirtual 58	android/os/Parcel:recycle	()V
        //   55: return
        //   56: aload_2
        //   57: iconst_0
        //   58: invokevirtual 40	android/os/Parcel:writeInt	(I)V
        //   61: goto -32 -> 29
        //   64: astore_1
        //   65: aload_3
        //   66: invokevirtual 58	android/os/Parcel:recycle	()V
        //   69: aload_2
        //   70: invokevirtual 58	android/os/Parcel:recycle	()V
        //   73: aload_1
        //   74: athrow
        // Local variable table:
        //   start	length	slot	name	signature
        //   0	75	0	this	zza
        //   0	75	1	paramSessionStopRequest	SessionStopRequest
        //   3	67	2	localParcel1	Parcel
        //   7	59	3	localParcel2	Parcel
        // Exception table:
        //   from	to	target	type
        //   8	14	64	finally
        //   18	29	64	finally
        //   29	47	64	finally
        //   56	61	64	finally
      }
      
      /* Error */
      public void zza(SessionUnregistrationRequest paramSessionUnregistrationRequest)
        throws RemoteException
      {
        // Byte code:
        //   0: invokestatic 30	android/os/Parcel:obtain	()Landroid/os/Parcel;
        //   3: astore_2
        //   4: invokestatic 30	android/os/Parcel:obtain	()Landroid/os/Parcel;
        //   7: astore_3
        //   8: aload_2
        //   9: ldc 32
        //   11: invokevirtual 36	android/os/Parcel:writeInterfaceToken	(Ljava/lang/String;)V
        //   14: aload_1
        //   15: ifnull +42 -> 57
        //   18: aload_2
        //   19: iconst_1
        //   20: invokevirtual 40	android/os/Parcel:writeInt	(I)V
        //   23: aload_1
        //   24: aload_2
        //   25: iconst_0
        //   26: invokevirtual 79	com/google/android/gms/fitness/request/SessionUnregistrationRequest:writeToParcel	(Landroid/os/Parcel;I)V
        //   29: aload_0
        //   30: getfield 18	com/google/android/gms/internal/zzoq$zza$zza:zzoz	Landroid/os/IBinder;
        //   33: bipush 6
        //   35: aload_2
        //   36: aload_3
        //   37: iconst_0
        //   38: invokeinterface 52 5 0
        //   43: pop
        //   44: aload_3
        //   45: invokevirtual 55	android/os/Parcel:readException	()V
        //   48: aload_3
        //   49: invokevirtual 58	android/os/Parcel:recycle	()V
        //   52: aload_2
        //   53: invokevirtual 58	android/os/Parcel:recycle	()V
        //   56: return
        //   57: aload_2
        //   58: iconst_0
        //   59: invokevirtual 40	android/os/Parcel:writeInt	(I)V
        //   62: goto -33 -> 29
        //   65: astore_1
        //   66: aload_3
        //   67: invokevirtual 58	android/os/Parcel:recycle	()V
        //   70: aload_2
        //   71: invokevirtual 58	android/os/Parcel:recycle	()V
        //   74: aload_1
        //   75: athrow
        // Local variable table:
        //   start	length	slot	name	signature
        //   0	76	0	this	zza
        //   0	76	1	paramSessionUnregistrationRequest	SessionUnregistrationRequest
        //   3	68	2	localParcel1	Parcel
        //   7	60	3	localParcel2	Parcel
        // Exception table:
        //   from	to	target	type
        //   8	14	65	finally
        //   18	29	65	finally
        //   29	48	65	finally
        //   57	62	65	finally
      }
    }
  }
}


/* Location:              C:\Users\Genbu Hase\ÉhÉLÉÖÉÅÉìÉg\Genbu\Tool\Programing\Jad\BlockLauncher 1.12.8.jar!\com\google\android\gms\internal\zzoq.class
 * Java compiler version: 6 (50.0)
 * JD-Core Version:       0.7.1-SNAPSHOT-20140817
 */