package com.google.android.gms.drive.realtime.internal;

import android.os.Binder;
import android.os.IBinder;
import android.os.IInterface;
import android.os.Parcel;
import android.os.Parcelable.Creator;
import android.os.RemoteException;
import com.google.android.gms.common.data.DataHolder;
import com.google.android.gms.drive.DriveId;
import com.google.android.gms.drive.realtime.internal.event.ParcelableEventList;

public abstract interface zzm
  extends IInterface
{
  public abstract void zza(int paramInt, zzj paramzzj)
    throws RemoteException;
  
  public abstract void zza(int paramInt, zzo paramzzo)
    throws RemoteException;
  
  public abstract void zza(DriveId paramDriveId, zzo paramzzo)
    throws RemoteException;
  
  public abstract void zza(BeginCompoundOperationRequest paramBeginCompoundOperationRequest, zzo paramzzo)
    throws RemoteException;
  
  public abstract void zza(EndCompoundOperationRequest paramEndCompoundOperationRequest, zzj paramzzj)
    throws RemoteException;
  
  public abstract void zza(EndCompoundOperationRequest paramEndCompoundOperationRequest, zzo paramzzo)
    throws RemoteException;
  
  public abstract void zza(ParcelableIndexReference paramParcelableIndexReference, zzn paramzzn)
    throws RemoteException;
  
  public abstract void zza(zzc paramzzc)
    throws RemoteException;
  
  public abstract void zza(zzd paramzzd)
    throws RemoteException;
  
  public abstract void zza(zze paramzze)
    throws RemoteException;
  
  public abstract void zza(zzh paramzzh)
    throws RemoteException;
  
  public abstract void zza(zzi paramzzi)
    throws RemoteException;
  
  public abstract void zza(zzj paramzzj)
    throws RemoteException;
  
  public abstract void zza(zzl paramzzl)
    throws RemoteException;
  
  public abstract void zza(zzo paramzzo)
    throws RemoteException;
  
  public abstract void zza(String paramString, int paramInt1, int paramInt2, zzg paramzzg)
    throws RemoteException;
  
  public abstract void zza(String paramString, int paramInt1, int paramInt2, zzj paramzzj)
    throws RemoteException;
  
  public abstract void zza(String paramString, int paramInt, DataHolder paramDataHolder, zzg paramzzg)
    throws RemoteException;
  
  public abstract void zza(String paramString, int paramInt, DataHolder paramDataHolder, zzj paramzzj)
    throws RemoteException;
  
  public abstract void zza(String paramString, int paramInt, zzn paramzzn)
    throws RemoteException;
  
  public abstract void zza(String paramString, int paramInt, zzo paramzzo)
    throws RemoteException;
  
  public abstract void zza(String paramString1, int paramInt1, String paramString2, int paramInt2, zzj paramzzj)
    throws RemoteException;
  
  public abstract void zza(String paramString1, int paramInt, String paramString2, zzj paramzzj)
    throws RemoteException;
  
  public abstract void zza(String paramString, DataHolder paramDataHolder, zzj paramzzj)
    throws RemoteException;
  
  public abstract void zza(String paramString, zzf paramzzf)
    throws RemoteException;
  
  public abstract void zza(String paramString, zzj paramzzj)
    throws RemoteException;
  
  public abstract void zza(String paramString, zzk paramzzk)
    throws RemoteException;
  
  public abstract void zza(String paramString, zzl paramzzl)
    throws RemoteException;
  
  public abstract void zza(String paramString, zzn paramzzn)
    throws RemoteException;
  
  public abstract void zza(String paramString, zzo paramzzo)
    throws RemoteException;
  
  public abstract void zza(String paramString1, String paramString2, DataHolder paramDataHolder, zzj paramzzj)
    throws RemoteException;
  
  public abstract void zza(String paramString1, String paramString2, zzf paramzzf)
    throws RemoteException;
  
  public abstract void zza(String paramString1, String paramString2, zzg paramzzg)
    throws RemoteException;
  
  public abstract void zza(String paramString1, String paramString2, zzj paramzzj)
    throws RemoteException;
  
  public abstract void zza(boolean paramBoolean, zzo paramzzo)
    throws RemoteException;
  
  public abstract void zzb(zzc paramzzc)
    throws RemoteException;
  
  public abstract void zzb(zzj paramzzj)
    throws RemoteException;
  
  public abstract void zzb(zzl paramzzl)
    throws RemoteException;
  
  public abstract void zzb(zzo paramzzo)
    throws RemoteException;
  
  public abstract void zzb(String paramString, zzf paramzzf)
    throws RemoteException;
  
  public abstract void zzb(String paramString, zzl paramzzl)
    throws RemoteException;
  
  public abstract void zzb(String paramString, zzn paramzzn)
    throws RemoteException;
  
  public abstract void zzb(String paramString, zzo paramzzo)
    throws RemoteException;
  
  public abstract void zzb(String paramString1, String paramString2, zzf paramzzf)
    throws RemoteException;
  
  public abstract void zzc(zzc paramzzc)
    throws RemoteException;
  
  public abstract void zzc(zzo paramzzo)
    throws RemoteException;
  
  public abstract void zzc(String paramString, zzl paramzzl)
    throws RemoteException;
  
  public abstract void zzd(zzc paramzzc)
    throws RemoteException;
  
  public abstract void zze(zzc paramzzc)
    throws RemoteException;
  
  public abstract ParcelableEventList zzf(String paramString1, String paramString2, String paramString3)
    throws RemoteException;
  
  public abstract void zztT()
    throws RemoteException;
  
  public static abstract class zza
    extends Binder
    implements zzm
  {
    public static zzm zzbo(IBinder paramIBinder)
    {
      if (paramIBinder == null) {
        return null;
      }
      IInterface localIInterface = paramIBinder.queryLocalInterface("com.google.android.gms.drive.realtime.internal.IRealtimeService");
      if ((localIInterface != null) && ((localIInterface instanceof zzm))) {
        return (zzm)localIInterface;
      }
      return new zza(paramIBinder);
    }
    
    public boolean onTransact(int paramInt1, Parcel paramParcel1, Parcel paramParcel2, int paramInt2)
      throws RemoteException
    {
      String str2 = null;
      Object localObject2 = null;
      Object localObject3 = null;
      Object localObject4 = null;
      Object localObject5 = null;
      Object localObject1 = null;
      Object localObject6 = null;
      Object localObject7 = null;
      String str1 = null;
      switch (paramInt1)
      {
      default: 
        return super.onTransact(paramInt1, paramParcel1, paramParcel2, paramInt2);
      case 1598968902: 
        paramParcel2.writeString("com.google.android.gms.drive.realtime.internal.IRealtimeService");
        return true;
      case 1: 
        paramParcel1.enforceInterface("com.google.android.gms.drive.realtime.internal.IRealtimeService");
        zza(paramParcel1.readString(), zzn.zza.zzbp(paramParcel1.readStrongBinder()));
        paramParcel2.writeNoException();
        return true;
      case 2: 
        paramParcel1.enforceInterface("com.google.android.gms.drive.realtime.internal.IRealtimeService");
        zza(zzc.zza.zzbe(paramParcel1.readStrongBinder()));
        paramParcel2.writeNoException();
        return true;
      case 3: 
        paramParcel1.enforceInterface("com.google.android.gms.drive.realtime.internal.IRealtimeService");
        zza(zzo.zza.zzbq(paramParcel1.readStrongBinder()));
        paramParcel2.writeNoException();
        return true;
      case 33: 
        paramParcel1.enforceInterface("com.google.android.gms.drive.realtime.internal.IRealtimeService");
        zzb(zzc.zza.zzbe(paramParcel1.readStrongBinder()));
        paramParcel2.writeNoException();
        return true;
      case 35: 
        paramParcel1.enforceInterface("com.google.android.gms.drive.realtime.internal.IRealtimeService");
        zzb(zzo.zza.zzbq(paramParcel1.readStrongBinder()));
        paramParcel2.writeNoException();
        return true;
      case 40: 
        paramParcel1.enforceInterface("com.google.android.gms.drive.realtime.internal.IRealtimeService");
        zza(zzl.zza.zzbn(paramParcel1.readStrongBinder()));
        paramParcel2.writeNoException();
        return true;
      case 45: 
        paramParcel1.enforceInterface("com.google.android.gms.drive.realtime.internal.IRealtimeService");
        zzc(zzc.zza.zzbe(paramParcel1.readStrongBinder()));
        paramParcel2.writeNoException();
        return true;
      case 46: 
        paramParcel1.enforceInterface("com.google.android.gms.drive.realtime.internal.IRealtimeService");
        zza(paramParcel1.readString(), paramParcel1.readInt(), zzn.zza.zzbp(paramParcel1.readStrongBinder()));
        paramParcel2.writeNoException();
        return true;
      case 4: 
        paramParcel1.enforceInterface("com.google.android.gms.drive.realtime.internal.IRealtimeService");
        zza(paramParcel1.readString(), paramParcel1.readString(), zzf.zza.zzbh(paramParcel1.readStrongBinder()));
        paramParcel2.writeNoException();
        return true;
      case 5: 
        paramParcel1.enforceInterface("com.google.android.gms.drive.realtime.internal.IRealtimeService");
        zza(paramParcel1.readString(), zzl.zza.zzbn(paramParcel1.readStrongBinder()));
        paramParcel2.writeNoException();
        return true;
      case 6: 
        paramParcel1.enforceInterface("com.google.android.gms.drive.realtime.internal.IRealtimeService");
        str2 = paramParcel1.readString();
        localObject1 = str1;
        if (paramParcel1.readInt() != 0) {
          localObject1 = DataHolder.CREATOR.zzak(paramParcel1);
        }
        zza(str2, (DataHolder)localObject1, zzj.zza.zzbl(paramParcel1.readStrongBinder()));
        paramParcel2.writeNoException();
        return true;
      case 7: 
        paramParcel1.enforceInterface("com.google.android.gms.drive.realtime.internal.IRealtimeService");
        zza(paramParcel1.readString(), zzj.zza.zzbl(paramParcel1.readStrongBinder()));
        paramParcel2.writeNoException();
        return true;
      case 20: 
        paramParcel1.enforceInterface("com.google.android.gms.drive.realtime.internal.IRealtimeService");
        zza(paramParcel1.readString(), zzf.zza.zzbh(paramParcel1.readStrongBinder()));
        paramParcel2.writeNoException();
        return true;
      case 21: 
        paramParcel1.enforceInterface("com.google.android.gms.drive.realtime.internal.IRealtimeService");
        zza(paramParcel1.readString(), paramParcel1.readString(), zzg.zza.zzbi(paramParcel1.readStrongBinder()));
        paramParcel2.writeNoException();
        return true;
      case 8: 
        paramParcel1.enforceInterface("com.google.android.gms.drive.realtime.internal.IRealtimeService");
        zzb(paramParcel1.readString(), zzl.zza.zzbn(paramParcel1.readStrongBinder()));
        paramParcel2.writeNoException();
        return true;
      case 9: 
        paramParcel1.enforceInterface("com.google.android.gms.drive.realtime.internal.IRealtimeService");
        zzb(paramParcel1.readString(), zzn.zza.zzbp(paramParcel1.readStrongBinder()));
        paramParcel2.writeNoException();
        return true;
      case 10: 
        paramParcel1.enforceInterface("com.google.android.gms.drive.realtime.internal.IRealtimeService");
        zza(paramParcel1.readString(), paramParcel1.readInt(), paramParcel1.readString(), zzj.zza.zzbl(paramParcel1.readStrongBinder()));
        paramParcel2.writeNoException();
        return true;
      case 11: 
        paramParcel1.enforceInterface("com.google.android.gms.drive.realtime.internal.IRealtimeService");
        zza(paramParcel1.readString(), paramParcel1.readInt(), paramParcel1.readInt(), zzj.zza.zzbl(paramParcel1.readStrongBinder()));
        paramParcel2.writeNoException();
        return true;
      case 12: 
        paramParcel1.enforceInterface("com.google.android.gms.drive.realtime.internal.IRealtimeService");
        zza(paramParcel1.readString(), paramParcel1.readString(), zzj.zza.zzbl(paramParcel1.readStrongBinder()));
        paramParcel2.writeNoException();
        return true;
      case 13: 
        paramParcel1.enforceInterface("com.google.android.gms.drive.realtime.internal.IRealtimeService");
        zzb(paramParcel1.readString(), zzf.zza.zzbh(paramParcel1.readStrongBinder()));
        paramParcel2.writeNoException();
        return true;
      case 14: 
        paramParcel1.enforceInterface("com.google.android.gms.drive.realtime.internal.IRealtimeService");
        zzc(paramParcel1.readString(), zzl.zza.zzbn(paramParcel1.readStrongBinder()));
        paramParcel2.writeNoException();
        return true;
      case 15: 
        paramParcel1.enforceInterface("com.google.android.gms.drive.realtime.internal.IRealtimeService");
        str1 = paramParcel1.readString();
        paramInt1 = paramParcel1.readInt();
        localObject1 = str2;
        if (paramParcel1.readInt() != 0) {
          localObject1 = DataHolder.CREATOR.zzak(paramParcel1);
        }
        zza(str1, paramInt1, (DataHolder)localObject1, zzj.zza.zzbl(paramParcel1.readStrongBinder()));
        paramParcel2.writeNoException();
        return true;
      case 16: 
        paramParcel1.enforceInterface("com.google.android.gms.drive.realtime.internal.IRealtimeService");
        str1 = paramParcel1.readString();
        paramInt1 = paramParcel1.readInt();
        localObject1 = localObject2;
        if (paramParcel1.readInt() != 0) {
          localObject1 = DataHolder.CREATOR.zzak(paramParcel1);
        }
        zza(str1, paramInt1, (DataHolder)localObject1, zzg.zza.zzbi(paramParcel1.readStrongBinder()));
        paramParcel2.writeNoException();
        return true;
      case 17: 
        paramParcel1.enforceInterface("com.google.android.gms.drive.realtime.internal.IRealtimeService");
        zza(paramParcel1.readString(), paramParcel1.readInt(), paramParcel1.readInt(), zzg.zza.zzbi(paramParcel1.readStrongBinder()));
        paramParcel2.writeNoException();
        return true;
      case 37: 
        paramParcel1.enforceInterface("com.google.android.gms.drive.realtime.internal.IRealtimeService");
        zza(paramParcel1.readString(), paramParcel1.readInt(), paramParcel1.readString(), paramParcel1.readInt(), zzj.zza.zzbl(paramParcel1.readStrongBinder()));
        paramParcel2.writeNoException();
        return true;
      case 18: 
        paramParcel1.enforceInterface("com.google.android.gms.drive.realtime.internal.IRealtimeService");
        localObject1 = localObject3;
        if (paramParcel1.readInt() != 0) {
          localObject1 = (BeginCompoundOperationRequest)BeginCompoundOperationRequest.CREATOR.createFromParcel(paramParcel1);
        }
        zza((BeginCompoundOperationRequest)localObject1, zzo.zza.zzbq(paramParcel1.readStrongBinder()));
        paramParcel2.writeNoException();
        return true;
      case 41: 
        paramParcel1.enforceInterface("com.google.android.gms.drive.realtime.internal.IRealtimeService");
        localObject1 = localObject4;
        if (paramParcel1.readInt() != 0) {
          localObject1 = (EndCompoundOperationRequest)EndCompoundOperationRequest.CREATOR.createFromParcel(paramParcel1);
        }
        zza((EndCompoundOperationRequest)localObject1, zzj.zza.zzbl(paramParcel1.readStrongBinder()));
        paramParcel2.writeNoException();
        return true;
      case 22: 
        paramParcel1.enforceInterface("com.google.android.gms.drive.realtime.internal.IRealtimeService");
        zza(zzj.zza.zzbl(paramParcel1.readStrongBinder()));
        paramParcel2.writeNoException();
        return true;
      case 23: 
        paramParcel1.enforceInterface("com.google.android.gms.drive.realtime.internal.IRealtimeService");
        zzb(zzj.zza.zzbl(paramParcel1.readStrongBinder()));
        paramParcel2.writeNoException();
        return true;
      case 24: 
        paramParcel1.enforceInterface("com.google.android.gms.drive.realtime.internal.IRealtimeService");
        zzd(zzc.zza.zzbe(paramParcel1.readStrongBinder()));
        paramParcel2.writeNoException();
        return true;
      case 25: 
        paramParcel1.enforceInterface("com.google.android.gms.drive.realtime.internal.IRealtimeService");
        zze(zzc.zza.zzbe(paramParcel1.readStrongBinder()));
        paramParcel2.writeNoException();
        return true;
      case 47: 
        paramParcel1.enforceInterface("com.google.android.gms.drive.realtime.internal.IRealtimeService");
        if (paramParcel1.readInt() != 0) {}
        for (boolean bool = true;; bool = false)
        {
          zza(bool, zzo.zza.zzbq(paramParcel1.readStrongBinder()));
          paramParcel2.writeNoException();
          return true;
        }
      case 50: 
        paramParcel1.enforceInterface("com.google.android.gms.drive.realtime.internal.IRealtimeService");
        zza(paramParcel1.readInt(), zzo.zza.zzbq(paramParcel1.readStrongBinder()));
        paramParcel2.writeNoException();
        return true;
      case 26: 
        paramParcel1.enforceInterface("com.google.android.gms.drive.realtime.internal.IRealtimeService");
        localObject1 = localObject5;
        if (paramParcel1.readInt() != 0) {
          localObject1 = (ParcelableIndexReference)ParcelableIndexReference.CREATOR.createFromParcel(paramParcel1);
        }
        zza((ParcelableIndexReference)localObject1, zzn.zza.zzbp(paramParcel1.readStrongBinder()));
        paramParcel2.writeNoException();
        return true;
      case 27: 
        paramParcel1.enforceInterface("com.google.android.gms.drive.realtime.internal.IRealtimeService");
        zza(paramParcel1.readString(), zzk.zza.zzbm(paramParcel1.readStrongBinder()));
        paramParcel2.writeNoException();
        return true;
      case 28: 
        paramParcel1.enforceInterface("com.google.android.gms.drive.realtime.internal.IRealtimeService");
        zza(paramParcel1.readString(), paramParcel1.readInt(), zzo.zza.zzbq(paramParcel1.readStrongBinder()));
        paramParcel2.writeNoException();
        return true;
      case 29: 
        paramParcel1.enforceInterface("com.google.android.gms.drive.realtime.internal.IRealtimeService");
        zzb(zzl.zza.zzbn(paramParcel1.readStrongBinder()));
        paramParcel2.writeNoException();
        return true;
      case 30: 
        paramParcel1.enforceInterface("com.google.android.gms.drive.realtime.internal.IRealtimeService");
        zza(paramParcel1.readInt(), zzj.zza.zzbl(paramParcel1.readStrongBinder()));
        paramParcel2.writeNoException();
        return true;
      case 31: 
        paramParcel1.enforceInterface("com.google.android.gms.drive.realtime.internal.IRealtimeService");
        zza(zze.zza.zzbg(paramParcel1.readStrongBinder()));
        paramParcel2.writeNoException();
        return true;
      case 32: 
        paramParcel1.enforceInterface("com.google.android.gms.drive.realtime.internal.IRealtimeService");
        zza(zzd.zza.zzbf(paramParcel1.readStrongBinder()));
        paramParcel2.writeNoException();
        return true;
      case 34: 
        paramParcel1.enforceInterface("com.google.android.gms.drive.realtime.internal.IRealtimeService");
        zza(zzi.zza.zzbk(paramParcel1.readStrongBinder()));
        paramParcel2.writeNoException();
        return true;
      case 36: 
        paramParcel1.enforceInterface("com.google.android.gms.drive.realtime.internal.IRealtimeService");
        zza(zzh.zza.zzbj(paramParcel1.readStrongBinder()));
        paramParcel2.writeNoException();
        return true;
      case 38: 
        paramParcel1.enforceInterface("com.google.android.gms.drive.realtime.internal.IRealtimeService");
        zza(paramParcel1.readString(), zzo.zza.zzbq(paramParcel1.readStrongBinder()));
        paramParcel2.writeNoException();
        return true;
      case 39: 
        paramParcel1.enforceInterface("com.google.android.gms.drive.realtime.internal.IRealtimeService");
        zzb(paramParcel1.readString(), zzo.zza.zzbq(paramParcel1.readStrongBinder()));
        paramParcel2.writeNoException();
        return true;
      case 42: 
        paramParcel1.enforceInterface("com.google.android.gms.drive.realtime.internal.IRealtimeService");
        zzb(paramParcel1.readString(), paramParcel1.readString(), zzf.zza.zzbh(paramParcel1.readStrongBinder()));
        paramParcel2.writeNoException();
        return true;
      case 43: 
        paramParcel1.enforceInterface("com.google.android.gms.drive.realtime.internal.IRealtimeService");
        str1 = paramParcel1.readString();
        str2 = paramParcel1.readString();
        if (paramParcel1.readInt() != 0) {
          localObject1 = DataHolder.CREATOR.zzak(paramParcel1);
        }
        zza(str1, str2, (DataHolder)localObject1, zzj.zza.zzbl(paramParcel1.readStrongBinder()));
        paramParcel2.writeNoException();
        return true;
      case 44: 
        paramParcel1.enforceInterface("com.google.android.gms.drive.realtime.internal.IRealtimeService");
        zztT();
        paramParcel2.writeNoException();
        return true;
      case 48: 
        paramParcel1.enforceInterface("com.google.android.gms.drive.realtime.internal.IRealtimeService");
        localObject1 = localObject6;
        if (paramParcel1.readInt() != 0) {
          localObject1 = (DriveId)DriveId.CREATOR.createFromParcel(paramParcel1);
        }
        zza((DriveId)localObject1, zzo.zza.zzbq(paramParcel1.readStrongBinder()));
        paramParcel2.writeNoException();
        return true;
      case 49: 
        paramParcel1.enforceInterface("com.google.android.gms.drive.realtime.internal.IRealtimeService");
        zzc(zzo.zza.zzbq(paramParcel1.readStrongBinder()));
        paramParcel2.writeNoException();
        return true;
      case 19: 
        paramParcel1.enforceInterface("com.google.android.gms.drive.realtime.internal.IRealtimeService");
        localObject1 = localObject7;
        if (paramParcel1.readInt() != 0) {
          localObject1 = (EndCompoundOperationRequest)EndCompoundOperationRequest.CREATOR.createFromParcel(paramParcel1);
        }
        zza((EndCompoundOperationRequest)localObject1, zzo.zza.zzbq(paramParcel1.readStrongBinder()));
        paramParcel2.writeNoException();
        return true;
      }
      paramParcel1.enforceInterface("com.google.android.gms.drive.realtime.internal.IRealtimeService");
      paramParcel1 = zzf(paramParcel1.readString(), paramParcel1.readString(), paramParcel1.readString());
      paramParcel2.writeNoException();
      if (paramParcel1 != null)
      {
        paramParcel2.writeInt(1);
        paramParcel1.writeToParcel(paramParcel2, 1);
        return true;
      }
      paramParcel2.writeInt(0);
      return true;
    }
    
    private static class zza
      implements zzm
    {
      private IBinder zzoz;
      
      zza(IBinder paramIBinder)
      {
        this.zzoz = paramIBinder;
      }
      
      public IBinder asBinder()
      {
        return this.zzoz;
      }
      
      /* Error */
      public void zza(int paramInt, zzj paramzzj)
        throws RemoteException
      {
        // Byte code:
        //   0: invokestatic 30	android/os/Parcel:obtain	()Landroid/os/Parcel;
        //   3: astore_3
        //   4: invokestatic 30	android/os/Parcel:obtain	()Landroid/os/Parcel;
        //   7: astore 4
        //   9: aload_3
        //   10: ldc 32
        //   12: invokevirtual 36	android/os/Parcel:writeInterfaceToken	(Ljava/lang/String;)V
        //   15: aload_3
        //   16: iload_1
        //   17: invokevirtual 40	android/os/Parcel:writeInt	(I)V
        //   20: aload_2
        //   21: ifnull +46 -> 67
        //   24: aload_2
        //   25: invokeinterface 44 1 0
        //   30: astore_2
        //   31: aload_3
        //   32: aload_2
        //   33: invokevirtual 47	android/os/Parcel:writeStrongBinder	(Landroid/os/IBinder;)V
        //   36: aload_0
        //   37: getfield 18	com/google/android/gms/drive/realtime/internal/zzm$zza$zza:zzoz	Landroid/os/IBinder;
        //   40: bipush 30
        //   42: aload_3
        //   43: aload 4
        //   45: iconst_0
        //   46: invokeinterface 53 5 0
        //   51: pop
        //   52: aload 4
        //   54: invokevirtual 56	android/os/Parcel:readException	()V
        //   57: aload 4
        //   59: invokevirtual 59	android/os/Parcel:recycle	()V
        //   62: aload_3
        //   63: invokevirtual 59	android/os/Parcel:recycle	()V
        //   66: return
        //   67: aconst_null
        //   68: astore_2
        //   69: goto -38 -> 31
        //   72: astore_2
        //   73: aload 4
        //   75: invokevirtual 59	android/os/Parcel:recycle	()V
        //   78: aload_3
        //   79: invokevirtual 59	android/os/Parcel:recycle	()V
        //   82: aload_2
        //   83: athrow
        // Local variable table:
        //   start	length	slot	name	signature
        //   0	84	0	this	zza
        //   0	84	1	paramInt	int
        //   0	84	2	paramzzj	zzj
        //   3	76	3	localParcel1	Parcel
        //   7	67	4	localParcel2	Parcel
        // Exception table:
        //   from	to	target	type
        //   9	20	72	finally
        //   24	31	72	finally
        //   31	57	72	finally
      }
      
      /* Error */
      public void zza(int paramInt, zzo paramzzo)
        throws RemoteException
      {
        // Byte code:
        //   0: invokestatic 30	android/os/Parcel:obtain	()Landroid/os/Parcel;
        //   3: astore_3
        //   4: invokestatic 30	android/os/Parcel:obtain	()Landroid/os/Parcel;
        //   7: astore 4
        //   9: aload_3
        //   10: ldc 32
        //   12: invokevirtual 36	android/os/Parcel:writeInterfaceToken	(Ljava/lang/String;)V
        //   15: aload_3
        //   16: iload_1
        //   17: invokevirtual 40	android/os/Parcel:writeInt	(I)V
        //   20: aload_2
        //   21: ifnull +46 -> 67
        //   24: aload_2
        //   25: invokeinterface 64 1 0
        //   30: astore_2
        //   31: aload_3
        //   32: aload_2
        //   33: invokevirtual 47	android/os/Parcel:writeStrongBinder	(Landroid/os/IBinder;)V
        //   36: aload_0
        //   37: getfield 18	com/google/android/gms/drive/realtime/internal/zzm$zza$zza:zzoz	Landroid/os/IBinder;
        //   40: bipush 50
        //   42: aload_3
        //   43: aload 4
        //   45: iconst_0
        //   46: invokeinterface 53 5 0
        //   51: pop
        //   52: aload 4
        //   54: invokevirtual 56	android/os/Parcel:readException	()V
        //   57: aload 4
        //   59: invokevirtual 59	android/os/Parcel:recycle	()V
        //   62: aload_3
        //   63: invokevirtual 59	android/os/Parcel:recycle	()V
        //   66: return
        //   67: aconst_null
        //   68: astore_2
        //   69: goto -38 -> 31
        //   72: astore_2
        //   73: aload 4
        //   75: invokevirtual 59	android/os/Parcel:recycle	()V
        //   78: aload_3
        //   79: invokevirtual 59	android/os/Parcel:recycle	()V
        //   82: aload_2
        //   83: athrow
        // Local variable table:
        //   start	length	slot	name	signature
        //   0	84	0	this	zza
        //   0	84	1	paramInt	int
        //   0	84	2	paramzzo	zzo
        //   3	76	3	localParcel1	Parcel
        //   7	67	4	localParcel2	Parcel
        // Exception table:
        //   from	to	target	type
        //   9	20	72	finally
        //   24	31	72	finally
        //   31	57	72	finally
      }
      
      public void zza(DriveId paramDriveId, zzo paramzzo)
        throws RemoteException
      {
        Parcel localParcel1 = Parcel.obtain();
        Parcel localParcel2 = Parcel.obtain();
        for (;;)
        {
          try
          {
            localParcel1.writeInterfaceToken("com.google.android.gms.drive.realtime.internal.IRealtimeService");
            if (paramDriveId != null)
            {
              localParcel1.writeInt(1);
              paramDriveId.writeToParcel(localParcel1, 0);
              if (paramzzo != null)
              {
                paramDriveId = paramzzo.asBinder();
                localParcel1.writeStrongBinder(paramDriveId);
                this.zzoz.transact(48, localParcel1, localParcel2, 0);
                localParcel2.readException();
              }
            }
            else
            {
              localParcel1.writeInt(0);
              continue;
            }
            paramDriveId = null;
          }
          finally
          {
            localParcel2.recycle();
            localParcel1.recycle();
          }
        }
      }
      
      public void zza(BeginCompoundOperationRequest paramBeginCompoundOperationRequest, zzo paramzzo)
        throws RemoteException
      {
        Parcel localParcel1 = Parcel.obtain();
        Parcel localParcel2 = Parcel.obtain();
        for (;;)
        {
          try
          {
            localParcel1.writeInterfaceToken("com.google.android.gms.drive.realtime.internal.IRealtimeService");
            if (paramBeginCompoundOperationRequest != null)
            {
              localParcel1.writeInt(1);
              paramBeginCompoundOperationRequest.writeToParcel(localParcel1, 0);
              if (paramzzo != null)
              {
                paramBeginCompoundOperationRequest = paramzzo.asBinder();
                localParcel1.writeStrongBinder(paramBeginCompoundOperationRequest);
                this.zzoz.transact(18, localParcel1, localParcel2, 0);
                localParcel2.readException();
              }
            }
            else
            {
              localParcel1.writeInt(0);
              continue;
            }
            paramBeginCompoundOperationRequest = null;
          }
          finally
          {
            localParcel2.recycle();
            localParcel1.recycle();
          }
        }
      }
      
      public void zza(EndCompoundOperationRequest paramEndCompoundOperationRequest, zzj paramzzj)
        throws RemoteException
      {
        Parcel localParcel1 = Parcel.obtain();
        Parcel localParcel2 = Parcel.obtain();
        for (;;)
        {
          try
          {
            localParcel1.writeInterfaceToken("com.google.android.gms.drive.realtime.internal.IRealtimeService");
            if (paramEndCompoundOperationRequest != null)
            {
              localParcel1.writeInt(1);
              paramEndCompoundOperationRequest.writeToParcel(localParcel1, 0);
              if (paramzzj != null)
              {
                paramEndCompoundOperationRequest = paramzzj.asBinder();
                localParcel1.writeStrongBinder(paramEndCompoundOperationRequest);
                this.zzoz.transact(41, localParcel1, localParcel2, 0);
                localParcel2.readException();
              }
            }
            else
            {
              localParcel1.writeInt(0);
              continue;
            }
            paramEndCompoundOperationRequest = null;
          }
          finally
          {
            localParcel2.recycle();
            localParcel1.recycle();
          }
        }
      }
      
      public void zza(EndCompoundOperationRequest paramEndCompoundOperationRequest, zzo paramzzo)
        throws RemoteException
      {
        Parcel localParcel1 = Parcel.obtain();
        Parcel localParcel2 = Parcel.obtain();
        for (;;)
        {
          try
          {
            localParcel1.writeInterfaceToken("com.google.android.gms.drive.realtime.internal.IRealtimeService");
            if (paramEndCompoundOperationRequest != null)
            {
              localParcel1.writeInt(1);
              paramEndCompoundOperationRequest.writeToParcel(localParcel1, 0);
              if (paramzzo != null)
              {
                paramEndCompoundOperationRequest = paramzzo.asBinder();
                localParcel1.writeStrongBinder(paramEndCompoundOperationRequest);
                this.zzoz.transact(19, localParcel1, localParcel2, 0);
                localParcel2.readException();
              }
            }
            else
            {
              localParcel1.writeInt(0);
              continue;
            }
            paramEndCompoundOperationRequest = null;
          }
          finally
          {
            localParcel2.recycle();
            localParcel1.recycle();
          }
        }
      }
      
      public void zza(ParcelableIndexReference paramParcelableIndexReference, zzn paramzzn)
        throws RemoteException
      {
        Parcel localParcel1 = Parcel.obtain();
        Parcel localParcel2 = Parcel.obtain();
        for (;;)
        {
          try
          {
            localParcel1.writeInterfaceToken("com.google.android.gms.drive.realtime.internal.IRealtimeService");
            if (paramParcelableIndexReference != null)
            {
              localParcel1.writeInt(1);
              paramParcelableIndexReference.writeToParcel(localParcel1, 0);
              if (paramzzn != null)
              {
                paramParcelableIndexReference = paramzzn.asBinder();
                localParcel1.writeStrongBinder(paramParcelableIndexReference);
                this.zzoz.transact(26, localParcel1, localParcel2, 0);
                localParcel2.readException();
              }
            }
            else
            {
              localParcel1.writeInt(0);
              continue;
            }
            paramParcelableIndexReference = null;
          }
          finally
          {
            localParcel2.recycle();
            localParcel1.recycle();
          }
        }
      }
      
      /* Error */
      public void zza(zzc paramzzc)
        throws RemoteException
      {
        // Byte code:
        //   0: invokestatic 30	android/os/Parcel:obtain	()Landroid/os/Parcel;
        //   3: astore_2
        //   4: invokestatic 30	android/os/Parcel:obtain	()Landroid/os/Parcel;
        //   7: astore_3
        //   8: aload_2
        //   9: ldc 32
        //   11: invokevirtual 36	android/os/Parcel:writeInterfaceToken	(Ljava/lang/String;)V
        //   14: aload_1
        //   15: ifnull +42 -> 57
        //   18: aload_1
        //   19: invokeinterface 91 1 0
        //   24: astore_1
        //   25: aload_2
        //   26: aload_1
        //   27: invokevirtual 47	android/os/Parcel:writeStrongBinder	(Landroid/os/IBinder;)V
        //   30: aload_0
        //   31: getfield 18	com/google/android/gms/drive/realtime/internal/zzm$zza$zza:zzoz	Landroid/os/IBinder;
        //   34: iconst_2
        //   35: aload_2
        //   36: aload_3
        //   37: iconst_0
        //   38: invokeinterface 53 5 0
        //   43: pop
        //   44: aload_3
        //   45: invokevirtual 56	android/os/Parcel:readException	()V
        //   48: aload_3
        //   49: invokevirtual 59	android/os/Parcel:recycle	()V
        //   52: aload_2
        //   53: invokevirtual 59	android/os/Parcel:recycle	()V
        //   56: return
        //   57: aconst_null
        //   58: astore_1
        //   59: goto -34 -> 25
        //   62: astore_1
        //   63: aload_3
        //   64: invokevirtual 59	android/os/Parcel:recycle	()V
        //   67: aload_2
        //   68: invokevirtual 59	android/os/Parcel:recycle	()V
        //   71: aload_1
        //   72: athrow
        // Local variable table:
        //   start	length	slot	name	signature
        //   0	73	0	this	zza
        //   0	73	1	paramzzc	zzc
        //   3	65	2	localParcel1	Parcel
        //   7	57	3	localParcel2	Parcel
        // Exception table:
        //   from	to	target	type
        //   8	14	62	finally
        //   18	25	62	finally
        //   25	48	62	finally
      }
      
      /* Error */
      public void zza(zzd paramzzd)
        throws RemoteException
      {
        // Byte code:
        //   0: invokestatic 30	android/os/Parcel:obtain	()Landroid/os/Parcel;
        //   3: astore_2
        //   4: invokestatic 30	android/os/Parcel:obtain	()Landroid/os/Parcel;
        //   7: astore_3
        //   8: aload_2
        //   9: ldc 32
        //   11: invokevirtual 36	android/os/Parcel:writeInterfaceToken	(Ljava/lang/String;)V
        //   14: aload_1
        //   15: ifnull +43 -> 58
        //   18: aload_1
        //   19: invokeinterface 95 1 0
        //   24: astore_1
        //   25: aload_2
        //   26: aload_1
        //   27: invokevirtual 47	android/os/Parcel:writeStrongBinder	(Landroid/os/IBinder;)V
        //   30: aload_0
        //   31: getfield 18	com/google/android/gms/drive/realtime/internal/zzm$zza$zza:zzoz	Landroid/os/IBinder;
        //   34: bipush 32
        //   36: aload_2
        //   37: aload_3
        //   38: iconst_0
        //   39: invokeinterface 53 5 0
        //   44: pop
        //   45: aload_3
        //   46: invokevirtual 56	android/os/Parcel:readException	()V
        //   49: aload_3
        //   50: invokevirtual 59	android/os/Parcel:recycle	()V
        //   53: aload_2
        //   54: invokevirtual 59	android/os/Parcel:recycle	()V
        //   57: return
        //   58: aconst_null
        //   59: astore_1
        //   60: goto -35 -> 25
        //   63: astore_1
        //   64: aload_3
        //   65: invokevirtual 59	android/os/Parcel:recycle	()V
        //   68: aload_2
        //   69: invokevirtual 59	android/os/Parcel:recycle	()V
        //   72: aload_1
        //   73: athrow
        // Local variable table:
        //   start	length	slot	name	signature
        //   0	74	0	this	zza
        //   0	74	1	paramzzd	zzd
        //   3	66	2	localParcel1	Parcel
        //   7	58	3	localParcel2	Parcel
        // Exception table:
        //   from	to	target	type
        //   8	14	63	finally
        //   18	25	63	finally
        //   25	49	63	finally
      }
      
      /* Error */
      public void zza(zze paramzze)
        throws RemoteException
      {
        // Byte code:
        //   0: invokestatic 30	android/os/Parcel:obtain	()Landroid/os/Parcel;
        //   3: astore_2
        //   4: invokestatic 30	android/os/Parcel:obtain	()Landroid/os/Parcel;
        //   7: astore_3
        //   8: aload_2
        //   9: ldc 32
        //   11: invokevirtual 36	android/os/Parcel:writeInterfaceToken	(Ljava/lang/String;)V
        //   14: aload_1
        //   15: ifnull +43 -> 58
        //   18: aload_1
        //   19: invokeinterface 99 1 0
        //   24: astore_1
        //   25: aload_2
        //   26: aload_1
        //   27: invokevirtual 47	android/os/Parcel:writeStrongBinder	(Landroid/os/IBinder;)V
        //   30: aload_0
        //   31: getfield 18	com/google/android/gms/drive/realtime/internal/zzm$zza$zza:zzoz	Landroid/os/IBinder;
        //   34: bipush 31
        //   36: aload_2
        //   37: aload_3
        //   38: iconst_0
        //   39: invokeinterface 53 5 0
        //   44: pop
        //   45: aload_3
        //   46: invokevirtual 56	android/os/Parcel:readException	()V
        //   49: aload_3
        //   50: invokevirtual 59	android/os/Parcel:recycle	()V
        //   53: aload_2
        //   54: invokevirtual 59	android/os/Parcel:recycle	()V
        //   57: return
        //   58: aconst_null
        //   59: astore_1
        //   60: goto -35 -> 25
        //   63: astore_1
        //   64: aload_3
        //   65: invokevirtual 59	android/os/Parcel:recycle	()V
        //   68: aload_2
        //   69: invokevirtual 59	android/os/Parcel:recycle	()V
        //   72: aload_1
        //   73: athrow
        // Local variable table:
        //   start	length	slot	name	signature
        //   0	74	0	this	zza
        //   0	74	1	paramzze	zze
        //   3	66	2	localParcel1	Parcel
        //   7	58	3	localParcel2	Parcel
        // Exception table:
        //   from	to	target	type
        //   8	14	63	finally
        //   18	25	63	finally
        //   25	49	63	finally
      }
      
      /* Error */
      public void zza(zzh paramzzh)
        throws RemoteException
      {
        // Byte code:
        //   0: invokestatic 30	android/os/Parcel:obtain	()Landroid/os/Parcel;
        //   3: astore_2
        //   4: invokestatic 30	android/os/Parcel:obtain	()Landroid/os/Parcel;
        //   7: astore_3
        //   8: aload_2
        //   9: ldc 32
        //   11: invokevirtual 36	android/os/Parcel:writeInterfaceToken	(Ljava/lang/String;)V
        //   14: aload_1
        //   15: ifnull +43 -> 58
        //   18: aload_1
        //   19: invokeinterface 103 1 0
        //   24: astore_1
        //   25: aload_2
        //   26: aload_1
        //   27: invokevirtual 47	android/os/Parcel:writeStrongBinder	(Landroid/os/IBinder;)V
        //   30: aload_0
        //   31: getfield 18	com/google/android/gms/drive/realtime/internal/zzm$zza$zza:zzoz	Landroid/os/IBinder;
        //   34: bipush 36
        //   36: aload_2
        //   37: aload_3
        //   38: iconst_0
        //   39: invokeinterface 53 5 0
        //   44: pop
        //   45: aload_3
        //   46: invokevirtual 56	android/os/Parcel:readException	()V
        //   49: aload_3
        //   50: invokevirtual 59	android/os/Parcel:recycle	()V
        //   53: aload_2
        //   54: invokevirtual 59	android/os/Parcel:recycle	()V
        //   57: return
        //   58: aconst_null
        //   59: astore_1
        //   60: goto -35 -> 25
        //   63: astore_1
        //   64: aload_3
        //   65: invokevirtual 59	android/os/Parcel:recycle	()V
        //   68: aload_2
        //   69: invokevirtual 59	android/os/Parcel:recycle	()V
        //   72: aload_1
        //   73: athrow
        // Local variable table:
        //   start	length	slot	name	signature
        //   0	74	0	this	zza
        //   0	74	1	paramzzh	zzh
        //   3	66	2	localParcel1	Parcel
        //   7	58	3	localParcel2	Parcel
        // Exception table:
        //   from	to	target	type
        //   8	14	63	finally
        //   18	25	63	finally
        //   25	49	63	finally
      }
      
      /* Error */
      public void zza(zzi paramzzi)
        throws RemoteException
      {
        // Byte code:
        //   0: invokestatic 30	android/os/Parcel:obtain	()Landroid/os/Parcel;
        //   3: astore_2
        //   4: invokestatic 30	android/os/Parcel:obtain	()Landroid/os/Parcel;
        //   7: astore_3
        //   8: aload_2
        //   9: ldc 32
        //   11: invokevirtual 36	android/os/Parcel:writeInterfaceToken	(Ljava/lang/String;)V
        //   14: aload_1
        //   15: ifnull +43 -> 58
        //   18: aload_1
        //   19: invokeinterface 107 1 0
        //   24: astore_1
        //   25: aload_2
        //   26: aload_1
        //   27: invokevirtual 47	android/os/Parcel:writeStrongBinder	(Landroid/os/IBinder;)V
        //   30: aload_0
        //   31: getfield 18	com/google/android/gms/drive/realtime/internal/zzm$zza$zza:zzoz	Landroid/os/IBinder;
        //   34: bipush 34
        //   36: aload_2
        //   37: aload_3
        //   38: iconst_0
        //   39: invokeinterface 53 5 0
        //   44: pop
        //   45: aload_3
        //   46: invokevirtual 56	android/os/Parcel:readException	()V
        //   49: aload_3
        //   50: invokevirtual 59	android/os/Parcel:recycle	()V
        //   53: aload_2
        //   54: invokevirtual 59	android/os/Parcel:recycle	()V
        //   57: return
        //   58: aconst_null
        //   59: astore_1
        //   60: goto -35 -> 25
        //   63: astore_1
        //   64: aload_3
        //   65: invokevirtual 59	android/os/Parcel:recycle	()V
        //   68: aload_2
        //   69: invokevirtual 59	android/os/Parcel:recycle	()V
        //   72: aload_1
        //   73: athrow
        // Local variable table:
        //   start	length	slot	name	signature
        //   0	74	0	this	zza
        //   0	74	1	paramzzi	zzi
        //   3	66	2	localParcel1	Parcel
        //   7	58	3	localParcel2	Parcel
        // Exception table:
        //   from	to	target	type
        //   8	14	63	finally
        //   18	25	63	finally
        //   25	49	63	finally
      }
      
      /* Error */
      public void zza(zzj paramzzj)
        throws RemoteException
      {
        // Byte code:
        //   0: invokestatic 30	android/os/Parcel:obtain	()Landroid/os/Parcel;
        //   3: astore_2
        //   4: invokestatic 30	android/os/Parcel:obtain	()Landroid/os/Parcel;
        //   7: astore_3
        //   8: aload_2
        //   9: ldc 32
        //   11: invokevirtual 36	android/os/Parcel:writeInterfaceToken	(Ljava/lang/String;)V
        //   14: aload_1
        //   15: ifnull +43 -> 58
        //   18: aload_1
        //   19: invokeinterface 44 1 0
        //   24: astore_1
        //   25: aload_2
        //   26: aload_1
        //   27: invokevirtual 47	android/os/Parcel:writeStrongBinder	(Landroid/os/IBinder;)V
        //   30: aload_0
        //   31: getfield 18	com/google/android/gms/drive/realtime/internal/zzm$zza$zza:zzoz	Landroid/os/IBinder;
        //   34: bipush 22
        //   36: aload_2
        //   37: aload_3
        //   38: iconst_0
        //   39: invokeinterface 53 5 0
        //   44: pop
        //   45: aload_3
        //   46: invokevirtual 56	android/os/Parcel:readException	()V
        //   49: aload_3
        //   50: invokevirtual 59	android/os/Parcel:recycle	()V
        //   53: aload_2
        //   54: invokevirtual 59	android/os/Parcel:recycle	()V
        //   57: return
        //   58: aconst_null
        //   59: astore_1
        //   60: goto -35 -> 25
        //   63: astore_1
        //   64: aload_3
        //   65: invokevirtual 59	android/os/Parcel:recycle	()V
        //   68: aload_2
        //   69: invokevirtual 59	android/os/Parcel:recycle	()V
        //   72: aload_1
        //   73: athrow
        // Local variable table:
        //   start	length	slot	name	signature
        //   0	74	0	this	zza
        //   0	74	1	paramzzj	zzj
        //   3	66	2	localParcel1	Parcel
        //   7	58	3	localParcel2	Parcel
        // Exception table:
        //   from	to	target	type
        //   8	14	63	finally
        //   18	25	63	finally
        //   25	49	63	finally
      }
      
      /* Error */
      public void zza(zzl paramzzl)
        throws RemoteException
      {
        // Byte code:
        //   0: invokestatic 30	android/os/Parcel:obtain	()Landroid/os/Parcel;
        //   3: astore_2
        //   4: invokestatic 30	android/os/Parcel:obtain	()Landroid/os/Parcel;
        //   7: astore_3
        //   8: aload_2
        //   9: ldc 32
        //   11: invokevirtual 36	android/os/Parcel:writeInterfaceToken	(Ljava/lang/String;)V
        //   14: aload_1
        //   15: ifnull +43 -> 58
        //   18: aload_1
        //   19: invokeinterface 112 1 0
        //   24: astore_1
        //   25: aload_2
        //   26: aload_1
        //   27: invokevirtual 47	android/os/Parcel:writeStrongBinder	(Landroid/os/IBinder;)V
        //   30: aload_0
        //   31: getfield 18	com/google/android/gms/drive/realtime/internal/zzm$zza$zza:zzoz	Landroid/os/IBinder;
        //   34: bipush 40
        //   36: aload_2
        //   37: aload_3
        //   38: iconst_0
        //   39: invokeinterface 53 5 0
        //   44: pop
        //   45: aload_3
        //   46: invokevirtual 56	android/os/Parcel:readException	()V
        //   49: aload_3
        //   50: invokevirtual 59	android/os/Parcel:recycle	()V
        //   53: aload_2
        //   54: invokevirtual 59	android/os/Parcel:recycle	()V
        //   57: return
        //   58: aconst_null
        //   59: astore_1
        //   60: goto -35 -> 25
        //   63: astore_1
        //   64: aload_3
        //   65: invokevirtual 59	android/os/Parcel:recycle	()V
        //   68: aload_2
        //   69: invokevirtual 59	android/os/Parcel:recycle	()V
        //   72: aload_1
        //   73: athrow
        // Local variable table:
        //   start	length	slot	name	signature
        //   0	74	0	this	zza
        //   0	74	1	paramzzl	zzl
        //   3	66	2	localParcel1	Parcel
        //   7	58	3	localParcel2	Parcel
        // Exception table:
        //   from	to	target	type
        //   8	14	63	finally
        //   18	25	63	finally
        //   25	49	63	finally
      }
      
      /* Error */
      public void zza(zzo paramzzo)
        throws RemoteException
      {
        // Byte code:
        //   0: invokestatic 30	android/os/Parcel:obtain	()Landroid/os/Parcel;
        //   3: astore_2
        //   4: invokestatic 30	android/os/Parcel:obtain	()Landroid/os/Parcel;
        //   7: astore_3
        //   8: aload_2
        //   9: ldc 32
        //   11: invokevirtual 36	android/os/Parcel:writeInterfaceToken	(Ljava/lang/String;)V
        //   14: aload_1
        //   15: ifnull +42 -> 57
        //   18: aload_1
        //   19: invokeinterface 64 1 0
        //   24: astore_1
        //   25: aload_2
        //   26: aload_1
        //   27: invokevirtual 47	android/os/Parcel:writeStrongBinder	(Landroid/os/IBinder;)V
        //   30: aload_0
        //   31: getfield 18	com/google/android/gms/drive/realtime/internal/zzm$zza$zza:zzoz	Landroid/os/IBinder;
        //   34: iconst_3
        //   35: aload_2
        //   36: aload_3
        //   37: iconst_0
        //   38: invokeinterface 53 5 0
        //   43: pop
        //   44: aload_3
        //   45: invokevirtual 56	android/os/Parcel:readException	()V
        //   48: aload_3
        //   49: invokevirtual 59	android/os/Parcel:recycle	()V
        //   52: aload_2
        //   53: invokevirtual 59	android/os/Parcel:recycle	()V
        //   56: return
        //   57: aconst_null
        //   58: astore_1
        //   59: goto -34 -> 25
        //   62: astore_1
        //   63: aload_3
        //   64: invokevirtual 59	android/os/Parcel:recycle	()V
        //   67: aload_2
        //   68: invokevirtual 59	android/os/Parcel:recycle	()V
        //   71: aload_1
        //   72: athrow
        // Local variable table:
        //   start	length	slot	name	signature
        //   0	73	0	this	zza
        //   0	73	1	paramzzo	zzo
        //   3	65	2	localParcel1	Parcel
        //   7	57	3	localParcel2	Parcel
        // Exception table:
        //   from	to	target	type
        //   8	14	62	finally
        //   18	25	62	finally
        //   25	48	62	finally
      }
      
      /* Error */
      public void zza(String paramString, int paramInt1, int paramInt2, zzg paramzzg)
        throws RemoteException
      {
        // Byte code:
        //   0: invokestatic 30	android/os/Parcel:obtain	()Landroid/os/Parcel;
        //   3: astore 5
        //   5: invokestatic 30	android/os/Parcel:obtain	()Landroid/os/Parcel;
        //   8: astore 6
        //   10: aload 5
        //   12: ldc 32
        //   14: invokevirtual 36	android/os/Parcel:writeInterfaceToken	(Ljava/lang/String;)V
        //   17: aload 5
        //   19: aload_1
        //   20: invokevirtual 117	android/os/Parcel:writeString	(Ljava/lang/String;)V
        //   23: aload 5
        //   25: iload_2
        //   26: invokevirtual 40	android/os/Parcel:writeInt	(I)V
        //   29: aload 5
        //   31: iload_3
        //   32: invokevirtual 40	android/os/Parcel:writeInt	(I)V
        //   35: aload 4
        //   37: ifnull +50 -> 87
        //   40: aload 4
        //   42: invokeinterface 120 1 0
        //   47: astore_1
        //   48: aload 5
        //   50: aload_1
        //   51: invokevirtual 47	android/os/Parcel:writeStrongBinder	(Landroid/os/IBinder;)V
        //   54: aload_0
        //   55: getfield 18	com/google/android/gms/drive/realtime/internal/zzm$zza$zza:zzoz	Landroid/os/IBinder;
        //   58: bipush 17
        //   60: aload 5
        //   62: aload 6
        //   64: iconst_0
        //   65: invokeinterface 53 5 0
        //   70: pop
        //   71: aload 6
        //   73: invokevirtual 56	android/os/Parcel:readException	()V
        //   76: aload 6
        //   78: invokevirtual 59	android/os/Parcel:recycle	()V
        //   81: aload 5
        //   83: invokevirtual 59	android/os/Parcel:recycle	()V
        //   86: return
        //   87: aconst_null
        //   88: astore_1
        //   89: goto -41 -> 48
        //   92: astore_1
        //   93: aload 6
        //   95: invokevirtual 59	android/os/Parcel:recycle	()V
        //   98: aload 5
        //   100: invokevirtual 59	android/os/Parcel:recycle	()V
        //   103: aload_1
        //   104: athrow
        // Local variable table:
        //   start	length	slot	name	signature
        //   0	105	0	this	zza
        //   0	105	1	paramString	String
        //   0	105	2	paramInt1	int
        //   0	105	3	paramInt2	int
        //   0	105	4	paramzzg	zzg
        //   3	96	5	localParcel1	Parcel
        //   8	86	6	localParcel2	Parcel
        // Exception table:
        //   from	to	target	type
        //   10	35	92	finally
        //   40	48	92	finally
        //   48	76	92	finally
      }
      
      /* Error */
      public void zza(String paramString, int paramInt1, int paramInt2, zzj paramzzj)
        throws RemoteException
      {
        // Byte code:
        //   0: invokestatic 30	android/os/Parcel:obtain	()Landroid/os/Parcel;
        //   3: astore 5
        //   5: invokestatic 30	android/os/Parcel:obtain	()Landroid/os/Parcel;
        //   8: astore 6
        //   10: aload 5
        //   12: ldc 32
        //   14: invokevirtual 36	android/os/Parcel:writeInterfaceToken	(Ljava/lang/String;)V
        //   17: aload 5
        //   19: aload_1
        //   20: invokevirtual 117	android/os/Parcel:writeString	(Ljava/lang/String;)V
        //   23: aload 5
        //   25: iload_2
        //   26: invokevirtual 40	android/os/Parcel:writeInt	(I)V
        //   29: aload 5
        //   31: iload_3
        //   32: invokevirtual 40	android/os/Parcel:writeInt	(I)V
        //   35: aload 4
        //   37: ifnull +50 -> 87
        //   40: aload 4
        //   42: invokeinterface 44 1 0
        //   47: astore_1
        //   48: aload 5
        //   50: aload_1
        //   51: invokevirtual 47	android/os/Parcel:writeStrongBinder	(Landroid/os/IBinder;)V
        //   54: aload_0
        //   55: getfield 18	com/google/android/gms/drive/realtime/internal/zzm$zza$zza:zzoz	Landroid/os/IBinder;
        //   58: bipush 11
        //   60: aload 5
        //   62: aload 6
        //   64: iconst_0
        //   65: invokeinterface 53 5 0
        //   70: pop
        //   71: aload 6
        //   73: invokevirtual 56	android/os/Parcel:readException	()V
        //   76: aload 6
        //   78: invokevirtual 59	android/os/Parcel:recycle	()V
        //   81: aload 5
        //   83: invokevirtual 59	android/os/Parcel:recycle	()V
        //   86: return
        //   87: aconst_null
        //   88: astore_1
        //   89: goto -41 -> 48
        //   92: astore_1
        //   93: aload 6
        //   95: invokevirtual 59	android/os/Parcel:recycle	()V
        //   98: aload 5
        //   100: invokevirtual 59	android/os/Parcel:recycle	()V
        //   103: aload_1
        //   104: athrow
        // Local variable table:
        //   start	length	slot	name	signature
        //   0	105	0	this	zza
        //   0	105	1	paramString	String
        //   0	105	2	paramInt1	int
        //   0	105	3	paramInt2	int
        //   0	105	4	paramzzj	zzj
        //   3	96	5	localParcel1	Parcel
        //   8	86	6	localParcel2	Parcel
        // Exception table:
        //   from	to	target	type
        //   10	35	92	finally
        //   40	48	92	finally
        //   48	76	92	finally
      }
      
      public void zza(String paramString, int paramInt, DataHolder paramDataHolder, zzg paramzzg)
        throws RemoteException
      {
        Parcel localParcel1 = Parcel.obtain();
        Parcel localParcel2 = Parcel.obtain();
        for (;;)
        {
          try
          {
            localParcel1.writeInterfaceToken("com.google.android.gms.drive.realtime.internal.IRealtimeService");
            localParcel1.writeString(paramString);
            localParcel1.writeInt(paramInt);
            if (paramDataHolder != null)
            {
              localParcel1.writeInt(1);
              paramDataHolder.writeToParcel(localParcel1, 0);
              if (paramzzg != null)
              {
                paramString = paramzzg.asBinder();
                localParcel1.writeStrongBinder(paramString);
                this.zzoz.transact(16, localParcel1, localParcel2, 0);
                localParcel2.readException();
              }
            }
            else
            {
              localParcel1.writeInt(0);
              continue;
            }
            paramString = null;
          }
          finally
          {
            localParcel2.recycle();
            localParcel1.recycle();
          }
        }
      }
      
      public void zza(String paramString, int paramInt, DataHolder paramDataHolder, zzj paramzzj)
        throws RemoteException
      {
        Parcel localParcel1 = Parcel.obtain();
        Parcel localParcel2 = Parcel.obtain();
        for (;;)
        {
          try
          {
            localParcel1.writeInterfaceToken("com.google.android.gms.drive.realtime.internal.IRealtimeService");
            localParcel1.writeString(paramString);
            localParcel1.writeInt(paramInt);
            if (paramDataHolder != null)
            {
              localParcel1.writeInt(1);
              paramDataHolder.writeToParcel(localParcel1, 0);
              if (paramzzj != null)
              {
                paramString = paramzzj.asBinder();
                localParcel1.writeStrongBinder(paramString);
                this.zzoz.transact(15, localParcel1, localParcel2, 0);
                localParcel2.readException();
              }
            }
            else
            {
              localParcel1.writeInt(0);
              continue;
            }
            paramString = null;
          }
          finally
          {
            localParcel2.recycle();
            localParcel1.recycle();
          }
        }
      }
      
      /* Error */
      public void zza(String paramString, int paramInt, zzn paramzzn)
        throws RemoteException
      {
        // Byte code:
        //   0: invokestatic 30	android/os/Parcel:obtain	()Landroid/os/Parcel;
        //   3: astore 4
        //   5: invokestatic 30	android/os/Parcel:obtain	()Landroid/os/Parcel;
        //   8: astore 5
        //   10: aload 4
        //   12: ldc 32
        //   14: invokevirtual 36	android/os/Parcel:writeInterfaceToken	(Ljava/lang/String;)V
        //   17: aload 4
        //   19: aload_1
        //   20: invokevirtual 117	android/os/Parcel:writeString	(Ljava/lang/String;)V
        //   23: aload 4
        //   25: iload_2
        //   26: invokevirtual 40	android/os/Parcel:writeInt	(I)V
        //   29: aload_3
        //   30: ifnull +49 -> 79
        //   33: aload_3
        //   34: invokeinterface 87 1 0
        //   39: astore_1
        //   40: aload 4
        //   42: aload_1
        //   43: invokevirtual 47	android/os/Parcel:writeStrongBinder	(Landroid/os/IBinder;)V
        //   46: aload_0
        //   47: getfield 18	com/google/android/gms/drive/realtime/internal/zzm$zza$zza:zzoz	Landroid/os/IBinder;
        //   50: bipush 46
        //   52: aload 4
        //   54: aload 5
        //   56: iconst_0
        //   57: invokeinterface 53 5 0
        //   62: pop
        //   63: aload 5
        //   65: invokevirtual 56	android/os/Parcel:readException	()V
        //   68: aload 5
        //   70: invokevirtual 59	android/os/Parcel:recycle	()V
        //   73: aload 4
        //   75: invokevirtual 59	android/os/Parcel:recycle	()V
        //   78: return
        //   79: aconst_null
        //   80: astore_1
        //   81: goto -41 -> 40
        //   84: astore_1
        //   85: aload 5
        //   87: invokevirtual 59	android/os/Parcel:recycle	()V
        //   90: aload 4
        //   92: invokevirtual 59	android/os/Parcel:recycle	()V
        //   95: aload_1
        //   96: athrow
        // Local variable table:
        //   start	length	slot	name	signature
        //   0	97	0	this	zza
        //   0	97	1	paramString	String
        //   0	97	2	paramInt	int
        //   0	97	3	paramzzn	zzn
        //   3	88	4	localParcel1	Parcel
        //   8	78	5	localParcel2	Parcel
        // Exception table:
        //   from	to	target	type
        //   10	29	84	finally
        //   33	40	84	finally
        //   40	68	84	finally
      }
      
      /* Error */
      public void zza(String paramString, int paramInt, zzo paramzzo)
        throws RemoteException
      {
        // Byte code:
        //   0: invokestatic 30	android/os/Parcel:obtain	()Landroid/os/Parcel;
        //   3: astore 4
        //   5: invokestatic 30	android/os/Parcel:obtain	()Landroid/os/Parcel;
        //   8: astore 5
        //   10: aload 4
        //   12: ldc 32
        //   14: invokevirtual 36	android/os/Parcel:writeInterfaceToken	(Ljava/lang/String;)V
        //   17: aload 4
        //   19: aload_1
        //   20: invokevirtual 117	android/os/Parcel:writeString	(Ljava/lang/String;)V
        //   23: aload 4
        //   25: iload_2
        //   26: invokevirtual 40	android/os/Parcel:writeInt	(I)V
        //   29: aload_3
        //   30: ifnull +49 -> 79
        //   33: aload_3
        //   34: invokeinterface 64 1 0
        //   39: astore_1
        //   40: aload 4
        //   42: aload_1
        //   43: invokevirtual 47	android/os/Parcel:writeStrongBinder	(Landroid/os/IBinder;)V
        //   46: aload_0
        //   47: getfield 18	com/google/android/gms/drive/realtime/internal/zzm$zza$zza:zzoz	Landroid/os/IBinder;
        //   50: bipush 28
        //   52: aload 4
        //   54: aload 5
        //   56: iconst_0
        //   57: invokeinterface 53 5 0
        //   62: pop
        //   63: aload 5
        //   65: invokevirtual 56	android/os/Parcel:readException	()V
        //   68: aload 5
        //   70: invokevirtual 59	android/os/Parcel:recycle	()V
        //   73: aload 4
        //   75: invokevirtual 59	android/os/Parcel:recycle	()V
        //   78: return
        //   79: aconst_null
        //   80: astore_1
        //   81: goto -41 -> 40
        //   84: astore_1
        //   85: aload 5
        //   87: invokevirtual 59	android/os/Parcel:recycle	()V
        //   90: aload 4
        //   92: invokevirtual 59	android/os/Parcel:recycle	()V
        //   95: aload_1
        //   96: athrow
        // Local variable table:
        //   start	length	slot	name	signature
        //   0	97	0	this	zza
        //   0	97	1	paramString	String
        //   0	97	2	paramInt	int
        //   0	97	3	paramzzo	zzo
        //   3	88	4	localParcel1	Parcel
        //   8	78	5	localParcel2	Parcel
        // Exception table:
        //   from	to	target	type
        //   10	29	84	finally
        //   33	40	84	finally
        //   40	68	84	finally
      }
      
      /* Error */
      public void zza(String paramString1, int paramInt1, String paramString2, int paramInt2, zzj paramzzj)
        throws RemoteException
      {
        // Byte code:
        //   0: invokestatic 30	android/os/Parcel:obtain	()Landroid/os/Parcel;
        //   3: astore 6
        //   5: invokestatic 30	android/os/Parcel:obtain	()Landroid/os/Parcel;
        //   8: astore 7
        //   10: aload 6
        //   12: ldc 32
        //   14: invokevirtual 36	android/os/Parcel:writeInterfaceToken	(Ljava/lang/String;)V
        //   17: aload 6
        //   19: aload_1
        //   20: invokevirtual 117	android/os/Parcel:writeString	(Ljava/lang/String;)V
        //   23: aload 6
        //   25: iload_2
        //   26: invokevirtual 40	android/os/Parcel:writeInt	(I)V
        //   29: aload 6
        //   31: aload_3
        //   32: invokevirtual 117	android/os/Parcel:writeString	(Ljava/lang/String;)V
        //   35: aload 6
        //   37: iload 4
        //   39: invokevirtual 40	android/os/Parcel:writeInt	(I)V
        //   42: aload 5
        //   44: ifnull +50 -> 94
        //   47: aload 5
        //   49: invokeinterface 44 1 0
        //   54: astore_1
        //   55: aload 6
        //   57: aload_1
        //   58: invokevirtual 47	android/os/Parcel:writeStrongBinder	(Landroid/os/IBinder;)V
        //   61: aload_0
        //   62: getfield 18	com/google/android/gms/drive/realtime/internal/zzm$zza$zza:zzoz	Landroid/os/IBinder;
        //   65: bipush 37
        //   67: aload 6
        //   69: aload 7
        //   71: iconst_0
        //   72: invokeinterface 53 5 0
        //   77: pop
        //   78: aload 7
        //   80: invokevirtual 56	android/os/Parcel:readException	()V
        //   83: aload 7
        //   85: invokevirtual 59	android/os/Parcel:recycle	()V
        //   88: aload 6
        //   90: invokevirtual 59	android/os/Parcel:recycle	()V
        //   93: return
        //   94: aconst_null
        //   95: astore_1
        //   96: goto -41 -> 55
        //   99: astore_1
        //   100: aload 7
        //   102: invokevirtual 59	android/os/Parcel:recycle	()V
        //   105: aload 6
        //   107: invokevirtual 59	android/os/Parcel:recycle	()V
        //   110: aload_1
        //   111: athrow
        // Local variable table:
        //   start	length	slot	name	signature
        //   0	112	0	this	zza
        //   0	112	1	paramString1	String
        //   0	112	2	paramInt1	int
        //   0	112	3	paramString2	String
        //   0	112	4	paramInt2	int
        //   0	112	5	paramzzj	zzj
        //   3	103	6	localParcel1	Parcel
        //   8	93	7	localParcel2	Parcel
        // Exception table:
        //   from	to	target	type
        //   10	42	99	finally
        //   47	55	99	finally
        //   55	83	99	finally
      }
      
      /* Error */
      public void zza(String paramString1, int paramInt, String paramString2, zzj paramzzj)
        throws RemoteException
      {
        // Byte code:
        //   0: invokestatic 30	android/os/Parcel:obtain	()Landroid/os/Parcel;
        //   3: astore 5
        //   5: invokestatic 30	android/os/Parcel:obtain	()Landroid/os/Parcel;
        //   8: astore 6
        //   10: aload 5
        //   12: ldc 32
        //   14: invokevirtual 36	android/os/Parcel:writeInterfaceToken	(Ljava/lang/String;)V
        //   17: aload 5
        //   19: aload_1
        //   20: invokevirtual 117	android/os/Parcel:writeString	(Ljava/lang/String;)V
        //   23: aload 5
        //   25: iload_2
        //   26: invokevirtual 40	android/os/Parcel:writeInt	(I)V
        //   29: aload 5
        //   31: aload_3
        //   32: invokevirtual 117	android/os/Parcel:writeString	(Ljava/lang/String;)V
        //   35: aload 4
        //   37: ifnull +50 -> 87
        //   40: aload 4
        //   42: invokeinterface 44 1 0
        //   47: astore_1
        //   48: aload 5
        //   50: aload_1
        //   51: invokevirtual 47	android/os/Parcel:writeStrongBinder	(Landroid/os/IBinder;)V
        //   54: aload_0
        //   55: getfield 18	com/google/android/gms/drive/realtime/internal/zzm$zza$zza:zzoz	Landroid/os/IBinder;
        //   58: bipush 10
        //   60: aload 5
        //   62: aload 6
        //   64: iconst_0
        //   65: invokeinterface 53 5 0
        //   70: pop
        //   71: aload 6
        //   73: invokevirtual 56	android/os/Parcel:readException	()V
        //   76: aload 6
        //   78: invokevirtual 59	android/os/Parcel:recycle	()V
        //   81: aload 5
        //   83: invokevirtual 59	android/os/Parcel:recycle	()V
        //   86: return
        //   87: aconst_null
        //   88: astore_1
        //   89: goto -41 -> 48
        //   92: astore_1
        //   93: aload 6
        //   95: invokevirtual 59	android/os/Parcel:recycle	()V
        //   98: aload 5
        //   100: invokevirtual 59	android/os/Parcel:recycle	()V
        //   103: aload_1
        //   104: athrow
        // Local variable table:
        //   start	length	slot	name	signature
        //   0	105	0	this	zza
        //   0	105	1	paramString1	String
        //   0	105	2	paramInt	int
        //   0	105	3	paramString2	String
        //   0	105	4	paramzzj	zzj
        //   3	96	5	localParcel1	Parcel
        //   8	86	6	localParcel2	Parcel
        // Exception table:
        //   from	to	target	type
        //   10	35	92	finally
        //   40	48	92	finally
        //   48	76	92	finally
      }
      
      public void zza(String paramString, DataHolder paramDataHolder, zzj paramzzj)
        throws RemoteException
      {
        Parcel localParcel1 = Parcel.obtain();
        Parcel localParcel2 = Parcel.obtain();
        for (;;)
        {
          try
          {
            localParcel1.writeInterfaceToken("com.google.android.gms.drive.realtime.internal.IRealtimeService");
            localParcel1.writeString(paramString);
            if (paramDataHolder != null)
            {
              localParcel1.writeInt(1);
              paramDataHolder.writeToParcel(localParcel1, 0);
              if (paramzzj != null)
              {
                paramString = paramzzj.asBinder();
                localParcel1.writeStrongBinder(paramString);
                this.zzoz.transact(6, localParcel1, localParcel2, 0);
                localParcel2.readException();
              }
            }
            else
            {
              localParcel1.writeInt(0);
              continue;
            }
            paramString = null;
          }
          finally
          {
            localParcel2.recycle();
            localParcel1.recycle();
          }
        }
      }
      
      /* Error */
      public void zza(String paramString, zzf paramzzf)
        throws RemoteException
      {
        // Byte code:
        //   0: invokestatic 30	android/os/Parcel:obtain	()Landroid/os/Parcel;
        //   3: astore_3
        //   4: invokestatic 30	android/os/Parcel:obtain	()Landroid/os/Parcel;
        //   7: astore 4
        //   9: aload_3
        //   10: ldc 32
        //   12: invokevirtual 36	android/os/Parcel:writeInterfaceToken	(Ljava/lang/String;)V
        //   15: aload_3
        //   16: aload_1
        //   17: invokevirtual 117	android/os/Parcel:writeString	(Ljava/lang/String;)V
        //   20: aload_2
        //   21: ifnull +46 -> 67
        //   24: aload_2
        //   25: invokeinterface 135 1 0
        //   30: astore_1
        //   31: aload_3
        //   32: aload_1
        //   33: invokevirtual 47	android/os/Parcel:writeStrongBinder	(Landroid/os/IBinder;)V
        //   36: aload_0
        //   37: getfield 18	com/google/android/gms/drive/realtime/internal/zzm$zza$zza:zzoz	Landroid/os/IBinder;
        //   40: bipush 20
        //   42: aload_3
        //   43: aload 4
        //   45: iconst_0
        //   46: invokeinterface 53 5 0
        //   51: pop
        //   52: aload 4
        //   54: invokevirtual 56	android/os/Parcel:readException	()V
        //   57: aload 4
        //   59: invokevirtual 59	android/os/Parcel:recycle	()V
        //   62: aload_3
        //   63: invokevirtual 59	android/os/Parcel:recycle	()V
        //   66: return
        //   67: aconst_null
        //   68: astore_1
        //   69: goto -38 -> 31
        //   72: astore_1
        //   73: aload 4
        //   75: invokevirtual 59	android/os/Parcel:recycle	()V
        //   78: aload_3
        //   79: invokevirtual 59	android/os/Parcel:recycle	()V
        //   82: aload_1
        //   83: athrow
        // Local variable table:
        //   start	length	slot	name	signature
        //   0	84	0	this	zza
        //   0	84	1	paramString	String
        //   0	84	2	paramzzf	zzf
        //   3	76	3	localParcel1	Parcel
        //   7	67	4	localParcel2	Parcel
        // Exception table:
        //   from	to	target	type
        //   9	20	72	finally
        //   24	31	72	finally
        //   31	57	72	finally
      }
      
      /* Error */
      public void zza(String paramString, zzj paramzzj)
        throws RemoteException
      {
        // Byte code:
        //   0: invokestatic 30	android/os/Parcel:obtain	()Landroid/os/Parcel;
        //   3: astore_3
        //   4: invokestatic 30	android/os/Parcel:obtain	()Landroid/os/Parcel;
        //   7: astore 4
        //   9: aload_3
        //   10: ldc 32
        //   12: invokevirtual 36	android/os/Parcel:writeInterfaceToken	(Ljava/lang/String;)V
        //   15: aload_3
        //   16: aload_1
        //   17: invokevirtual 117	android/os/Parcel:writeString	(Ljava/lang/String;)V
        //   20: aload_2
        //   21: ifnull +46 -> 67
        //   24: aload_2
        //   25: invokeinterface 44 1 0
        //   30: astore_1
        //   31: aload_3
        //   32: aload_1
        //   33: invokevirtual 47	android/os/Parcel:writeStrongBinder	(Landroid/os/IBinder;)V
        //   36: aload_0
        //   37: getfield 18	com/google/android/gms/drive/realtime/internal/zzm$zza$zza:zzoz	Landroid/os/IBinder;
        //   40: bipush 7
        //   42: aload_3
        //   43: aload 4
        //   45: iconst_0
        //   46: invokeinterface 53 5 0
        //   51: pop
        //   52: aload 4
        //   54: invokevirtual 56	android/os/Parcel:readException	()V
        //   57: aload 4
        //   59: invokevirtual 59	android/os/Parcel:recycle	()V
        //   62: aload_3
        //   63: invokevirtual 59	android/os/Parcel:recycle	()V
        //   66: return
        //   67: aconst_null
        //   68: astore_1
        //   69: goto -38 -> 31
        //   72: astore_1
        //   73: aload 4
        //   75: invokevirtual 59	android/os/Parcel:recycle	()V
        //   78: aload_3
        //   79: invokevirtual 59	android/os/Parcel:recycle	()V
        //   82: aload_1
        //   83: athrow
        // Local variable table:
        //   start	length	slot	name	signature
        //   0	84	0	this	zza
        //   0	84	1	paramString	String
        //   0	84	2	paramzzj	zzj
        //   3	76	3	localParcel1	Parcel
        //   7	67	4	localParcel2	Parcel
        // Exception table:
        //   from	to	target	type
        //   9	20	72	finally
        //   24	31	72	finally
        //   31	57	72	finally
      }
      
      /* Error */
      public void zza(String paramString, zzk paramzzk)
        throws RemoteException
      {
        // Byte code:
        //   0: invokestatic 30	android/os/Parcel:obtain	()Landroid/os/Parcel;
        //   3: astore_3
        //   4: invokestatic 30	android/os/Parcel:obtain	()Landroid/os/Parcel;
        //   7: astore 4
        //   9: aload_3
        //   10: ldc 32
        //   12: invokevirtual 36	android/os/Parcel:writeInterfaceToken	(Ljava/lang/String;)V
        //   15: aload_3
        //   16: aload_1
        //   17: invokevirtual 117	android/os/Parcel:writeString	(Ljava/lang/String;)V
        //   20: aload_2
        //   21: ifnull +46 -> 67
        //   24: aload_2
        //   25: invokeinterface 140 1 0
        //   30: astore_1
        //   31: aload_3
        //   32: aload_1
        //   33: invokevirtual 47	android/os/Parcel:writeStrongBinder	(Landroid/os/IBinder;)V
        //   36: aload_0
        //   37: getfield 18	com/google/android/gms/drive/realtime/internal/zzm$zza$zza:zzoz	Landroid/os/IBinder;
        //   40: bipush 27
        //   42: aload_3
        //   43: aload 4
        //   45: iconst_0
        //   46: invokeinterface 53 5 0
        //   51: pop
        //   52: aload 4
        //   54: invokevirtual 56	android/os/Parcel:readException	()V
        //   57: aload 4
        //   59: invokevirtual 59	android/os/Parcel:recycle	()V
        //   62: aload_3
        //   63: invokevirtual 59	android/os/Parcel:recycle	()V
        //   66: return
        //   67: aconst_null
        //   68: astore_1
        //   69: goto -38 -> 31
        //   72: astore_1
        //   73: aload 4
        //   75: invokevirtual 59	android/os/Parcel:recycle	()V
        //   78: aload_3
        //   79: invokevirtual 59	android/os/Parcel:recycle	()V
        //   82: aload_1
        //   83: athrow
        // Local variable table:
        //   start	length	slot	name	signature
        //   0	84	0	this	zza
        //   0	84	1	paramString	String
        //   0	84	2	paramzzk	zzk
        //   3	76	3	localParcel1	Parcel
        //   7	67	4	localParcel2	Parcel
        // Exception table:
        //   from	to	target	type
        //   9	20	72	finally
        //   24	31	72	finally
        //   31	57	72	finally
      }
      
      /* Error */
      public void zza(String paramString, zzl paramzzl)
        throws RemoteException
      {
        // Byte code:
        //   0: invokestatic 30	android/os/Parcel:obtain	()Landroid/os/Parcel;
        //   3: astore_3
        //   4: invokestatic 30	android/os/Parcel:obtain	()Landroid/os/Parcel;
        //   7: astore 4
        //   9: aload_3
        //   10: ldc 32
        //   12: invokevirtual 36	android/os/Parcel:writeInterfaceToken	(Ljava/lang/String;)V
        //   15: aload_3
        //   16: aload_1
        //   17: invokevirtual 117	android/os/Parcel:writeString	(Ljava/lang/String;)V
        //   20: aload_2
        //   21: ifnull +45 -> 66
        //   24: aload_2
        //   25: invokeinterface 112 1 0
        //   30: astore_1
        //   31: aload_3
        //   32: aload_1
        //   33: invokevirtual 47	android/os/Parcel:writeStrongBinder	(Landroid/os/IBinder;)V
        //   36: aload_0
        //   37: getfield 18	com/google/android/gms/drive/realtime/internal/zzm$zza$zza:zzoz	Landroid/os/IBinder;
        //   40: iconst_5
        //   41: aload_3
        //   42: aload 4
        //   44: iconst_0
        //   45: invokeinterface 53 5 0
        //   50: pop
        //   51: aload 4
        //   53: invokevirtual 56	android/os/Parcel:readException	()V
        //   56: aload 4
        //   58: invokevirtual 59	android/os/Parcel:recycle	()V
        //   61: aload_3
        //   62: invokevirtual 59	android/os/Parcel:recycle	()V
        //   65: return
        //   66: aconst_null
        //   67: astore_1
        //   68: goto -37 -> 31
        //   71: astore_1
        //   72: aload 4
        //   74: invokevirtual 59	android/os/Parcel:recycle	()V
        //   77: aload_3
        //   78: invokevirtual 59	android/os/Parcel:recycle	()V
        //   81: aload_1
        //   82: athrow
        // Local variable table:
        //   start	length	slot	name	signature
        //   0	83	0	this	zza
        //   0	83	1	paramString	String
        //   0	83	2	paramzzl	zzl
        //   3	75	3	localParcel1	Parcel
        //   7	66	4	localParcel2	Parcel
        // Exception table:
        //   from	to	target	type
        //   9	20	71	finally
        //   24	31	71	finally
        //   31	56	71	finally
      }
      
      /* Error */
      public void zza(String paramString, zzn paramzzn)
        throws RemoteException
      {
        // Byte code:
        //   0: invokestatic 30	android/os/Parcel:obtain	()Landroid/os/Parcel;
        //   3: astore_3
        //   4: invokestatic 30	android/os/Parcel:obtain	()Landroid/os/Parcel;
        //   7: astore 4
        //   9: aload_3
        //   10: ldc 32
        //   12: invokevirtual 36	android/os/Parcel:writeInterfaceToken	(Ljava/lang/String;)V
        //   15: aload_3
        //   16: aload_1
        //   17: invokevirtual 117	android/os/Parcel:writeString	(Ljava/lang/String;)V
        //   20: aload_2
        //   21: ifnull +45 -> 66
        //   24: aload_2
        //   25: invokeinterface 87 1 0
        //   30: astore_1
        //   31: aload_3
        //   32: aload_1
        //   33: invokevirtual 47	android/os/Parcel:writeStrongBinder	(Landroid/os/IBinder;)V
        //   36: aload_0
        //   37: getfield 18	com/google/android/gms/drive/realtime/internal/zzm$zza$zza:zzoz	Landroid/os/IBinder;
        //   40: iconst_1
        //   41: aload_3
        //   42: aload 4
        //   44: iconst_0
        //   45: invokeinterface 53 5 0
        //   50: pop
        //   51: aload 4
        //   53: invokevirtual 56	android/os/Parcel:readException	()V
        //   56: aload 4
        //   58: invokevirtual 59	android/os/Parcel:recycle	()V
        //   61: aload_3
        //   62: invokevirtual 59	android/os/Parcel:recycle	()V
        //   65: return
        //   66: aconst_null
        //   67: astore_1
        //   68: goto -37 -> 31
        //   71: astore_1
        //   72: aload 4
        //   74: invokevirtual 59	android/os/Parcel:recycle	()V
        //   77: aload_3
        //   78: invokevirtual 59	android/os/Parcel:recycle	()V
        //   81: aload_1
        //   82: athrow
        // Local variable table:
        //   start	length	slot	name	signature
        //   0	83	0	this	zza
        //   0	83	1	paramString	String
        //   0	83	2	paramzzn	zzn
        //   3	75	3	localParcel1	Parcel
        //   7	66	4	localParcel2	Parcel
        // Exception table:
        //   from	to	target	type
        //   9	20	71	finally
        //   24	31	71	finally
        //   31	56	71	finally
      }
      
      /* Error */
      public void zza(String paramString, zzo paramzzo)
        throws RemoteException
      {
        // Byte code:
        //   0: invokestatic 30	android/os/Parcel:obtain	()Landroid/os/Parcel;
        //   3: astore_3
        //   4: invokestatic 30	android/os/Parcel:obtain	()Landroid/os/Parcel;
        //   7: astore 4
        //   9: aload_3
        //   10: ldc 32
        //   12: invokevirtual 36	android/os/Parcel:writeInterfaceToken	(Ljava/lang/String;)V
        //   15: aload_3
        //   16: aload_1
        //   17: invokevirtual 117	android/os/Parcel:writeString	(Ljava/lang/String;)V
        //   20: aload_2
        //   21: ifnull +46 -> 67
        //   24: aload_2
        //   25: invokeinterface 64 1 0
        //   30: astore_1
        //   31: aload_3
        //   32: aload_1
        //   33: invokevirtual 47	android/os/Parcel:writeStrongBinder	(Landroid/os/IBinder;)V
        //   36: aload_0
        //   37: getfield 18	com/google/android/gms/drive/realtime/internal/zzm$zza$zza:zzoz	Landroid/os/IBinder;
        //   40: bipush 38
        //   42: aload_3
        //   43: aload 4
        //   45: iconst_0
        //   46: invokeinterface 53 5 0
        //   51: pop
        //   52: aload 4
        //   54: invokevirtual 56	android/os/Parcel:readException	()V
        //   57: aload 4
        //   59: invokevirtual 59	android/os/Parcel:recycle	()V
        //   62: aload_3
        //   63: invokevirtual 59	android/os/Parcel:recycle	()V
        //   66: return
        //   67: aconst_null
        //   68: astore_1
        //   69: goto -38 -> 31
        //   72: astore_1
        //   73: aload 4
        //   75: invokevirtual 59	android/os/Parcel:recycle	()V
        //   78: aload_3
        //   79: invokevirtual 59	android/os/Parcel:recycle	()V
        //   82: aload_1
        //   83: athrow
        // Local variable table:
        //   start	length	slot	name	signature
        //   0	84	0	this	zza
        //   0	84	1	paramString	String
        //   0	84	2	paramzzo	zzo
        //   3	76	3	localParcel1	Parcel
        //   7	67	4	localParcel2	Parcel
        // Exception table:
        //   from	to	target	type
        //   9	20	72	finally
        //   24	31	72	finally
        //   31	57	72	finally
      }
      
      public void zza(String paramString1, String paramString2, DataHolder paramDataHolder, zzj paramzzj)
        throws RemoteException
      {
        Parcel localParcel1 = Parcel.obtain();
        Parcel localParcel2 = Parcel.obtain();
        for (;;)
        {
          try
          {
            localParcel1.writeInterfaceToken("com.google.android.gms.drive.realtime.internal.IRealtimeService");
            localParcel1.writeString(paramString1);
            localParcel1.writeString(paramString2);
            if (paramDataHolder != null)
            {
              localParcel1.writeInt(1);
              paramDataHolder.writeToParcel(localParcel1, 0);
              if (paramzzj != null)
              {
                paramString1 = paramzzj.asBinder();
                localParcel1.writeStrongBinder(paramString1);
                this.zzoz.transact(43, localParcel1, localParcel2, 0);
                localParcel2.readException();
              }
            }
            else
            {
              localParcel1.writeInt(0);
              continue;
            }
            paramString1 = null;
          }
          finally
          {
            localParcel2.recycle();
            localParcel1.recycle();
          }
        }
      }
      
      /* Error */
      public void zza(String paramString1, String paramString2, zzf paramzzf)
        throws RemoteException
      {
        // Byte code:
        //   0: invokestatic 30	android/os/Parcel:obtain	()Landroid/os/Parcel;
        //   3: astore 4
        //   5: invokestatic 30	android/os/Parcel:obtain	()Landroid/os/Parcel;
        //   8: astore 5
        //   10: aload 4
        //   12: ldc 32
        //   14: invokevirtual 36	android/os/Parcel:writeInterfaceToken	(Ljava/lang/String;)V
        //   17: aload 4
        //   19: aload_1
        //   20: invokevirtual 117	android/os/Parcel:writeString	(Ljava/lang/String;)V
        //   23: aload 4
        //   25: aload_2
        //   26: invokevirtual 117	android/os/Parcel:writeString	(Ljava/lang/String;)V
        //   29: aload_3
        //   30: ifnull +48 -> 78
        //   33: aload_3
        //   34: invokeinterface 135 1 0
        //   39: astore_1
        //   40: aload 4
        //   42: aload_1
        //   43: invokevirtual 47	android/os/Parcel:writeStrongBinder	(Landroid/os/IBinder;)V
        //   46: aload_0
        //   47: getfield 18	com/google/android/gms/drive/realtime/internal/zzm$zza$zza:zzoz	Landroid/os/IBinder;
        //   50: iconst_4
        //   51: aload 4
        //   53: aload 5
        //   55: iconst_0
        //   56: invokeinterface 53 5 0
        //   61: pop
        //   62: aload 5
        //   64: invokevirtual 56	android/os/Parcel:readException	()V
        //   67: aload 5
        //   69: invokevirtual 59	android/os/Parcel:recycle	()V
        //   72: aload 4
        //   74: invokevirtual 59	android/os/Parcel:recycle	()V
        //   77: return
        //   78: aconst_null
        //   79: astore_1
        //   80: goto -40 -> 40
        //   83: astore_1
        //   84: aload 5
        //   86: invokevirtual 59	android/os/Parcel:recycle	()V
        //   89: aload 4
        //   91: invokevirtual 59	android/os/Parcel:recycle	()V
        //   94: aload_1
        //   95: athrow
        // Local variable table:
        //   start	length	slot	name	signature
        //   0	96	0	this	zza
        //   0	96	1	paramString1	String
        //   0	96	2	paramString2	String
        //   0	96	3	paramzzf	zzf
        //   3	87	4	localParcel1	Parcel
        //   8	77	5	localParcel2	Parcel
        // Exception table:
        //   from	to	target	type
        //   10	29	83	finally
        //   33	40	83	finally
        //   40	67	83	finally
      }
      
      /* Error */
      public void zza(String paramString1, String paramString2, zzg paramzzg)
        throws RemoteException
      {
        // Byte code:
        //   0: invokestatic 30	android/os/Parcel:obtain	()Landroid/os/Parcel;
        //   3: astore 4
        //   5: invokestatic 30	android/os/Parcel:obtain	()Landroid/os/Parcel;
        //   8: astore 5
        //   10: aload 4
        //   12: ldc 32
        //   14: invokevirtual 36	android/os/Parcel:writeInterfaceToken	(Ljava/lang/String;)V
        //   17: aload 4
        //   19: aload_1
        //   20: invokevirtual 117	android/os/Parcel:writeString	(Ljava/lang/String;)V
        //   23: aload 4
        //   25: aload_2
        //   26: invokevirtual 117	android/os/Parcel:writeString	(Ljava/lang/String;)V
        //   29: aload_3
        //   30: ifnull +49 -> 79
        //   33: aload_3
        //   34: invokeinterface 120 1 0
        //   39: astore_1
        //   40: aload 4
        //   42: aload_1
        //   43: invokevirtual 47	android/os/Parcel:writeStrongBinder	(Landroid/os/IBinder;)V
        //   46: aload_0
        //   47: getfield 18	com/google/android/gms/drive/realtime/internal/zzm$zza$zza:zzoz	Landroid/os/IBinder;
        //   50: bipush 21
        //   52: aload 4
        //   54: aload 5
        //   56: iconst_0
        //   57: invokeinterface 53 5 0
        //   62: pop
        //   63: aload 5
        //   65: invokevirtual 56	android/os/Parcel:readException	()V
        //   68: aload 5
        //   70: invokevirtual 59	android/os/Parcel:recycle	()V
        //   73: aload 4
        //   75: invokevirtual 59	android/os/Parcel:recycle	()V
        //   78: return
        //   79: aconst_null
        //   80: astore_1
        //   81: goto -41 -> 40
        //   84: astore_1
        //   85: aload 5
        //   87: invokevirtual 59	android/os/Parcel:recycle	()V
        //   90: aload 4
        //   92: invokevirtual 59	android/os/Parcel:recycle	()V
        //   95: aload_1
        //   96: athrow
        // Local variable table:
        //   start	length	slot	name	signature
        //   0	97	0	this	zza
        //   0	97	1	paramString1	String
        //   0	97	2	paramString2	String
        //   0	97	3	paramzzg	zzg
        //   3	88	4	localParcel1	Parcel
        //   8	78	5	localParcel2	Parcel
        // Exception table:
        //   from	to	target	type
        //   10	29	84	finally
        //   33	40	84	finally
        //   40	68	84	finally
      }
      
      /* Error */
      public void zza(String paramString1, String paramString2, zzj paramzzj)
        throws RemoteException
      {
        // Byte code:
        //   0: invokestatic 30	android/os/Parcel:obtain	()Landroid/os/Parcel;
        //   3: astore 4
        //   5: invokestatic 30	android/os/Parcel:obtain	()Landroid/os/Parcel;
        //   8: astore 5
        //   10: aload 4
        //   12: ldc 32
        //   14: invokevirtual 36	android/os/Parcel:writeInterfaceToken	(Ljava/lang/String;)V
        //   17: aload 4
        //   19: aload_1
        //   20: invokevirtual 117	android/os/Parcel:writeString	(Ljava/lang/String;)V
        //   23: aload 4
        //   25: aload_2
        //   26: invokevirtual 117	android/os/Parcel:writeString	(Ljava/lang/String;)V
        //   29: aload_3
        //   30: ifnull +49 -> 79
        //   33: aload_3
        //   34: invokeinterface 44 1 0
        //   39: astore_1
        //   40: aload 4
        //   42: aload_1
        //   43: invokevirtual 47	android/os/Parcel:writeStrongBinder	(Landroid/os/IBinder;)V
        //   46: aload_0
        //   47: getfield 18	com/google/android/gms/drive/realtime/internal/zzm$zza$zza:zzoz	Landroid/os/IBinder;
        //   50: bipush 12
        //   52: aload 4
        //   54: aload 5
        //   56: iconst_0
        //   57: invokeinterface 53 5 0
        //   62: pop
        //   63: aload 5
        //   65: invokevirtual 56	android/os/Parcel:readException	()V
        //   68: aload 5
        //   70: invokevirtual 59	android/os/Parcel:recycle	()V
        //   73: aload 4
        //   75: invokevirtual 59	android/os/Parcel:recycle	()V
        //   78: return
        //   79: aconst_null
        //   80: astore_1
        //   81: goto -41 -> 40
        //   84: astore_1
        //   85: aload 5
        //   87: invokevirtual 59	android/os/Parcel:recycle	()V
        //   90: aload 4
        //   92: invokevirtual 59	android/os/Parcel:recycle	()V
        //   95: aload_1
        //   96: athrow
        // Local variable table:
        //   start	length	slot	name	signature
        //   0	97	0	this	zza
        //   0	97	1	paramString1	String
        //   0	97	2	paramString2	String
        //   0	97	3	paramzzj	zzj
        //   3	88	4	localParcel1	Parcel
        //   8	78	5	localParcel2	Parcel
        // Exception table:
        //   from	to	target	type
        //   10	29	84	finally
        //   33	40	84	finally
        //   40	68	84	finally
      }
      
      /* Error */
      public void zza(boolean paramBoolean, zzo paramzzo)
        throws RemoteException
      {
        // Byte code:
        //   0: iconst_0
        //   1: istore_3
        //   2: invokestatic 30	android/os/Parcel:obtain	()Landroid/os/Parcel;
        //   5: astore 4
        //   7: invokestatic 30	android/os/Parcel:obtain	()Landroid/os/Parcel;
        //   10: astore 5
        //   12: aload 4
        //   14: ldc 32
        //   16: invokevirtual 36	android/os/Parcel:writeInterfaceToken	(Ljava/lang/String;)V
        //   19: iload_1
        //   20: ifeq +5 -> 25
        //   23: iconst_1
        //   24: istore_3
        //   25: aload 4
        //   27: iload_3
        //   28: invokevirtual 40	android/os/Parcel:writeInt	(I)V
        //   31: aload_2
        //   32: ifnull +49 -> 81
        //   35: aload_2
        //   36: invokeinterface 64 1 0
        //   41: astore_2
        //   42: aload 4
        //   44: aload_2
        //   45: invokevirtual 47	android/os/Parcel:writeStrongBinder	(Landroid/os/IBinder;)V
        //   48: aload_0
        //   49: getfield 18	com/google/android/gms/drive/realtime/internal/zzm$zza$zza:zzoz	Landroid/os/IBinder;
        //   52: bipush 47
        //   54: aload 4
        //   56: aload 5
        //   58: iconst_0
        //   59: invokeinterface 53 5 0
        //   64: pop
        //   65: aload 5
        //   67: invokevirtual 56	android/os/Parcel:readException	()V
        //   70: aload 5
        //   72: invokevirtual 59	android/os/Parcel:recycle	()V
        //   75: aload 4
        //   77: invokevirtual 59	android/os/Parcel:recycle	()V
        //   80: return
        //   81: aconst_null
        //   82: astore_2
        //   83: goto -41 -> 42
        //   86: astore_2
        //   87: aload 5
        //   89: invokevirtual 59	android/os/Parcel:recycle	()V
        //   92: aload 4
        //   94: invokevirtual 59	android/os/Parcel:recycle	()V
        //   97: aload_2
        //   98: athrow
        // Local variable table:
        //   start	length	slot	name	signature
        //   0	99	0	this	zza
        //   0	99	1	paramBoolean	boolean
        //   0	99	2	paramzzo	zzo
        //   1	27	3	i	int
        //   5	88	4	localParcel1	Parcel
        //   10	78	5	localParcel2	Parcel
        // Exception table:
        //   from	to	target	type
        //   12	19	86	finally
        //   25	31	86	finally
        //   35	42	86	finally
        //   42	70	86	finally
      }
      
      /* Error */
      public void zzb(zzc paramzzc)
        throws RemoteException
      {
        // Byte code:
        //   0: invokestatic 30	android/os/Parcel:obtain	()Landroid/os/Parcel;
        //   3: astore_2
        //   4: invokestatic 30	android/os/Parcel:obtain	()Landroid/os/Parcel;
        //   7: astore_3
        //   8: aload_2
        //   9: ldc 32
        //   11: invokevirtual 36	android/os/Parcel:writeInterfaceToken	(Ljava/lang/String;)V
        //   14: aload_1
        //   15: ifnull +43 -> 58
        //   18: aload_1
        //   19: invokeinterface 91 1 0
        //   24: astore_1
        //   25: aload_2
        //   26: aload_1
        //   27: invokevirtual 47	android/os/Parcel:writeStrongBinder	(Landroid/os/IBinder;)V
        //   30: aload_0
        //   31: getfield 18	com/google/android/gms/drive/realtime/internal/zzm$zza$zza:zzoz	Landroid/os/IBinder;
        //   34: bipush 33
        //   36: aload_2
        //   37: aload_3
        //   38: iconst_0
        //   39: invokeinterface 53 5 0
        //   44: pop
        //   45: aload_3
        //   46: invokevirtual 56	android/os/Parcel:readException	()V
        //   49: aload_3
        //   50: invokevirtual 59	android/os/Parcel:recycle	()V
        //   53: aload_2
        //   54: invokevirtual 59	android/os/Parcel:recycle	()V
        //   57: return
        //   58: aconst_null
        //   59: astore_1
        //   60: goto -35 -> 25
        //   63: astore_1
        //   64: aload_3
        //   65: invokevirtual 59	android/os/Parcel:recycle	()V
        //   68: aload_2
        //   69: invokevirtual 59	android/os/Parcel:recycle	()V
        //   72: aload_1
        //   73: athrow
        // Local variable table:
        //   start	length	slot	name	signature
        //   0	74	0	this	zza
        //   0	74	1	paramzzc	zzc
        //   3	66	2	localParcel1	Parcel
        //   7	58	3	localParcel2	Parcel
        // Exception table:
        //   from	to	target	type
        //   8	14	63	finally
        //   18	25	63	finally
        //   25	49	63	finally
      }
      
      /* Error */
      public void zzb(zzj paramzzj)
        throws RemoteException
      {
        // Byte code:
        //   0: invokestatic 30	android/os/Parcel:obtain	()Landroid/os/Parcel;
        //   3: astore_2
        //   4: invokestatic 30	android/os/Parcel:obtain	()Landroid/os/Parcel;
        //   7: astore_3
        //   8: aload_2
        //   9: ldc 32
        //   11: invokevirtual 36	android/os/Parcel:writeInterfaceToken	(Ljava/lang/String;)V
        //   14: aload_1
        //   15: ifnull +43 -> 58
        //   18: aload_1
        //   19: invokeinterface 44 1 0
        //   24: astore_1
        //   25: aload_2
        //   26: aload_1
        //   27: invokevirtual 47	android/os/Parcel:writeStrongBinder	(Landroid/os/IBinder;)V
        //   30: aload_0
        //   31: getfield 18	com/google/android/gms/drive/realtime/internal/zzm$zza$zza:zzoz	Landroid/os/IBinder;
        //   34: bipush 23
        //   36: aload_2
        //   37: aload_3
        //   38: iconst_0
        //   39: invokeinterface 53 5 0
        //   44: pop
        //   45: aload_3
        //   46: invokevirtual 56	android/os/Parcel:readException	()V
        //   49: aload_3
        //   50: invokevirtual 59	android/os/Parcel:recycle	()V
        //   53: aload_2
        //   54: invokevirtual 59	android/os/Parcel:recycle	()V
        //   57: return
        //   58: aconst_null
        //   59: astore_1
        //   60: goto -35 -> 25
        //   63: astore_1
        //   64: aload_3
        //   65: invokevirtual 59	android/os/Parcel:recycle	()V
        //   68: aload_2
        //   69: invokevirtual 59	android/os/Parcel:recycle	()V
        //   72: aload_1
        //   73: athrow
        // Local variable table:
        //   start	length	slot	name	signature
        //   0	74	0	this	zza
        //   0	74	1	paramzzj	zzj
        //   3	66	2	localParcel1	Parcel
        //   7	58	3	localParcel2	Parcel
        // Exception table:
        //   from	to	target	type
        //   8	14	63	finally
        //   18	25	63	finally
        //   25	49	63	finally
      }
      
      /* Error */
      public void zzb(zzl paramzzl)
        throws RemoteException
      {
        // Byte code:
        //   0: invokestatic 30	android/os/Parcel:obtain	()Landroid/os/Parcel;
        //   3: astore_2
        //   4: invokestatic 30	android/os/Parcel:obtain	()Landroid/os/Parcel;
        //   7: astore_3
        //   8: aload_2
        //   9: ldc 32
        //   11: invokevirtual 36	android/os/Parcel:writeInterfaceToken	(Ljava/lang/String;)V
        //   14: aload_1
        //   15: ifnull +43 -> 58
        //   18: aload_1
        //   19: invokeinterface 112 1 0
        //   24: astore_1
        //   25: aload_2
        //   26: aload_1
        //   27: invokevirtual 47	android/os/Parcel:writeStrongBinder	(Landroid/os/IBinder;)V
        //   30: aload_0
        //   31: getfield 18	com/google/android/gms/drive/realtime/internal/zzm$zza$zza:zzoz	Landroid/os/IBinder;
        //   34: bipush 29
        //   36: aload_2
        //   37: aload_3
        //   38: iconst_0
        //   39: invokeinterface 53 5 0
        //   44: pop
        //   45: aload_3
        //   46: invokevirtual 56	android/os/Parcel:readException	()V
        //   49: aload_3
        //   50: invokevirtual 59	android/os/Parcel:recycle	()V
        //   53: aload_2
        //   54: invokevirtual 59	android/os/Parcel:recycle	()V
        //   57: return
        //   58: aconst_null
        //   59: astore_1
        //   60: goto -35 -> 25
        //   63: astore_1
        //   64: aload_3
        //   65: invokevirtual 59	android/os/Parcel:recycle	()V
        //   68: aload_2
        //   69: invokevirtual 59	android/os/Parcel:recycle	()V
        //   72: aload_1
        //   73: athrow
        // Local variable table:
        //   start	length	slot	name	signature
        //   0	74	0	this	zza
        //   0	74	1	paramzzl	zzl
        //   3	66	2	localParcel1	Parcel
        //   7	58	3	localParcel2	Parcel
        // Exception table:
        //   from	to	target	type
        //   8	14	63	finally
        //   18	25	63	finally
        //   25	49	63	finally
      }
      
      /* Error */
      public void zzb(zzo paramzzo)
        throws RemoteException
      {
        // Byte code:
        //   0: invokestatic 30	android/os/Parcel:obtain	()Landroid/os/Parcel;
        //   3: astore_2
        //   4: invokestatic 30	android/os/Parcel:obtain	()Landroid/os/Parcel;
        //   7: astore_3
        //   8: aload_2
        //   9: ldc 32
        //   11: invokevirtual 36	android/os/Parcel:writeInterfaceToken	(Ljava/lang/String;)V
        //   14: aload_1
        //   15: ifnull +43 -> 58
        //   18: aload_1
        //   19: invokeinterface 64 1 0
        //   24: astore_1
        //   25: aload_2
        //   26: aload_1
        //   27: invokevirtual 47	android/os/Parcel:writeStrongBinder	(Landroid/os/IBinder;)V
        //   30: aload_0
        //   31: getfield 18	com/google/android/gms/drive/realtime/internal/zzm$zza$zza:zzoz	Landroid/os/IBinder;
        //   34: bipush 35
        //   36: aload_2
        //   37: aload_3
        //   38: iconst_0
        //   39: invokeinterface 53 5 0
        //   44: pop
        //   45: aload_3
        //   46: invokevirtual 56	android/os/Parcel:readException	()V
        //   49: aload_3
        //   50: invokevirtual 59	android/os/Parcel:recycle	()V
        //   53: aload_2
        //   54: invokevirtual 59	android/os/Parcel:recycle	()V
        //   57: return
        //   58: aconst_null
        //   59: astore_1
        //   60: goto -35 -> 25
        //   63: astore_1
        //   64: aload_3
        //   65: invokevirtual 59	android/os/Parcel:recycle	()V
        //   68: aload_2
        //   69: invokevirtual 59	android/os/Parcel:recycle	()V
        //   72: aload_1
        //   73: athrow
        // Local variable table:
        //   start	length	slot	name	signature
        //   0	74	0	this	zza
        //   0	74	1	paramzzo	zzo
        //   3	66	2	localParcel1	Parcel
        //   7	58	3	localParcel2	Parcel
        // Exception table:
        //   from	to	target	type
        //   8	14	63	finally
        //   18	25	63	finally
        //   25	49	63	finally
      }
      
      /* Error */
      public void zzb(String paramString, zzf paramzzf)
        throws RemoteException
      {
        // Byte code:
        //   0: invokestatic 30	android/os/Parcel:obtain	()Landroid/os/Parcel;
        //   3: astore_3
        //   4: invokestatic 30	android/os/Parcel:obtain	()Landroid/os/Parcel;
        //   7: astore 4
        //   9: aload_3
        //   10: ldc 32
        //   12: invokevirtual 36	android/os/Parcel:writeInterfaceToken	(Ljava/lang/String;)V
        //   15: aload_3
        //   16: aload_1
        //   17: invokevirtual 117	android/os/Parcel:writeString	(Ljava/lang/String;)V
        //   20: aload_2
        //   21: ifnull +46 -> 67
        //   24: aload_2
        //   25: invokeinterface 135 1 0
        //   30: astore_1
        //   31: aload_3
        //   32: aload_1
        //   33: invokevirtual 47	android/os/Parcel:writeStrongBinder	(Landroid/os/IBinder;)V
        //   36: aload_0
        //   37: getfield 18	com/google/android/gms/drive/realtime/internal/zzm$zza$zza:zzoz	Landroid/os/IBinder;
        //   40: bipush 13
        //   42: aload_3
        //   43: aload 4
        //   45: iconst_0
        //   46: invokeinterface 53 5 0
        //   51: pop
        //   52: aload 4
        //   54: invokevirtual 56	android/os/Parcel:readException	()V
        //   57: aload 4
        //   59: invokevirtual 59	android/os/Parcel:recycle	()V
        //   62: aload_3
        //   63: invokevirtual 59	android/os/Parcel:recycle	()V
        //   66: return
        //   67: aconst_null
        //   68: astore_1
        //   69: goto -38 -> 31
        //   72: astore_1
        //   73: aload 4
        //   75: invokevirtual 59	android/os/Parcel:recycle	()V
        //   78: aload_3
        //   79: invokevirtual 59	android/os/Parcel:recycle	()V
        //   82: aload_1
        //   83: athrow
        // Local variable table:
        //   start	length	slot	name	signature
        //   0	84	0	this	zza
        //   0	84	1	paramString	String
        //   0	84	2	paramzzf	zzf
        //   3	76	3	localParcel1	Parcel
        //   7	67	4	localParcel2	Parcel
        // Exception table:
        //   from	to	target	type
        //   9	20	72	finally
        //   24	31	72	finally
        //   31	57	72	finally
      }
      
      /* Error */
      public void zzb(String paramString, zzl paramzzl)
        throws RemoteException
      {
        // Byte code:
        //   0: invokestatic 30	android/os/Parcel:obtain	()Landroid/os/Parcel;
        //   3: astore_3
        //   4: invokestatic 30	android/os/Parcel:obtain	()Landroid/os/Parcel;
        //   7: astore 4
        //   9: aload_3
        //   10: ldc 32
        //   12: invokevirtual 36	android/os/Parcel:writeInterfaceToken	(Ljava/lang/String;)V
        //   15: aload_3
        //   16: aload_1
        //   17: invokevirtual 117	android/os/Parcel:writeString	(Ljava/lang/String;)V
        //   20: aload_2
        //   21: ifnull +46 -> 67
        //   24: aload_2
        //   25: invokeinterface 112 1 0
        //   30: astore_1
        //   31: aload_3
        //   32: aload_1
        //   33: invokevirtual 47	android/os/Parcel:writeStrongBinder	(Landroid/os/IBinder;)V
        //   36: aload_0
        //   37: getfield 18	com/google/android/gms/drive/realtime/internal/zzm$zza$zza:zzoz	Landroid/os/IBinder;
        //   40: bipush 8
        //   42: aload_3
        //   43: aload 4
        //   45: iconst_0
        //   46: invokeinterface 53 5 0
        //   51: pop
        //   52: aload 4
        //   54: invokevirtual 56	android/os/Parcel:readException	()V
        //   57: aload 4
        //   59: invokevirtual 59	android/os/Parcel:recycle	()V
        //   62: aload_3
        //   63: invokevirtual 59	android/os/Parcel:recycle	()V
        //   66: return
        //   67: aconst_null
        //   68: astore_1
        //   69: goto -38 -> 31
        //   72: astore_1
        //   73: aload 4
        //   75: invokevirtual 59	android/os/Parcel:recycle	()V
        //   78: aload_3
        //   79: invokevirtual 59	android/os/Parcel:recycle	()V
        //   82: aload_1
        //   83: athrow
        // Local variable table:
        //   start	length	slot	name	signature
        //   0	84	0	this	zza
        //   0	84	1	paramString	String
        //   0	84	2	paramzzl	zzl
        //   3	76	3	localParcel1	Parcel
        //   7	67	4	localParcel2	Parcel
        // Exception table:
        //   from	to	target	type
        //   9	20	72	finally
        //   24	31	72	finally
        //   31	57	72	finally
      }
      
      /* Error */
      public void zzb(String paramString, zzn paramzzn)
        throws RemoteException
      {
        // Byte code:
        //   0: invokestatic 30	android/os/Parcel:obtain	()Landroid/os/Parcel;
        //   3: astore_3
        //   4: invokestatic 30	android/os/Parcel:obtain	()Landroid/os/Parcel;
        //   7: astore 4
        //   9: aload_3
        //   10: ldc 32
        //   12: invokevirtual 36	android/os/Parcel:writeInterfaceToken	(Ljava/lang/String;)V
        //   15: aload_3
        //   16: aload_1
        //   17: invokevirtual 117	android/os/Parcel:writeString	(Ljava/lang/String;)V
        //   20: aload_2
        //   21: ifnull +46 -> 67
        //   24: aload_2
        //   25: invokeinterface 87 1 0
        //   30: astore_1
        //   31: aload_3
        //   32: aload_1
        //   33: invokevirtual 47	android/os/Parcel:writeStrongBinder	(Landroid/os/IBinder;)V
        //   36: aload_0
        //   37: getfield 18	com/google/android/gms/drive/realtime/internal/zzm$zza$zza:zzoz	Landroid/os/IBinder;
        //   40: bipush 9
        //   42: aload_3
        //   43: aload 4
        //   45: iconst_0
        //   46: invokeinterface 53 5 0
        //   51: pop
        //   52: aload 4
        //   54: invokevirtual 56	android/os/Parcel:readException	()V
        //   57: aload 4
        //   59: invokevirtual 59	android/os/Parcel:recycle	()V
        //   62: aload_3
        //   63: invokevirtual 59	android/os/Parcel:recycle	()V
        //   66: return
        //   67: aconst_null
        //   68: astore_1
        //   69: goto -38 -> 31
        //   72: astore_1
        //   73: aload 4
        //   75: invokevirtual 59	android/os/Parcel:recycle	()V
        //   78: aload_3
        //   79: invokevirtual 59	android/os/Parcel:recycle	()V
        //   82: aload_1
        //   83: athrow
        // Local variable table:
        //   start	length	slot	name	signature
        //   0	84	0	this	zza
        //   0	84	1	paramString	String
        //   0	84	2	paramzzn	zzn
        //   3	76	3	localParcel1	Parcel
        //   7	67	4	localParcel2	Parcel
        // Exception table:
        //   from	to	target	type
        //   9	20	72	finally
        //   24	31	72	finally
        //   31	57	72	finally
      }
      
      /* Error */
      public void zzb(String paramString, zzo paramzzo)
        throws RemoteException
      {
        // Byte code:
        //   0: invokestatic 30	android/os/Parcel:obtain	()Landroid/os/Parcel;
        //   3: astore_3
        //   4: invokestatic 30	android/os/Parcel:obtain	()Landroid/os/Parcel;
        //   7: astore 4
        //   9: aload_3
        //   10: ldc 32
        //   12: invokevirtual 36	android/os/Parcel:writeInterfaceToken	(Ljava/lang/String;)V
        //   15: aload_3
        //   16: aload_1
        //   17: invokevirtual 117	android/os/Parcel:writeString	(Ljava/lang/String;)V
        //   20: aload_2
        //   21: ifnull +46 -> 67
        //   24: aload_2
        //   25: invokeinterface 64 1 0
        //   30: astore_1
        //   31: aload_3
        //   32: aload_1
        //   33: invokevirtual 47	android/os/Parcel:writeStrongBinder	(Landroid/os/IBinder;)V
        //   36: aload_0
        //   37: getfield 18	com/google/android/gms/drive/realtime/internal/zzm$zza$zza:zzoz	Landroid/os/IBinder;
        //   40: bipush 39
        //   42: aload_3
        //   43: aload 4
        //   45: iconst_0
        //   46: invokeinterface 53 5 0
        //   51: pop
        //   52: aload 4
        //   54: invokevirtual 56	android/os/Parcel:readException	()V
        //   57: aload 4
        //   59: invokevirtual 59	android/os/Parcel:recycle	()V
        //   62: aload_3
        //   63: invokevirtual 59	android/os/Parcel:recycle	()V
        //   66: return
        //   67: aconst_null
        //   68: astore_1
        //   69: goto -38 -> 31
        //   72: astore_1
        //   73: aload 4
        //   75: invokevirtual 59	android/os/Parcel:recycle	()V
        //   78: aload_3
        //   79: invokevirtual 59	android/os/Parcel:recycle	()V
        //   82: aload_1
        //   83: athrow
        // Local variable table:
        //   start	length	slot	name	signature
        //   0	84	0	this	zza
        //   0	84	1	paramString	String
        //   0	84	2	paramzzo	zzo
        //   3	76	3	localParcel1	Parcel
        //   7	67	4	localParcel2	Parcel
        // Exception table:
        //   from	to	target	type
        //   9	20	72	finally
        //   24	31	72	finally
        //   31	57	72	finally
      }
      
      /* Error */
      public void zzb(String paramString1, String paramString2, zzf paramzzf)
        throws RemoteException
      {
        // Byte code:
        //   0: invokestatic 30	android/os/Parcel:obtain	()Landroid/os/Parcel;
        //   3: astore 4
        //   5: invokestatic 30	android/os/Parcel:obtain	()Landroid/os/Parcel;
        //   8: astore 5
        //   10: aload 4
        //   12: ldc 32
        //   14: invokevirtual 36	android/os/Parcel:writeInterfaceToken	(Ljava/lang/String;)V
        //   17: aload 4
        //   19: aload_1
        //   20: invokevirtual 117	android/os/Parcel:writeString	(Ljava/lang/String;)V
        //   23: aload 4
        //   25: aload_2
        //   26: invokevirtual 117	android/os/Parcel:writeString	(Ljava/lang/String;)V
        //   29: aload_3
        //   30: ifnull +49 -> 79
        //   33: aload_3
        //   34: invokeinterface 135 1 0
        //   39: astore_1
        //   40: aload 4
        //   42: aload_1
        //   43: invokevirtual 47	android/os/Parcel:writeStrongBinder	(Landroid/os/IBinder;)V
        //   46: aload_0
        //   47: getfield 18	com/google/android/gms/drive/realtime/internal/zzm$zza$zza:zzoz	Landroid/os/IBinder;
        //   50: bipush 42
        //   52: aload 4
        //   54: aload 5
        //   56: iconst_0
        //   57: invokeinterface 53 5 0
        //   62: pop
        //   63: aload 5
        //   65: invokevirtual 56	android/os/Parcel:readException	()V
        //   68: aload 5
        //   70: invokevirtual 59	android/os/Parcel:recycle	()V
        //   73: aload 4
        //   75: invokevirtual 59	android/os/Parcel:recycle	()V
        //   78: return
        //   79: aconst_null
        //   80: astore_1
        //   81: goto -41 -> 40
        //   84: astore_1
        //   85: aload 5
        //   87: invokevirtual 59	android/os/Parcel:recycle	()V
        //   90: aload 4
        //   92: invokevirtual 59	android/os/Parcel:recycle	()V
        //   95: aload_1
        //   96: athrow
        // Local variable table:
        //   start	length	slot	name	signature
        //   0	97	0	this	zza
        //   0	97	1	paramString1	String
        //   0	97	2	paramString2	String
        //   0	97	3	paramzzf	zzf
        //   3	88	4	localParcel1	Parcel
        //   8	78	5	localParcel2	Parcel
        // Exception table:
        //   from	to	target	type
        //   10	29	84	finally
        //   33	40	84	finally
        //   40	68	84	finally
      }
      
      /* Error */
      public void zzc(zzc paramzzc)
        throws RemoteException
      {
        // Byte code:
        //   0: invokestatic 30	android/os/Parcel:obtain	()Landroid/os/Parcel;
        //   3: astore_2
        //   4: invokestatic 30	android/os/Parcel:obtain	()Landroid/os/Parcel;
        //   7: astore_3
        //   8: aload_2
        //   9: ldc 32
        //   11: invokevirtual 36	android/os/Parcel:writeInterfaceToken	(Ljava/lang/String;)V
        //   14: aload_1
        //   15: ifnull +43 -> 58
        //   18: aload_1
        //   19: invokeinterface 91 1 0
        //   24: astore_1
        //   25: aload_2
        //   26: aload_1
        //   27: invokevirtual 47	android/os/Parcel:writeStrongBinder	(Landroid/os/IBinder;)V
        //   30: aload_0
        //   31: getfield 18	com/google/android/gms/drive/realtime/internal/zzm$zza$zza:zzoz	Landroid/os/IBinder;
        //   34: bipush 45
        //   36: aload_2
        //   37: aload_3
        //   38: iconst_0
        //   39: invokeinterface 53 5 0
        //   44: pop
        //   45: aload_3
        //   46: invokevirtual 56	android/os/Parcel:readException	()V
        //   49: aload_3
        //   50: invokevirtual 59	android/os/Parcel:recycle	()V
        //   53: aload_2
        //   54: invokevirtual 59	android/os/Parcel:recycle	()V
        //   57: return
        //   58: aconst_null
        //   59: astore_1
        //   60: goto -35 -> 25
        //   63: astore_1
        //   64: aload_3
        //   65: invokevirtual 59	android/os/Parcel:recycle	()V
        //   68: aload_2
        //   69: invokevirtual 59	android/os/Parcel:recycle	()V
        //   72: aload_1
        //   73: athrow
        // Local variable table:
        //   start	length	slot	name	signature
        //   0	74	0	this	zza
        //   0	74	1	paramzzc	zzc
        //   3	66	2	localParcel1	Parcel
        //   7	58	3	localParcel2	Parcel
        // Exception table:
        //   from	to	target	type
        //   8	14	63	finally
        //   18	25	63	finally
        //   25	49	63	finally
      }
      
      /* Error */
      public void zzc(zzo paramzzo)
        throws RemoteException
      {
        // Byte code:
        //   0: invokestatic 30	android/os/Parcel:obtain	()Landroid/os/Parcel;
        //   3: astore_2
        //   4: invokestatic 30	android/os/Parcel:obtain	()Landroid/os/Parcel;
        //   7: astore_3
        //   8: aload_2
        //   9: ldc 32
        //   11: invokevirtual 36	android/os/Parcel:writeInterfaceToken	(Ljava/lang/String;)V
        //   14: aload_1
        //   15: ifnull +43 -> 58
        //   18: aload_1
        //   19: invokeinterface 64 1 0
        //   24: astore_1
        //   25: aload_2
        //   26: aload_1
        //   27: invokevirtual 47	android/os/Parcel:writeStrongBinder	(Landroid/os/IBinder;)V
        //   30: aload_0
        //   31: getfield 18	com/google/android/gms/drive/realtime/internal/zzm$zza$zza:zzoz	Landroid/os/IBinder;
        //   34: bipush 49
        //   36: aload_2
        //   37: aload_3
        //   38: iconst_0
        //   39: invokeinterface 53 5 0
        //   44: pop
        //   45: aload_3
        //   46: invokevirtual 56	android/os/Parcel:readException	()V
        //   49: aload_3
        //   50: invokevirtual 59	android/os/Parcel:recycle	()V
        //   53: aload_2
        //   54: invokevirtual 59	android/os/Parcel:recycle	()V
        //   57: return
        //   58: aconst_null
        //   59: astore_1
        //   60: goto -35 -> 25
        //   63: astore_1
        //   64: aload_3
        //   65: invokevirtual 59	android/os/Parcel:recycle	()V
        //   68: aload_2
        //   69: invokevirtual 59	android/os/Parcel:recycle	()V
        //   72: aload_1
        //   73: athrow
        // Local variable table:
        //   start	length	slot	name	signature
        //   0	74	0	this	zza
        //   0	74	1	paramzzo	zzo
        //   3	66	2	localParcel1	Parcel
        //   7	58	3	localParcel2	Parcel
        // Exception table:
        //   from	to	target	type
        //   8	14	63	finally
        //   18	25	63	finally
        //   25	49	63	finally
      }
      
      /* Error */
      public void zzc(String paramString, zzl paramzzl)
        throws RemoteException
      {
        // Byte code:
        //   0: invokestatic 30	android/os/Parcel:obtain	()Landroid/os/Parcel;
        //   3: astore_3
        //   4: invokestatic 30	android/os/Parcel:obtain	()Landroid/os/Parcel;
        //   7: astore 4
        //   9: aload_3
        //   10: ldc 32
        //   12: invokevirtual 36	android/os/Parcel:writeInterfaceToken	(Ljava/lang/String;)V
        //   15: aload_3
        //   16: aload_1
        //   17: invokevirtual 117	android/os/Parcel:writeString	(Ljava/lang/String;)V
        //   20: aload_2
        //   21: ifnull +46 -> 67
        //   24: aload_2
        //   25: invokeinterface 112 1 0
        //   30: astore_1
        //   31: aload_3
        //   32: aload_1
        //   33: invokevirtual 47	android/os/Parcel:writeStrongBinder	(Landroid/os/IBinder;)V
        //   36: aload_0
        //   37: getfield 18	com/google/android/gms/drive/realtime/internal/zzm$zza$zza:zzoz	Landroid/os/IBinder;
        //   40: bipush 14
        //   42: aload_3
        //   43: aload 4
        //   45: iconst_0
        //   46: invokeinterface 53 5 0
        //   51: pop
        //   52: aload 4
        //   54: invokevirtual 56	android/os/Parcel:readException	()V
        //   57: aload 4
        //   59: invokevirtual 59	android/os/Parcel:recycle	()V
        //   62: aload_3
        //   63: invokevirtual 59	android/os/Parcel:recycle	()V
        //   66: return
        //   67: aconst_null
        //   68: astore_1
        //   69: goto -38 -> 31
        //   72: astore_1
        //   73: aload 4
        //   75: invokevirtual 59	android/os/Parcel:recycle	()V
        //   78: aload_3
        //   79: invokevirtual 59	android/os/Parcel:recycle	()V
        //   82: aload_1
        //   83: athrow
        // Local variable table:
        //   start	length	slot	name	signature
        //   0	84	0	this	zza
        //   0	84	1	paramString	String
        //   0	84	2	paramzzl	zzl
        //   3	76	3	localParcel1	Parcel
        //   7	67	4	localParcel2	Parcel
        // Exception table:
        //   from	to	target	type
        //   9	20	72	finally
        //   24	31	72	finally
        //   31	57	72	finally
      }
      
      /* Error */
      public void zzd(zzc paramzzc)
        throws RemoteException
      {
        // Byte code:
        //   0: invokestatic 30	android/os/Parcel:obtain	()Landroid/os/Parcel;
        //   3: astore_2
        //   4: invokestatic 30	android/os/Parcel:obtain	()Landroid/os/Parcel;
        //   7: astore_3
        //   8: aload_2
        //   9: ldc 32
        //   11: invokevirtual 36	android/os/Parcel:writeInterfaceToken	(Ljava/lang/String;)V
        //   14: aload_1
        //   15: ifnull +43 -> 58
        //   18: aload_1
        //   19: invokeinterface 91 1 0
        //   24: astore_1
        //   25: aload_2
        //   26: aload_1
        //   27: invokevirtual 47	android/os/Parcel:writeStrongBinder	(Landroid/os/IBinder;)V
        //   30: aload_0
        //   31: getfield 18	com/google/android/gms/drive/realtime/internal/zzm$zza$zza:zzoz	Landroid/os/IBinder;
        //   34: bipush 24
        //   36: aload_2
        //   37: aload_3
        //   38: iconst_0
        //   39: invokeinterface 53 5 0
        //   44: pop
        //   45: aload_3
        //   46: invokevirtual 56	android/os/Parcel:readException	()V
        //   49: aload_3
        //   50: invokevirtual 59	android/os/Parcel:recycle	()V
        //   53: aload_2
        //   54: invokevirtual 59	android/os/Parcel:recycle	()V
        //   57: return
        //   58: aconst_null
        //   59: astore_1
        //   60: goto -35 -> 25
        //   63: astore_1
        //   64: aload_3
        //   65: invokevirtual 59	android/os/Parcel:recycle	()V
        //   68: aload_2
        //   69: invokevirtual 59	android/os/Parcel:recycle	()V
        //   72: aload_1
        //   73: athrow
        // Local variable table:
        //   start	length	slot	name	signature
        //   0	74	0	this	zza
        //   0	74	1	paramzzc	zzc
        //   3	66	2	localParcel1	Parcel
        //   7	58	3	localParcel2	Parcel
        // Exception table:
        //   from	to	target	type
        //   8	14	63	finally
        //   18	25	63	finally
        //   25	49	63	finally
      }
      
      /* Error */
      public void zze(zzc paramzzc)
        throws RemoteException
      {
        // Byte code:
        //   0: invokestatic 30	android/os/Parcel:obtain	()Landroid/os/Parcel;
        //   3: astore_2
        //   4: invokestatic 30	android/os/Parcel:obtain	()Landroid/os/Parcel;
        //   7: astore_3
        //   8: aload_2
        //   9: ldc 32
        //   11: invokevirtual 36	android/os/Parcel:writeInterfaceToken	(Ljava/lang/String;)V
        //   14: aload_1
        //   15: ifnull +43 -> 58
        //   18: aload_1
        //   19: invokeinterface 91 1 0
        //   24: astore_1
        //   25: aload_2
        //   26: aload_1
        //   27: invokevirtual 47	android/os/Parcel:writeStrongBinder	(Landroid/os/IBinder;)V
        //   30: aload_0
        //   31: getfield 18	com/google/android/gms/drive/realtime/internal/zzm$zza$zza:zzoz	Landroid/os/IBinder;
        //   34: bipush 25
        //   36: aload_2
        //   37: aload_3
        //   38: iconst_0
        //   39: invokeinterface 53 5 0
        //   44: pop
        //   45: aload_3
        //   46: invokevirtual 56	android/os/Parcel:readException	()V
        //   49: aload_3
        //   50: invokevirtual 59	android/os/Parcel:recycle	()V
        //   53: aload_2
        //   54: invokevirtual 59	android/os/Parcel:recycle	()V
        //   57: return
        //   58: aconst_null
        //   59: astore_1
        //   60: goto -35 -> 25
        //   63: astore_1
        //   64: aload_3
        //   65: invokevirtual 59	android/os/Parcel:recycle	()V
        //   68: aload_2
        //   69: invokevirtual 59	android/os/Parcel:recycle	()V
        //   72: aload_1
        //   73: athrow
        // Local variable table:
        //   start	length	slot	name	signature
        //   0	74	0	this	zza
        //   0	74	1	paramzzc	zzc
        //   3	66	2	localParcel1	Parcel
        //   7	58	3	localParcel2	Parcel
        // Exception table:
        //   from	to	target	type
        //   8	14	63	finally
        //   18	25	63	finally
        //   25	49	63	finally
      }
      
      /* Error */
      public ParcelableEventList zzf(String paramString1, String paramString2, String paramString3)
        throws RemoteException
      {
        // Byte code:
        //   0: invokestatic 30	android/os/Parcel:obtain	()Landroid/os/Parcel;
        //   3: astore 4
        //   5: invokestatic 30	android/os/Parcel:obtain	()Landroid/os/Parcel;
        //   8: astore 5
        //   10: aload 4
        //   12: ldc 32
        //   14: invokevirtual 36	android/os/Parcel:writeInterfaceToken	(Ljava/lang/String;)V
        //   17: aload 4
        //   19: aload_1
        //   20: invokevirtual 117	android/os/Parcel:writeString	(Ljava/lang/String;)V
        //   23: aload 4
        //   25: aload_2
        //   26: invokevirtual 117	android/os/Parcel:writeString	(Ljava/lang/String;)V
        //   29: aload 4
        //   31: aload_3
        //   32: invokevirtual 117	android/os/Parcel:writeString	(Ljava/lang/String;)V
        //   35: aload_0
        //   36: getfield 18	com/google/android/gms/drive/realtime/internal/zzm$zza$zza:zzoz	Landroid/os/IBinder;
        //   39: bipush 51
        //   41: aload 4
        //   43: aload 5
        //   45: iconst_0
        //   46: invokeinterface 53 5 0
        //   51: pop
        //   52: aload 5
        //   54: invokevirtual 56	android/os/Parcel:readException	()V
        //   57: aload 5
        //   59: invokevirtual 158	android/os/Parcel:readInt	()I
        //   62: ifeq +29 -> 91
        //   65: getstatic 164	com/google/android/gms/drive/realtime/internal/event/ParcelableEventList:CREATOR	Landroid/os/Parcelable$Creator;
        //   68: aload 5
        //   70: invokeinterface 170 2 0
        //   75: checkcast 160	com/google/android/gms/drive/realtime/internal/event/ParcelableEventList
        //   78: astore_1
        //   79: aload 5
        //   81: invokevirtual 59	android/os/Parcel:recycle	()V
        //   84: aload 4
        //   86: invokevirtual 59	android/os/Parcel:recycle	()V
        //   89: aload_1
        //   90: areturn
        //   91: aconst_null
        //   92: astore_1
        //   93: goto -14 -> 79
        //   96: astore_1
        //   97: aload 5
        //   99: invokevirtual 59	android/os/Parcel:recycle	()V
        //   102: aload 4
        //   104: invokevirtual 59	android/os/Parcel:recycle	()V
        //   107: aload_1
        //   108: athrow
        // Local variable table:
        //   start	length	slot	name	signature
        //   0	109	0	this	zza
        //   0	109	1	paramString1	String
        //   0	109	2	paramString2	String
        //   0	109	3	paramString3	String
        //   3	100	4	localParcel1	Parcel
        //   8	90	5	localParcel2	Parcel
        // Exception table:
        //   from	to	target	type
        //   10	79	96	finally
      }
      
      public void zztT()
        throws RemoteException
      {
        Parcel localParcel1 = Parcel.obtain();
        Parcel localParcel2 = Parcel.obtain();
        try
        {
          localParcel1.writeInterfaceToken("com.google.android.gms.drive.realtime.internal.IRealtimeService");
          this.zzoz.transact(44, localParcel1, localParcel2, 0);
          localParcel2.readException();
          return;
        }
        finally
        {
          localParcel2.recycle();
          localParcel1.recycle();
        }
      }
    }
  }
}


/* Location:              C:\Users\Genbu Hase\hLg\Genbu\Tool\Programing\Jad\BlockLauncher 1.12.8.jar!\com\google\android\gms\drive\realtime\internal\zzm.class
 * Java compiler version: 6 (50.0)
 * JD-Core Version:       0.7.1-SNAPSHOT-20140817
 */