package com.amazon.venezia.command;

import android.os.Binder;
import android.os.IBinder;
import android.os.IInterface;
import android.os.Parcel;
import android.os.RemoteException;

public abstract interface ResultCallback
  extends IInterface
{
  public abstract void onDecide(DecisionResult paramDecisionResult)
    throws RemoteException;
  
  public abstract void onException(ExceptionResult paramExceptionResult)
    throws RemoteException;
  
  public abstract void onFailure(FailureResult paramFailureResult)
    throws RemoteException;
  
  public abstract void onSuccess(SuccessResult paramSuccessResult)
    throws RemoteException;
  
  public static abstract class Stub
    extends Binder
    implements ResultCallback
  {
    private static final String DESCRIPTOR = "com.amazon.venezia.command.ResultCallback";
    static final int TRANSACTION_onDecide = 3;
    static final int TRANSACTION_onException = 4;
    static final int TRANSACTION_onFailure = 2;
    static final int TRANSACTION_onSuccess = 1;
    
    public Stub()
    {
      attachInterface(this, "com.amazon.venezia.command.ResultCallback");
    }
    
    public static ResultCallback asInterface(IBinder paramIBinder)
    {
      if (paramIBinder == null) {
        return null;
      }
      IInterface localIInterface = paramIBinder.queryLocalInterface("com.amazon.venezia.command.ResultCallback");
      if ((localIInterface != null) && ((localIInterface instanceof ResultCallback))) {
        return (ResultCallback)localIInterface;
      }
      return new Proxy(paramIBinder);
    }
    
    public IBinder asBinder()
    {
      return this;
    }
    
    public boolean onTransact(int paramInt1, Parcel paramParcel1, Parcel paramParcel2, int paramInt2)
      throws RemoteException
    {
      switch (paramInt1)
      {
      default: 
        return super.onTransact(paramInt1, paramParcel1, paramParcel2, paramInt2);
      case 1598968902: 
        paramParcel2.writeString("com.amazon.venezia.command.ResultCallback");
        return true;
      case 1: 
        paramParcel1.enforceInterface("com.amazon.venezia.command.ResultCallback");
        onSuccess(SuccessResult.Stub.asInterface(paramParcel1.readStrongBinder()));
        paramParcel2.writeNoException();
        return true;
      case 2: 
        paramParcel1.enforceInterface("com.amazon.venezia.command.ResultCallback");
        onFailure(FailureResult.Stub.asInterface(paramParcel1.readStrongBinder()));
        paramParcel2.writeNoException();
        return true;
      case 3: 
        paramParcel1.enforceInterface("com.amazon.venezia.command.ResultCallback");
        onDecide(DecisionResult.Stub.asInterface(paramParcel1.readStrongBinder()));
        paramParcel2.writeNoException();
        return true;
      }
      paramParcel1.enforceInterface("com.amazon.venezia.command.ResultCallback");
      onException(ExceptionResult.Stub.asInterface(paramParcel1.readStrongBinder()));
      paramParcel2.writeNoException();
      return true;
    }
    
    private static class Proxy
      implements ResultCallback
    {
      private IBinder mRemote;
      
      Proxy(IBinder paramIBinder)
      {
        this.mRemote = paramIBinder;
      }
      
      public IBinder asBinder()
      {
        return this.mRemote;
      }
      
      public String getInterfaceDescriptor()
      {
        return "com.amazon.venezia.command.ResultCallback";
      }
      
      /* Error */
      public void onDecide(DecisionResult paramDecisionResult)
        throws RemoteException
      {
        // Byte code:
        //   0: invokestatic 36	android/os/Parcel:obtain	()Landroid/os/Parcel;
        //   3: astore_2
        //   4: invokestatic 36	android/os/Parcel:obtain	()Landroid/os/Parcel;
        //   7: astore_3
        //   8: aload_2
        //   9: ldc 26
        //   11: invokevirtual 40	android/os/Parcel:writeInterfaceToken	(Ljava/lang/String;)V
        //   14: aload_1
        //   15: ifnull +42 -> 57
        //   18: aload_1
        //   19: invokeinterface 44 1 0
        //   24: astore_1
        //   25: aload_2
        //   26: aload_1
        //   27: invokevirtual 47	android/os/Parcel:writeStrongBinder	(Landroid/os/IBinder;)V
        //   30: aload_0
        //   31: getfield 19	com/amazon/venezia/command/ResultCallback$Stub$Proxy:mRemote	Landroid/os/IBinder;
        //   34: iconst_3
        //   35: aload_2
        //   36: aload_3
        //   37: iconst_0
        //   38: invokeinterface 53 5 0
        //   43: pop
        //   44: aload_3
        //   45: invokevirtual 56	android/os/Parcel:readException	()V
        //   48: aload_3
        //   49: invokevirtual 59	android/os/Parcel:recycle	()V
        //   52: aload_2
        //   53: invokevirtual 59	android/os/Parcel:recycle	()V
        //   56: return
        //   57: aconst_null
        //   58: astore_1
        //   59: goto -34 -> 25
        //   62: astore_1
        //   63: aload_3
        //   64: invokevirtual 59	android/os/Parcel:recycle	()V
        //   67: aload_2
        //   68: invokevirtual 59	android/os/Parcel:recycle	()V
        //   71: aload_1
        //   72: athrow
        // Local variable table:
        //   start	length	slot	name	signature
        //   0	73	0	this	Proxy
        //   0	73	1	paramDecisionResult	DecisionResult
        //   3	65	2	localParcel1	Parcel
        //   7	57	3	localParcel2	Parcel
        // Exception table:
        //   from	to	target	type
        //   8	14	62	finally
        //   18	25	62	finally
        //   25	48	62	finally
      }
      
      /* Error */
      public void onException(ExceptionResult paramExceptionResult)
        throws RemoteException
      {
        // Byte code:
        //   0: invokestatic 36	android/os/Parcel:obtain	()Landroid/os/Parcel;
        //   3: astore_2
        //   4: invokestatic 36	android/os/Parcel:obtain	()Landroid/os/Parcel;
        //   7: astore_3
        //   8: aload_2
        //   9: ldc 26
        //   11: invokevirtual 40	android/os/Parcel:writeInterfaceToken	(Ljava/lang/String;)V
        //   14: aload_1
        //   15: ifnull +42 -> 57
        //   18: aload_1
        //   19: invokeinterface 65 1 0
        //   24: astore_1
        //   25: aload_2
        //   26: aload_1
        //   27: invokevirtual 47	android/os/Parcel:writeStrongBinder	(Landroid/os/IBinder;)V
        //   30: aload_0
        //   31: getfield 19	com/amazon/venezia/command/ResultCallback$Stub$Proxy:mRemote	Landroid/os/IBinder;
        //   34: iconst_4
        //   35: aload_2
        //   36: aload_3
        //   37: iconst_0
        //   38: invokeinterface 53 5 0
        //   43: pop
        //   44: aload_3
        //   45: invokevirtual 56	android/os/Parcel:readException	()V
        //   48: aload_3
        //   49: invokevirtual 59	android/os/Parcel:recycle	()V
        //   52: aload_2
        //   53: invokevirtual 59	android/os/Parcel:recycle	()V
        //   56: return
        //   57: aconst_null
        //   58: astore_1
        //   59: goto -34 -> 25
        //   62: astore_1
        //   63: aload_3
        //   64: invokevirtual 59	android/os/Parcel:recycle	()V
        //   67: aload_2
        //   68: invokevirtual 59	android/os/Parcel:recycle	()V
        //   71: aload_1
        //   72: athrow
        // Local variable table:
        //   start	length	slot	name	signature
        //   0	73	0	this	Proxy
        //   0	73	1	paramExceptionResult	ExceptionResult
        //   3	65	2	localParcel1	Parcel
        //   7	57	3	localParcel2	Parcel
        // Exception table:
        //   from	to	target	type
        //   8	14	62	finally
        //   18	25	62	finally
        //   25	48	62	finally
      }
      
      /* Error */
      public void onFailure(FailureResult paramFailureResult)
        throws RemoteException
      {
        // Byte code:
        //   0: invokestatic 36	android/os/Parcel:obtain	()Landroid/os/Parcel;
        //   3: astore_2
        //   4: invokestatic 36	android/os/Parcel:obtain	()Landroid/os/Parcel;
        //   7: astore_3
        //   8: aload_2
        //   9: ldc 26
        //   11: invokevirtual 40	android/os/Parcel:writeInterfaceToken	(Ljava/lang/String;)V
        //   14: aload_1
        //   15: ifnull +42 -> 57
        //   18: aload_1
        //   19: invokeinterface 70 1 0
        //   24: astore_1
        //   25: aload_2
        //   26: aload_1
        //   27: invokevirtual 47	android/os/Parcel:writeStrongBinder	(Landroid/os/IBinder;)V
        //   30: aload_0
        //   31: getfield 19	com/amazon/venezia/command/ResultCallback$Stub$Proxy:mRemote	Landroid/os/IBinder;
        //   34: iconst_2
        //   35: aload_2
        //   36: aload_3
        //   37: iconst_0
        //   38: invokeinterface 53 5 0
        //   43: pop
        //   44: aload_3
        //   45: invokevirtual 56	android/os/Parcel:readException	()V
        //   48: aload_3
        //   49: invokevirtual 59	android/os/Parcel:recycle	()V
        //   52: aload_2
        //   53: invokevirtual 59	android/os/Parcel:recycle	()V
        //   56: return
        //   57: aconst_null
        //   58: astore_1
        //   59: goto -34 -> 25
        //   62: astore_1
        //   63: aload_3
        //   64: invokevirtual 59	android/os/Parcel:recycle	()V
        //   67: aload_2
        //   68: invokevirtual 59	android/os/Parcel:recycle	()V
        //   71: aload_1
        //   72: athrow
        // Local variable table:
        //   start	length	slot	name	signature
        //   0	73	0	this	Proxy
        //   0	73	1	paramFailureResult	FailureResult
        //   3	65	2	localParcel1	Parcel
        //   7	57	3	localParcel2	Parcel
        // Exception table:
        //   from	to	target	type
        //   8	14	62	finally
        //   18	25	62	finally
        //   25	48	62	finally
      }
      
      /* Error */
      public void onSuccess(SuccessResult paramSuccessResult)
        throws RemoteException
      {
        // Byte code:
        //   0: invokestatic 36	android/os/Parcel:obtain	()Landroid/os/Parcel;
        //   3: astore_2
        //   4: invokestatic 36	android/os/Parcel:obtain	()Landroid/os/Parcel;
        //   7: astore_3
        //   8: aload_2
        //   9: ldc 26
        //   11: invokevirtual 40	android/os/Parcel:writeInterfaceToken	(Ljava/lang/String;)V
        //   14: aload_1
        //   15: ifnull +42 -> 57
        //   18: aload_1
        //   19: invokeinterface 75 1 0
        //   24: astore_1
        //   25: aload_2
        //   26: aload_1
        //   27: invokevirtual 47	android/os/Parcel:writeStrongBinder	(Landroid/os/IBinder;)V
        //   30: aload_0
        //   31: getfield 19	com/amazon/venezia/command/ResultCallback$Stub$Proxy:mRemote	Landroid/os/IBinder;
        //   34: iconst_1
        //   35: aload_2
        //   36: aload_3
        //   37: iconst_0
        //   38: invokeinterface 53 5 0
        //   43: pop
        //   44: aload_3
        //   45: invokevirtual 56	android/os/Parcel:readException	()V
        //   48: aload_3
        //   49: invokevirtual 59	android/os/Parcel:recycle	()V
        //   52: aload_2
        //   53: invokevirtual 59	android/os/Parcel:recycle	()V
        //   56: return
        //   57: aconst_null
        //   58: astore_1
        //   59: goto -34 -> 25
        //   62: astore_1
        //   63: aload_3
        //   64: invokevirtual 59	android/os/Parcel:recycle	()V
        //   67: aload_2
        //   68: invokevirtual 59	android/os/Parcel:recycle	()V
        //   71: aload_1
        //   72: athrow
        // Local variable table:
        //   start	length	slot	name	signature
        //   0	73	0	this	Proxy
        //   0	73	1	paramSuccessResult	SuccessResult
        //   3	65	2	localParcel1	Parcel
        //   7	57	3	localParcel2	Parcel
        // Exception table:
        //   from	to	target	type
        //   8	14	62	finally
        //   18	25	62	finally
        //   25	48	62	finally
      }
    }
  }
}


/* Location:              C:\Users\Genbu Hase\ÉhÉLÉÖÉÅÉìÉg\Genbu\Tool\Programing\Jad\MCPE.jar!\com\amazon\venezia\command\ResultCallback.class
 * Java compiler version: 6 (50.0)
 * JD-Core Version:       0.7.1-SNAPSHOT-20140817
 */