package com.amazon.venezia.command;

import android.os.IBinder;

final class t
  implements f
{
  private IBinder a;
  
  t(IBinder paramIBinder)
  {
    this.a = paramIBinder;
  }
  
  /* Error */
  public final void a(FailureResult paramFailureResult)
    throws android.os.RemoteException
  {
    // Byte code:
    //   0: invokestatic 25	android/os/Parcel:obtain	()Landroid/os/Parcel;
    //   3: astore_2
    //   4: invokestatic 25	android/os/Parcel:obtain	()Landroid/os/Parcel;
    //   7: astore_3
    //   8: aload_2
    //   9: ldc 27
    //   11: invokevirtual 31	android/os/Parcel:writeInterfaceToken	(Ljava/lang/String;)V
    //   14: aload_1
    //   15: ifnull +42 -> 57
    //   18: aload_1
    //   19: invokeinterface 37 1 0
    //   24: astore_1
    //   25: aload_2
    //   26: aload_1
    //   27: invokevirtual 40	android/os/Parcel:writeStrongBinder	(Landroid/os/IBinder;)V
    //   30: aload_0
    //   31: getfield 15	com/amazon/venezia/command/t:a	Landroid/os/IBinder;
    //   34: iconst_2
    //   35: aload_2
    //   36: aload_3
    //   37: iconst_0
    //   38: invokeinterface 46 5 0
    //   43: pop
    //   44: aload_3
    //   45: invokevirtual 49	android/os/Parcel:readException	()V
    //   48: aload_3
    //   49: invokevirtual 52	android/os/Parcel:recycle	()V
    //   52: aload_2
    //   53: invokevirtual 52	android/os/Parcel:recycle	()V
    //   56: return
    //   57: aconst_null
    //   58: astore_1
    //   59: goto -34 -> 25
    //   62: astore_1
    //   63: aload_3
    //   64: invokevirtual 52	android/os/Parcel:recycle	()V
    //   67: aload_2
    //   68: invokevirtual 52	android/os/Parcel:recycle	()V
    //   71: aload_1
    //   72: athrow
    // Local variable table:
    //   start	length	slot	name	signature
    //   0	73	0	this	t
    //   0	73	1	paramFailureResult	FailureResult
    //   3	65	2	localParcel1	android.os.Parcel
    //   7	57	3	localParcel2	android.os.Parcel
    // Exception table:
    //   from	to	target	type
    //   8	14	62	finally
    //   18	25	62	finally
    //   25	48	62	finally
  }
  
  /* Error */
  public final void a(SuccessResult paramSuccessResult)
    throws android.os.RemoteException
  {
    // Byte code:
    //   0: invokestatic 25	android/os/Parcel:obtain	()Landroid/os/Parcel;
    //   3: astore_2
    //   4: invokestatic 25	android/os/Parcel:obtain	()Landroid/os/Parcel;
    //   7: astore_3
    //   8: aload_2
    //   9: ldc 27
    //   11: invokevirtual 31	android/os/Parcel:writeInterfaceToken	(Ljava/lang/String;)V
    //   14: aload_1
    //   15: ifnull +42 -> 57
    //   18: aload_1
    //   19: invokeinterface 57 1 0
    //   24: astore_1
    //   25: aload_2
    //   26: aload_1
    //   27: invokevirtual 40	android/os/Parcel:writeStrongBinder	(Landroid/os/IBinder;)V
    //   30: aload_0
    //   31: getfield 15	com/amazon/venezia/command/t:a	Landroid/os/IBinder;
    //   34: iconst_1
    //   35: aload_2
    //   36: aload_3
    //   37: iconst_0
    //   38: invokeinterface 46 5 0
    //   43: pop
    //   44: aload_3
    //   45: invokevirtual 49	android/os/Parcel:readException	()V
    //   48: aload_3
    //   49: invokevirtual 52	android/os/Parcel:recycle	()V
    //   52: aload_2
    //   53: invokevirtual 52	android/os/Parcel:recycle	()V
    //   56: return
    //   57: aconst_null
    //   58: astore_1
    //   59: goto -34 -> 25
    //   62: astore_1
    //   63: aload_3
    //   64: invokevirtual 52	android/os/Parcel:recycle	()V
    //   67: aload_2
    //   68: invokevirtual 52	android/os/Parcel:recycle	()V
    //   71: aload_1
    //   72: athrow
    // Local variable table:
    //   start	length	slot	name	signature
    //   0	73	0	this	t
    //   0	73	1	paramSuccessResult	SuccessResult
    //   3	65	2	localParcel1	android.os.Parcel
    //   7	57	3	localParcel2	android.os.Parcel
    // Exception table:
    //   from	to	target	type
    //   8	14	62	finally
    //   18	25	62	finally
    //   25	48	62	finally
  }
  
  /* Error */
  public final void a(j paramj)
    throws android.os.RemoteException
  {
    // Byte code:
    //   0: invokestatic 25	android/os/Parcel:obtain	()Landroid/os/Parcel;
    //   3: astore_2
    //   4: invokestatic 25	android/os/Parcel:obtain	()Landroid/os/Parcel;
    //   7: astore_3
    //   8: aload_2
    //   9: ldc 27
    //   11: invokevirtual 31	android/os/Parcel:writeInterfaceToken	(Ljava/lang/String;)V
    //   14: aload_1
    //   15: ifnull +42 -> 57
    //   18: aload_1
    //   19: invokeinterface 61 1 0
    //   24: astore_1
    //   25: aload_2
    //   26: aload_1
    //   27: invokevirtual 40	android/os/Parcel:writeStrongBinder	(Landroid/os/IBinder;)V
    //   30: aload_0
    //   31: getfield 15	com/amazon/venezia/command/t:a	Landroid/os/IBinder;
    //   34: iconst_4
    //   35: aload_2
    //   36: aload_3
    //   37: iconst_0
    //   38: invokeinterface 46 5 0
    //   43: pop
    //   44: aload_3
    //   45: invokevirtual 49	android/os/Parcel:readException	()V
    //   48: aload_3
    //   49: invokevirtual 52	android/os/Parcel:recycle	()V
    //   52: aload_2
    //   53: invokevirtual 52	android/os/Parcel:recycle	()V
    //   56: return
    //   57: aconst_null
    //   58: astore_1
    //   59: goto -34 -> 25
    //   62: astore_1
    //   63: aload_3
    //   64: invokevirtual 52	android/os/Parcel:recycle	()V
    //   67: aload_2
    //   68: invokevirtual 52	android/os/Parcel:recycle	()V
    //   71: aload_1
    //   72: athrow
    // Local variable table:
    //   start	length	slot	name	signature
    //   0	73	0	this	t
    //   0	73	1	paramj	j
    //   3	65	2	localParcel1	android.os.Parcel
    //   7	57	3	localParcel2	android.os.Parcel
    // Exception table:
    //   from	to	target	type
    //   8	14	62	finally
    //   18	25	62	finally
    //   25	48	62	finally
  }
  
  /* Error */
  public final void a(r paramr)
    throws android.os.RemoteException
  {
    // Byte code:
    //   0: invokestatic 25	android/os/Parcel:obtain	()Landroid/os/Parcel;
    //   3: astore_2
    //   4: invokestatic 25	android/os/Parcel:obtain	()Landroid/os/Parcel;
    //   7: astore_3
    //   8: aload_2
    //   9: ldc 27
    //   11: invokevirtual 31	android/os/Parcel:writeInterfaceToken	(Ljava/lang/String;)V
    //   14: aload_1
    //   15: ifnull +42 -> 57
    //   18: aload_1
    //   19: invokeinterface 65 1 0
    //   24: astore_1
    //   25: aload_2
    //   26: aload_1
    //   27: invokevirtual 40	android/os/Parcel:writeStrongBinder	(Landroid/os/IBinder;)V
    //   30: aload_0
    //   31: getfield 15	com/amazon/venezia/command/t:a	Landroid/os/IBinder;
    //   34: iconst_3
    //   35: aload_2
    //   36: aload_3
    //   37: iconst_0
    //   38: invokeinterface 46 5 0
    //   43: pop
    //   44: aload_3
    //   45: invokevirtual 49	android/os/Parcel:readException	()V
    //   48: aload_3
    //   49: invokevirtual 52	android/os/Parcel:recycle	()V
    //   52: aload_2
    //   53: invokevirtual 52	android/os/Parcel:recycle	()V
    //   56: return
    //   57: aconst_null
    //   58: astore_1
    //   59: goto -34 -> 25
    //   62: astore_1
    //   63: aload_3
    //   64: invokevirtual 52	android/os/Parcel:recycle	()V
    //   67: aload_2
    //   68: invokevirtual 52	android/os/Parcel:recycle	()V
    //   71: aload_1
    //   72: athrow
    // Local variable table:
    //   start	length	slot	name	signature
    //   0	73	0	this	t
    //   0	73	1	paramr	r
    //   3	65	2	localParcel1	android.os.Parcel
    //   7	57	3	localParcel2	android.os.Parcel
    // Exception table:
    //   from	to	target	type
    //   8	14	62	finally
    //   18	25	62	finally
    //   25	48	62	finally
  }
  
  public final IBinder asBinder()
  {
    return this.a;
  }
}


/* Location:              C:\Users\Genbu Hase\ÉhÉLÉÖÉÅÉìÉg\Genbu\Tool\Programing\Jad\MCPE.jar!\com\amazon\venezia\command\t.class
 * Java compiler version: 6 (50.0)
 * JD-Core Version:       0.7.1-SNAPSHOT-20140817
 */