package com.google.android.gms.games.internal;

import android.os.Binder;
import android.os.Bundle;
import android.os.IBinder;
import android.os.IInterface;
import android.os.Parcel;
import android.os.Parcelable.Creator;
import android.os.RemoteException;
import com.google.android.gms.common.data.DataHolder;
import com.google.android.gms.common.data.zze;
import com.google.android.gms.drive.Contents;
import com.google.android.gms.games.multiplayer.realtime.RealTimeMessage;
import com.google.android.gms.games.video.VideoCapabilities;

public abstract interface IGamesCallbacks
  extends IInterface
{
  public abstract void onInvitationRemoved(String paramString)
    throws RemoteException;
  
  public abstract void onLeftRoom(int paramInt, String paramString)
    throws RemoteException;
  
  public abstract void onP2PConnected(String paramString)
    throws RemoteException;
  
  public abstract void onP2PDisconnected(String paramString)
    throws RemoteException;
  
  public abstract void onRealTimeMessageReceived(RealTimeMessage paramRealTimeMessage)
    throws RemoteException;
  
  public abstract void onRequestRemoved(String paramString)
    throws RemoteException;
  
  public abstract void onTurnBasedMatchRemoved(String paramString)
    throws RemoteException;
  
  public abstract void zzA(DataHolder paramDataHolder)
    throws RemoteException;
  
  public abstract void zzB(DataHolder paramDataHolder)
    throws RemoteException;
  
  public abstract void zzC(DataHolder paramDataHolder)
    throws RemoteException;
  
  public abstract void zzD(DataHolder paramDataHolder)
    throws RemoteException;
  
  public abstract void zzE(DataHolder paramDataHolder)
    throws RemoteException;
  
  public abstract void zzF(DataHolder paramDataHolder)
    throws RemoteException;
  
  public abstract void zzG(DataHolder paramDataHolder)
    throws RemoteException;
  
  public abstract void zzH(DataHolder paramDataHolder)
    throws RemoteException;
  
  public abstract void zzI(DataHolder paramDataHolder)
    throws RemoteException;
  
  public abstract void zzJ(DataHolder paramDataHolder)
    throws RemoteException;
  
  public abstract void zzK(DataHolder paramDataHolder)
    throws RemoteException;
  
  public abstract void zzL(DataHolder paramDataHolder)
    throws RemoteException;
  
  public abstract void zzM(DataHolder paramDataHolder)
    throws RemoteException;
  
  public abstract void zzN(DataHolder paramDataHolder)
    throws RemoteException;
  
  public abstract void zzO(DataHolder paramDataHolder)
    throws RemoteException;
  
  public abstract void zzP(DataHolder paramDataHolder)
    throws RemoteException;
  
  public abstract void zzQ(DataHolder paramDataHolder)
    throws RemoteException;
  
  public abstract void zzR(DataHolder paramDataHolder)
    throws RemoteException;
  
  public abstract void zzS(DataHolder paramDataHolder)
    throws RemoteException;
  
  public abstract void zzT(DataHolder paramDataHolder)
    throws RemoteException;
  
  public abstract void zzU(DataHolder paramDataHolder)
    throws RemoteException;
  
  public abstract void zzV(DataHolder paramDataHolder)
    throws RemoteException;
  
  public abstract void zzW(DataHolder paramDataHolder)
    throws RemoteException;
  
  public abstract void zzX(DataHolder paramDataHolder)
    throws RemoteException;
  
  public abstract void zza(int paramInt, VideoCapabilities paramVideoCapabilities)
    throws RemoteException;
  
  public abstract void zza(int paramInt, String paramString, boolean paramBoolean)
    throws RemoteException;
  
  public abstract void zza(int paramInt, long[] paramArrayOfLong)
    throws RemoteException;
  
  public abstract void zza(DataHolder paramDataHolder1, DataHolder paramDataHolder2)
    throws RemoteException;
  
  public abstract void zza(DataHolder paramDataHolder, Contents paramContents)
    throws RemoteException;
  
  public abstract void zza(DataHolder paramDataHolder, String paramString, Contents paramContents1, Contents paramContents2, Contents paramContents3)
    throws RemoteException;
  
  public abstract void zza(DataHolder paramDataHolder, String[] paramArrayOfString)
    throws RemoteException;
  
  public abstract void zza(DataHolder[] paramArrayOfDataHolder)
    throws RemoteException;
  
  public abstract void zzb(int paramInt1, int paramInt2, String paramString)
    throws RemoteException;
  
  public abstract void zzb(DataHolder paramDataHolder, String[] paramArrayOfString)
    throws RemoteException;
  
  public abstract void zzc(int paramInt, Bundle paramBundle)
    throws RemoteException;
  
  public abstract void zzc(DataHolder paramDataHolder, String[] paramArrayOfString)
    throws RemoteException;
  
  public abstract void zzd(int paramInt, Bundle paramBundle)
    throws RemoteException;
  
  public abstract void zzd(int paramInt, boolean paramBoolean)
    throws RemoteException;
  
  public abstract void zzd(DataHolder paramDataHolder, String[] paramArrayOfString)
    throws RemoteException;
  
  public abstract void zze(int paramInt, Bundle paramBundle)
    throws RemoteException;
  
  public abstract void zze(DataHolder paramDataHolder, String[] paramArrayOfString)
    throws RemoteException;
  
  public abstract void zzf(int paramInt, Bundle paramBundle)
    throws RemoteException;
  
  public abstract void zzf(DataHolder paramDataHolder, String[] paramArrayOfString)
    throws RemoteException;
  
  public abstract void zzg(int paramInt, Bundle paramBundle)
    throws RemoteException;
  
  public abstract void zzg(int paramInt, String paramString)
    throws RemoteException;
  
  public abstract void zzgn(int paramInt)
    throws RemoteException;
  
  public abstract void zzgo(int paramInt)
    throws RemoteException;
  
  public abstract void zzgp(int paramInt)
    throws RemoteException;
  
  public abstract void zzgq(int paramInt)
    throws RemoteException;
  
  public abstract void zzh(int paramInt, String paramString)
    throws RemoteException;
  
  public abstract void zzh(DataHolder paramDataHolder)
    throws RemoteException;
  
  public abstract void zzi(int paramInt, String paramString)
    throws RemoteException;
  
  public abstract void zzi(DataHolder paramDataHolder)
    throws RemoteException;
  
  public abstract void zzj(int paramInt, String paramString)
    throws RemoteException;
  
  public abstract void zzj(DataHolder paramDataHolder)
    throws RemoteException;
  
  public abstract void zzk(DataHolder paramDataHolder)
    throws RemoteException;
  
  public abstract void zzl(DataHolder paramDataHolder)
    throws RemoteException;
  
  public abstract void zzm(DataHolder paramDataHolder)
    throws RemoteException;
  
  public abstract void zzn(DataHolder paramDataHolder)
    throws RemoteException;
  
  public abstract void zzo(DataHolder paramDataHolder)
    throws RemoteException;
  
  public abstract void zzp(DataHolder paramDataHolder)
    throws RemoteException;
  
  public abstract void zzq(DataHolder paramDataHolder)
    throws RemoteException;
  
  public abstract void zzr(DataHolder paramDataHolder)
    throws RemoteException;
  
  public abstract void zzs(DataHolder paramDataHolder)
    throws RemoteException;
  
  public abstract void zzt(DataHolder paramDataHolder)
    throws RemoteException;
  
  public abstract void zzu(DataHolder paramDataHolder)
    throws RemoteException;
  
  public abstract void zzv(DataHolder paramDataHolder)
    throws RemoteException;
  
  public abstract void zzw(DataHolder paramDataHolder)
    throws RemoteException;
  
  public abstract void zzwr()
    throws RemoteException;
  
  public abstract void zzx(DataHolder paramDataHolder)
    throws RemoteException;
  
  public abstract void zzy(DataHolder paramDataHolder)
    throws RemoteException;
  
  public abstract void zzz(DataHolder paramDataHolder)
    throws RemoteException;
  
  public static abstract class Stub
    extends Binder
    implements IGamesCallbacks
  {
    public Stub()
    {
      attachInterface(this, "com.google.android.gms.games.internal.IGamesCallbacks");
    }
    
    public static IGamesCallbacks zzbW(IBinder paramIBinder)
    {
      if (paramIBinder == null) {
        return null;
      }
      IInterface localIInterface = paramIBinder.queryLocalInterface("com.google.android.gms.games.internal.IGamesCallbacks");
      if ((localIInterface != null) && ((localIInterface instanceof IGamesCallbacks))) {
        return (IGamesCallbacks)localIInterface;
      }
      return new Proxy(paramIBinder);
    }
    
    public IBinder asBinder()
    {
      return this;
    }
    
    public boolean onTransact(int paramInt1, Parcel paramParcel1, Parcel paramParcel2, int paramInt2)
      throws RemoteException
    {
      boolean bool2 = false;
      boolean bool1 = false;
      Object localObject2 = null;
      Contents localContents1 = null;
      String str = null;
      Object localObject3 = null;
      Object localObject4 = null;
      Object localObject5 = null;
      Object localObject6 = null;
      Object localObject7 = null;
      Object localObject8 = null;
      Object localObject9 = null;
      Object localObject10 = null;
      Object localObject11 = null;
      Object localObject12 = null;
      Object localObject13 = null;
      Object localObject14 = null;
      Object localObject15 = null;
      Object localObject16 = null;
      Object localObject17 = null;
      Object localObject18 = null;
      Object localObject19 = null;
      Object localObject20 = null;
      Object localObject21 = null;
      Object localObject22 = null;
      Object localObject23 = null;
      Object localObject24 = null;
      Object localObject25 = null;
      Object localObject26 = null;
      Object localObject27 = null;
      Object localObject28 = null;
      Object localObject29 = null;
      Object localObject30 = null;
      Object localObject31 = null;
      Object localObject32 = null;
      Object localObject33 = null;
      Object localObject34 = null;
      Object localObject35 = null;
      Object localObject36 = null;
      Contents localContents2 = null;
      Object localObject37 = null;
      Object localObject38 = null;
      Object localObject39 = null;
      Object localObject40 = null;
      Object localObject41 = null;
      Object localObject42 = null;
      Object localObject43 = null;
      Object localObject44 = null;
      Object localObject45 = null;
      Object localObject46 = null;
      Object localObject47 = null;
      Object localObject1 = null;
      switch (paramInt1)
      {
      default: 
        return super.onTransact(paramInt1, paramParcel1, paramParcel2, paramInt2);
      case 1598968902: 
        paramParcel2.writeString("com.google.android.gms.games.internal.IGamesCallbacks");
        return true;
      case 5001: 
        paramParcel1.enforceInterface("com.google.android.gms.games.internal.IGamesCallbacks");
        zzg(paramParcel1.readInt(), paramParcel1.readString());
        paramParcel2.writeNoException();
        return true;
      case 5002: 
        paramParcel1.enforceInterface("com.google.android.gms.games.internal.IGamesCallbacks");
        if (paramParcel1.readInt() != 0) {}
        for (paramParcel1 = DataHolder.CREATOR.zzak(paramParcel1);; paramParcel1 = null)
        {
          zzh(paramParcel1);
          paramParcel2.writeNoException();
          return true;
        }
      case 5003: 
        paramParcel1.enforceInterface("com.google.android.gms.games.internal.IGamesCallbacks");
        zzh(paramParcel1.readInt(), paramParcel1.readString());
        paramParcel2.writeNoException();
        return true;
      case 5004: 
        paramParcel1.enforceInterface("com.google.android.gms.games.internal.IGamesCallbacks");
        if (paramParcel1.readInt() != 0) {
          localObject1 = DataHolder.CREATOR.zzak(paramParcel1);
        }
        zzj((DataHolder)localObject1);
        paramParcel2.writeNoException();
        return true;
      case 5005: 
        paramParcel1.enforceInterface("com.google.android.gms.games.internal.IGamesCallbacks");
        if (paramParcel1.readInt() != 0) {}
        for (localObject1 = DataHolder.CREATOR.zzak(paramParcel1);; localObject1 = null)
        {
          if (paramParcel1.readInt() != 0) {
            localObject2 = DataHolder.CREATOR.zzak(paramParcel1);
          }
          zza((DataHolder)localObject1, (DataHolder)localObject2);
          paramParcel2.writeNoException();
          return true;
        }
      case 5006: 
        paramParcel1.enforceInterface("com.google.android.gms.games.internal.IGamesCallbacks");
        localObject1 = localContents1;
        if (paramParcel1.readInt() != 0) {
          localObject1 = DataHolder.CREATOR.zzak(paramParcel1);
        }
        zzk((DataHolder)localObject1);
        paramParcel2.writeNoException();
        return true;
      case 5007: 
        paramParcel1.enforceInterface("com.google.android.gms.games.internal.IGamesCallbacks");
        localObject1 = str;
        if (paramParcel1.readInt() != 0) {
          localObject1 = DataHolder.CREATOR.zzak(paramParcel1);
        }
        zzl((DataHolder)localObject1);
        paramParcel2.writeNoException();
        return true;
      case 5008: 
        paramParcel1.enforceInterface("com.google.android.gms.games.internal.IGamesCallbacks");
        localObject1 = localObject3;
        if (paramParcel1.readInt() != 0) {
          localObject1 = DataHolder.CREATOR.zzak(paramParcel1);
        }
        zzm((DataHolder)localObject1);
        paramParcel2.writeNoException();
        return true;
      case 5009: 
        paramParcel1.enforceInterface("com.google.android.gms.games.internal.IGamesCallbacks");
        localObject1 = localObject4;
        if (paramParcel1.readInt() != 0) {
          localObject1 = DataHolder.CREATOR.zzak(paramParcel1);
        }
        zzn((DataHolder)localObject1);
        paramParcel2.writeNoException();
        return true;
      case 5010: 
        paramParcel1.enforceInterface("com.google.android.gms.games.internal.IGamesCallbacks");
        localObject1 = localObject5;
        if (paramParcel1.readInt() != 0) {
          localObject1 = DataHolder.CREATOR.zzak(paramParcel1);
        }
        zzo((DataHolder)localObject1);
        paramParcel2.writeNoException();
        return true;
      case 5011: 
        paramParcel1.enforceInterface("com.google.android.gms.games.internal.IGamesCallbacks");
        localObject1 = localObject6;
        if (paramParcel1.readInt() != 0) {
          localObject1 = DataHolder.CREATOR.zzak(paramParcel1);
        }
        zzp((DataHolder)localObject1);
        paramParcel2.writeNoException();
        return true;
      case 5016: 
        paramParcel1.enforceInterface("com.google.android.gms.games.internal.IGamesCallbacks");
        zzwr();
        paramParcel2.writeNoException();
        return true;
      case 5017: 
        paramParcel1.enforceInterface("com.google.android.gms.games.internal.IGamesCallbacks");
        localObject1 = localObject7;
        if (paramParcel1.readInt() != 0) {
          localObject1 = DataHolder.CREATOR.zzak(paramParcel1);
        }
        zzr((DataHolder)localObject1);
        paramParcel2.writeNoException();
        return true;
      case 5037: 
        paramParcel1.enforceInterface("com.google.android.gms.games.internal.IGamesCallbacks");
        localObject1 = localObject8;
        if (paramParcel1.readInt() != 0) {
          localObject1 = DataHolder.CREATOR.zzak(paramParcel1);
        }
        zzs((DataHolder)localObject1);
        paramParcel2.writeNoException();
        return true;
      case 5018: 
        paramParcel1.enforceInterface("com.google.android.gms.games.internal.IGamesCallbacks");
        localObject1 = localObject9;
        if (paramParcel1.readInt() != 0) {
          localObject1 = DataHolder.CREATOR.zzak(paramParcel1);
        }
        zzz((DataHolder)localObject1);
        paramParcel2.writeNoException();
        return true;
      case 5019: 
        paramParcel1.enforceInterface("com.google.android.gms.games.internal.IGamesCallbacks");
        localObject1 = localObject10;
        if (paramParcel1.readInt() != 0) {
          localObject1 = DataHolder.CREATOR.zzak(paramParcel1);
        }
        zzA((DataHolder)localObject1);
        paramParcel2.writeNoException();
        return true;
      case 5020: 
        paramParcel1.enforceInterface("com.google.android.gms.games.internal.IGamesCallbacks");
        onLeftRoom(paramParcel1.readInt(), paramParcel1.readString());
        paramParcel2.writeNoException();
        return true;
      case 5021: 
        paramParcel1.enforceInterface("com.google.android.gms.games.internal.IGamesCallbacks");
        localObject1 = localObject11;
        if (paramParcel1.readInt() != 0) {
          localObject1 = DataHolder.CREATOR.zzak(paramParcel1);
        }
        zzB((DataHolder)localObject1);
        paramParcel2.writeNoException();
        return true;
      case 5022: 
        paramParcel1.enforceInterface("com.google.android.gms.games.internal.IGamesCallbacks");
        localObject1 = localObject12;
        if (paramParcel1.readInt() != 0) {
          localObject1 = DataHolder.CREATOR.zzak(paramParcel1);
        }
        zzC((DataHolder)localObject1);
        paramParcel2.writeNoException();
        return true;
      case 5023: 
        paramParcel1.enforceInterface("com.google.android.gms.games.internal.IGamesCallbacks");
        localObject1 = localObject13;
        if (paramParcel1.readInt() != 0) {
          localObject1 = DataHolder.CREATOR.zzak(paramParcel1);
        }
        zzD((DataHolder)localObject1);
        paramParcel2.writeNoException();
        return true;
      case 5024: 
        paramParcel1.enforceInterface("com.google.android.gms.games.internal.IGamesCallbacks");
        localObject1 = localObject14;
        if (paramParcel1.readInt() != 0) {
          localObject1 = DataHolder.CREATOR.zzak(paramParcel1);
        }
        zzE((DataHolder)localObject1);
        paramParcel2.writeNoException();
        return true;
      case 5025: 
        paramParcel1.enforceInterface("com.google.android.gms.games.internal.IGamesCallbacks");
        localObject1 = localObject15;
        if (paramParcel1.readInt() != 0) {
          localObject1 = DataHolder.CREATOR.zzak(paramParcel1);
        }
        zzF((DataHolder)localObject1);
        paramParcel2.writeNoException();
        return true;
      case 5026: 
        paramParcel1.enforceInterface("com.google.android.gms.games.internal.IGamesCallbacks");
        localObject1 = localObject16;
        if (paramParcel1.readInt() != 0) {
          localObject1 = DataHolder.CREATOR.zzak(paramParcel1);
        }
        zza((DataHolder)localObject1, paramParcel1.createStringArray());
        paramParcel2.writeNoException();
        return true;
      case 5027: 
        paramParcel1.enforceInterface("com.google.android.gms.games.internal.IGamesCallbacks");
        localObject1 = localObject17;
        if (paramParcel1.readInt() != 0) {
          localObject1 = DataHolder.CREATOR.zzak(paramParcel1);
        }
        zzb((DataHolder)localObject1, paramParcel1.createStringArray());
        paramParcel2.writeNoException();
        return true;
      case 5028: 
        paramParcel1.enforceInterface("com.google.android.gms.games.internal.IGamesCallbacks");
        localObject1 = localObject18;
        if (paramParcel1.readInt() != 0) {
          localObject1 = DataHolder.CREATOR.zzak(paramParcel1);
        }
        zzc((DataHolder)localObject1, paramParcel1.createStringArray());
        paramParcel2.writeNoException();
        return true;
      case 5029: 
        paramParcel1.enforceInterface("com.google.android.gms.games.internal.IGamesCallbacks");
        localObject1 = localObject19;
        if (paramParcel1.readInt() != 0) {
          localObject1 = DataHolder.CREATOR.zzak(paramParcel1);
        }
        zzd((DataHolder)localObject1, paramParcel1.createStringArray());
        paramParcel2.writeNoException();
        return true;
      case 5030: 
        paramParcel1.enforceInterface("com.google.android.gms.games.internal.IGamesCallbacks");
        localObject1 = localObject20;
        if (paramParcel1.readInt() != 0) {
          localObject1 = DataHolder.CREATOR.zzak(paramParcel1);
        }
        zze((DataHolder)localObject1, paramParcel1.createStringArray());
        paramParcel2.writeNoException();
        return true;
      case 5031: 
        paramParcel1.enforceInterface("com.google.android.gms.games.internal.IGamesCallbacks");
        localObject1 = localObject21;
        if (paramParcel1.readInt() != 0) {
          localObject1 = DataHolder.CREATOR.zzak(paramParcel1);
        }
        zzf((DataHolder)localObject1, paramParcel1.createStringArray());
        paramParcel2.writeNoException();
        return true;
      case 5032: 
        paramParcel1.enforceInterface("com.google.android.gms.games.internal.IGamesCallbacks");
        if (paramParcel1.readInt() != 0) {}
        for (paramParcel1 = (RealTimeMessage)RealTimeMessage.CREATOR.createFromParcel(paramParcel1);; paramParcel1 = null)
        {
          onRealTimeMessageReceived(paramParcel1);
          paramParcel2.writeNoException();
          return true;
        }
      case 5033: 
        paramParcel1.enforceInterface("com.google.android.gms.games.internal.IGamesCallbacks");
        zzb(paramParcel1.readInt(), paramParcel1.readInt(), paramParcel1.readString());
        paramParcel2.writeNoException();
        return true;
      case 5034: 
        paramParcel1.enforceInterface("com.google.android.gms.games.internal.IGamesCallbacks");
        paramInt1 = paramParcel1.readInt();
        localObject1 = paramParcel1.readString();
        if (paramParcel1.readInt() != 0) {
          bool1 = true;
        }
        zza(paramInt1, (String)localObject1, bool1);
        paramParcel2.writeNoException();
        return true;
      case 5038: 
        paramParcel1.enforceInterface("com.google.android.gms.games.internal.IGamesCallbacks");
        localObject1 = localObject22;
        if (paramParcel1.readInt() != 0) {
          localObject1 = DataHolder.CREATOR.zzak(paramParcel1);
        }
        zzG((DataHolder)localObject1);
        paramParcel2.writeNoException();
        return true;
      case 5035: 
        paramParcel1.enforceInterface("com.google.android.gms.games.internal.IGamesCallbacks");
        localObject1 = localObject23;
        if (paramParcel1.readInt() != 0) {
          localObject1 = DataHolder.CREATOR.zzak(paramParcel1);
        }
        zzH((DataHolder)localObject1);
        paramParcel2.writeNoException();
        return true;
      case 5036: 
        paramParcel1.enforceInterface("com.google.android.gms.games.internal.IGamesCallbacks");
        zzgn(paramParcel1.readInt());
        paramParcel2.writeNoException();
        return true;
      case 5039: 
        paramParcel1.enforceInterface("com.google.android.gms.games.internal.IGamesCallbacks");
        localObject1 = localObject24;
        if (paramParcel1.readInt() != 0) {
          localObject1 = DataHolder.CREATOR.zzak(paramParcel1);
        }
        zzI((DataHolder)localObject1);
        paramParcel2.writeNoException();
        return true;
      case 5040: 
        paramParcel1.enforceInterface("com.google.android.gms.games.internal.IGamesCallbacks");
        zzgo(paramParcel1.readInt());
        paramParcel2.writeNoException();
        return true;
      case 6001: 
        paramParcel1.enforceInterface("com.google.android.gms.games.internal.IGamesCallbacks");
        onP2PConnected(paramParcel1.readString());
        paramParcel2.writeNoException();
        return true;
      case 6002: 
        paramParcel1.enforceInterface("com.google.android.gms.games.internal.IGamesCallbacks");
        onP2PDisconnected(paramParcel1.readString());
        paramParcel2.writeNoException();
        return true;
      case 8001: 
        paramParcel1.enforceInterface("com.google.android.gms.games.internal.IGamesCallbacks");
        localObject1 = localObject25;
        if (paramParcel1.readInt() != 0) {
          localObject1 = DataHolder.CREATOR.zzak(paramParcel1);
        }
        zzJ((DataHolder)localObject1);
        paramParcel2.writeNoException();
        return true;
      case 8002: 
        paramParcel1.enforceInterface("com.google.android.gms.games.internal.IGamesCallbacks");
        paramInt1 = paramParcel1.readInt();
        if (paramParcel1.readInt() != 0) {}
        for (paramParcel1 = (Bundle)Bundle.CREATOR.createFromParcel(paramParcel1);; paramParcel1 = null)
        {
          zzc(paramInt1, paramParcel1);
          paramParcel2.writeNoException();
          return true;
        }
      case 8003: 
        paramParcel1.enforceInterface("com.google.android.gms.games.internal.IGamesCallbacks");
        localObject1 = localObject26;
        if (paramParcel1.readInt() != 0) {
          localObject1 = DataHolder.CREATOR.zzak(paramParcel1);
        }
        zzu((DataHolder)localObject1);
        paramParcel2.writeNoException();
        return true;
      case 8004: 
        paramParcel1.enforceInterface("com.google.android.gms.games.internal.IGamesCallbacks");
        localObject1 = localObject27;
        if (paramParcel1.readInt() != 0) {
          localObject1 = DataHolder.CREATOR.zzak(paramParcel1);
        }
        zzv((DataHolder)localObject1);
        paramParcel2.writeNoException();
        return true;
      case 8005: 
        paramParcel1.enforceInterface("com.google.android.gms.games.internal.IGamesCallbacks");
        localObject1 = localObject28;
        if (paramParcel1.readInt() != 0) {
          localObject1 = DataHolder.CREATOR.zzak(paramParcel1);
        }
        zzw((DataHolder)localObject1);
        paramParcel2.writeNoException();
        return true;
      case 8006: 
        paramParcel1.enforceInterface("com.google.android.gms.games.internal.IGamesCallbacks");
        localObject1 = localObject29;
        if (paramParcel1.readInt() != 0) {
          localObject1 = DataHolder.CREATOR.zzak(paramParcel1);
        }
        zzx((DataHolder)localObject1);
        paramParcel2.writeNoException();
        return true;
      case 8007: 
        paramParcel1.enforceInterface("com.google.android.gms.games.internal.IGamesCallbacks");
        zzi(paramParcel1.readInt(), paramParcel1.readString());
        paramParcel2.writeNoException();
        return true;
      case 8008: 
        paramParcel1.enforceInterface("com.google.android.gms.games.internal.IGamesCallbacks");
        localObject1 = localObject30;
        if (paramParcel1.readInt() != 0) {
          localObject1 = DataHolder.CREATOR.zzak(paramParcel1);
        }
        zzy((DataHolder)localObject1);
        paramParcel2.writeNoException();
        return true;
      case 8009: 
        paramParcel1.enforceInterface("com.google.android.gms.games.internal.IGamesCallbacks");
        onTurnBasedMatchRemoved(paramParcel1.readString());
        paramParcel2.writeNoException();
        return true;
      case 8010: 
        paramParcel1.enforceInterface("com.google.android.gms.games.internal.IGamesCallbacks");
        onInvitationRemoved(paramParcel1.readString());
        paramParcel2.writeNoException();
        return true;
      case 9001: 
        paramParcel1.enforceInterface("com.google.android.gms.games.internal.IGamesCallbacks");
        localObject1 = localObject31;
        if (paramParcel1.readInt() != 0) {
          localObject1 = DataHolder.CREATOR.zzak(paramParcel1);
        }
        zzq((DataHolder)localObject1);
        paramParcel2.writeNoException();
        return true;
      case 10001: 
        paramParcel1.enforceInterface("com.google.android.gms.games.internal.IGamesCallbacks");
        localObject1 = localObject32;
        if (paramParcel1.readInt() != 0) {
          localObject1 = DataHolder.CREATOR.zzak(paramParcel1);
        }
        zzt((DataHolder)localObject1);
        paramParcel2.writeNoException();
        return true;
      case 10002: 
        paramParcel1.enforceInterface("com.google.android.gms.games.internal.IGamesCallbacks");
        onRequestRemoved(paramParcel1.readString());
        paramParcel2.writeNoException();
        return true;
      case 10003: 
        paramParcel1.enforceInterface("com.google.android.gms.games.internal.IGamesCallbacks");
        localObject1 = localObject33;
        if (paramParcel1.readInt() != 0) {
          localObject1 = DataHolder.CREATOR.zzak(paramParcel1);
        }
        zzK((DataHolder)localObject1);
        paramParcel2.writeNoException();
        return true;
      case 10004: 
        paramParcel1.enforceInterface("com.google.android.gms.games.internal.IGamesCallbacks");
        localObject1 = localObject34;
        if (paramParcel1.readInt() != 0) {
          localObject1 = DataHolder.CREATOR.zzak(paramParcel1);
        }
        zzL((DataHolder)localObject1);
        paramParcel2.writeNoException();
        return true;
      case 10005: 
        paramParcel1.enforceInterface("com.google.android.gms.games.internal.IGamesCallbacks");
        paramInt1 = paramParcel1.readInt();
        if (paramParcel1.readInt() != 0) {}
        for (paramParcel1 = (Bundle)Bundle.CREATOR.createFromParcel(paramParcel1);; paramParcel1 = null)
        {
          zzd(paramInt1, paramParcel1);
          paramParcel2.writeNoException();
          return true;
        }
      case 10006: 
        paramParcel1.enforceInterface("com.google.android.gms.games.internal.IGamesCallbacks");
        localObject1 = localObject35;
        if (paramParcel1.readInt() != 0) {
          localObject1 = DataHolder.CREATOR.zzak(paramParcel1);
        }
        zzM((DataHolder)localObject1);
        paramParcel2.writeNoException();
        return true;
      case 11001: 
        paramParcel1.enforceInterface("com.google.android.gms.games.internal.IGamesCallbacks");
        paramInt1 = paramParcel1.readInt();
        if (paramParcel1.readInt() != 0) {}
        for (paramParcel1 = (Bundle)Bundle.CREATOR.createFromParcel(paramParcel1);; paramParcel1 = null)
        {
          zze(paramInt1, paramParcel1);
          paramParcel2.writeNoException();
          return true;
        }
      case 12001: 
        paramParcel1.enforceInterface("com.google.android.gms.games.internal.IGamesCallbacks");
        localObject1 = localObject36;
        if (paramParcel1.readInt() != 0) {
          localObject1 = DataHolder.CREATOR.zzak(paramParcel1);
        }
        zzN((DataHolder)localObject1);
        paramParcel2.writeNoException();
        return true;
      case 12004: 
        paramParcel1.enforceInterface("com.google.android.gms.games.internal.IGamesCallbacks");
        if (paramParcel1.readInt() != 0)
        {
          localObject1 = DataHolder.CREATOR.zzak(paramParcel1);
          if (paramParcel1.readInt() == 0) {
            break label2916;
          }
        }
        for (paramParcel1 = (Contents)Contents.CREATOR.createFromParcel(paramParcel1);; paramParcel1 = null)
        {
          zza((DataHolder)localObject1, paramParcel1);
          paramParcel2.writeNoException();
          return true;
          localObject1 = null;
          break;
        }
      case 12017: 
        paramParcel1.enforceInterface("com.google.android.gms.games.internal.IGamesCallbacks");
        if (paramParcel1.readInt() != 0)
        {
          localObject1 = DataHolder.CREATOR.zzak(paramParcel1);
          str = paramParcel1.readString();
          if (paramParcel1.readInt() == 0) {
            break label3038;
          }
          localObject2 = (Contents)Contents.CREATOR.createFromParcel(paramParcel1);
          if (paramParcel1.readInt() == 0) {
            break label3044;
          }
        }
        for (localContents1 = (Contents)Contents.CREATOR.createFromParcel(paramParcel1);; localContents1 = null)
        {
          if (paramParcel1.readInt() != 0) {
            localContents2 = (Contents)Contents.CREATOR.createFromParcel(paramParcel1);
          }
          zza((DataHolder)localObject1, str, (Contents)localObject2, localContents1, localContents2);
          paramParcel2.writeNoException();
          return true;
          localObject1 = null;
          break;
          localObject2 = null;
          break label2970;
        }
      case 12005: 
        paramParcel1.enforceInterface("com.google.android.gms.games.internal.IGamesCallbacks");
        localObject1 = localObject37;
        if (paramParcel1.readInt() != 0) {
          localObject1 = DataHolder.CREATOR.zzak(paramParcel1);
        }
        zzO((DataHolder)localObject1);
        paramParcel2.writeNoException();
        return true;
      case 12012: 
        paramParcel1.enforceInterface("com.google.android.gms.games.internal.IGamesCallbacks");
        zzj(paramParcel1.readInt(), paramParcel1.readString());
        paramParcel2.writeNoException();
        return true;
      case 12003: 
        paramParcel1.enforceInterface("com.google.android.gms.games.internal.IGamesCallbacks");
        paramInt1 = paramParcel1.readInt();
        if (paramParcel1.readInt() != 0) {}
        for (paramParcel1 = (Bundle)Bundle.CREATOR.createFromParcel(paramParcel1);; paramParcel1 = null)
        {
          zzf(paramInt1, paramParcel1);
          paramParcel2.writeNoException();
          return true;
        }
      case 12013: 
        paramParcel1.enforceInterface("com.google.android.gms.games.internal.IGamesCallbacks");
        localObject1 = localObject38;
        if (paramParcel1.readInt() != 0) {
          localObject1 = DataHolder.CREATOR.zzak(paramParcel1);
        }
        zzU((DataHolder)localObject1);
        paramParcel2.writeNoException();
        return true;
      case 12011: 
        paramParcel1.enforceInterface("com.google.android.gms.games.internal.IGamesCallbacks");
        localObject1 = localObject39;
        if (paramParcel1.readInt() != 0) {
          localObject1 = DataHolder.CREATOR.zzak(paramParcel1);
        }
        zzi((DataHolder)localObject1);
        paramParcel2.writeNoException();
        return true;
      case 12006: 
        paramParcel1.enforceInterface("com.google.android.gms.games.internal.IGamesCallbacks");
        localObject1 = localObject40;
        if (paramParcel1.readInt() != 0) {
          localObject1 = DataHolder.CREATOR.zzak(paramParcel1);
        }
        zzP((DataHolder)localObject1);
        paramParcel2.writeNoException();
        return true;
      case 12007: 
        paramParcel1.enforceInterface("com.google.android.gms.games.internal.IGamesCallbacks");
        localObject1 = localObject41;
        if (paramParcel1.readInt() != 0) {
          localObject1 = DataHolder.CREATOR.zzak(paramParcel1);
        }
        zzQ((DataHolder)localObject1);
        paramParcel2.writeNoException();
        return true;
      case 12014: 
        paramParcel1.enforceInterface("com.google.android.gms.games.internal.IGamesCallbacks");
        localObject1 = localObject42;
        if (paramParcel1.readInt() != 0) {
          localObject1 = DataHolder.CREATOR.zzak(paramParcel1);
        }
        zzR((DataHolder)localObject1);
        paramParcel2.writeNoException();
        return true;
      case 12016: 
        paramParcel1.enforceInterface("com.google.android.gms.games.internal.IGamesCallbacks");
        localObject1 = localObject43;
        if (paramParcel1.readInt() != 0) {
          localObject1 = DataHolder.CREATOR.zzak(paramParcel1);
        }
        zzS((DataHolder)localObject1);
        paramParcel2.writeNoException();
        return true;
      case 12008: 
        paramParcel1.enforceInterface("com.google.android.gms.games.internal.IGamesCallbacks");
        localObject1 = localObject44;
        if (paramParcel1.readInt() != 0) {
          localObject1 = DataHolder.CREATOR.zzak(paramParcel1);
        }
        zzT((DataHolder)localObject1);
        paramParcel2.writeNoException();
        return true;
      case 12015: 
        paramParcel1.enforceInterface("com.google.android.gms.games.internal.IGamesCallbacks");
        paramInt1 = paramParcel1.readInt();
        if (paramParcel1.readInt() != 0) {}
        for (paramParcel1 = (Bundle)Bundle.CREATOR.createFromParcel(paramParcel1);; paramParcel1 = null)
        {
          zzg(paramInt1, paramParcel1);
          paramParcel2.writeNoException();
          return true;
        }
      case 13001: 
        paramParcel1.enforceInterface("com.google.android.gms.games.internal.IGamesCallbacks");
        localObject1 = localObject45;
        if (paramParcel1.readInt() != 0) {
          localObject1 = DataHolder.CREATOR.zzak(paramParcel1);
        }
        zzV((DataHolder)localObject1);
        paramParcel2.writeNoException();
        return true;
      case 13002: 
        paramParcel1.enforceInterface("com.google.android.gms.games.internal.IGamesCallbacks");
        zzgp(paramParcel1.readInt());
        paramParcel2.writeNoException();
        return true;
      case 14001: 
        paramParcel1.enforceInterface("com.google.android.gms.games.internal.IGamesCallbacks");
        zza((DataHolder[])paramParcel1.createTypedArray(DataHolder.CREATOR));
        paramParcel2.writeNoException();
        return true;
      case 15001: 
        paramParcel1.enforceInterface("com.google.android.gms.games.internal.IGamesCallbacks");
        localObject1 = localObject46;
        if (paramParcel1.readInt() != 0) {
          localObject1 = DataHolder.CREATOR.zzak(paramParcel1);
        }
        zzW((DataHolder)localObject1);
        paramParcel2.writeNoException();
        return true;
      case 17001: 
        paramParcel1.enforceInterface("com.google.android.gms.games.internal.IGamesCallbacks");
        localObject1 = localObject47;
        if (paramParcel1.readInt() != 0) {
          localObject1 = DataHolder.CREATOR.zzak(paramParcel1);
        }
        zzX((DataHolder)localObject1);
        paramParcel2.writeNoException();
        return true;
      case 17002: 
        paramParcel1.enforceInterface("com.google.android.gms.games.internal.IGamesCallbacks");
        zzgq(paramParcel1.readInt());
        paramParcel2.writeNoException();
        return true;
      case 19001: 
        paramParcel1.enforceInterface("com.google.android.gms.games.internal.IGamesCallbacks");
        paramInt1 = paramParcel1.readInt();
        if (paramParcel1.readInt() != 0) {}
        for (paramParcel1 = (VideoCapabilities)VideoCapabilities.CREATOR.createFromParcel(paramParcel1);; paramParcel1 = null)
        {
          zza(paramInt1, paramParcel1);
          paramParcel2.writeNoException();
          return true;
        }
      case 19002: 
        label2916:
        label2970:
        label3038:
        label3044:
        paramParcel1.enforceInterface("com.google.android.gms.games.internal.IGamesCallbacks");
        paramInt1 = paramParcel1.readInt();
        bool1 = bool2;
        if (paramParcel1.readInt() != 0) {
          bool1 = true;
        }
        zzd(paramInt1, bool1);
        paramParcel2.writeNoException();
        return true;
      }
      paramParcel1.enforceInterface("com.google.android.gms.games.internal.IGamesCallbacks");
      zza(paramParcel1.readInt(), paramParcel1.createLongArray());
      paramParcel2.writeNoException();
      return true;
    }
    
    private static class Proxy
      implements IGamesCallbacks
    {
      private IBinder zzoz;
      
      Proxy(IBinder paramIBinder)
      {
        this.zzoz = paramIBinder;
      }
      
      public IBinder asBinder()
      {
        return this.zzoz;
      }
      
      public void onInvitationRemoved(String paramString)
        throws RemoteException
      {
        Parcel localParcel1 = Parcel.obtain();
        Parcel localParcel2 = Parcel.obtain();
        try
        {
          localParcel1.writeInterfaceToken("com.google.android.gms.games.internal.IGamesCallbacks");
          localParcel1.writeString(paramString);
          this.zzoz.transact(8010, localParcel1, localParcel2, 0);
          localParcel2.readException();
          return;
        }
        finally
        {
          localParcel2.recycle();
          localParcel1.recycle();
        }
      }
      
      public void onLeftRoom(int paramInt, String paramString)
        throws RemoteException
      {
        Parcel localParcel1 = Parcel.obtain();
        Parcel localParcel2 = Parcel.obtain();
        try
        {
          localParcel1.writeInterfaceToken("com.google.android.gms.games.internal.IGamesCallbacks");
          localParcel1.writeInt(paramInt);
          localParcel1.writeString(paramString);
          this.zzoz.transact(5020, localParcel1, localParcel2, 0);
          localParcel2.readException();
          return;
        }
        finally
        {
          localParcel2.recycle();
          localParcel1.recycle();
        }
      }
      
      public void onP2PConnected(String paramString)
        throws RemoteException
      {
        Parcel localParcel1 = Parcel.obtain();
        Parcel localParcel2 = Parcel.obtain();
        try
        {
          localParcel1.writeInterfaceToken("com.google.android.gms.games.internal.IGamesCallbacks");
          localParcel1.writeString(paramString);
          this.zzoz.transact(6001, localParcel1, localParcel2, 0);
          localParcel2.readException();
          return;
        }
        finally
        {
          localParcel2.recycle();
          localParcel1.recycle();
        }
      }
      
      public void onP2PDisconnected(String paramString)
        throws RemoteException
      {
        Parcel localParcel1 = Parcel.obtain();
        Parcel localParcel2 = Parcel.obtain();
        try
        {
          localParcel1.writeInterfaceToken("com.google.android.gms.games.internal.IGamesCallbacks");
          localParcel1.writeString(paramString);
          this.zzoz.transact(6002, localParcel1, localParcel2, 0);
          localParcel2.readException();
          return;
        }
        finally
        {
          localParcel2.recycle();
          localParcel1.recycle();
        }
      }
      
      /* Error */
      public void onRealTimeMessageReceived(RealTimeMessage paramRealTimeMessage)
        throws RemoteException
      {
        // Byte code:
        //   0: invokestatic 32	android/os/Parcel:obtain	()Landroid/os/Parcel;
        //   3: astore_2
        //   4: invokestatic 32	android/os/Parcel:obtain	()Landroid/os/Parcel;
        //   7: astore_3
        //   8: aload_2
        //   9: ldc 34
        //   11: invokevirtual 37	android/os/Parcel:writeInterfaceToken	(Ljava/lang/String;)V
        //   14: aload_1
        //   15: ifnull +43 -> 58
        //   18: aload_2
        //   19: iconst_1
        //   20: invokevirtual 59	android/os/Parcel:writeInt	(I)V
        //   23: aload_1
        //   24: aload_2
        //   25: iconst_0
        //   26: invokevirtual 69	com/google/android/gms/games/multiplayer/realtime/RealTimeMessage:writeToParcel	(Landroid/os/Parcel;I)V
        //   29: aload_0
        //   30: getfield 19	com/google/android/gms/games/internal/IGamesCallbacks$Stub$Proxy:zzoz	Landroid/os/IBinder;
        //   33: sipush 5032
        //   36: aload_2
        //   37: aload_3
        //   38: iconst_0
        //   39: invokeinterface 46 5 0
        //   44: pop
        //   45: aload_3
        //   46: invokevirtual 49	android/os/Parcel:readException	()V
        //   49: aload_3
        //   50: invokevirtual 52	android/os/Parcel:recycle	()V
        //   53: aload_2
        //   54: invokevirtual 52	android/os/Parcel:recycle	()V
        //   57: return
        //   58: aload_2
        //   59: iconst_0
        //   60: invokevirtual 59	android/os/Parcel:writeInt	(I)V
        //   63: goto -34 -> 29
        //   66: astore_1
        //   67: aload_3
        //   68: invokevirtual 52	android/os/Parcel:recycle	()V
        //   71: aload_2
        //   72: invokevirtual 52	android/os/Parcel:recycle	()V
        //   75: aload_1
        //   76: athrow
        // Local variable table:
        //   start	length	slot	name	signature
        //   0	77	0	this	Proxy
        //   0	77	1	paramRealTimeMessage	RealTimeMessage
        //   3	69	2	localParcel1	Parcel
        //   7	61	3	localParcel2	Parcel
        // Exception table:
        //   from	to	target	type
        //   8	14	66	finally
        //   18	29	66	finally
        //   29	49	66	finally
        //   58	63	66	finally
      }
      
      public void onRequestRemoved(String paramString)
        throws RemoteException
      {
        Parcel localParcel1 = Parcel.obtain();
        Parcel localParcel2 = Parcel.obtain();
        try
        {
          localParcel1.writeInterfaceToken("com.google.android.gms.games.internal.IGamesCallbacks");
          localParcel1.writeString(paramString);
          this.zzoz.transact(10002, localParcel1, localParcel2, 0);
          localParcel2.readException();
          return;
        }
        finally
        {
          localParcel2.recycle();
          localParcel1.recycle();
        }
      }
      
      public void onTurnBasedMatchRemoved(String paramString)
        throws RemoteException
      {
        Parcel localParcel1 = Parcel.obtain();
        Parcel localParcel2 = Parcel.obtain();
        try
        {
          localParcel1.writeInterfaceToken("com.google.android.gms.games.internal.IGamesCallbacks");
          localParcel1.writeString(paramString);
          this.zzoz.transact(8009, localParcel1, localParcel2, 0);
          localParcel2.readException();
          return;
        }
        finally
        {
          localParcel2.recycle();
          localParcel1.recycle();
        }
      }
      
      /* Error */
      public void zzA(DataHolder paramDataHolder)
        throws RemoteException
      {
        // Byte code:
        //   0: invokestatic 32	android/os/Parcel:obtain	()Landroid/os/Parcel;
        //   3: astore_2
        //   4: invokestatic 32	android/os/Parcel:obtain	()Landroid/os/Parcel;
        //   7: astore_3
        //   8: aload_2
        //   9: ldc 34
        //   11: invokevirtual 37	android/os/Parcel:writeInterfaceToken	(Ljava/lang/String;)V
        //   14: aload_1
        //   15: ifnull +43 -> 58
        //   18: aload_2
        //   19: iconst_1
        //   20: invokevirtual 59	android/os/Parcel:writeInt	(I)V
        //   23: aload_1
        //   24: aload_2
        //   25: iconst_0
        //   26: invokevirtual 76	com/google/android/gms/common/data/DataHolder:writeToParcel	(Landroid/os/Parcel;I)V
        //   29: aload_0
        //   30: getfield 19	com/google/android/gms/games/internal/IGamesCallbacks$Stub$Proxy:zzoz	Landroid/os/IBinder;
        //   33: sipush 5019
        //   36: aload_2
        //   37: aload_3
        //   38: iconst_0
        //   39: invokeinterface 46 5 0
        //   44: pop
        //   45: aload_3
        //   46: invokevirtual 49	android/os/Parcel:readException	()V
        //   49: aload_3
        //   50: invokevirtual 52	android/os/Parcel:recycle	()V
        //   53: aload_2
        //   54: invokevirtual 52	android/os/Parcel:recycle	()V
        //   57: return
        //   58: aload_2
        //   59: iconst_0
        //   60: invokevirtual 59	android/os/Parcel:writeInt	(I)V
        //   63: goto -34 -> 29
        //   66: astore_1
        //   67: aload_3
        //   68: invokevirtual 52	android/os/Parcel:recycle	()V
        //   71: aload_2
        //   72: invokevirtual 52	android/os/Parcel:recycle	()V
        //   75: aload_1
        //   76: athrow
        // Local variable table:
        //   start	length	slot	name	signature
        //   0	77	0	this	Proxy
        //   0	77	1	paramDataHolder	DataHolder
        //   3	69	2	localParcel1	Parcel
        //   7	61	3	localParcel2	Parcel
        // Exception table:
        //   from	to	target	type
        //   8	14	66	finally
        //   18	29	66	finally
        //   29	49	66	finally
        //   58	63	66	finally
      }
      
      /* Error */
      public void zzB(DataHolder paramDataHolder)
        throws RemoteException
      {
        // Byte code:
        //   0: invokestatic 32	android/os/Parcel:obtain	()Landroid/os/Parcel;
        //   3: astore_2
        //   4: invokestatic 32	android/os/Parcel:obtain	()Landroid/os/Parcel;
        //   7: astore_3
        //   8: aload_2
        //   9: ldc 34
        //   11: invokevirtual 37	android/os/Parcel:writeInterfaceToken	(Ljava/lang/String;)V
        //   14: aload_1
        //   15: ifnull +43 -> 58
        //   18: aload_2
        //   19: iconst_1
        //   20: invokevirtual 59	android/os/Parcel:writeInt	(I)V
        //   23: aload_1
        //   24: aload_2
        //   25: iconst_0
        //   26: invokevirtual 76	com/google/android/gms/common/data/DataHolder:writeToParcel	(Landroid/os/Parcel;I)V
        //   29: aload_0
        //   30: getfield 19	com/google/android/gms/games/internal/IGamesCallbacks$Stub$Proxy:zzoz	Landroid/os/IBinder;
        //   33: sipush 5021
        //   36: aload_2
        //   37: aload_3
        //   38: iconst_0
        //   39: invokeinterface 46 5 0
        //   44: pop
        //   45: aload_3
        //   46: invokevirtual 49	android/os/Parcel:readException	()V
        //   49: aload_3
        //   50: invokevirtual 52	android/os/Parcel:recycle	()V
        //   53: aload_2
        //   54: invokevirtual 52	android/os/Parcel:recycle	()V
        //   57: return
        //   58: aload_2
        //   59: iconst_0
        //   60: invokevirtual 59	android/os/Parcel:writeInt	(I)V
        //   63: goto -34 -> 29
        //   66: astore_1
        //   67: aload_3
        //   68: invokevirtual 52	android/os/Parcel:recycle	()V
        //   71: aload_2
        //   72: invokevirtual 52	android/os/Parcel:recycle	()V
        //   75: aload_1
        //   76: athrow
        // Local variable table:
        //   start	length	slot	name	signature
        //   0	77	0	this	Proxy
        //   0	77	1	paramDataHolder	DataHolder
        //   3	69	2	localParcel1	Parcel
        //   7	61	3	localParcel2	Parcel
        // Exception table:
        //   from	to	target	type
        //   8	14	66	finally
        //   18	29	66	finally
        //   29	49	66	finally
        //   58	63	66	finally
      }
      
      /* Error */
      public void zzC(DataHolder paramDataHolder)
        throws RemoteException
      {
        // Byte code:
        //   0: invokestatic 32	android/os/Parcel:obtain	()Landroid/os/Parcel;
        //   3: astore_2
        //   4: invokestatic 32	android/os/Parcel:obtain	()Landroid/os/Parcel;
        //   7: astore_3
        //   8: aload_2
        //   9: ldc 34
        //   11: invokevirtual 37	android/os/Parcel:writeInterfaceToken	(Ljava/lang/String;)V
        //   14: aload_1
        //   15: ifnull +43 -> 58
        //   18: aload_2
        //   19: iconst_1
        //   20: invokevirtual 59	android/os/Parcel:writeInt	(I)V
        //   23: aload_1
        //   24: aload_2
        //   25: iconst_0
        //   26: invokevirtual 76	com/google/android/gms/common/data/DataHolder:writeToParcel	(Landroid/os/Parcel;I)V
        //   29: aload_0
        //   30: getfield 19	com/google/android/gms/games/internal/IGamesCallbacks$Stub$Proxy:zzoz	Landroid/os/IBinder;
        //   33: sipush 5022
        //   36: aload_2
        //   37: aload_3
        //   38: iconst_0
        //   39: invokeinterface 46 5 0
        //   44: pop
        //   45: aload_3
        //   46: invokevirtual 49	android/os/Parcel:readException	()V
        //   49: aload_3
        //   50: invokevirtual 52	android/os/Parcel:recycle	()V
        //   53: aload_2
        //   54: invokevirtual 52	android/os/Parcel:recycle	()V
        //   57: return
        //   58: aload_2
        //   59: iconst_0
        //   60: invokevirtual 59	android/os/Parcel:writeInt	(I)V
        //   63: goto -34 -> 29
        //   66: astore_1
        //   67: aload_3
        //   68: invokevirtual 52	android/os/Parcel:recycle	()V
        //   71: aload_2
        //   72: invokevirtual 52	android/os/Parcel:recycle	()V
        //   75: aload_1
        //   76: athrow
        // Local variable table:
        //   start	length	slot	name	signature
        //   0	77	0	this	Proxy
        //   0	77	1	paramDataHolder	DataHolder
        //   3	69	2	localParcel1	Parcel
        //   7	61	3	localParcel2	Parcel
        // Exception table:
        //   from	to	target	type
        //   8	14	66	finally
        //   18	29	66	finally
        //   29	49	66	finally
        //   58	63	66	finally
      }
      
      /* Error */
      public void zzD(DataHolder paramDataHolder)
        throws RemoteException
      {
        // Byte code:
        //   0: invokestatic 32	android/os/Parcel:obtain	()Landroid/os/Parcel;
        //   3: astore_2
        //   4: invokestatic 32	android/os/Parcel:obtain	()Landroid/os/Parcel;
        //   7: astore_3
        //   8: aload_2
        //   9: ldc 34
        //   11: invokevirtual 37	android/os/Parcel:writeInterfaceToken	(Ljava/lang/String;)V
        //   14: aload_1
        //   15: ifnull +43 -> 58
        //   18: aload_2
        //   19: iconst_1
        //   20: invokevirtual 59	android/os/Parcel:writeInt	(I)V
        //   23: aload_1
        //   24: aload_2
        //   25: iconst_0
        //   26: invokevirtual 76	com/google/android/gms/common/data/DataHolder:writeToParcel	(Landroid/os/Parcel;I)V
        //   29: aload_0
        //   30: getfield 19	com/google/android/gms/games/internal/IGamesCallbacks$Stub$Proxy:zzoz	Landroid/os/IBinder;
        //   33: sipush 5023
        //   36: aload_2
        //   37: aload_3
        //   38: iconst_0
        //   39: invokeinterface 46 5 0
        //   44: pop
        //   45: aload_3
        //   46: invokevirtual 49	android/os/Parcel:readException	()V
        //   49: aload_3
        //   50: invokevirtual 52	android/os/Parcel:recycle	()V
        //   53: aload_2
        //   54: invokevirtual 52	android/os/Parcel:recycle	()V
        //   57: return
        //   58: aload_2
        //   59: iconst_0
        //   60: invokevirtual 59	android/os/Parcel:writeInt	(I)V
        //   63: goto -34 -> 29
        //   66: astore_1
        //   67: aload_3
        //   68: invokevirtual 52	android/os/Parcel:recycle	()V
        //   71: aload_2
        //   72: invokevirtual 52	android/os/Parcel:recycle	()V
        //   75: aload_1
        //   76: athrow
        // Local variable table:
        //   start	length	slot	name	signature
        //   0	77	0	this	Proxy
        //   0	77	1	paramDataHolder	DataHolder
        //   3	69	2	localParcel1	Parcel
        //   7	61	3	localParcel2	Parcel
        // Exception table:
        //   from	to	target	type
        //   8	14	66	finally
        //   18	29	66	finally
        //   29	49	66	finally
        //   58	63	66	finally
      }
      
      /* Error */
      public void zzE(DataHolder paramDataHolder)
        throws RemoteException
      {
        // Byte code:
        //   0: invokestatic 32	android/os/Parcel:obtain	()Landroid/os/Parcel;
        //   3: astore_2
        //   4: invokestatic 32	android/os/Parcel:obtain	()Landroid/os/Parcel;
        //   7: astore_3
        //   8: aload_2
        //   9: ldc 34
        //   11: invokevirtual 37	android/os/Parcel:writeInterfaceToken	(Ljava/lang/String;)V
        //   14: aload_1
        //   15: ifnull +43 -> 58
        //   18: aload_2
        //   19: iconst_1
        //   20: invokevirtual 59	android/os/Parcel:writeInt	(I)V
        //   23: aload_1
        //   24: aload_2
        //   25: iconst_0
        //   26: invokevirtual 76	com/google/android/gms/common/data/DataHolder:writeToParcel	(Landroid/os/Parcel;I)V
        //   29: aload_0
        //   30: getfield 19	com/google/android/gms/games/internal/IGamesCallbacks$Stub$Proxy:zzoz	Landroid/os/IBinder;
        //   33: sipush 5024
        //   36: aload_2
        //   37: aload_3
        //   38: iconst_0
        //   39: invokeinterface 46 5 0
        //   44: pop
        //   45: aload_3
        //   46: invokevirtual 49	android/os/Parcel:readException	()V
        //   49: aload_3
        //   50: invokevirtual 52	android/os/Parcel:recycle	()V
        //   53: aload_2
        //   54: invokevirtual 52	android/os/Parcel:recycle	()V
        //   57: return
        //   58: aload_2
        //   59: iconst_0
        //   60: invokevirtual 59	android/os/Parcel:writeInt	(I)V
        //   63: goto -34 -> 29
        //   66: astore_1
        //   67: aload_3
        //   68: invokevirtual 52	android/os/Parcel:recycle	()V
        //   71: aload_2
        //   72: invokevirtual 52	android/os/Parcel:recycle	()V
        //   75: aload_1
        //   76: athrow
        // Local variable table:
        //   start	length	slot	name	signature
        //   0	77	0	this	Proxy
        //   0	77	1	paramDataHolder	DataHolder
        //   3	69	2	localParcel1	Parcel
        //   7	61	3	localParcel2	Parcel
        // Exception table:
        //   from	to	target	type
        //   8	14	66	finally
        //   18	29	66	finally
        //   29	49	66	finally
        //   58	63	66	finally
      }
      
      /* Error */
      public void zzF(DataHolder paramDataHolder)
        throws RemoteException
      {
        // Byte code:
        //   0: invokestatic 32	android/os/Parcel:obtain	()Landroid/os/Parcel;
        //   3: astore_2
        //   4: invokestatic 32	android/os/Parcel:obtain	()Landroid/os/Parcel;
        //   7: astore_3
        //   8: aload_2
        //   9: ldc 34
        //   11: invokevirtual 37	android/os/Parcel:writeInterfaceToken	(Ljava/lang/String;)V
        //   14: aload_1
        //   15: ifnull +43 -> 58
        //   18: aload_2
        //   19: iconst_1
        //   20: invokevirtual 59	android/os/Parcel:writeInt	(I)V
        //   23: aload_1
        //   24: aload_2
        //   25: iconst_0
        //   26: invokevirtual 76	com/google/android/gms/common/data/DataHolder:writeToParcel	(Landroid/os/Parcel;I)V
        //   29: aload_0
        //   30: getfield 19	com/google/android/gms/games/internal/IGamesCallbacks$Stub$Proxy:zzoz	Landroid/os/IBinder;
        //   33: sipush 5025
        //   36: aload_2
        //   37: aload_3
        //   38: iconst_0
        //   39: invokeinterface 46 5 0
        //   44: pop
        //   45: aload_3
        //   46: invokevirtual 49	android/os/Parcel:readException	()V
        //   49: aload_3
        //   50: invokevirtual 52	android/os/Parcel:recycle	()V
        //   53: aload_2
        //   54: invokevirtual 52	android/os/Parcel:recycle	()V
        //   57: return
        //   58: aload_2
        //   59: iconst_0
        //   60: invokevirtual 59	android/os/Parcel:writeInt	(I)V
        //   63: goto -34 -> 29
        //   66: astore_1
        //   67: aload_3
        //   68: invokevirtual 52	android/os/Parcel:recycle	()V
        //   71: aload_2
        //   72: invokevirtual 52	android/os/Parcel:recycle	()V
        //   75: aload_1
        //   76: athrow
        // Local variable table:
        //   start	length	slot	name	signature
        //   0	77	0	this	Proxy
        //   0	77	1	paramDataHolder	DataHolder
        //   3	69	2	localParcel1	Parcel
        //   7	61	3	localParcel2	Parcel
        // Exception table:
        //   from	to	target	type
        //   8	14	66	finally
        //   18	29	66	finally
        //   29	49	66	finally
        //   58	63	66	finally
      }
      
      /* Error */
      public void zzG(DataHolder paramDataHolder)
        throws RemoteException
      {
        // Byte code:
        //   0: invokestatic 32	android/os/Parcel:obtain	()Landroid/os/Parcel;
        //   3: astore_2
        //   4: invokestatic 32	android/os/Parcel:obtain	()Landroid/os/Parcel;
        //   7: astore_3
        //   8: aload_2
        //   9: ldc 34
        //   11: invokevirtual 37	android/os/Parcel:writeInterfaceToken	(Ljava/lang/String;)V
        //   14: aload_1
        //   15: ifnull +43 -> 58
        //   18: aload_2
        //   19: iconst_1
        //   20: invokevirtual 59	android/os/Parcel:writeInt	(I)V
        //   23: aload_1
        //   24: aload_2
        //   25: iconst_0
        //   26: invokevirtual 76	com/google/android/gms/common/data/DataHolder:writeToParcel	(Landroid/os/Parcel;I)V
        //   29: aload_0
        //   30: getfield 19	com/google/android/gms/games/internal/IGamesCallbacks$Stub$Proxy:zzoz	Landroid/os/IBinder;
        //   33: sipush 5038
        //   36: aload_2
        //   37: aload_3
        //   38: iconst_0
        //   39: invokeinterface 46 5 0
        //   44: pop
        //   45: aload_3
        //   46: invokevirtual 49	android/os/Parcel:readException	()V
        //   49: aload_3
        //   50: invokevirtual 52	android/os/Parcel:recycle	()V
        //   53: aload_2
        //   54: invokevirtual 52	android/os/Parcel:recycle	()V
        //   57: return
        //   58: aload_2
        //   59: iconst_0
        //   60: invokevirtual 59	android/os/Parcel:writeInt	(I)V
        //   63: goto -34 -> 29
        //   66: astore_1
        //   67: aload_3
        //   68: invokevirtual 52	android/os/Parcel:recycle	()V
        //   71: aload_2
        //   72: invokevirtual 52	android/os/Parcel:recycle	()V
        //   75: aload_1
        //   76: athrow
        // Local variable table:
        //   start	length	slot	name	signature
        //   0	77	0	this	Proxy
        //   0	77	1	paramDataHolder	DataHolder
        //   3	69	2	localParcel1	Parcel
        //   7	61	3	localParcel2	Parcel
        // Exception table:
        //   from	to	target	type
        //   8	14	66	finally
        //   18	29	66	finally
        //   29	49	66	finally
        //   58	63	66	finally
      }
      
      /* Error */
      public void zzH(DataHolder paramDataHolder)
        throws RemoteException
      {
        // Byte code:
        //   0: invokestatic 32	android/os/Parcel:obtain	()Landroid/os/Parcel;
        //   3: astore_2
        //   4: invokestatic 32	android/os/Parcel:obtain	()Landroid/os/Parcel;
        //   7: astore_3
        //   8: aload_2
        //   9: ldc 34
        //   11: invokevirtual 37	android/os/Parcel:writeInterfaceToken	(Ljava/lang/String;)V
        //   14: aload_1
        //   15: ifnull +43 -> 58
        //   18: aload_2
        //   19: iconst_1
        //   20: invokevirtual 59	android/os/Parcel:writeInt	(I)V
        //   23: aload_1
        //   24: aload_2
        //   25: iconst_0
        //   26: invokevirtual 76	com/google/android/gms/common/data/DataHolder:writeToParcel	(Landroid/os/Parcel;I)V
        //   29: aload_0
        //   30: getfield 19	com/google/android/gms/games/internal/IGamesCallbacks$Stub$Proxy:zzoz	Landroid/os/IBinder;
        //   33: sipush 5035
        //   36: aload_2
        //   37: aload_3
        //   38: iconst_0
        //   39: invokeinterface 46 5 0
        //   44: pop
        //   45: aload_3
        //   46: invokevirtual 49	android/os/Parcel:readException	()V
        //   49: aload_3
        //   50: invokevirtual 52	android/os/Parcel:recycle	()V
        //   53: aload_2
        //   54: invokevirtual 52	android/os/Parcel:recycle	()V
        //   57: return
        //   58: aload_2
        //   59: iconst_0
        //   60: invokevirtual 59	android/os/Parcel:writeInt	(I)V
        //   63: goto -34 -> 29
        //   66: astore_1
        //   67: aload_3
        //   68: invokevirtual 52	android/os/Parcel:recycle	()V
        //   71: aload_2
        //   72: invokevirtual 52	android/os/Parcel:recycle	()V
        //   75: aload_1
        //   76: athrow
        // Local variable table:
        //   start	length	slot	name	signature
        //   0	77	0	this	Proxy
        //   0	77	1	paramDataHolder	DataHolder
        //   3	69	2	localParcel1	Parcel
        //   7	61	3	localParcel2	Parcel
        // Exception table:
        //   from	to	target	type
        //   8	14	66	finally
        //   18	29	66	finally
        //   29	49	66	finally
        //   58	63	66	finally
      }
      
      /* Error */
      public void zzI(DataHolder paramDataHolder)
        throws RemoteException
      {
        // Byte code:
        //   0: invokestatic 32	android/os/Parcel:obtain	()Landroid/os/Parcel;
        //   3: astore_2
        //   4: invokestatic 32	android/os/Parcel:obtain	()Landroid/os/Parcel;
        //   7: astore_3
        //   8: aload_2
        //   9: ldc 34
        //   11: invokevirtual 37	android/os/Parcel:writeInterfaceToken	(Ljava/lang/String;)V
        //   14: aload_1
        //   15: ifnull +43 -> 58
        //   18: aload_2
        //   19: iconst_1
        //   20: invokevirtual 59	android/os/Parcel:writeInt	(I)V
        //   23: aload_1
        //   24: aload_2
        //   25: iconst_0
        //   26: invokevirtual 76	com/google/android/gms/common/data/DataHolder:writeToParcel	(Landroid/os/Parcel;I)V
        //   29: aload_0
        //   30: getfield 19	com/google/android/gms/games/internal/IGamesCallbacks$Stub$Proxy:zzoz	Landroid/os/IBinder;
        //   33: sipush 5039
        //   36: aload_2
        //   37: aload_3
        //   38: iconst_0
        //   39: invokeinterface 46 5 0
        //   44: pop
        //   45: aload_3
        //   46: invokevirtual 49	android/os/Parcel:readException	()V
        //   49: aload_3
        //   50: invokevirtual 52	android/os/Parcel:recycle	()V
        //   53: aload_2
        //   54: invokevirtual 52	android/os/Parcel:recycle	()V
        //   57: return
        //   58: aload_2
        //   59: iconst_0
        //   60: invokevirtual 59	android/os/Parcel:writeInt	(I)V
        //   63: goto -34 -> 29
        //   66: astore_1
        //   67: aload_3
        //   68: invokevirtual 52	android/os/Parcel:recycle	()V
        //   71: aload_2
        //   72: invokevirtual 52	android/os/Parcel:recycle	()V
        //   75: aload_1
        //   76: athrow
        // Local variable table:
        //   start	length	slot	name	signature
        //   0	77	0	this	Proxy
        //   0	77	1	paramDataHolder	DataHolder
        //   3	69	2	localParcel1	Parcel
        //   7	61	3	localParcel2	Parcel
        // Exception table:
        //   from	to	target	type
        //   8	14	66	finally
        //   18	29	66	finally
        //   29	49	66	finally
        //   58	63	66	finally
      }
      
      /* Error */
      public void zzJ(DataHolder paramDataHolder)
        throws RemoteException
      {
        // Byte code:
        //   0: invokestatic 32	android/os/Parcel:obtain	()Landroid/os/Parcel;
        //   3: astore_2
        //   4: invokestatic 32	android/os/Parcel:obtain	()Landroid/os/Parcel;
        //   7: astore_3
        //   8: aload_2
        //   9: ldc 34
        //   11: invokevirtual 37	android/os/Parcel:writeInterfaceToken	(Ljava/lang/String;)V
        //   14: aload_1
        //   15: ifnull +43 -> 58
        //   18: aload_2
        //   19: iconst_1
        //   20: invokevirtual 59	android/os/Parcel:writeInt	(I)V
        //   23: aload_1
        //   24: aload_2
        //   25: iconst_0
        //   26: invokevirtual 76	com/google/android/gms/common/data/DataHolder:writeToParcel	(Landroid/os/Parcel;I)V
        //   29: aload_0
        //   30: getfield 19	com/google/android/gms/games/internal/IGamesCallbacks$Stub$Proxy:zzoz	Landroid/os/IBinder;
        //   33: sipush 8001
        //   36: aload_2
        //   37: aload_3
        //   38: iconst_0
        //   39: invokeinterface 46 5 0
        //   44: pop
        //   45: aload_3
        //   46: invokevirtual 49	android/os/Parcel:readException	()V
        //   49: aload_3
        //   50: invokevirtual 52	android/os/Parcel:recycle	()V
        //   53: aload_2
        //   54: invokevirtual 52	android/os/Parcel:recycle	()V
        //   57: return
        //   58: aload_2
        //   59: iconst_0
        //   60: invokevirtual 59	android/os/Parcel:writeInt	(I)V
        //   63: goto -34 -> 29
        //   66: astore_1
        //   67: aload_3
        //   68: invokevirtual 52	android/os/Parcel:recycle	()V
        //   71: aload_2
        //   72: invokevirtual 52	android/os/Parcel:recycle	()V
        //   75: aload_1
        //   76: athrow
        // Local variable table:
        //   start	length	slot	name	signature
        //   0	77	0	this	Proxy
        //   0	77	1	paramDataHolder	DataHolder
        //   3	69	2	localParcel1	Parcel
        //   7	61	3	localParcel2	Parcel
        // Exception table:
        //   from	to	target	type
        //   8	14	66	finally
        //   18	29	66	finally
        //   29	49	66	finally
        //   58	63	66	finally
      }
      
      /* Error */
      public void zzK(DataHolder paramDataHolder)
        throws RemoteException
      {
        // Byte code:
        //   0: invokestatic 32	android/os/Parcel:obtain	()Landroid/os/Parcel;
        //   3: astore_2
        //   4: invokestatic 32	android/os/Parcel:obtain	()Landroid/os/Parcel;
        //   7: astore_3
        //   8: aload_2
        //   9: ldc 34
        //   11: invokevirtual 37	android/os/Parcel:writeInterfaceToken	(Ljava/lang/String;)V
        //   14: aload_1
        //   15: ifnull +43 -> 58
        //   18: aload_2
        //   19: iconst_1
        //   20: invokevirtual 59	android/os/Parcel:writeInt	(I)V
        //   23: aload_1
        //   24: aload_2
        //   25: iconst_0
        //   26: invokevirtual 76	com/google/android/gms/common/data/DataHolder:writeToParcel	(Landroid/os/Parcel;I)V
        //   29: aload_0
        //   30: getfield 19	com/google/android/gms/games/internal/IGamesCallbacks$Stub$Proxy:zzoz	Landroid/os/IBinder;
        //   33: sipush 10003
        //   36: aload_2
        //   37: aload_3
        //   38: iconst_0
        //   39: invokeinterface 46 5 0
        //   44: pop
        //   45: aload_3
        //   46: invokevirtual 49	android/os/Parcel:readException	()V
        //   49: aload_3
        //   50: invokevirtual 52	android/os/Parcel:recycle	()V
        //   53: aload_2
        //   54: invokevirtual 52	android/os/Parcel:recycle	()V
        //   57: return
        //   58: aload_2
        //   59: iconst_0
        //   60: invokevirtual 59	android/os/Parcel:writeInt	(I)V
        //   63: goto -34 -> 29
        //   66: astore_1
        //   67: aload_3
        //   68: invokevirtual 52	android/os/Parcel:recycle	()V
        //   71: aload_2
        //   72: invokevirtual 52	android/os/Parcel:recycle	()V
        //   75: aload_1
        //   76: athrow
        // Local variable table:
        //   start	length	slot	name	signature
        //   0	77	0	this	Proxy
        //   0	77	1	paramDataHolder	DataHolder
        //   3	69	2	localParcel1	Parcel
        //   7	61	3	localParcel2	Parcel
        // Exception table:
        //   from	to	target	type
        //   8	14	66	finally
        //   18	29	66	finally
        //   29	49	66	finally
        //   58	63	66	finally
      }
      
      /* Error */
      public void zzL(DataHolder paramDataHolder)
        throws RemoteException
      {
        // Byte code:
        //   0: invokestatic 32	android/os/Parcel:obtain	()Landroid/os/Parcel;
        //   3: astore_2
        //   4: invokestatic 32	android/os/Parcel:obtain	()Landroid/os/Parcel;
        //   7: astore_3
        //   8: aload_2
        //   9: ldc 34
        //   11: invokevirtual 37	android/os/Parcel:writeInterfaceToken	(Ljava/lang/String;)V
        //   14: aload_1
        //   15: ifnull +43 -> 58
        //   18: aload_2
        //   19: iconst_1
        //   20: invokevirtual 59	android/os/Parcel:writeInt	(I)V
        //   23: aload_1
        //   24: aload_2
        //   25: iconst_0
        //   26: invokevirtual 76	com/google/android/gms/common/data/DataHolder:writeToParcel	(Landroid/os/Parcel;I)V
        //   29: aload_0
        //   30: getfield 19	com/google/android/gms/games/internal/IGamesCallbacks$Stub$Proxy:zzoz	Landroid/os/IBinder;
        //   33: sipush 10004
        //   36: aload_2
        //   37: aload_3
        //   38: iconst_0
        //   39: invokeinterface 46 5 0
        //   44: pop
        //   45: aload_3
        //   46: invokevirtual 49	android/os/Parcel:readException	()V
        //   49: aload_3
        //   50: invokevirtual 52	android/os/Parcel:recycle	()V
        //   53: aload_2
        //   54: invokevirtual 52	android/os/Parcel:recycle	()V
        //   57: return
        //   58: aload_2
        //   59: iconst_0
        //   60: invokevirtual 59	android/os/Parcel:writeInt	(I)V
        //   63: goto -34 -> 29
        //   66: astore_1
        //   67: aload_3
        //   68: invokevirtual 52	android/os/Parcel:recycle	()V
        //   71: aload_2
        //   72: invokevirtual 52	android/os/Parcel:recycle	()V
        //   75: aload_1
        //   76: athrow
        // Local variable table:
        //   start	length	slot	name	signature
        //   0	77	0	this	Proxy
        //   0	77	1	paramDataHolder	DataHolder
        //   3	69	2	localParcel1	Parcel
        //   7	61	3	localParcel2	Parcel
        // Exception table:
        //   from	to	target	type
        //   8	14	66	finally
        //   18	29	66	finally
        //   29	49	66	finally
        //   58	63	66	finally
      }
      
      /* Error */
      public void zzM(DataHolder paramDataHolder)
        throws RemoteException
      {
        // Byte code:
        //   0: invokestatic 32	android/os/Parcel:obtain	()Landroid/os/Parcel;
        //   3: astore_2
        //   4: invokestatic 32	android/os/Parcel:obtain	()Landroid/os/Parcel;
        //   7: astore_3
        //   8: aload_2
        //   9: ldc 34
        //   11: invokevirtual 37	android/os/Parcel:writeInterfaceToken	(Ljava/lang/String;)V
        //   14: aload_1
        //   15: ifnull +43 -> 58
        //   18: aload_2
        //   19: iconst_1
        //   20: invokevirtual 59	android/os/Parcel:writeInt	(I)V
        //   23: aload_1
        //   24: aload_2
        //   25: iconst_0
        //   26: invokevirtual 76	com/google/android/gms/common/data/DataHolder:writeToParcel	(Landroid/os/Parcel;I)V
        //   29: aload_0
        //   30: getfield 19	com/google/android/gms/games/internal/IGamesCallbacks$Stub$Proxy:zzoz	Landroid/os/IBinder;
        //   33: sipush 10006
        //   36: aload_2
        //   37: aload_3
        //   38: iconst_0
        //   39: invokeinterface 46 5 0
        //   44: pop
        //   45: aload_3
        //   46: invokevirtual 49	android/os/Parcel:readException	()V
        //   49: aload_3
        //   50: invokevirtual 52	android/os/Parcel:recycle	()V
        //   53: aload_2
        //   54: invokevirtual 52	android/os/Parcel:recycle	()V
        //   57: return
        //   58: aload_2
        //   59: iconst_0
        //   60: invokevirtual 59	android/os/Parcel:writeInt	(I)V
        //   63: goto -34 -> 29
        //   66: astore_1
        //   67: aload_3
        //   68: invokevirtual 52	android/os/Parcel:recycle	()V
        //   71: aload_2
        //   72: invokevirtual 52	android/os/Parcel:recycle	()V
        //   75: aload_1
        //   76: athrow
        // Local variable table:
        //   start	length	slot	name	signature
        //   0	77	0	this	Proxy
        //   0	77	1	paramDataHolder	DataHolder
        //   3	69	2	localParcel1	Parcel
        //   7	61	3	localParcel2	Parcel
        // Exception table:
        //   from	to	target	type
        //   8	14	66	finally
        //   18	29	66	finally
        //   29	49	66	finally
        //   58	63	66	finally
      }
      
      /* Error */
      public void zzN(DataHolder paramDataHolder)
        throws RemoteException
      {
        // Byte code:
        //   0: invokestatic 32	android/os/Parcel:obtain	()Landroid/os/Parcel;
        //   3: astore_2
        //   4: invokestatic 32	android/os/Parcel:obtain	()Landroid/os/Parcel;
        //   7: astore_3
        //   8: aload_2
        //   9: ldc 34
        //   11: invokevirtual 37	android/os/Parcel:writeInterfaceToken	(Ljava/lang/String;)V
        //   14: aload_1
        //   15: ifnull +43 -> 58
        //   18: aload_2
        //   19: iconst_1
        //   20: invokevirtual 59	android/os/Parcel:writeInt	(I)V
        //   23: aload_1
        //   24: aload_2
        //   25: iconst_0
        //   26: invokevirtual 76	com/google/android/gms/common/data/DataHolder:writeToParcel	(Landroid/os/Parcel;I)V
        //   29: aload_0
        //   30: getfield 19	com/google/android/gms/games/internal/IGamesCallbacks$Stub$Proxy:zzoz	Landroid/os/IBinder;
        //   33: sipush 12001
        //   36: aload_2
        //   37: aload_3
        //   38: iconst_0
        //   39: invokeinterface 46 5 0
        //   44: pop
        //   45: aload_3
        //   46: invokevirtual 49	android/os/Parcel:readException	()V
        //   49: aload_3
        //   50: invokevirtual 52	android/os/Parcel:recycle	()V
        //   53: aload_2
        //   54: invokevirtual 52	android/os/Parcel:recycle	()V
        //   57: return
        //   58: aload_2
        //   59: iconst_0
        //   60: invokevirtual 59	android/os/Parcel:writeInt	(I)V
        //   63: goto -34 -> 29
        //   66: astore_1
        //   67: aload_3
        //   68: invokevirtual 52	android/os/Parcel:recycle	()V
        //   71: aload_2
        //   72: invokevirtual 52	android/os/Parcel:recycle	()V
        //   75: aload_1
        //   76: athrow
        // Local variable table:
        //   start	length	slot	name	signature
        //   0	77	0	this	Proxy
        //   0	77	1	paramDataHolder	DataHolder
        //   3	69	2	localParcel1	Parcel
        //   7	61	3	localParcel2	Parcel
        // Exception table:
        //   from	to	target	type
        //   8	14	66	finally
        //   18	29	66	finally
        //   29	49	66	finally
        //   58	63	66	finally
      }
      
      /* Error */
      public void zzO(DataHolder paramDataHolder)
        throws RemoteException
      {
        // Byte code:
        //   0: invokestatic 32	android/os/Parcel:obtain	()Landroid/os/Parcel;
        //   3: astore_2
        //   4: invokestatic 32	android/os/Parcel:obtain	()Landroid/os/Parcel;
        //   7: astore_3
        //   8: aload_2
        //   9: ldc 34
        //   11: invokevirtual 37	android/os/Parcel:writeInterfaceToken	(Ljava/lang/String;)V
        //   14: aload_1
        //   15: ifnull +43 -> 58
        //   18: aload_2
        //   19: iconst_1
        //   20: invokevirtual 59	android/os/Parcel:writeInt	(I)V
        //   23: aload_1
        //   24: aload_2
        //   25: iconst_0
        //   26: invokevirtual 76	com/google/android/gms/common/data/DataHolder:writeToParcel	(Landroid/os/Parcel;I)V
        //   29: aload_0
        //   30: getfield 19	com/google/android/gms/games/internal/IGamesCallbacks$Stub$Proxy:zzoz	Landroid/os/IBinder;
        //   33: sipush 12005
        //   36: aload_2
        //   37: aload_3
        //   38: iconst_0
        //   39: invokeinterface 46 5 0
        //   44: pop
        //   45: aload_3
        //   46: invokevirtual 49	android/os/Parcel:readException	()V
        //   49: aload_3
        //   50: invokevirtual 52	android/os/Parcel:recycle	()V
        //   53: aload_2
        //   54: invokevirtual 52	android/os/Parcel:recycle	()V
        //   57: return
        //   58: aload_2
        //   59: iconst_0
        //   60: invokevirtual 59	android/os/Parcel:writeInt	(I)V
        //   63: goto -34 -> 29
        //   66: astore_1
        //   67: aload_3
        //   68: invokevirtual 52	android/os/Parcel:recycle	()V
        //   71: aload_2
        //   72: invokevirtual 52	android/os/Parcel:recycle	()V
        //   75: aload_1
        //   76: athrow
        // Local variable table:
        //   start	length	slot	name	signature
        //   0	77	0	this	Proxy
        //   0	77	1	paramDataHolder	DataHolder
        //   3	69	2	localParcel1	Parcel
        //   7	61	3	localParcel2	Parcel
        // Exception table:
        //   from	to	target	type
        //   8	14	66	finally
        //   18	29	66	finally
        //   29	49	66	finally
        //   58	63	66	finally
      }
      
      /* Error */
      public void zzP(DataHolder paramDataHolder)
        throws RemoteException
      {
        // Byte code:
        //   0: invokestatic 32	android/os/Parcel:obtain	()Landroid/os/Parcel;
        //   3: astore_2
        //   4: invokestatic 32	android/os/Parcel:obtain	()Landroid/os/Parcel;
        //   7: astore_3
        //   8: aload_2
        //   9: ldc 34
        //   11: invokevirtual 37	android/os/Parcel:writeInterfaceToken	(Ljava/lang/String;)V
        //   14: aload_1
        //   15: ifnull +43 -> 58
        //   18: aload_2
        //   19: iconst_1
        //   20: invokevirtual 59	android/os/Parcel:writeInt	(I)V
        //   23: aload_1
        //   24: aload_2
        //   25: iconst_0
        //   26: invokevirtual 76	com/google/android/gms/common/data/DataHolder:writeToParcel	(Landroid/os/Parcel;I)V
        //   29: aload_0
        //   30: getfield 19	com/google/android/gms/games/internal/IGamesCallbacks$Stub$Proxy:zzoz	Landroid/os/IBinder;
        //   33: sipush 12006
        //   36: aload_2
        //   37: aload_3
        //   38: iconst_0
        //   39: invokeinterface 46 5 0
        //   44: pop
        //   45: aload_3
        //   46: invokevirtual 49	android/os/Parcel:readException	()V
        //   49: aload_3
        //   50: invokevirtual 52	android/os/Parcel:recycle	()V
        //   53: aload_2
        //   54: invokevirtual 52	android/os/Parcel:recycle	()V
        //   57: return
        //   58: aload_2
        //   59: iconst_0
        //   60: invokevirtual 59	android/os/Parcel:writeInt	(I)V
        //   63: goto -34 -> 29
        //   66: astore_1
        //   67: aload_3
        //   68: invokevirtual 52	android/os/Parcel:recycle	()V
        //   71: aload_2
        //   72: invokevirtual 52	android/os/Parcel:recycle	()V
        //   75: aload_1
        //   76: athrow
        // Local variable table:
        //   start	length	slot	name	signature
        //   0	77	0	this	Proxy
        //   0	77	1	paramDataHolder	DataHolder
        //   3	69	2	localParcel1	Parcel
        //   7	61	3	localParcel2	Parcel
        // Exception table:
        //   from	to	target	type
        //   8	14	66	finally
        //   18	29	66	finally
        //   29	49	66	finally
        //   58	63	66	finally
      }
      
      /* Error */
      public void zzQ(DataHolder paramDataHolder)
        throws RemoteException
      {
        // Byte code:
        //   0: invokestatic 32	android/os/Parcel:obtain	()Landroid/os/Parcel;
        //   3: astore_2
        //   4: invokestatic 32	android/os/Parcel:obtain	()Landroid/os/Parcel;
        //   7: astore_3
        //   8: aload_2
        //   9: ldc 34
        //   11: invokevirtual 37	android/os/Parcel:writeInterfaceToken	(Ljava/lang/String;)V
        //   14: aload_1
        //   15: ifnull +43 -> 58
        //   18: aload_2
        //   19: iconst_1
        //   20: invokevirtual 59	android/os/Parcel:writeInt	(I)V
        //   23: aload_1
        //   24: aload_2
        //   25: iconst_0
        //   26: invokevirtual 76	com/google/android/gms/common/data/DataHolder:writeToParcel	(Landroid/os/Parcel;I)V
        //   29: aload_0
        //   30: getfield 19	com/google/android/gms/games/internal/IGamesCallbacks$Stub$Proxy:zzoz	Landroid/os/IBinder;
        //   33: sipush 12007
        //   36: aload_2
        //   37: aload_3
        //   38: iconst_0
        //   39: invokeinterface 46 5 0
        //   44: pop
        //   45: aload_3
        //   46: invokevirtual 49	android/os/Parcel:readException	()V
        //   49: aload_3
        //   50: invokevirtual 52	android/os/Parcel:recycle	()V
        //   53: aload_2
        //   54: invokevirtual 52	android/os/Parcel:recycle	()V
        //   57: return
        //   58: aload_2
        //   59: iconst_0
        //   60: invokevirtual 59	android/os/Parcel:writeInt	(I)V
        //   63: goto -34 -> 29
        //   66: astore_1
        //   67: aload_3
        //   68: invokevirtual 52	android/os/Parcel:recycle	()V
        //   71: aload_2
        //   72: invokevirtual 52	android/os/Parcel:recycle	()V
        //   75: aload_1
        //   76: athrow
        // Local variable table:
        //   start	length	slot	name	signature
        //   0	77	0	this	Proxy
        //   0	77	1	paramDataHolder	DataHolder
        //   3	69	2	localParcel1	Parcel
        //   7	61	3	localParcel2	Parcel
        // Exception table:
        //   from	to	target	type
        //   8	14	66	finally
        //   18	29	66	finally
        //   29	49	66	finally
        //   58	63	66	finally
      }
      
      /* Error */
      public void zzR(DataHolder paramDataHolder)
        throws RemoteException
      {
        // Byte code:
        //   0: invokestatic 32	android/os/Parcel:obtain	()Landroid/os/Parcel;
        //   3: astore_2
        //   4: invokestatic 32	android/os/Parcel:obtain	()Landroid/os/Parcel;
        //   7: astore_3
        //   8: aload_2
        //   9: ldc 34
        //   11: invokevirtual 37	android/os/Parcel:writeInterfaceToken	(Ljava/lang/String;)V
        //   14: aload_1
        //   15: ifnull +43 -> 58
        //   18: aload_2
        //   19: iconst_1
        //   20: invokevirtual 59	android/os/Parcel:writeInt	(I)V
        //   23: aload_1
        //   24: aload_2
        //   25: iconst_0
        //   26: invokevirtual 76	com/google/android/gms/common/data/DataHolder:writeToParcel	(Landroid/os/Parcel;I)V
        //   29: aload_0
        //   30: getfield 19	com/google/android/gms/games/internal/IGamesCallbacks$Stub$Proxy:zzoz	Landroid/os/IBinder;
        //   33: sipush 12014
        //   36: aload_2
        //   37: aload_3
        //   38: iconst_0
        //   39: invokeinterface 46 5 0
        //   44: pop
        //   45: aload_3
        //   46: invokevirtual 49	android/os/Parcel:readException	()V
        //   49: aload_3
        //   50: invokevirtual 52	android/os/Parcel:recycle	()V
        //   53: aload_2
        //   54: invokevirtual 52	android/os/Parcel:recycle	()V
        //   57: return
        //   58: aload_2
        //   59: iconst_0
        //   60: invokevirtual 59	android/os/Parcel:writeInt	(I)V
        //   63: goto -34 -> 29
        //   66: astore_1
        //   67: aload_3
        //   68: invokevirtual 52	android/os/Parcel:recycle	()V
        //   71: aload_2
        //   72: invokevirtual 52	android/os/Parcel:recycle	()V
        //   75: aload_1
        //   76: athrow
        // Local variable table:
        //   start	length	slot	name	signature
        //   0	77	0	this	Proxy
        //   0	77	1	paramDataHolder	DataHolder
        //   3	69	2	localParcel1	Parcel
        //   7	61	3	localParcel2	Parcel
        // Exception table:
        //   from	to	target	type
        //   8	14	66	finally
        //   18	29	66	finally
        //   29	49	66	finally
        //   58	63	66	finally
      }
      
      /* Error */
      public void zzS(DataHolder paramDataHolder)
        throws RemoteException
      {
        // Byte code:
        //   0: invokestatic 32	android/os/Parcel:obtain	()Landroid/os/Parcel;
        //   3: astore_2
        //   4: invokestatic 32	android/os/Parcel:obtain	()Landroid/os/Parcel;
        //   7: astore_3
        //   8: aload_2
        //   9: ldc 34
        //   11: invokevirtual 37	android/os/Parcel:writeInterfaceToken	(Ljava/lang/String;)V
        //   14: aload_1
        //   15: ifnull +43 -> 58
        //   18: aload_2
        //   19: iconst_1
        //   20: invokevirtual 59	android/os/Parcel:writeInt	(I)V
        //   23: aload_1
        //   24: aload_2
        //   25: iconst_0
        //   26: invokevirtual 76	com/google/android/gms/common/data/DataHolder:writeToParcel	(Landroid/os/Parcel;I)V
        //   29: aload_0
        //   30: getfield 19	com/google/android/gms/games/internal/IGamesCallbacks$Stub$Proxy:zzoz	Landroid/os/IBinder;
        //   33: sipush 12016
        //   36: aload_2
        //   37: aload_3
        //   38: iconst_0
        //   39: invokeinterface 46 5 0
        //   44: pop
        //   45: aload_3
        //   46: invokevirtual 49	android/os/Parcel:readException	()V
        //   49: aload_3
        //   50: invokevirtual 52	android/os/Parcel:recycle	()V
        //   53: aload_2
        //   54: invokevirtual 52	android/os/Parcel:recycle	()V
        //   57: return
        //   58: aload_2
        //   59: iconst_0
        //   60: invokevirtual 59	android/os/Parcel:writeInt	(I)V
        //   63: goto -34 -> 29
        //   66: astore_1
        //   67: aload_3
        //   68: invokevirtual 52	android/os/Parcel:recycle	()V
        //   71: aload_2
        //   72: invokevirtual 52	android/os/Parcel:recycle	()V
        //   75: aload_1
        //   76: athrow
        // Local variable table:
        //   start	length	slot	name	signature
        //   0	77	0	this	Proxy
        //   0	77	1	paramDataHolder	DataHolder
        //   3	69	2	localParcel1	Parcel
        //   7	61	3	localParcel2	Parcel
        // Exception table:
        //   from	to	target	type
        //   8	14	66	finally
        //   18	29	66	finally
        //   29	49	66	finally
        //   58	63	66	finally
      }
      
      /* Error */
      public void zzT(DataHolder paramDataHolder)
        throws RemoteException
      {
        // Byte code:
        //   0: invokestatic 32	android/os/Parcel:obtain	()Landroid/os/Parcel;
        //   3: astore_2
        //   4: invokestatic 32	android/os/Parcel:obtain	()Landroid/os/Parcel;
        //   7: astore_3
        //   8: aload_2
        //   9: ldc 34
        //   11: invokevirtual 37	android/os/Parcel:writeInterfaceToken	(Ljava/lang/String;)V
        //   14: aload_1
        //   15: ifnull +43 -> 58
        //   18: aload_2
        //   19: iconst_1
        //   20: invokevirtual 59	android/os/Parcel:writeInt	(I)V
        //   23: aload_1
        //   24: aload_2
        //   25: iconst_0
        //   26: invokevirtual 76	com/google/android/gms/common/data/DataHolder:writeToParcel	(Landroid/os/Parcel;I)V
        //   29: aload_0
        //   30: getfield 19	com/google/android/gms/games/internal/IGamesCallbacks$Stub$Proxy:zzoz	Landroid/os/IBinder;
        //   33: sipush 12008
        //   36: aload_2
        //   37: aload_3
        //   38: iconst_0
        //   39: invokeinterface 46 5 0
        //   44: pop
        //   45: aload_3
        //   46: invokevirtual 49	android/os/Parcel:readException	()V
        //   49: aload_3
        //   50: invokevirtual 52	android/os/Parcel:recycle	()V
        //   53: aload_2
        //   54: invokevirtual 52	android/os/Parcel:recycle	()V
        //   57: return
        //   58: aload_2
        //   59: iconst_0
        //   60: invokevirtual 59	android/os/Parcel:writeInt	(I)V
        //   63: goto -34 -> 29
        //   66: astore_1
        //   67: aload_3
        //   68: invokevirtual 52	android/os/Parcel:recycle	()V
        //   71: aload_2
        //   72: invokevirtual 52	android/os/Parcel:recycle	()V
        //   75: aload_1
        //   76: athrow
        // Local variable table:
        //   start	length	slot	name	signature
        //   0	77	0	this	Proxy
        //   0	77	1	paramDataHolder	DataHolder
        //   3	69	2	localParcel1	Parcel
        //   7	61	3	localParcel2	Parcel
        // Exception table:
        //   from	to	target	type
        //   8	14	66	finally
        //   18	29	66	finally
        //   29	49	66	finally
        //   58	63	66	finally
      }
      
      /* Error */
      public void zzU(DataHolder paramDataHolder)
        throws RemoteException
      {
        // Byte code:
        //   0: invokestatic 32	android/os/Parcel:obtain	()Landroid/os/Parcel;
        //   3: astore_2
        //   4: invokestatic 32	android/os/Parcel:obtain	()Landroid/os/Parcel;
        //   7: astore_3
        //   8: aload_2
        //   9: ldc 34
        //   11: invokevirtual 37	android/os/Parcel:writeInterfaceToken	(Ljava/lang/String;)V
        //   14: aload_1
        //   15: ifnull +43 -> 58
        //   18: aload_2
        //   19: iconst_1
        //   20: invokevirtual 59	android/os/Parcel:writeInt	(I)V
        //   23: aload_1
        //   24: aload_2
        //   25: iconst_0
        //   26: invokevirtual 76	com/google/android/gms/common/data/DataHolder:writeToParcel	(Landroid/os/Parcel;I)V
        //   29: aload_0
        //   30: getfield 19	com/google/android/gms/games/internal/IGamesCallbacks$Stub$Proxy:zzoz	Landroid/os/IBinder;
        //   33: sipush 12013
        //   36: aload_2
        //   37: aload_3
        //   38: iconst_0
        //   39: invokeinterface 46 5 0
        //   44: pop
        //   45: aload_3
        //   46: invokevirtual 49	android/os/Parcel:readException	()V
        //   49: aload_3
        //   50: invokevirtual 52	android/os/Parcel:recycle	()V
        //   53: aload_2
        //   54: invokevirtual 52	android/os/Parcel:recycle	()V
        //   57: return
        //   58: aload_2
        //   59: iconst_0
        //   60: invokevirtual 59	android/os/Parcel:writeInt	(I)V
        //   63: goto -34 -> 29
        //   66: astore_1
        //   67: aload_3
        //   68: invokevirtual 52	android/os/Parcel:recycle	()V
        //   71: aload_2
        //   72: invokevirtual 52	android/os/Parcel:recycle	()V
        //   75: aload_1
        //   76: athrow
        // Local variable table:
        //   start	length	slot	name	signature
        //   0	77	0	this	Proxy
        //   0	77	1	paramDataHolder	DataHolder
        //   3	69	2	localParcel1	Parcel
        //   7	61	3	localParcel2	Parcel
        // Exception table:
        //   from	to	target	type
        //   8	14	66	finally
        //   18	29	66	finally
        //   29	49	66	finally
        //   58	63	66	finally
      }
      
      /* Error */
      public void zzV(DataHolder paramDataHolder)
        throws RemoteException
      {
        // Byte code:
        //   0: invokestatic 32	android/os/Parcel:obtain	()Landroid/os/Parcel;
        //   3: astore_2
        //   4: invokestatic 32	android/os/Parcel:obtain	()Landroid/os/Parcel;
        //   7: astore_3
        //   8: aload_2
        //   9: ldc 34
        //   11: invokevirtual 37	android/os/Parcel:writeInterfaceToken	(Ljava/lang/String;)V
        //   14: aload_1
        //   15: ifnull +43 -> 58
        //   18: aload_2
        //   19: iconst_1
        //   20: invokevirtual 59	android/os/Parcel:writeInt	(I)V
        //   23: aload_1
        //   24: aload_2
        //   25: iconst_0
        //   26: invokevirtual 76	com/google/android/gms/common/data/DataHolder:writeToParcel	(Landroid/os/Parcel;I)V
        //   29: aload_0
        //   30: getfield 19	com/google/android/gms/games/internal/IGamesCallbacks$Stub$Proxy:zzoz	Landroid/os/IBinder;
        //   33: sipush 13001
        //   36: aload_2
        //   37: aload_3
        //   38: iconst_0
        //   39: invokeinterface 46 5 0
        //   44: pop
        //   45: aload_3
        //   46: invokevirtual 49	android/os/Parcel:readException	()V
        //   49: aload_3
        //   50: invokevirtual 52	android/os/Parcel:recycle	()V
        //   53: aload_2
        //   54: invokevirtual 52	android/os/Parcel:recycle	()V
        //   57: return
        //   58: aload_2
        //   59: iconst_0
        //   60: invokevirtual 59	android/os/Parcel:writeInt	(I)V
        //   63: goto -34 -> 29
        //   66: astore_1
        //   67: aload_3
        //   68: invokevirtual 52	android/os/Parcel:recycle	()V
        //   71: aload_2
        //   72: invokevirtual 52	android/os/Parcel:recycle	()V
        //   75: aload_1
        //   76: athrow
        // Local variable table:
        //   start	length	slot	name	signature
        //   0	77	0	this	Proxy
        //   0	77	1	paramDataHolder	DataHolder
        //   3	69	2	localParcel1	Parcel
        //   7	61	3	localParcel2	Parcel
        // Exception table:
        //   from	to	target	type
        //   8	14	66	finally
        //   18	29	66	finally
        //   29	49	66	finally
        //   58	63	66	finally
      }
      
      /* Error */
      public void zzW(DataHolder paramDataHolder)
        throws RemoteException
      {
        // Byte code:
        //   0: invokestatic 32	android/os/Parcel:obtain	()Landroid/os/Parcel;
        //   3: astore_2
        //   4: invokestatic 32	android/os/Parcel:obtain	()Landroid/os/Parcel;
        //   7: astore_3
        //   8: aload_2
        //   9: ldc 34
        //   11: invokevirtual 37	android/os/Parcel:writeInterfaceToken	(Ljava/lang/String;)V
        //   14: aload_1
        //   15: ifnull +43 -> 58
        //   18: aload_2
        //   19: iconst_1
        //   20: invokevirtual 59	android/os/Parcel:writeInt	(I)V
        //   23: aload_1
        //   24: aload_2
        //   25: iconst_0
        //   26: invokevirtual 76	com/google/android/gms/common/data/DataHolder:writeToParcel	(Landroid/os/Parcel;I)V
        //   29: aload_0
        //   30: getfield 19	com/google/android/gms/games/internal/IGamesCallbacks$Stub$Proxy:zzoz	Landroid/os/IBinder;
        //   33: sipush 15001
        //   36: aload_2
        //   37: aload_3
        //   38: iconst_0
        //   39: invokeinterface 46 5 0
        //   44: pop
        //   45: aload_3
        //   46: invokevirtual 49	android/os/Parcel:readException	()V
        //   49: aload_3
        //   50: invokevirtual 52	android/os/Parcel:recycle	()V
        //   53: aload_2
        //   54: invokevirtual 52	android/os/Parcel:recycle	()V
        //   57: return
        //   58: aload_2
        //   59: iconst_0
        //   60: invokevirtual 59	android/os/Parcel:writeInt	(I)V
        //   63: goto -34 -> 29
        //   66: astore_1
        //   67: aload_3
        //   68: invokevirtual 52	android/os/Parcel:recycle	()V
        //   71: aload_2
        //   72: invokevirtual 52	android/os/Parcel:recycle	()V
        //   75: aload_1
        //   76: athrow
        // Local variable table:
        //   start	length	slot	name	signature
        //   0	77	0	this	Proxy
        //   0	77	1	paramDataHolder	DataHolder
        //   3	69	2	localParcel1	Parcel
        //   7	61	3	localParcel2	Parcel
        // Exception table:
        //   from	to	target	type
        //   8	14	66	finally
        //   18	29	66	finally
        //   29	49	66	finally
        //   58	63	66	finally
      }
      
      /* Error */
      public void zzX(DataHolder paramDataHolder)
        throws RemoteException
      {
        // Byte code:
        //   0: invokestatic 32	android/os/Parcel:obtain	()Landroid/os/Parcel;
        //   3: astore_2
        //   4: invokestatic 32	android/os/Parcel:obtain	()Landroid/os/Parcel;
        //   7: astore_3
        //   8: aload_2
        //   9: ldc 34
        //   11: invokevirtual 37	android/os/Parcel:writeInterfaceToken	(Ljava/lang/String;)V
        //   14: aload_1
        //   15: ifnull +43 -> 58
        //   18: aload_2
        //   19: iconst_1
        //   20: invokevirtual 59	android/os/Parcel:writeInt	(I)V
        //   23: aload_1
        //   24: aload_2
        //   25: iconst_0
        //   26: invokevirtual 76	com/google/android/gms/common/data/DataHolder:writeToParcel	(Landroid/os/Parcel;I)V
        //   29: aload_0
        //   30: getfield 19	com/google/android/gms/games/internal/IGamesCallbacks$Stub$Proxy:zzoz	Landroid/os/IBinder;
        //   33: sipush 17001
        //   36: aload_2
        //   37: aload_3
        //   38: iconst_0
        //   39: invokeinterface 46 5 0
        //   44: pop
        //   45: aload_3
        //   46: invokevirtual 49	android/os/Parcel:readException	()V
        //   49: aload_3
        //   50: invokevirtual 52	android/os/Parcel:recycle	()V
        //   53: aload_2
        //   54: invokevirtual 52	android/os/Parcel:recycle	()V
        //   57: return
        //   58: aload_2
        //   59: iconst_0
        //   60: invokevirtual 59	android/os/Parcel:writeInt	(I)V
        //   63: goto -34 -> 29
        //   66: astore_1
        //   67: aload_3
        //   68: invokevirtual 52	android/os/Parcel:recycle	()V
        //   71: aload_2
        //   72: invokevirtual 52	android/os/Parcel:recycle	()V
        //   75: aload_1
        //   76: athrow
        // Local variable table:
        //   start	length	slot	name	signature
        //   0	77	0	this	Proxy
        //   0	77	1	paramDataHolder	DataHolder
        //   3	69	2	localParcel1	Parcel
        //   7	61	3	localParcel2	Parcel
        // Exception table:
        //   from	to	target	type
        //   8	14	66	finally
        //   18	29	66	finally
        //   29	49	66	finally
        //   58	63	66	finally
      }
      
      /* Error */
      public void zza(int paramInt, VideoCapabilities paramVideoCapabilities)
        throws RemoteException
      {
        // Byte code:
        //   0: invokestatic 32	android/os/Parcel:obtain	()Landroid/os/Parcel;
        //   3: astore_3
        //   4: invokestatic 32	android/os/Parcel:obtain	()Landroid/os/Parcel;
        //   7: astore 4
        //   9: aload_3
        //   10: ldc 34
        //   12: invokevirtual 37	android/os/Parcel:writeInterfaceToken	(Ljava/lang/String;)V
        //   15: aload_3
        //   16: iload_1
        //   17: invokevirtual 59	android/os/Parcel:writeInt	(I)V
        //   20: aload_2
        //   21: ifnull +46 -> 67
        //   24: aload_3
        //   25: iconst_1
        //   26: invokevirtual 59	android/os/Parcel:writeInt	(I)V
        //   29: aload_2
        //   30: aload_3
        //   31: iconst_0
        //   32: invokevirtual 104	com/google/android/gms/games/video/VideoCapabilities:writeToParcel	(Landroid/os/Parcel;I)V
        //   35: aload_0
        //   36: getfield 19	com/google/android/gms/games/internal/IGamesCallbacks$Stub$Proxy:zzoz	Landroid/os/IBinder;
        //   39: sipush 19001
        //   42: aload_3
        //   43: aload 4
        //   45: iconst_0
        //   46: invokeinterface 46 5 0
        //   51: pop
        //   52: aload 4
        //   54: invokevirtual 49	android/os/Parcel:readException	()V
        //   57: aload 4
        //   59: invokevirtual 52	android/os/Parcel:recycle	()V
        //   62: aload_3
        //   63: invokevirtual 52	android/os/Parcel:recycle	()V
        //   66: return
        //   67: aload_3
        //   68: iconst_0
        //   69: invokevirtual 59	android/os/Parcel:writeInt	(I)V
        //   72: goto -37 -> 35
        //   75: astore_2
        //   76: aload 4
        //   78: invokevirtual 52	android/os/Parcel:recycle	()V
        //   81: aload_3
        //   82: invokevirtual 52	android/os/Parcel:recycle	()V
        //   85: aload_2
        //   86: athrow
        // Local variable table:
        //   start	length	slot	name	signature
        //   0	87	0	this	Proxy
        //   0	87	1	paramInt	int
        //   0	87	2	paramVideoCapabilities	VideoCapabilities
        //   3	79	3	localParcel1	Parcel
        //   7	70	4	localParcel2	Parcel
        // Exception table:
        //   from	to	target	type
        //   9	20	75	finally
        //   24	35	75	finally
        //   35	57	75	finally
        //   67	72	75	finally
      }
      
      public void zza(int paramInt, String paramString, boolean paramBoolean)
        throws RemoteException
      {
        int i = 0;
        Parcel localParcel1 = Parcel.obtain();
        Parcel localParcel2 = Parcel.obtain();
        try
        {
          localParcel1.writeInterfaceToken("com.google.android.gms.games.internal.IGamesCallbacks");
          localParcel1.writeInt(paramInt);
          localParcel1.writeString(paramString);
          paramInt = i;
          if (paramBoolean) {
            paramInt = 1;
          }
          localParcel1.writeInt(paramInt);
          this.zzoz.transact(5034, localParcel1, localParcel2, 0);
          localParcel2.readException();
          return;
        }
        finally
        {
          localParcel2.recycle();
          localParcel1.recycle();
        }
      }
      
      public void zza(int paramInt, long[] paramArrayOfLong)
        throws RemoteException
      {
        Parcel localParcel1 = Parcel.obtain();
        Parcel localParcel2 = Parcel.obtain();
        try
        {
          localParcel1.writeInterfaceToken("com.google.android.gms.games.internal.IGamesCallbacks");
          localParcel1.writeInt(paramInt);
          localParcel1.writeLongArray(paramArrayOfLong);
          this.zzoz.transact(19003, localParcel1, localParcel2, 0);
          localParcel2.readException();
          return;
        }
        finally
        {
          localParcel2.recycle();
          localParcel1.recycle();
        }
      }
      
      public void zza(DataHolder paramDataHolder1, DataHolder paramDataHolder2)
        throws RemoteException
      {
        Parcel localParcel1 = Parcel.obtain();
        Parcel localParcel2 = Parcel.obtain();
        for (;;)
        {
          try
          {
            localParcel1.writeInterfaceToken("com.google.android.gms.games.internal.IGamesCallbacks");
            if (paramDataHolder1 != null)
            {
              localParcel1.writeInt(1);
              paramDataHolder1.writeToParcel(localParcel1, 0);
              if (paramDataHolder2 != null)
              {
                localParcel1.writeInt(1);
                paramDataHolder2.writeToParcel(localParcel1, 0);
                this.zzoz.transact(5005, localParcel1, localParcel2, 0);
                localParcel2.readException();
              }
            }
            else
            {
              localParcel1.writeInt(0);
              continue;
            }
            localParcel1.writeInt(0);
          }
          finally
          {
            localParcel2.recycle();
            localParcel1.recycle();
          }
        }
      }
      
      public void zza(DataHolder paramDataHolder, Contents paramContents)
        throws RemoteException
      {
        Parcel localParcel1 = Parcel.obtain();
        Parcel localParcel2 = Parcel.obtain();
        for (;;)
        {
          try
          {
            localParcel1.writeInterfaceToken("com.google.android.gms.games.internal.IGamesCallbacks");
            if (paramDataHolder != null)
            {
              localParcel1.writeInt(1);
              paramDataHolder.writeToParcel(localParcel1, 0);
              if (paramContents != null)
              {
                localParcel1.writeInt(1);
                paramContents.writeToParcel(localParcel1, 0);
                this.zzoz.transact(12004, localParcel1, localParcel2, 0);
                localParcel2.readException();
              }
            }
            else
            {
              localParcel1.writeInt(0);
              continue;
            }
            localParcel1.writeInt(0);
          }
          finally
          {
            localParcel2.recycle();
            localParcel1.recycle();
          }
        }
      }
      
      public void zza(DataHolder paramDataHolder, String paramString, Contents paramContents1, Contents paramContents2, Contents paramContents3)
        throws RemoteException
      {
        Parcel localParcel1 = Parcel.obtain();
        Parcel localParcel2 = Parcel.obtain();
        for (;;)
        {
          try
          {
            localParcel1.writeInterfaceToken("com.google.android.gms.games.internal.IGamesCallbacks");
            if (paramDataHolder != null)
            {
              localParcel1.writeInt(1);
              paramDataHolder.writeToParcel(localParcel1, 0);
              localParcel1.writeString(paramString);
              if (paramContents1 != null)
              {
                localParcel1.writeInt(1);
                paramContents1.writeToParcel(localParcel1, 0);
                if (paramContents2 == null) {
                  break label160;
                }
                localParcel1.writeInt(1);
                paramContents2.writeToParcel(localParcel1, 0);
                if (paramContents3 == null) {
                  break label169;
                }
                localParcel1.writeInt(1);
                paramContents3.writeToParcel(localParcel1, 0);
                this.zzoz.transact(12017, localParcel1, localParcel2, 0);
                localParcel2.readException();
              }
            }
            else
            {
              localParcel1.writeInt(0);
              continue;
            }
            localParcel1.writeInt(0);
          }
          finally
          {
            localParcel2.recycle();
            localParcel1.recycle();
          }
          continue;
          label160:
          localParcel1.writeInt(0);
          continue;
          label169:
          localParcel1.writeInt(0);
        }
      }
      
      /* Error */
      public void zza(DataHolder paramDataHolder, String[] paramArrayOfString)
        throws RemoteException
      {
        // Byte code:
        //   0: invokestatic 32	android/os/Parcel:obtain	()Landroid/os/Parcel;
        //   3: astore_3
        //   4: invokestatic 32	android/os/Parcel:obtain	()Landroid/os/Parcel;
        //   7: astore 4
        //   9: aload_3
        //   10: ldc 34
        //   12: invokevirtual 37	android/os/Parcel:writeInterfaceToken	(Ljava/lang/String;)V
        //   15: aload_1
        //   16: ifnull +51 -> 67
        //   19: aload_3
        //   20: iconst_1
        //   21: invokevirtual 59	android/os/Parcel:writeInt	(I)V
        //   24: aload_1
        //   25: aload_3
        //   26: iconst_0
        //   27: invokevirtual 76	com/google/android/gms/common/data/DataHolder:writeToParcel	(Landroid/os/Parcel;I)V
        //   30: aload_3
        //   31: aload_2
        //   32: invokevirtual 121	android/os/Parcel:writeStringArray	([Ljava/lang/String;)V
        //   35: aload_0
        //   36: getfield 19	com/google/android/gms/games/internal/IGamesCallbacks$Stub$Proxy:zzoz	Landroid/os/IBinder;
        //   39: sipush 5026
        //   42: aload_3
        //   43: aload 4
        //   45: iconst_0
        //   46: invokeinterface 46 5 0
        //   51: pop
        //   52: aload 4
        //   54: invokevirtual 49	android/os/Parcel:readException	()V
        //   57: aload 4
        //   59: invokevirtual 52	android/os/Parcel:recycle	()V
        //   62: aload_3
        //   63: invokevirtual 52	android/os/Parcel:recycle	()V
        //   66: return
        //   67: aload_3
        //   68: iconst_0
        //   69: invokevirtual 59	android/os/Parcel:writeInt	(I)V
        //   72: goto -42 -> 30
        //   75: astore_1
        //   76: aload 4
        //   78: invokevirtual 52	android/os/Parcel:recycle	()V
        //   81: aload_3
        //   82: invokevirtual 52	android/os/Parcel:recycle	()V
        //   85: aload_1
        //   86: athrow
        // Local variable table:
        //   start	length	slot	name	signature
        //   0	87	0	this	Proxy
        //   0	87	1	paramDataHolder	DataHolder
        //   0	87	2	paramArrayOfString	String[]
        //   3	79	3	localParcel1	Parcel
        //   7	70	4	localParcel2	Parcel
        // Exception table:
        //   from	to	target	type
        //   9	15	75	finally
        //   19	30	75	finally
        //   30	57	75	finally
        //   67	72	75	finally
      }
      
      public void zza(DataHolder[] paramArrayOfDataHolder)
        throws RemoteException
      {
        Parcel localParcel1 = Parcel.obtain();
        Parcel localParcel2 = Parcel.obtain();
        try
        {
          localParcel1.writeInterfaceToken("com.google.android.gms.games.internal.IGamesCallbacks");
          localParcel1.writeTypedArray(paramArrayOfDataHolder, 0);
          this.zzoz.transact(14001, localParcel1, localParcel2, 0);
          localParcel2.readException();
          return;
        }
        finally
        {
          localParcel2.recycle();
          localParcel1.recycle();
        }
      }
      
      public void zzb(int paramInt1, int paramInt2, String paramString)
        throws RemoteException
      {
        Parcel localParcel1 = Parcel.obtain();
        Parcel localParcel2 = Parcel.obtain();
        try
        {
          localParcel1.writeInterfaceToken("com.google.android.gms.games.internal.IGamesCallbacks");
          localParcel1.writeInt(paramInt1);
          localParcel1.writeInt(paramInt2);
          localParcel1.writeString(paramString);
          this.zzoz.transact(5033, localParcel1, localParcel2, 0);
          localParcel2.readException();
          return;
        }
        finally
        {
          localParcel2.recycle();
          localParcel1.recycle();
        }
      }
      
      /* Error */
      public void zzb(DataHolder paramDataHolder, String[] paramArrayOfString)
        throws RemoteException
      {
        // Byte code:
        //   0: invokestatic 32	android/os/Parcel:obtain	()Landroid/os/Parcel;
        //   3: astore_3
        //   4: invokestatic 32	android/os/Parcel:obtain	()Landroid/os/Parcel;
        //   7: astore 4
        //   9: aload_3
        //   10: ldc 34
        //   12: invokevirtual 37	android/os/Parcel:writeInterfaceToken	(Ljava/lang/String;)V
        //   15: aload_1
        //   16: ifnull +51 -> 67
        //   19: aload_3
        //   20: iconst_1
        //   21: invokevirtual 59	android/os/Parcel:writeInt	(I)V
        //   24: aload_1
        //   25: aload_3
        //   26: iconst_0
        //   27: invokevirtual 76	com/google/android/gms/common/data/DataHolder:writeToParcel	(Landroid/os/Parcel;I)V
        //   30: aload_3
        //   31: aload_2
        //   32: invokevirtual 121	android/os/Parcel:writeStringArray	([Ljava/lang/String;)V
        //   35: aload_0
        //   36: getfield 19	com/google/android/gms/games/internal/IGamesCallbacks$Stub$Proxy:zzoz	Landroid/os/IBinder;
        //   39: sipush 5027
        //   42: aload_3
        //   43: aload 4
        //   45: iconst_0
        //   46: invokeinterface 46 5 0
        //   51: pop
        //   52: aload 4
        //   54: invokevirtual 49	android/os/Parcel:readException	()V
        //   57: aload 4
        //   59: invokevirtual 52	android/os/Parcel:recycle	()V
        //   62: aload_3
        //   63: invokevirtual 52	android/os/Parcel:recycle	()V
        //   66: return
        //   67: aload_3
        //   68: iconst_0
        //   69: invokevirtual 59	android/os/Parcel:writeInt	(I)V
        //   72: goto -42 -> 30
        //   75: astore_1
        //   76: aload 4
        //   78: invokevirtual 52	android/os/Parcel:recycle	()V
        //   81: aload_3
        //   82: invokevirtual 52	android/os/Parcel:recycle	()V
        //   85: aload_1
        //   86: athrow
        // Local variable table:
        //   start	length	slot	name	signature
        //   0	87	0	this	Proxy
        //   0	87	1	paramDataHolder	DataHolder
        //   0	87	2	paramArrayOfString	String[]
        //   3	79	3	localParcel1	Parcel
        //   7	70	4	localParcel2	Parcel
        // Exception table:
        //   from	to	target	type
        //   9	15	75	finally
        //   19	30	75	finally
        //   30	57	75	finally
        //   67	72	75	finally
      }
      
      /* Error */
      public void zzc(int paramInt, Bundle paramBundle)
        throws RemoteException
      {
        // Byte code:
        //   0: invokestatic 32	android/os/Parcel:obtain	()Landroid/os/Parcel;
        //   3: astore_3
        //   4: invokestatic 32	android/os/Parcel:obtain	()Landroid/os/Parcel;
        //   7: astore 4
        //   9: aload_3
        //   10: ldc 34
        //   12: invokevirtual 37	android/os/Parcel:writeInterfaceToken	(Ljava/lang/String;)V
        //   15: aload_3
        //   16: iload_1
        //   17: invokevirtual 59	android/os/Parcel:writeInt	(I)V
        //   20: aload_2
        //   21: ifnull +46 -> 67
        //   24: aload_3
        //   25: iconst_1
        //   26: invokevirtual 59	android/os/Parcel:writeInt	(I)V
        //   29: aload_2
        //   30: aload_3
        //   31: iconst_0
        //   32: invokevirtual 133	android/os/Bundle:writeToParcel	(Landroid/os/Parcel;I)V
        //   35: aload_0
        //   36: getfield 19	com/google/android/gms/games/internal/IGamesCallbacks$Stub$Proxy:zzoz	Landroid/os/IBinder;
        //   39: sipush 8002
        //   42: aload_3
        //   43: aload 4
        //   45: iconst_0
        //   46: invokeinterface 46 5 0
        //   51: pop
        //   52: aload 4
        //   54: invokevirtual 49	android/os/Parcel:readException	()V
        //   57: aload 4
        //   59: invokevirtual 52	android/os/Parcel:recycle	()V
        //   62: aload_3
        //   63: invokevirtual 52	android/os/Parcel:recycle	()V
        //   66: return
        //   67: aload_3
        //   68: iconst_0
        //   69: invokevirtual 59	android/os/Parcel:writeInt	(I)V
        //   72: goto -37 -> 35
        //   75: astore_2
        //   76: aload 4
        //   78: invokevirtual 52	android/os/Parcel:recycle	()V
        //   81: aload_3
        //   82: invokevirtual 52	android/os/Parcel:recycle	()V
        //   85: aload_2
        //   86: athrow
        // Local variable table:
        //   start	length	slot	name	signature
        //   0	87	0	this	Proxy
        //   0	87	1	paramInt	int
        //   0	87	2	paramBundle	Bundle
        //   3	79	3	localParcel1	Parcel
        //   7	70	4	localParcel2	Parcel
        // Exception table:
        //   from	to	target	type
        //   9	20	75	finally
        //   24	35	75	finally
        //   35	57	75	finally
        //   67	72	75	finally
      }
      
      /* Error */
      public void zzc(DataHolder paramDataHolder, String[] paramArrayOfString)
        throws RemoteException
      {
        // Byte code:
        //   0: invokestatic 32	android/os/Parcel:obtain	()Landroid/os/Parcel;
        //   3: astore_3
        //   4: invokestatic 32	android/os/Parcel:obtain	()Landroid/os/Parcel;
        //   7: astore 4
        //   9: aload_3
        //   10: ldc 34
        //   12: invokevirtual 37	android/os/Parcel:writeInterfaceToken	(Ljava/lang/String;)V
        //   15: aload_1
        //   16: ifnull +51 -> 67
        //   19: aload_3
        //   20: iconst_1
        //   21: invokevirtual 59	android/os/Parcel:writeInt	(I)V
        //   24: aload_1
        //   25: aload_3
        //   26: iconst_0
        //   27: invokevirtual 76	com/google/android/gms/common/data/DataHolder:writeToParcel	(Landroid/os/Parcel;I)V
        //   30: aload_3
        //   31: aload_2
        //   32: invokevirtual 121	android/os/Parcel:writeStringArray	([Ljava/lang/String;)V
        //   35: aload_0
        //   36: getfield 19	com/google/android/gms/games/internal/IGamesCallbacks$Stub$Proxy:zzoz	Landroid/os/IBinder;
        //   39: sipush 5028
        //   42: aload_3
        //   43: aload 4
        //   45: iconst_0
        //   46: invokeinterface 46 5 0
        //   51: pop
        //   52: aload 4
        //   54: invokevirtual 49	android/os/Parcel:readException	()V
        //   57: aload 4
        //   59: invokevirtual 52	android/os/Parcel:recycle	()V
        //   62: aload_3
        //   63: invokevirtual 52	android/os/Parcel:recycle	()V
        //   66: return
        //   67: aload_3
        //   68: iconst_0
        //   69: invokevirtual 59	android/os/Parcel:writeInt	(I)V
        //   72: goto -42 -> 30
        //   75: astore_1
        //   76: aload 4
        //   78: invokevirtual 52	android/os/Parcel:recycle	()V
        //   81: aload_3
        //   82: invokevirtual 52	android/os/Parcel:recycle	()V
        //   85: aload_1
        //   86: athrow
        // Local variable table:
        //   start	length	slot	name	signature
        //   0	87	0	this	Proxy
        //   0	87	1	paramDataHolder	DataHolder
        //   0	87	2	paramArrayOfString	String[]
        //   3	79	3	localParcel1	Parcel
        //   7	70	4	localParcel2	Parcel
        // Exception table:
        //   from	to	target	type
        //   9	15	75	finally
        //   19	30	75	finally
        //   30	57	75	finally
        //   67	72	75	finally
      }
      
      /* Error */
      public void zzd(int paramInt, Bundle paramBundle)
        throws RemoteException
      {
        // Byte code:
        //   0: invokestatic 32	android/os/Parcel:obtain	()Landroid/os/Parcel;
        //   3: astore_3
        //   4: invokestatic 32	android/os/Parcel:obtain	()Landroid/os/Parcel;
        //   7: astore 4
        //   9: aload_3
        //   10: ldc 34
        //   12: invokevirtual 37	android/os/Parcel:writeInterfaceToken	(Ljava/lang/String;)V
        //   15: aload_3
        //   16: iload_1
        //   17: invokevirtual 59	android/os/Parcel:writeInt	(I)V
        //   20: aload_2
        //   21: ifnull +46 -> 67
        //   24: aload_3
        //   25: iconst_1
        //   26: invokevirtual 59	android/os/Parcel:writeInt	(I)V
        //   29: aload_2
        //   30: aload_3
        //   31: iconst_0
        //   32: invokevirtual 133	android/os/Bundle:writeToParcel	(Landroid/os/Parcel;I)V
        //   35: aload_0
        //   36: getfield 19	com/google/android/gms/games/internal/IGamesCallbacks$Stub$Proxy:zzoz	Landroid/os/IBinder;
        //   39: sipush 10005
        //   42: aload_3
        //   43: aload 4
        //   45: iconst_0
        //   46: invokeinterface 46 5 0
        //   51: pop
        //   52: aload 4
        //   54: invokevirtual 49	android/os/Parcel:readException	()V
        //   57: aload 4
        //   59: invokevirtual 52	android/os/Parcel:recycle	()V
        //   62: aload_3
        //   63: invokevirtual 52	android/os/Parcel:recycle	()V
        //   66: return
        //   67: aload_3
        //   68: iconst_0
        //   69: invokevirtual 59	android/os/Parcel:writeInt	(I)V
        //   72: goto -37 -> 35
        //   75: astore_2
        //   76: aload 4
        //   78: invokevirtual 52	android/os/Parcel:recycle	()V
        //   81: aload_3
        //   82: invokevirtual 52	android/os/Parcel:recycle	()V
        //   85: aload_2
        //   86: athrow
        // Local variable table:
        //   start	length	slot	name	signature
        //   0	87	0	this	Proxy
        //   0	87	1	paramInt	int
        //   0	87	2	paramBundle	Bundle
        //   3	79	3	localParcel1	Parcel
        //   7	70	4	localParcel2	Parcel
        // Exception table:
        //   from	to	target	type
        //   9	20	75	finally
        //   24	35	75	finally
        //   35	57	75	finally
        //   67	72	75	finally
      }
      
      public void zzd(int paramInt, boolean paramBoolean)
        throws RemoteException
      {
        int i = 0;
        Parcel localParcel1 = Parcel.obtain();
        Parcel localParcel2 = Parcel.obtain();
        try
        {
          localParcel1.writeInterfaceToken("com.google.android.gms.games.internal.IGamesCallbacks");
          localParcel1.writeInt(paramInt);
          paramInt = i;
          if (paramBoolean) {
            paramInt = 1;
          }
          localParcel1.writeInt(paramInt);
          this.zzoz.transact(19002, localParcel1, localParcel2, 0);
          localParcel2.readException();
          return;
        }
        finally
        {
          localParcel2.recycle();
          localParcel1.recycle();
        }
      }
      
      /* Error */
      public void zzd(DataHolder paramDataHolder, String[] paramArrayOfString)
        throws RemoteException
      {
        // Byte code:
        //   0: invokestatic 32	android/os/Parcel:obtain	()Landroid/os/Parcel;
        //   3: astore_3
        //   4: invokestatic 32	android/os/Parcel:obtain	()Landroid/os/Parcel;
        //   7: astore 4
        //   9: aload_3
        //   10: ldc 34
        //   12: invokevirtual 37	android/os/Parcel:writeInterfaceToken	(Ljava/lang/String;)V
        //   15: aload_1
        //   16: ifnull +51 -> 67
        //   19: aload_3
        //   20: iconst_1
        //   21: invokevirtual 59	android/os/Parcel:writeInt	(I)V
        //   24: aload_1
        //   25: aload_3
        //   26: iconst_0
        //   27: invokevirtual 76	com/google/android/gms/common/data/DataHolder:writeToParcel	(Landroid/os/Parcel;I)V
        //   30: aload_3
        //   31: aload_2
        //   32: invokevirtual 121	android/os/Parcel:writeStringArray	([Ljava/lang/String;)V
        //   35: aload_0
        //   36: getfield 19	com/google/android/gms/games/internal/IGamesCallbacks$Stub$Proxy:zzoz	Landroid/os/IBinder;
        //   39: sipush 5029
        //   42: aload_3
        //   43: aload 4
        //   45: iconst_0
        //   46: invokeinterface 46 5 0
        //   51: pop
        //   52: aload 4
        //   54: invokevirtual 49	android/os/Parcel:readException	()V
        //   57: aload 4
        //   59: invokevirtual 52	android/os/Parcel:recycle	()V
        //   62: aload_3
        //   63: invokevirtual 52	android/os/Parcel:recycle	()V
        //   66: return
        //   67: aload_3
        //   68: iconst_0
        //   69: invokevirtual 59	android/os/Parcel:writeInt	(I)V
        //   72: goto -42 -> 30
        //   75: astore_1
        //   76: aload 4
        //   78: invokevirtual 52	android/os/Parcel:recycle	()V
        //   81: aload_3
        //   82: invokevirtual 52	android/os/Parcel:recycle	()V
        //   85: aload_1
        //   86: athrow
        // Local variable table:
        //   start	length	slot	name	signature
        //   0	87	0	this	Proxy
        //   0	87	1	paramDataHolder	DataHolder
        //   0	87	2	paramArrayOfString	String[]
        //   3	79	3	localParcel1	Parcel
        //   7	70	4	localParcel2	Parcel
        // Exception table:
        //   from	to	target	type
        //   9	15	75	finally
        //   19	30	75	finally
        //   30	57	75	finally
        //   67	72	75	finally
      }
      
      /* Error */
      public void zze(int paramInt, Bundle paramBundle)
        throws RemoteException
      {
        // Byte code:
        //   0: invokestatic 32	android/os/Parcel:obtain	()Landroid/os/Parcel;
        //   3: astore_3
        //   4: invokestatic 32	android/os/Parcel:obtain	()Landroid/os/Parcel;
        //   7: astore 4
        //   9: aload_3
        //   10: ldc 34
        //   12: invokevirtual 37	android/os/Parcel:writeInterfaceToken	(Ljava/lang/String;)V
        //   15: aload_3
        //   16: iload_1
        //   17: invokevirtual 59	android/os/Parcel:writeInt	(I)V
        //   20: aload_2
        //   21: ifnull +46 -> 67
        //   24: aload_3
        //   25: iconst_1
        //   26: invokevirtual 59	android/os/Parcel:writeInt	(I)V
        //   29: aload_2
        //   30: aload_3
        //   31: iconst_0
        //   32: invokevirtual 133	android/os/Bundle:writeToParcel	(Landroid/os/Parcel;I)V
        //   35: aload_0
        //   36: getfield 19	com/google/android/gms/games/internal/IGamesCallbacks$Stub$Proxy:zzoz	Landroid/os/IBinder;
        //   39: sipush 11001
        //   42: aload_3
        //   43: aload 4
        //   45: iconst_0
        //   46: invokeinterface 46 5 0
        //   51: pop
        //   52: aload 4
        //   54: invokevirtual 49	android/os/Parcel:readException	()V
        //   57: aload 4
        //   59: invokevirtual 52	android/os/Parcel:recycle	()V
        //   62: aload_3
        //   63: invokevirtual 52	android/os/Parcel:recycle	()V
        //   66: return
        //   67: aload_3
        //   68: iconst_0
        //   69: invokevirtual 59	android/os/Parcel:writeInt	(I)V
        //   72: goto -37 -> 35
        //   75: astore_2
        //   76: aload 4
        //   78: invokevirtual 52	android/os/Parcel:recycle	()V
        //   81: aload_3
        //   82: invokevirtual 52	android/os/Parcel:recycle	()V
        //   85: aload_2
        //   86: athrow
        // Local variable table:
        //   start	length	slot	name	signature
        //   0	87	0	this	Proxy
        //   0	87	1	paramInt	int
        //   0	87	2	paramBundle	Bundle
        //   3	79	3	localParcel1	Parcel
        //   7	70	4	localParcel2	Parcel
        // Exception table:
        //   from	to	target	type
        //   9	20	75	finally
        //   24	35	75	finally
        //   35	57	75	finally
        //   67	72	75	finally
      }
      
      /* Error */
      public void zze(DataHolder paramDataHolder, String[] paramArrayOfString)
        throws RemoteException
      {
        // Byte code:
        //   0: invokestatic 32	android/os/Parcel:obtain	()Landroid/os/Parcel;
        //   3: astore_3
        //   4: invokestatic 32	android/os/Parcel:obtain	()Landroid/os/Parcel;
        //   7: astore 4
        //   9: aload_3
        //   10: ldc 34
        //   12: invokevirtual 37	android/os/Parcel:writeInterfaceToken	(Ljava/lang/String;)V
        //   15: aload_1
        //   16: ifnull +51 -> 67
        //   19: aload_3
        //   20: iconst_1
        //   21: invokevirtual 59	android/os/Parcel:writeInt	(I)V
        //   24: aload_1
        //   25: aload_3
        //   26: iconst_0
        //   27: invokevirtual 76	com/google/android/gms/common/data/DataHolder:writeToParcel	(Landroid/os/Parcel;I)V
        //   30: aload_3
        //   31: aload_2
        //   32: invokevirtual 121	android/os/Parcel:writeStringArray	([Ljava/lang/String;)V
        //   35: aload_0
        //   36: getfield 19	com/google/android/gms/games/internal/IGamesCallbacks$Stub$Proxy:zzoz	Landroid/os/IBinder;
        //   39: sipush 5030
        //   42: aload_3
        //   43: aload 4
        //   45: iconst_0
        //   46: invokeinterface 46 5 0
        //   51: pop
        //   52: aload 4
        //   54: invokevirtual 49	android/os/Parcel:readException	()V
        //   57: aload 4
        //   59: invokevirtual 52	android/os/Parcel:recycle	()V
        //   62: aload_3
        //   63: invokevirtual 52	android/os/Parcel:recycle	()V
        //   66: return
        //   67: aload_3
        //   68: iconst_0
        //   69: invokevirtual 59	android/os/Parcel:writeInt	(I)V
        //   72: goto -42 -> 30
        //   75: astore_1
        //   76: aload 4
        //   78: invokevirtual 52	android/os/Parcel:recycle	()V
        //   81: aload_3
        //   82: invokevirtual 52	android/os/Parcel:recycle	()V
        //   85: aload_1
        //   86: athrow
        // Local variable table:
        //   start	length	slot	name	signature
        //   0	87	0	this	Proxy
        //   0	87	1	paramDataHolder	DataHolder
        //   0	87	2	paramArrayOfString	String[]
        //   3	79	3	localParcel1	Parcel
        //   7	70	4	localParcel2	Parcel
        // Exception table:
        //   from	to	target	type
        //   9	15	75	finally
        //   19	30	75	finally
        //   30	57	75	finally
        //   67	72	75	finally
      }
      
      /* Error */
      public void zzf(int paramInt, Bundle paramBundle)
        throws RemoteException
      {
        // Byte code:
        //   0: invokestatic 32	android/os/Parcel:obtain	()Landroid/os/Parcel;
        //   3: astore_3
        //   4: invokestatic 32	android/os/Parcel:obtain	()Landroid/os/Parcel;
        //   7: astore 4
        //   9: aload_3
        //   10: ldc 34
        //   12: invokevirtual 37	android/os/Parcel:writeInterfaceToken	(Ljava/lang/String;)V
        //   15: aload_3
        //   16: iload_1
        //   17: invokevirtual 59	android/os/Parcel:writeInt	(I)V
        //   20: aload_2
        //   21: ifnull +46 -> 67
        //   24: aload_3
        //   25: iconst_1
        //   26: invokevirtual 59	android/os/Parcel:writeInt	(I)V
        //   29: aload_2
        //   30: aload_3
        //   31: iconst_0
        //   32: invokevirtual 133	android/os/Bundle:writeToParcel	(Landroid/os/Parcel;I)V
        //   35: aload_0
        //   36: getfield 19	com/google/android/gms/games/internal/IGamesCallbacks$Stub$Proxy:zzoz	Landroid/os/IBinder;
        //   39: sipush 12003
        //   42: aload_3
        //   43: aload 4
        //   45: iconst_0
        //   46: invokeinterface 46 5 0
        //   51: pop
        //   52: aload 4
        //   54: invokevirtual 49	android/os/Parcel:readException	()V
        //   57: aload 4
        //   59: invokevirtual 52	android/os/Parcel:recycle	()V
        //   62: aload_3
        //   63: invokevirtual 52	android/os/Parcel:recycle	()V
        //   66: return
        //   67: aload_3
        //   68: iconst_0
        //   69: invokevirtual 59	android/os/Parcel:writeInt	(I)V
        //   72: goto -37 -> 35
        //   75: astore_2
        //   76: aload 4
        //   78: invokevirtual 52	android/os/Parcel:recycle	()V
        //   81: aload_3
        //   82: invokevirtual 52	android/os/Parcel:recycle	()V
        //   85: aload_2
        //   86: athrow
        // Local variable table:
        //   start	length	slot	name	signature
        //   0	87	0	this	Proxy
        //   0	87	1	paramInt	int
        //   0	87	2	paramBundle	Bundle
        //   3	79	3	localParcel1	Parcel
        //   7	70	4	localParcel2	Parcel
        // Exception table:
        //   from	to	target	type
        //   9	20	75	finally
        //   24	35	75	finally
        //   35	57	75	finally
        //   67	72	75	finally
      }
      
      /* Error */
      public void zzf(DataHolder paramDataHolder, String[] paramArrayOfString)
        throws RemoteException
      {
        // Byte code:
        //   0: invokestatic 32	android/os/Parcel:obtain	()Landroid/os/Parcel;
        //   3: astore_3
        //   4: invokestatic 32	android/os/Parcel:obtain	()Landroid/os/Parcel;
        //   7: astore 4
        //   9: aload_3
        //   10: ldc 34
        //   12: invokevirtual 37	android/os/Parcel:writeInterfaceToken	(Ljava/lang/String;)V
        //   15: aload_1
        //   16: ifnull +51 -> 67
        //   19: aload_3
        //   20: iconst_1
        //   21: invokevirtual 59	android/os/Parcel:writeInt	(I)V
        //   24: aload_1
        //   25: aload_3
        //   26: iconst_0
        //   27: invokevirtual 76	com/google/android/gms/common/data/DataHolder:writeToParcel	(Landroid/os/Parcel;I)V
        //   30: aload_3
        //   31: aload_2
        //   32: invokevirtual 121	android/os/Parcel:writeStringArray	([Ljava/lang/String;)V
        //   35: aload_0
        //   36: getfield 19	com/google/android/gms/games/internal/IGamesCallbacks$Stub$Proxy:zzoz	Landroid/os/IBinder;
        //   39: sipush 5031
        //   42: aload_3
        //   43: aload 4
        //   45: iconst_0
        //   46: invokeinterface 46 5 0
        //   51: pop
        //   52: aload 4
        //   54: invokevirtual 49	android/os/Parcel:readException	()V
        //   57: aload 4
        //   59: invokevirtual 52	android/os/Parcel:recycle	()V
        //   62: aload_3
        //   63: invokevirtual 52	android/os/Parcel:recycle	()V
        //   66: return
        //   67: aload_3
        //   68: iconst_0
        //   69: invokevirtual 59	android/os/Parcel:writeInt	(I)V
        //   72: goto -42 -> 30
        //   75: astore_1
        //   76: aload 4
        //   78: invokevirtual 52	android/os/Parcel:recycle	()V
        //   81: aload_3
        //   82: invokevirtual 52	android/os/Parcel:recycle	()V
        //   85: aload_1
        //   86: athrow
        // Local variable table:
        //   start	length	slot	name	signature
        //   0	87	0	this	Proxy
        //   0	87	1	paramDataHolder	DataHolder
        //   0	87	2	paramArrayOfString	String[]
        //   3	79	3	localParcel1	Parcel
        //   7	70	4	localParcel2	Parcel
        // Exception table:
        //   from	to	target	type
        //   9	15	75	finally
        //   19	30	75	finally
        //   30	57	75	finally
        //   67	72	75	finally
      }
      
      /* Error */
      public void zzg(int paramInt, Bundle paramBundle)
        throws RemoteException
      {
        // Byte code:
        //   0: invokestatic 32	android/os/Parcel:obtain	()Landroid/os/Parcel;
        //   3: astore_3
        //   4: invokestatic 32	android/os/Parcel:obtain	()Landroid/os/Parcel;
        //   7: astore 4
        //   9: aload_3
        //   10: ldc 34
        //   12: invokevirtual 37	android/os/Parcel:writeInterfaceToken	(Ljava/lang/String;)V
        //   15: aload_3
        //   16: iload_1
        //   17: invokevirtual 59	android/os/Parcel:writeInt	(I)V
        //   20: aload_2
        //   21: ifnull +46 -> 67
        //   24: aload_3
        //   25: iconst_1
        //   26: invokevirtual 59	android/os/Parcel:writeInt	(I)V
        //   29: aload_2
        //   30: aload_3
        //   31: iconst_0
        //   32: invokevirtual 133	android/os/Bundle:writeToParcel	(Landroid/os/Parcel;I)V
        //   35: aload_0
        //   36: getfield 19	com/google/android/gms/games/internal/IGamesCallbacks$Stub$Proxy:zzoz	Landroid/os/IBinder;
        //   39: sipush 12015
        //   42: aload_3
        //   43: aload 4
        //   45: iconst_0
        //   46: invokeinterface 46 5 0
        //   51: pop
        //   52: aload 4
        //   54: invokevirtual 49	android/os/Parcel:readException	()V
        //   57: aload 4
        //   59: invokevirtual 52	android/os/Parcel:recycle	()V
        //   62: aload_3
        //   63: invokevirtual 52	android/os/Parcel:recycle	()V
        //   66: return
        //   67: aload_3
        //   68: iconst_0
        //   69: invokevirtual 59	android/os/Parcel:writeInt	(I)V
        //   72: goto -37 -> 35
        //   75: astore_2
        //   76: aload 4
        //   78: invokevirtual 52	android/os/Parcel:recycle	()V
        //   81: aload_3
        //   82: invokevirtual 52	android/os/Parcel:recycle	()V
        //   85: aload_2
        //   86: athrow
        // Local variable table:
        //   start	length	slot	name	signature
        //   0	87	0	this	Proxy
        //   0	87	1	paramInt	int
        //   0	87	2	paramBundle	Bundle
        //   3	79	3	localParcel1	Parcel
        //   7	70	4	localParcel2	Parcel
        // Exception table:
        //   from	to	target	type
        //   9	20	75	finally
        //   24	35	75	finally
        //   35	57	75	finally
        //   67	72	75	finally
      }
      
      public void zzg(int paramInt, String paramString)
        throws RemoteException
      {
        Parcel localParcel1 = Parcel.obtain();
        Parcel localParcel2 = Parcel.obtain();
        try
        {
          localParcel1.writeInterfaceToken("com.google.android.gms.games.internal.IGamesCallbacks");
          localParcel1.writeInt(paramInt);
          localParcel1.writeString(paramString);
          this.zzoz.transact(5001, localParcel1, localParcel2, 0);
          localParcel2.readException();
          return;
        }
        finally
        {
          localParcel2.recycle();
          localParcel1.recycle();
        }
      }
      
      public void zzgn(int paramInt)
        throws RemoteException
      {
        Parcel localParcel1 = Parcel.obtain();
        Parcel localParcel2 = Parcel.obtain();
        try
        {
          localParcel1.writeInterfaceToken("com.google.android.gms.games.internal.IGamesCallbacks");
          localParcel1.writeInt(paramInt);
          this.zzoz.transact(5036, localParcel1, localParcel2, 0);
          localParcel2.readException();
          return;
        }
        finally
        {
          localParcel2.recycle();
          localParcel1.recycle();
        }
      }
      
      public void zzgo(int paramInt)
        throws RemoteException
      {
        Parcel localParcel1 = Parcel.obtain();
        Parcel localParcel2 = Parcel.obtain();
        try
        {
          localParcel1.writeInterfaceToken("com.google.android.gms.games.internal.IGamesCallbacks");
          localParcel1.writeInt(paramInt);
          this.zzoz.transact(5040, localParcel1, localParcel2, 0);
          localParcel2.readException();
          return;
        }
        finally
        {
          localParcel2.recycle();
          localParcel1.recycle();
        }
      }
      
      public void zzgp(int paramInt)
        throws RemoteException
      {
        Parcel localParcel1 = Parcel.obtain();
        Parcel localParcel2 = Parcel.obtain();
        try
        {
          localParcel1.writeInterfaceToken("com.google.android.gms.games.internal.IGamesCallbacks");
          localParcel1.writeInt(paramInt);
          this.zzoz.transact(13002, localParcel1, localParcel2, 0);
          localParcel2.readException();
          return;
        }
        finally
        {
          localParcel2.recycle();
          localParcel1.recycle();
        }
      }
      
      public void zzgq(int paramInt)
        throws RemoteException
      {
        Parcel localParcel1 = Parcel.obtain();
        Parcel localParcel2 = Parcel.obtain();
        try
        {
          localParcel1.writeInterfaceToken("com.google.android.gms.games.internal.IGamesCallbacks");
          localParcel1.writeInt(paramInt);
          this.zzoz.transact(17002, localParcel1, localParcel2, 0);
          localParcel2.readException();
          return;
        }
        finally
        {
          localParcel2.recycle();
          localParcel1.recycle();
        }
      }
      
      public void zzh(int paramInt, String paramString)
        throws RemoteException
      {
        Parcel localParcel1 = Parcel.obtain();
        Parcel localParcel2 = Parcel.obtain();
        try
        {
          localParcel1.writeInterfaceToken("com.google.android.gms.games.internal.IGamesCallbacks");
          localParcel1.writeInt(paramInt);
          localParcel1.writeString(paramString);
          this.zzoz.transact(5003, localParcel1, localParcel2, 0);
          localParcel2.readException();
          return;
        }
        finally
        {
          localParcel2.recycle();
          localParcel1.recycle();
        }
      }
      
      /* Error */
      public void zzh(DataHolder paramDataHolder)
        throws RemoteException
      {
        // Byte code:
        //   0: invokestatic 32	android/os/Parcel:obtain	()Landroid/os/Parcel;
        //   3: astore_2
        //   4: invokestatic 32	android/os/Parcel:obtain	()Landroid/os/Parcel;
        //   7: astore_3
        //   8: aload_2
        //   9: ldc 34
        //   11: invokevirtual 37	android/os/Parcel:writeInterfaceToken	(Ljava/lang/String;)V
        //   14: aload_1
        //   15: ifnull +43 -> 58
        //   18: aload_2
        //   19: iconst_1
        //   20: invokevirtual 59	android/os/Parcel:writeInt	(I)V
        //   23: aload_1
        //   24: aload_2
        //   25: iconst_0
        //   26: invokevirtual 76	com/google/android/gms/common/data/DataHolder:writeToParcel	(Landroid/os/Parcel;I)V
        //   29: aload_0
        //   30: getfield 19	com/google/android/gms/games/internal/IGamesCallbacks$Stub$Proxy:zzoz	Landroid/os/IBinder;
        //   33: sipush 5002
        //   36: aload_2
        //   37: aload_3
        //   38: iconst_0
        //   39: invokeinterface 46 5 0
        //   44: pop
        //   45: aload_3
        //   46: invokevirtual 49	android/os/Parcel:readException	()V
        //   49: aload_3
        //   50: invokevirtual 52	android/os/Parcel:recycle	()V
        //   53: aload_2
        //   54: invokevirtual 52	android/os/Parcel:recycle	()V
        //   57: return
        //   58: aload_2
        //   59: iconst_0
        //   60: invokevirtual 59	android/os/Parcel:writeInt	(I)V
        //   63: goto -34 -> 29
        //   66: astore_1
        //   67: aload_3
        //   68: invokevirtual 52	android/os/Parcel:recycle	()V
        //   71: aload_2
        //   72: invokevirtual 52	android/os/Parcel:recycle	()V
        //   75: aload_1
        //   76: athrow
        // Local variable table:
        //   start	length	slot	name	signature
        //   0	77	0	this	Proxy
        //   0	77	1	paramDataHolder	DataHolder
        //   3	69	2	localParcel1	Parcel
        //   7	61	3	localParcel2	Parcel
        // Exception table:
        //   from	to	target	type
        //   8	14	66	finally
        //   18	29	66	finally
        //   29	49	66	finally
        //   58	63	66	finally
      }
      
      public void zzi(int paramInt, String paramString)
        throws RemoteException
      {
        Parcel localParcel1 = Parcel.obtain();
        Parcel localParcel2 = Parcel.obtain();
        try
        {
          localParcel1.writeInterfaceToken("com.google.android.gms.games.internal.IGamesCallbacks");
          localParcel1.writeInt(paramInt);
          localParcel1.writeString(paramString);
          this.zzoz.transact(8007, localParcel1, localParcel2, 0);
          localParcel2.readException();
          return;
        }
        finally
        {
          localParcel2.recycle();
          localParcel1.recycle();
        }
      }
      
      /* Error */
      public void zzi(DataHolder paramDataHolder)
        throws RemoteException
      {
        // Byte code:
        //   0: invokestatic 32	android/os/Parcel:obtain	()Landroid/os/Parcel;
        //   3: astore_2
        //   4: invokestatic 32	android/os/Parcel:obtain	()Landroid/os/Parcel;
        //   7: astore_3
        //   8: aload_2
        //   9: ldc 34
        //   11: invokevirtual 37	android/os/Parcel:writeInterfaceToken	(Ljava/lang/String;)V
        //   14: aload_1
        //   15: ifnull +43 -> 58
        //   18: aload_2
        //   19: iconst_1
        //   20: invokevirtual 59	android/os/Parcel:writeInt	(I)V
        //   23: aload_1
        //   24: aload_2
        //   25: iconst_0
        //   26: invokevirtual 76	com/google/android/gms/common/data/DataHolder:writeToParcel	(Landroid/os/Parcel;I)V
        //   29: aload_0
        //   30: getfield 19	com/google/android/gms/games/internal/IGamesCallbacks$Stub$Proxy:zzoz	Landroid/os/IBinder;
        //   33: sipush 12011
        //   36: aload_2
        //   37: aload_3
        //   38: iconst_0
        //   39: invokeinterface 46 5 0
        //   44: pop
        //   45: aload_3
        //   46: invokevirtual 49	android/os/Parcel:readException	()V
        //   49: aload_3
        //   50: invokevirtual 52	android/os/Parcel:recycle	()V
        //   53: aload_2
        //   54: invokevirtual 52	android/os/Parcel:recycle	()V
        //   57: return
        //   58: aload_2
        //   59: iconst_0
        //   60: invokevirtual 59	android/os/Parcel:writeInt	(I)V
        //   63: goto -34 -> 29
        //   66: astore_1
        //   67: aload_3
        //   68: invokevirtual 52	android/os/Parcel:recycle	()V
        //   71: aload_2
        //   72: invokevirtual 52	android/os/Parcel:recycle	()V
        //   75: aload_1
        //   76: athrow
        // Local variable table:
        //   start	length	slot	name	signature
        //   0	77	0	this	Proxy
        //   0	77	1	paramDataHolder	DataHolder
        //   3	69	2	localParcel1	Parcel
        //   7	61	3	localParcel2	Parcel
        // Exception table:
        //   from	to	target	type
        //   8	14	66	finally
        //   18	29	66	finally
        //   29	49	66	finally
        //   58	63	66	finally
      }
      
      public void zzj(int paramInt, String paramString)
        throws RemoteException
      {
        Parcel localParcel1 = Parcel.obtain();
        Parcel localParcel2 = Parcel.obtain();
        try
        {
          localParcel1.writeInterfaceToken("com.google.android.gms.games.internal.IGamesCallbacks");
          localParcel1.writeInt(paramInt);
          localParcel1.writeString(paramString);
          this.zzoz.transact(12012, localParcel1, localParcel2, 0);
          localParcel2.readException();
          return;
        }
        finally
        {
          localParcel2.recycle();
          localParcel1.recycle();
        }
      }
      
      /* Error */
      public void zzj(DataHolder paramDataHolder)
        throws RemoteException
      {
        // Byte code:
        //   0: invokestatic 32	android/os/Parcel:obtain	()Landroid/os/Parcel;
        //   3: astore_2
        //   4: invokestatic 32	android/os/Parcel:obtain	()Landroid/os/Parcel;
        //   7: astore_3
        //   8: aload_2
        //   9: ldc 34
        //   11: invokevirtual 37	android/os/Parcel:writeInterfaceToken	(Ljava/lang/String;)V
        //   14: aload_1
        //   15: ifnull +43 -> 58
        //   18: aload_2
        //   19: iconst_1
        //   20: invokevirtual 59	android/os/Parcel:writeInt	(I)V
        //   23: aload_1
        //   24: aload_2
        //   25: iconst_0
        //   26: invokevirtual 76	com/google/android/gms/common/data/DataHolder:writeToParcel	(Landroid/os/Parcel;I)V
        //   29: aload_0
        //   30: getfield 19	com/google/android/gms/games/internal/IGamesCallbacks$Stub$Proxy:zzoz	Landroid/os/IBinder;
        //   33: sipush 5004
        //   36: aload_2
        //   37: aload_3
        //   38: iconst_0
        //   39: invokeinterface 46 5 0
        //   44: pop
        //   45: aload_3
        //   46: invokevirtual 49	android/os/Parcel:readException	()V
        //   49: aload_3
        //   50: invokevirtual 52	android/os/Parcel:recycle	()V
        //   53: aload_2
        //   54: invokevirtual 52	android/os/Parcel:recycle	()V
        //   57: return
        //   58: aload_2
        //   59: iconst_0
        //   60: invokevirtual 59	android/os/Parcel:writeInt	(I)V
        //   63: goto -34 -> 29
        //   66: astore_1
        //   67: aload_3
        //   68: invokevirtual 52	android/os/Parcel:recycle	()V
        //   71: aload_2
        //   72: invokevirtual 52	android/os/Parcel:recycle	()V
        //   75: aload_1
        //   76: athrow
        // Local variable table:
        //   start	length	slot	name	signature
        //   0	77	0	this	Proxy
        //   0	77	1	paramDataHolder	DataHolder
        //   3	69	2	localParcel1	Parcel
        //   7	61	3	localParcel2	Parcel
        // Exception table:
        //   from	to	target	type
        //   8	14	66	finally
        //   18	29	66	finally
        //   29	49	66	finally
        //   58	63	66	finally
      }
      
      /* Error */
      public void zzk(DataHolder paramDataHolder)
        throws RemoteException
      {
        // Byte code:
        //   0: invokestatic 32	android/os/Parcel:obtain	()Landroid/os/Parcel;
        //   3: astore_2
        //   4: invokestatic 32	android/os/Parcel:obtain	()Landroid/os/Parcel;
        //   7: astore_3
        //   8: aload_2
        //   9: ldc 34
        //   11: invokevirtual 37	android/os/Parcel:writeInterfaceToken	(Ljava/lang/String;)V
        //   14: aload_1
        //   15: ifnull +43 -> 58
        //   18: aload_2
        //   19: iconst_1
        //   20: invokevirtual 59	android/os/Parcel:writeInt	(I)V
        //   23: aload_1
        //   24: aload_2
        //   25: iconst_0
        //   26: invokevirtual 76	com/google/android/gms/common/data/DataHolder:writeToParcel	(Landroid/os/Parcel;I)V
        //   29: aload_0
        //   30: getfield 19	com/google/android/gms/games/internal/IGamesCallbacks$Stub$Proxy:zzoz	Landroid/os/IBinder;
        //   33: sipush 5006
        //   36: aload_2
        //   37: aload_3
        //   38: iconst_0
        //   39: invokeinterface 46 5 0
        //   44: pop
        //   45: aload_3
        //   46: invokevirtual 49	android/os/Parcel:readException	()V
        //   49: aload_3
        //   50: invokevirtual 52	android/os/Parcel:recycle	()V
        //   53: aload_2
        //   54: invokevirtual 52	android/os/Parcel:recycle	()V
        //   57: return
        //   58: aload_2
        //   59: iconst_0
        //   60: invokevirtual 59	android/os/Parcel:writeInt	(I)V
        //   63: goto -34 -> 29
        //   66: astore_1
        //   67: aload_3
        //   68: invokevirtual 52	android/os/Parcel:recycle	()V
        //   71: aload_2
        //   72: invokevirtual 52	android/os/Parcel:recycle	()V
        //   75: aload_1
        //   76: athrow
        // Local variable table:
        //   start	length	slot	name	signature
        //   0	77	0	this	Proxy
        //   0	77	1	paramDataHolder	DataHolder
        //   3	69	2	localParcel1	Parcel
        //   7	61	3	localParcel2	Parcel
        // Exception table:
        //   from	to	target	type
        //   8	14	66	finally
        //   18	29	66	finally
        //   29	49	66	finally
        //   58	63	66	finally
      }
      
      /* Error */
      public void zzl(DataHolder paramDataHolder)
        throws RemoteException
      {
        // Byte code:
        //   0: invokestatic 32	android/os/Parcel:obtain	()Landroid/os/Parcel;
        //   3: astore_2
        //   4: invokestatic 32	android/os/Parcel:obtain	()Landroid/os/Parcel;
        //   7: astore_3
        //   8: aload_2
        //   9: ldc 34
        //   11: invokevirtual 37	android/os/Parcel:writeInterfaceToken	(Ljava/lang/String;)V
        //   14: aload_1
        //   15: ifnull +43 -> 58
        //   18: aload_2
        //   19: iconst_1
        //   20: invokevirtual 59	android/os/Parcel:writeInt	(I)V
        //   23: aload_1
        //   24: aload_2
        //   25: iconst_0
        //   26: invokevirtual 76	com/google/android/gms/common/data/DataHolder:writeToParcel	(Landroid/os/Parcel;I)V
        //   29: aload_0
        //   30: getfield 19	com/google/android/gms/games/internal/IGamesCallbacks$Stub$Proxy:zzoz	Landroid/os/IBinder;
        //   33: sipush 5007
        //   36: aload_2
        //   37: aload_3
        //   38: iconst_0
        //   39: invokeinterface 46 5 0
        //   44: pop
        //   45: aload_3
        //   46: invokevirtual 49	android/os/Parcel:readException	()V
        //   49: aload_3
        //   50: invokevirtual 52	android/os/Parcel:recycle	()V
        //   53: aload_2
        //   54: invokevirtual 52	android/os/Parcel:recycle	()V
        //   57: return
        //   58: aload_2
        //   59: iconst_0
        //   60: invokevirtual 59	android/os/Parcel:writeInt	(I)V
        //   63: goto -34 -> 29
        //   66: astore_1
        //   67: aload_3
        //   68: invokevirtual 52	android/os/Parcel:recycle	()V
        //   71: aload_2
        //   72: invokevirtual 52	android/os/Parcel:recycle	()V
        //   75: aload_1
        //   76: athrow
        // Local variable table:
        //   start	length	slot	name	signature
        //   0	77	0	this	Proxy
        //   0	77	1	paramDataHolder	DataHolder
        //   3	69	2	localParcel1	Parcel
        //   7	61	3	localParcel2	Parcel
        // Exception table:
        //   from	to	target	type
        //   8	14	66	finally
        //   18	29	66	finally
        //   29	49	66	finally
        //   58	63	66	finally
      }
      
      /* Error */
      public void zzm(DataHolder paramDataHolder)
        throws RemoteException
      {
        // Byte code:
        //   0: invokestatic 32	android/os/Parcel:obtain	()Landroid/os/Parcel;
        //   3: astore_2
        //   4: invokestatic 32	android/os/Parcel:obtain	()Landroid/os/Parcel;
        //   7: astore_3
        //   8: aload_2
        //   9: ldc 34
        //   11: invokevirtual 37	android/os/Parcel:writeInterfaceToken	(Ljava/lang/String;)V
        //   14: aload_1
        //   15: ifnull +43 -> 58
        //   18: aload_2
        //   19: iconst_1
        //   20: invokevirtual 59	android/os/Parcel:writeInt	(I)V
        //   23: aload_1
        //   24: aload_2
        //   25: iconst_0
        //   26: invokevirtual 76	com/google/android/gms/common/data/DataHolder:writeToParcel	(Landroid/os/Parcel;I)V
        //   29: aload_0
        //   30: getfield 19	com/google/android/gms/games/internal/IGamesCallbacks$Stub$Proxy:zzoz	Landroid/os/IBinder;
        //   33: sipush 5008
        //   36: aload_2
        //   37: aload_3
        //   38: iconst_0
        //   39: invokeinterface 46 5 0
        //   44: pop
        //   45: aload_3
        //   46: invokevirtual 49	android/os/Parcel:readException	()V
        //   49: aload_3
        //   50: invokevirtual 52	android/os/Parcel:recycle	()V
        //   53: aload_2
        //   54: invokevirtual 52	android/os/Parcel:recycle	()V
        //   57: return
        //   58: aload_2
        //   59: iconst_0
        //   60: invokevirtual 59	android/os/Parcel:writeInt	(I)V
        //   63: goto -34 -> 29
        //   66: astore_1
        //   67: aload_3
        //   68: invokevirtual 52	android/os/Parcel:recycle	()V
        //   71: aload_2
        //   72: invokevirtual 52	android/os/Parcel:recycle	()V
        //   75: aload_1
        //   76: athrow
        // Local variable table:
        //   start	length	slot	name	signature
        //   0	77	0	this	Proxy
        //   0	77	1	paramDataHolder	DataHolder
        //   3	69	2	localParcel1	Parcel
        //   7	61	3	localParcel2	Parcel
        // Exception table:
        //   from	to	target	type
        //   8	14	66	finally
        //   18	29	66	finally
        //   29	49	66	finally
        //   58	63	66	finally
      }
      
      /* Error */
      public void zzn(DataHolder paramDataHolder)
        throws RemoteException
      {
        // Byte code:
        //   0: invokestatic 32	android/os/Parcel:obtain	()Landroid/os/Parcel;
        //   3: astore_2
        //   4: invokestatic 32	android/os/Parcel:obtain	()Landroid/os/Parcel;
        //   7: astore_3
        //   8: aload_2
        //   9: ldc 34
        //   11: invokevirtual 37	android/os/Parcel:writeInterfaceToken	(Ljava/lang/String;)V
        //   14: aload_1
        //   15: ifnull +43 -> 58
        //   18: aload_2
        //   19: iconst_1
        //   20: invokevirtual 59	android/os/Parcel:writeInt	(I)V
        //   23: aload_1
        //   24: aload_2
        //   25: iconst_0
        //   26: invokevirtual 76	com/google/android/gms/common/data/DataHolder:writeToParcel	(Landroid/os/Parcel;I)V
        //   29: aload_0
        //   30: getfield 19	com/google/android/gms/games/internal/IGamesCallbacks$Stub$Proxy:zzoz	Landroid/os/IBinder;
        //   33: sipush 5009
        //   36: aload_2
        //   37: aload_3
        //   38: iconst_0
        //   39: invokeinterface 46 5 0
        //   44: pop
        //   45: aload_3
        //   46: invokevirtual 49	android/os/Parcel:readException	()V
        //   49: aload_3
        //   50: invokevirtual 52	android/os/Parcel:recycle	()V
        //   53: aload_2
        //   54: invokevirtual 52	android/os/Parcel:recycle	()V
        //   57: return
        //   58: aload_2
        //   59: iconst_0
        //   60: invokevirtual 59	android/os/Parcel:writeInt	(I)V
        //   63: goto -34 -> 29
        //   66: astore_1
        //   67: aload_3
        //   68: invokevirtual 52	android/os/Parcel:recycle	()V
        //   71: aload_2
        //   72: invokevirtual 52	android/os/Parcel:recycle	()V
        //   75: aload_1
        //   76: athrow
        // Local variable table:
        //   start	length	slot	name	signature
        //   0	77	0	this	Proxy
        //   0	77	1	paramDataHolder	DataHolder
        //   3	69	2	localParcel1	Parcel
        //   7	61	3	localParcel2	Parcel
        // Exception table:
        //   from	to	target	type
        //   8	14	66	finally
        //   18	29	66	finally
        //   29	49	66	finally
        //   58	63	66	finally
      }
      
      /* Error */
      public void zzo(DataHolder paramDataHolder)
        throws RemoteException
      {
        // Byte code:
        //   0: invokestatic 32	android/os/Parcel:obtain	()Landroid/os/Parcel;
        //   3: astore_2
        //   4: invokestatic 32	android/os/Parcel:obtain	()Landroid/os/Parcel;
        //   7: astore_3
        //   8: aload_2
        //   9: ldc 34
        //   11: invokevirtual 37	android/os/Parcel:writeInterfaceToken	(Ljava/lang/String;)V
        //   14: aload_1
        //   15: ifnull +43 -> 58
        //   18: aload_2
        //   19: iconst_1
        //   20: invokevirtual 59	android/os/Parcel:writeInt	(I)V
        //   23: aload_1
        //   24: aload_2
        //   25: iconst_0
        //   26: invokevirtual 76	com/google/android/gms/common/data/DataHolder:writeToParcel	(Landroid/os/Parcel;I)V
        //   29: aload_0
        //   30: getfield 19	com/google/android/gms/games/internal/IGamesCallbacks$Stub$Proxy:zzoz	Landroid/os/IBinder;
        //   33: sipush 5010
        //   36: aload_2
        //   37: aload_3
        //   38: iconst_0
        //   39: invokeinterface 46 5 0
        //   44: pop
        //   45: aload_3
        //   46: invokevirtual 49	android/os/Parcel:readException	()V
        //   49: aload_3
        //   50: invokevirtual 52	android/os/Parcel:recycle	()V
        //   53: aload_2
        //   54: invokevirtual 52	android/os/Parcel:recycle	()V
        //   57: return
        //   58: aload_2
        //   59: iconst_0
        //   60: invokevirtual 59	android/os/Parcel:writeInt	(I)V
        //   63: goto -34 -> 29
        //   66: astore_1
        //   67: aload_3
        //   68: invokevirtual 52	android/os/Parcel:recycle	()V
        //   71: aload_2
        //   72: invokevirtual 52	android/os/Parcel:recycle	()V
        //   75: aload_1
        //   76: athrow
        // Local variable table:
        //   start	length	slot	name	signature
        //   0	77	0	this	Proxy
        //   0	77	1	paramDataHolder	DataHolder
        //   3	69	2	localParcel1	Parcel
        //   7	61	3	localParcel2	Parcel
        // Exception table:
        //   from	to	target	type
        //   8	14	66	finally
        //   18	29	66	finally
        //   29	49	66	finally
        //   58	63	66	finally
      }
      
      /* Error */
      public void zzp(DataHolder paramDataHolder)
        throws RemoteException
      {
        // Byte code:
        //   0: invokestatic 32	android/os/Parcel:obtain	()Landroid/os/Parcel;
        //   3: astore_2
        //   4: invokestatic 32	android/os/Parcel:obtain	()Landroid/os/Parcel;
        //   7: astore_3
        //   8: aload_2
        //   9: ldc 34
        //   11: invokevirtual 37	android/os/Parcel:writeInterfaceToken	(Ljava/lang/String;)V
        //   14: aload_1
        //   15: ifnull +43 -> 58
        //   18: aload_2
        //   19: iconst_1
        //   20: invokevirtual 59	android/os/Parcel:writeInt	(I)V
        //   23: aload_1
        //   24: aload_2
        //   25: iconst_0
        //   26: invokevirtual 76	com/google/android/gms/common/data/DataHolder:writeToParcel	(Landroid/os/Parcel;I)V
        //   29: aload_0
        //   30: getfield 19	com/google/android/gms/games/internal/IGamesCallbacks$Stub$Proxy:zzoz	Landroid/os/IBinder;
        //   33: sipush 5011
        //   36: aload_2
        //   37: aload_3
        //   38: iconst_0
        //   39: invokeinterface 46 5 0
        //   44: pop
        //   45: aload_3
        //   46: invokevirtual 49	android/os/Parcel:readException	()V
        //   49: aload_3
        //   50: invokevirtual 52	android/os/Parcel:recycle	()V
        //   53: aload_2
        //   54: invokevirtual 52	android/os/Parcel:recycle	()V
        //   57: return
        //   58: aload_2
        //   59: iconst_0
        //   60: invokevirtual 59	android/os/Parcel:writeInt	(I)V
        //   63: goto -34 -> 29
        //   66: astore_1
        //   67: aload_3
        //   68: invokevirtual 52	android/os/Parcel:recycle	()V
        //   71: aload_2
        //   72: invokevirtual 52	android/os/Parcel:recycle	()V
        //   75: aload_1
        //   76: athrow
        // Local variable table:
        //   start	length	slot	name	signature
        //   0	77	0	this	Proxy
        //   0	77	1	paramDataHolder	DataHolder
        //   3	69	2	localParcel1	Parcel
        //   7	61	3	localParcel2	Parcel
        // Exception table:
        //   from	to	target	type
        //   8	14	66	finally
        //   18	29	66	finally
        //   29	49	66	finally
        //   58	63	66	finally
      }
      
      /* Error */
      public void zzq(DataHolder paramDataHolder)
        throws RemoteException
      {
        // Byte code:
        //   0: invokestatic 32	android/os/Parcel:obtain	()Landroid/os/Parcel;
        //   3: astore_2
        //   4: invokestatic 32	android/os/Parcel:obtain	()Landroid/os/Parcel;
        //   7: astore_3
        //   8: aload_2
        //   9: ldc 34
        //   11: invokevirtual 37	android/os/Parcel:writeInterfaceToken	(Ljava/lang/String;)V
        //   14: aload_1
        //   15: ifnull +43 -> 58
        //   18: aload_2
        //   19: iconst_1
        //   20: invokevirtual 59	android/os/Parcel:writeInt	(I)V
        //   23: aload_1
        //   24: aload_2
        //   25: iconst_0
        //   26: invokevirtual 76	com/google/android/gms/common/data/DataHolder:writeToParcel	(Landroid/os/Parcel;I)V
        //   29: aload_0
        //   30: getfield 19	com/google/android/gms/games/internal/IGamesCallbacks$Stub$Proxy:zzoz	Landroid/os/IBinder;
        //   33: sipush 9001
        //   36: aload_2
        //   37: aload_3
        //   38: iconst_0
        //   39: invokeinterface 46 5 0
        //   44: pop
        //   45: aload_3
        //   46: invokevirtual 49	android/os/Parcel:readException	()V
        //   49: aload_3
        //   50: invokevirtual 52	android/os/Parcel:recycle	()V
        //   53: aload_2
        //   54: invokevirtual 52	android/os/Parcel:recycle	()V
        //   57: return
        //   58: aload_2
        //   59: iconst_0
        //   60: invokevirtual 59	android/os/Parcel:writeInt	(I)V
        //   63: goto -34 -> 29
        //   66: astore_1
        //   67: aload_3
        //   68: invokevirtual 52	android/os/Parcel:recycle	()V
        //   71: aload_2
        //   72: invokevirtual 52	android/os/Parcel:recycle	()V
        //   75: aload_1
        //   76: athrow
        // Local variable table:
        //   start	length	slot	name	signature
        //   0	77	0	this	Proxy
        //   0	77	1	paramDataHolder	DataHolder
        //   3	69	2	localParcel1	Parcel
        //   7	61	3	localParcel2	Parcel
        // Exception table:
        //   from	to	target	type
        //   8	14	66	finally
        //   18	29	66	finally
        //   29	49	66	finally
        //   58	63	66	finally
      }
      
      /* Error */
      public void zzr(DataHolder paramDataHolder)
        throws RemoteException
      {
        // Byte code:
        //   0: invokestatic 32	android/os/Parcel:obtain	()Landroid/os/Parcel;
        //   3: astore_2
        //   4: invokestatic 32	android/os/Parcel:obtain	()Landroid/os/Parcel;
        //   7: astore_3
        //   8: aload_2
        //   9: ldc 34
        //   11: invokevirtual 37	android/os/Parcel:writeInterfaceToken	(Ljava/lang/String;)V
        //   14: aload_1
        //   15: ifnull +43 -> 58
        //   18: aload_2
        //   19: iconst_1
        //   20: invokevirtual 59	android/os/Parcel:writeInt	(I)V
        //   23: aload_1
        //   24: aload_2
        //   25: iconst_0
        //   26: invokevirtual 76	com/google/android/gms/common/data/DataHolder:writeToParcel	(Landroid/os/Parcel;I)V
        //   29: aload_0
        //   30: getfield 19	com/google/android/gms/games/internal/IGamesCallbacks$Stub$Proxy:zzoz	Landroid/os/IBinder;
        //   33: sipush 5017
        //   36: aload_2
        //   37: aload_3
        //   38: iconst_0
        //   39: invokeinterface 46 5 0
        //   44: pop
        //   45: aload_3
        //   46: invokevirtual 49	android/os/Parcel:readException	()V
        //   49: aload_3
        //   50: invokevirtual 52	android/os/Parcel:recycle	()V
        //   53: aload_2
        //   54: invokevirtual 52	android/os/Parcel:recycle	()V
        //   57: return
        //   58: aload_2
        //   59: iconst_0
        //   60: invokevirtual 59	android/os/Parcel:writeInt	(I)V
        //   63: goto -34 -> 29
        //   66: astore_1
        //   67: aload_3
        //   68: invokevirtual 52	android/os/Parcel:recycle	()V
        //   71: aload_2
        //   72: invokevirtual 52	android/os/Parcel:recycle	()V
        //   75: aload_1
        //   76: athrow
        // Local variable table:
        //   start	length	slot	name	signature
        //   0	77	0	this	Proxy
        //   0	77	1	paramDataHolder	DataHolder
        //   3	69	2	localParcel1	Parcel
        //   7	61	3	localParcel2	Parcel
        // Exception table:
        //   from	to	target	type
        //   8	14	66	finally
        //   18	29	66	finally
        //   29	49	66	finally
        //   58	63	66	finally
      }
      
      /* Error */
      public void zzs(DataHolder paramDataHolder)
        throws RemoteException
      {
        // Byte code:
        //   0: invokestatic 32	android/os/Parcel:obtain	()Landroid/os/Parcel;
        //   3: astore_2
        //   4: invokestatic 32	android/os/Parcel:obtain	()Landroid/os/Parcel;
        //   7: astore_3
        //   8: aload_2
        //   9: ldc 34
        //   11: invokevirtual 37	android/os/Parcel:writeInterfaceToken	(Ljava/lang/String;)V
        //   14: aload_1
        //   15: ifnull +43 -> 58
        //   18: aload_2
        //   19: iconst_1
        //   20: invokevirtual 59	android/os/Parcel:writeInt	(I)V
        //   23: aload_1
        //   24: aload_2
        //   25: iconst_0
        //   26: invokevirtual 76	com/google/android/gms/common/data/DataHolder:writeToParcel	(Landroid/os/Parcel;I)V
        //   29: aload_0
        //   30: getfield 19	com/google/android/gms/games/internal/IGamesCallbacks$Stub$Proxy:zzoz	Landroid/os/IBinder;
        //   33: sipush 5037
        //   36: aload_2
        //   37: aload_3
        //   38: iconst_0
        //   39: invokeinterface 46 5 0
        //   44: pop
        //   45: aload_3
        //   46: invokevirtual 49	android/os/Parcel:readException	()V
        //   49: aload_3
        //   50: invokevirtual 52	android/os/Parcel:recycle	()V
        //   53: aload_2
        //   54: invokevirtual 52	android/os/Parcel:recycle	()V
        //   57: return
        //   58: aload_2
        //   59: iconst_0
        //   60: invokevirtual 59	android/os/Parcel:writeInt	(I)V
        //   63: goto -34 -> 29
        //   66: astore_1
        //   67: aload_3
        //   68: invokevirtual 52	android/os/Parcel:recycle	()V
        //   71: aload_2
        //   72: invokevirtual 52	android/os/Parcel:recycle	()V
        //   75: aload_1
        //   76: athrow
        // Local variable table:
        //   start	length	slot	name	signature
        //   0	77	0	this	Proxy
        //   0	77	1	paramDataHolder	DataHolder
        //   3	69	2	localParcel1	Parcel
        //   7	61	3	localParcel2	Parcel
        // Exception table:
        //   from	to	target	type
        //   8	14	66	finally
        //   18	29	66	finally
        //   29	49	66	finally
        //   58	63	66	finally
      }
      
      /* Error */
      public void zzt(DataHolder paramDataHolder)
        throws RemoteException
      {
        // Byte code:
        //   0: invokestatic 32	android/os/Parcel:obtain	()Landroid/os/Parcel;
        //   3: astore_2
        //   4: invokestatic 32	android/os/Parcel:obtain	()Landroid/os/Parcel;
        //   7: astore_3
        //   8: aload_2
        //   9: ldc 34
        //   11: invokevirtual 37	android/os/Parcel:writeInterfaceToken	(Ljava/lang/String;)V
        //   14: aload_1
        //   15: ifnull +43 -> 58
        //   18: aload_2
        //   19: iconst_1
        //   20: invokevirtual 59	android/os/Parcel:writeInt	(I)V
        //   23: aload_1
        //   24: aload_2
        //   25: iconst_0
        //   26: invokevirtual 76	com/google/android/gms/common/data/DataHolder:writeToParcel	(Landroid/os/Parcel;I)V
        //   29: aload_0
        //   30: getfield 19	com/google/android/gms/games/internal/IGamesCallbacks$Stub$Proxy:zzoz	Landroid/os/IBinder;
        //   33: sipush 10001
        //   36: aload_2
        //   37: aload_3
        //   38: iconst_0
        //   39: invokeinterface 46 5 0
        //   44: pop
        //   45: aload_3
        //   46: invokevirtual 49	android/os/Parcel:readException	()V
        //   49: aload_3
        //   50: invokevirtual 52	android/os/Parcel:recycle	()V
        //   53: aload_2
        //   54: invokevirtual 52	android/os/Parcel:recycle	()V
        //   57: return
        //   58: aload_2
        //   59: iconst_0
        //   60: invokevirtual 59	android/os/Parcel:writeInt	(I)V
        //   63: goto -34 -> 29
        //   66: astore_1
        //   67: aload_3
        //   68: invokevirtual 52	android/os/Parcel:recycle	()V
        //   71: aload_2
        //   72: invokevirtual 52	android/os/Parcel:recycle	()V
        //   75: aload_1
        //   76: athrow
        // Local variable table:
        //   start	length	slot	name	signature
        //   0	77	0	this	Proxy
        //   0	77	1	paramDataHolder	DataHolder
        //   3	69	2	localParcel1	Parcel
        //   7	61	3	localParcel2	Parcel
        // Exception table:
        //   from	to	target	type
        //   8	14	66	finally
        //   18	29	66	finally
        //   29	49	66	finally
        //   58	63	66	finally
      }
      
      /* Error */
      public void zzu(DataHolder paramDataHolder)
        throws RemoteException
      {
        // Byte code:
        //   0: invokestatic 32	android/os/Parcel:obtain	()Landroid/os/Parcel;
        //   3: astore_2
        //   4: invokestatic 32	android/os/Parcel:obtain	()Landroid/os/Parcel;
        //   7: astore_3
        //   8: aload_2
        //   9: ldc 34
        //   11: invokevirtual 37	android/os/Parcel:writeInterfaceToken	(Ljava/lang/String;)V
        //   14: aload_1
        //   15: ifnull +43 -> 58
        //   18: aload_2
        //   19: iconst_1
        //   20: invokevirtual 59	android/os/Parcel:writeInt	(I)V
        //   23: aload_1
        //   24: aload_2
        //   25: iconst_0
        //   26: invokevirtual 76	com/google/android/gms/common/data/DataHolder:writeToParcel	(Landroid/os/Parcel;I)V
        //   29: aload_0
        //   30: getfield 19	com/google/android/gms/games/internal/IGamesCallbacks$Stub$Proxy:zzoz	Landroid/os/IBinder;
        //   33: sipush 8003
        //   36: aload_2
        //   37: aload_3
        //   38: iconst_0
        //   39: invokeinterface 46 5 0
        //   44: pop
        //   45: aload_3
        //   46: invokevirtual 49	android/os/Parcel:readException	()V
        //   49: aload_3
        //   50: invokevirtual 52	android/os/Parcel:recycle	()V
        //   53: aload_2
        //   54: invokevirtual 52	android/os/Parcel:recycle	()V
        //   57: return
        //   58: aload_2
        //   59: iconst_0
        //   60: invokevirtual 59	android/os/Parcel:writeInt	(I)V
        //   63: goto -34 -> 29
        //   66: astore_1
        //   67: aload_3
        //   68: invokevirtual 52	android/os/Parcel:recycle	()V
        //   71: aload_2
        //   72: invokevirtual 52	android/os/Parcel:recycle	()V
        //   75: aload_1
        //   76: athrow
        // Local variable table:
        //   start	length	slot	name	signature
        //   0	77	0	this	Proxy
        //   0	77	1	paramDataHolder	DataHolder
        //   3	69	2	localParcel1	Parcel
        //   7	61	3	localParcel2	Parcel
        // Exception table:
        //   from	to	target	type
        //   8	14	66	finally
        //   18	29	66	finally
        //   29	49	66	finally
        //   58	63	66	finally
      }
      
      /* Error */
      public void zzv(DataHolder paramDataHolder)
        throws RemoteException
      {
        // Byte code:
        //   0: invokestatic 32	android/os/Parcel:obtain	()Landroid/os/Parcel;
        //   3: astore_2
        //   4: invokestatic 32	android/os/Parcel:obtain	()Landroid/os/Parcel;
        //   7: astore_3
        //   8: aload_2
        //   9: ldc 34
        //   11: invokevirtual 37	android/os/Parcel:writeInterfaceToken	(Ljava/lang/String;)V
        //   14: aload_1
        //   15: ifnull +43 -> 58
        //   18: aload_2
        //   19: iconst_1
        //   20: invokevirtual 59	android/os/Parcel:writeInt	(I)V
        //   23: aload_1
        //   24: aload_2
        //   25: iconst_0
        //   26: invokevirtual 76	com/google/android/gms/common/data/DataHolder:writeToParcel	(Landroid/os/Parcel;I)V
        //   29: aload_0
        //   30: getfield 19	com/google/android/gms/games/internal/IGamesCallbacks$Stub$Proxy:zzoz	Landroid/os/IBinder;
        //   33: sipush 8004
        //   36: aload_2
        //   37: aload_3
        //   38: iconst_0
        //   39: invokeinterface 46 5 0
        //   44: pop
        //   45: aload_3
        //   46: invokevirtual 49	android/os/Parcel:readException	()V
        //   49: aload_3
        //   50: invokevirtual 52	android/os/Parcel:recycle	()V
        //   53: aload_2
        //   54: invokevirtual 52	android/os/Parcel:recycle	()V
        //   57: return
        //   58: aload_2
        //   59: iconst_0
        //   60: invokevirtual 59	android/os/Parcel:writeInt	(I)V
        //   63: goto -34 -> 29
        //   66: astore_1
        //   67: aload_3
        //   68: invokevirtual 52	android/os/Parcel:recycle	()V
        //   71: aload_2
        //   72: invokevirtual 52	android/os/Parcel:recycle	()V
        //   75: aload_1
        //   76: athrow
        // Local variable table:
        //   start	length	slot	name	signature
        //   0	77	0	this	Proxy
        //   0	77	1	paramDataHolder	DataHolder
        //   3	69	2	localParcel1	Parcel
        //   7	61	3	localParcel2	Parcel
        // Exception table:
        //   from	to	target	type
        //   8	14	66	finally
        //   18	29	66	finally
        //   29	49	66	finally
        //   58	63	66	finally
      }
      
      /* Error */
      public void zzw(DataHolder paramDataHolder)
        throws RemoteException
      {
        // Byte code:
        //   0: invokestatic 32	android/os/Parcel:obtain	()Landroid/os/Parcel;
        //   3: astore_2
        //   4: invokestatic 32	android/os/Parcel:obtain	()Landroid/os/Parcel;
        //   7: astore_3
        //   8: aload_2
        //   9: ldc 34
        //   11: invokevirtual 37	android/os/Parcel:writeInterfaceToken	(Ljava/lang/String;)V
        //   14: aload_1
        //   15: ifnull +43 -> 58
        //   18: aload_2
        //   19: iconst_1
        //   20: invokevirtual 59	android/os/Parcel:writeInt	(I)V
        //   23: aload_1
        //   24: aload_2
        //   25: iconst_0
        //   26: invokevirtual 76	com/google/android/gms/common/data/DataHolder:writeToParcel	(Landroid/os/Parcel;I)V
        //   29: aload_0
        //   30: getfield 19	com/google/android/gms/games/internal/IGamesCallbacks$Stub$Proxy:zzoz	Landroid/os/IBinder;
        //   33: sipush 8005
        //   36: aload_2
        //   37: aload_3
        //   38: iconst_0
        //   39: invokeinterface 46 5 0
        //   44: pop
        //   45: aload_3
        //   46: invokevirtual 49	android/os/Parcel:readException	()V
        //   49: aload_3
        //   50: invokevirtual 52	android/os/Parcel:recycle	()V
        //   53: aload_2
        //   54: invokevirtual 52	android/os/Parcel:recycle	()V
        //   57: return
        //   58: aload_2
        //   59: iconst_0
        //   60: invokevirtual 59	android/os/Parcel:writeInt	(I)V
        //   63: goto -34 -> 29
        //   66: astore_1
        //   67: aload_3
        //   68: invokevirtual 52	android/os/Parcel:recycle	()V
        //   71: aload_2
        //   72: invokevirtual 52	android/os/Parcel:recycle	()V
        //   75: aload_1
        //   76: athrow
        // Local variable table:
        //   start	length	slot	name	signature
        //   0	77	0	this	Proxy
        //   0	77	1	paramDataHolder	DataHolder
        //   3	69	2	localParcel1	Parcel
        //   7	61	3	localParcel2	Parcel
        // Exception table:
        //   from	to	target	type
        //   8	14	66	finally
        //   18	29	66	finally
        //   29	49	66	finally
        //   58	63	66	finally
      }
      
      public void zzwr()
        throws RemoteException
      {
        Parcel localParcel1 = Parcel.obtain();
        Parcel localParcel2 = Parcel.obtain();
        try
        {
          localParcel1.writeInterfaceToken("com.google.android.gms.games.internal.IGamesCallbacks");
          this.zzoz.transact(5016, localParcel1, localParcel2, 0);
          localParcel2.readException();
          return;
        }
        finally
        {
          localParcel2.recycle();
          localParcel1.recycle();
        }
      }
      
      /* Error */
      public void zzx(DataHolder paramDataHolder)
        throws RemoteException
      {
        // Byte code:
        //   0: invokestatic 32	android/os/Parcel:obtain	()Landroid/os/Parcel;
        //   3: astore_2
        //   4: invokestatic 32	android/os/Parcel:obtain	()Landroid/os/Parcel;
        //   7: astore_3
        //   8: aload_2
        //   9: ldc 34
        //   11: invokevirtual 37	android/os/Parcel:writeInterfaceToken	(Ljava/lang/String;)V
        //   14: aload_1
        //   15: ifnull +43 -> 58
        //   18: aload_2
        //   19: iconst_1
        //   20: invokevirtual 59	android/os/Parcel:writeInt	(I)V
        //   23: aload_1
        //   24: aload_2
        //   25: iconst_0
        //   26: invokevirtual 76	com/google/android/gms/common/data/DataHolder:writeToParcel	(Landroid/os/Parcel;I)V
        //   29: aload_0
        //   30: getfield 19	com/google/android/gms/games/internal/IGamesCallbacks$Stub$Proxy:zzoz	Landroid/os/IBinder;
        //   33: sipush 8006
        //   36: aload_2
        //   37: aload_3
        //   38: iconst_0
        //   39: invokeinterface 46 5 0
        //   44: pop
        //   45: aload_3
        //   46: invokevirtual 49	android/os/Parcel:readException	()V
        //   49: aload_3
        //   50: invokevirtual 52	android/os/Parcel:recycle	()V
        //   53: aload_2
        //   54: invokevirtual 52	android/os/Parcel:recycle	()V
        //   57: return
        //   58: aload_2
        //   59: iconst_0
        //   60: invokevirtual 59	android/os/Parcel:writeInt	(I)V
        //   63: goto -34 -> 29
        //   66: astore_1
        //   67: aload_3
        //   68: invokevirtual 52	android/os/Parcel:recycle	()V
        //   71: aload_2
        //   72: invokevirtual 52	android/os/Parcel:recycle	()V
        //   75: aload_1
        //   76: athrow
        // Local variable table:
        //   start	length	slot	name	signature
        //   0	77	0	this	Proxy
        //   0	77	1	paramDataHolder	DataHolder
        //   3	69	2	localParcel1	Parcel
        //   7	61	3	localParcel2	Parcel
        // Exception table:
        //   from	to	target	type
        //   8	14	66	finally
        //   18	29	66	finally
        //   29	49	66	finally
        //   58	63	66	finally
      }
      
      /* Error */
      public void zzy(DataHolder paramDataHolder)
        throws RemoteException
      {
        // Byte code:
        //   0: invokestatic 32	android/os/Parcel:obtain	()Landroid/os/Parcel;
        //   3: astore_2
        //   4: invokestatic 32	android/os/Parcel:obtain	()Landroid/os/Parcel;
        //   7: astore_3
        //   8: aload_2
        //   9: ldc 34
        //   11: invokevirtual 37	android/os/Parcel:writeInterfaceToken	(Ljava/lang/String;)V
        //   14: aload_1
        //   15: ifnull +43 -> 58
        //   18: aload_2
        //   19: iconst_1
        //   20: invokevirtual 59	android/os/Parcel:writeInt	(I)V
        //   23: aload_1
        //   24: aload_2
        //   25: iconst_0
        //   26: invokevirtual 76	com/google/android/gms/common/data/DataHolder:writeToParcel	(Landroid/os/Parcel;I)V
        //   29: aload_0
        //   30: getfield 19	com/google/android/gms/games/internal/IGamesCallbacks$Stub$Proxy:zzoz	Landroid/os/IBinder;
        //   33: sipush 8008
        //   36: aload_2
        //   37: aload_3
        //   38: iconst_0
        //   39: invokeinterface 46 5 0
        //   44: pop
        //   45: aload_3
        //   46: invokevirtual 49	android/os/Parcel:readException	()V
        //   49: aload_3
        //   50: invokevirtual 52	android/os/Parcel:recycle	()V
        //   53: aload_2
        //   54: invokevirtual 52	android/os/Parcel:recycle	()V
        //   57: return
        //   58: aload_2
        //   59: iconst_0
        //   60: invokevirtual 59	android/os/Parcel:writeInt	(I)V
        //   63: goto -34 -> 29
        //   66: astore_1
        //   67: aload_3
        //   68: invokevirtual 52	android/os/Parcel:recycle	()V
        //   71: aload_2
        //   72: invokevirtual 52	android/os/Parcel:recycle	()V
        //   75: aload_1
        //   76: athrow
        // Local variable table:
        //   start	length	slot	name	signature
        //   0	77	0	this	Proxy
        //   0	77	1	paramDataHolder	DataHolder
        //   3	69	2	localParcel1	Parcel
        //   7	61	3	localParcel2	Parcel
        // Exception table:
        //   from	to	target	type
        //   8	14	66	finally
        //   18	29	66	finally
        //   29	49	66	finally
        //   58	63	66	finally
      }
      
      /* Error */
      public void zzz(DataHolder paramDataHolder)
        throws RemoteException
      {
        // Byte code:
        //   0: invokestatic 32	android/os/Parcel:obtain	()Landroid/os/Parcel;
        //   3: astore_2
        //   4: invokestatic 32	android/os/Parcel:obtain	()Landroid/os/Parcel;
        //   7: astore_3
        //   8: aload_2
        //   9: ldc 34
        //   11: invokevirtual 37	android/os/Parcel:writeInterfaceToken	(Ljava/lang/String;)V
        //   14: aload_1
        //   15: ifnull +43 -> 58
        //   18: aload_2
        //   19: iconst_1
        //   20: invokevirtual 59	android/os/Parcel:writeInt	(I)V
        //   23: aload_1
        //   24: aload_2
        //   25: iconst_0
        //   26: invokevirtual 76	com/google/android/gms/common/data/DataHolder:writeToParcel	(Landroid/os/Parcel;I)V
        //   29: aload_0
        //   30: getfield 19	com/google/android/gms/games/internal/IGamesCallbacks$Stub$Proxy:zzoz	Landroid/os/IBinder;
        //   33: sipush 5018
        //   36: aload_2
        //   37: aload_3
        //   38: iconst_0
        //   39: invokeinterface 46 5 0
        //   44: pop
        //   45: aload_3
        //   46: invokevirtual 49	android/os/Parcel:readException	()V
        //   49: aload_3
        //   50: invokevirtual 52	android/os/Parcel:recycle	()V
        //   53: aload_2
        //   54: invokevirtual 52	android/os/Parcel:recycle	()V
        //   57: return
        //   58: aload_2
        //   59: iconst_0
        //   60: invokevirtual 59	android/os/Parcel:writeInt	(I)V
        //   63: goto -34 -> 29
        //   66: astore_1
        //   67: aload_3
        //   68: invokevirtual 52	android/os/Parcel:recycle	()V
        //   71: aload_2
        //   72: invokevirtual 52	android/os/Parcel:recycle	()V
        //   75: aload_1
        //   76: athrow
        // Local variable table:
        //   start	length	slot	name	signature
        //   0	77	0	this	Proxy
        //   0	77	1	paramDataHolder	DataHolder
        //   3	69	2	localParcel1	Parcel
        //   7	61	3	localParcel2	Parcel
        // Exception table:
        //   from	to	target	type
        //   8	14	66	finally
        //   18	29	66	finally
        //   29	49	66	finally
        //   58	63	66	finally
      }
    }
  }
}


/* Location:              C:\Users\Genbu Hase\hLg\Genbu\Tool\Programing\Jad\BlockLauncher 1.13.1.jar!\com\google\android\gms\games\internal\IGamesCallbacks.class
 * Java compiler version: 6 (50.0)
 * JD-Core Version:       0.7.1-SNAPSHOT-20140817
 */