package com.google.android.gms.analytics.internal;

import android.content.Context;
import android.text.TextUtils;
import com.google.android.gms.ads.identifier.AdvertisingIdClient;
import com.google.android.gms.ads.identifier.AdvertisingIdClient.Info;
import java.io.FileInputStream;
import java.io.FileNotFoundException;
import java.io.FileOutputStream;
import java.io.IOException;
import java.math.BigInteger;
import java.security.MessageDigest;
import java.util.Locale;

public class zza
  extends zzd
{
  public static boolean zzPV;
  private AdvertisingIdClient.Info zzPW;
  private final zzaj zzPX;
  private String zzPY;
  private boolean zzPZ = false;
  private Object zzQa = new Object();
  
  zza(zzf paramzzf)
  {
    super(paramzzf);
    this.zzPX = new zzaj(paramzzf.zzjl());
  }
  
  private boolean zza(AdvertisingIdClient.Info paramInfo1, AdvertisingIdClient.Info paramInfo2)
  {
    Object localObject1 = null;
    if (paramInfo2 == null) {}
    for (paramInfo2 = null; TextUtils.isEmpty(paramInfo2); paramInfo2 = paramInfo2.getId()) {
      return true;
    }
    String str = zzjr().zzkk();
    boolean bool;
    for (;;)
    {
      synchronized (this.zzQa)
      {
        if (!this.zzPZ)
        {
          this.zzPY = zzjb();
          this.zzPZ = true;
          paramInfo1 = zzbb(paramInfo2 + str);
          if (!TextUtils.isEmpty(paramInfo1)) {
            break;
          }
          return false;
        }
      }
      if (TextUtils.isEmpty(this.zzPY))
      {
        if (paramInfo1 == null) {}
        for (paramInfo1 = (AdvertisingIdClient.Info)localObject1; paramInfo1 == null; paramInfo1 = paramInfo1.getId())
        {
          bool = zzbc(paramInfo2 + str);
          return bool;
        }
        this.zzPY = zzbb(paramInfo1 + str);
      }
    }
    if (paramInfo1.equals(this.zzPY)) {
      return true;
    }
    if (!TextUtils.isEmpty(this.zzPY))
    {
      zzbd("Resetting the client id because Advertising Id changed.");
      paramInfo1 = zzjr().zzkl();
      zza("New client Id", paramInfo1);
    }
    for (;;)
    {
      bool = zzbc(paramInfo2 + paramInfo1);
      return bool;
      paramInfo1 = str;
    }
  }
  
  private static String zzbb(String paramString)
  {
    MessageDigest localMessageDigest = zzam.zzbv("MD5");
    if (localMessageDigest == null) {
      return null;
    }
    return String.format(Locale.US, "%032X", new Object[] { new BigInteger(1, localMessageDigest.digest(paramString.getBytes())) });
  }
  
  private boolean zzbc(String paramString)
  {
    try
    {
      paramString = zzbb(paramString);
      zzbd("Storing hashed adid.");
      FileOutputStream localFileOutputStream = getContext().openFileOutput("gaClientIdData", 0);
      localFileOutputStream.write(paramString.getBytes());
      localFileOutputStream.close();
      this.zzPY = paramString;
      return true;
    }
    catch (IOException paramString)
    {
      zze("Error creating hash file", paramString);
    }
    return false;
  }
  
  /* Error */
  private AdvertisingIdClient.Info zziZ()
  {
    // Byte code:
    //   0: aload_0
    //   1: monitorenter
    //   2: aload_0
    //   3: getfield 41	com/google/android/gms/analytics/internal/zza:zzPX	Lcom/google/android/gms/analytics/internal/zzaj;
    //   6: ldc2_w 176
    //   9: invokevirtual 181	com/google/android/gms/analytics/internal/zzaj:zzv	(J)Z
    //   12: ifeq +32 -> 44
    //   15: aload_0
    //   16: getfield 41	com/google/android/gms/analytics/internal/zza:zzPX	Lcom/google/android/gms/analytics/internal/zzaj;
    //   19: invokevirtual 184	com/google/android/gms/analytics/internal/zzaj:start	()V
    //   22: aload_0
    //   23: invokevirtual 187	com/google/android/gms/analytics/internal/zza:zzja	()Lcom/google/android/gms/ads/identifier/AdvertisingIdClient$Info;
    //   26: astore_1
    //   27: aload_0
    //   28: aload_0
    //   29: getfield 189	com/google/android/gms/analytics/internal/zza:zzPW	Lcom/google/android/gms/ads/identifier/AdvertisingIdClient$Info;
    //   32: aload_1
    //   33: invokespecial 191	com/google/android/gms/analytics/internal/zza:zza	(Lcom/google/android/gms/ads/identifier/AdvertisingIdClient$Info;Lcom/google/android/gms/ads/identifier/AdvertisingIdClient$Info;)Z
    //   36: ifeq +17 -> 53
    //   39: aload_0
    //   40: aload_1
    //   41: putfield 189	com/google/android/gms/analytics/internal/zza:zzPW	Lcom/google/android/gms/ads/identifier/AdvertisingIdClient$Info;
    //   44: aload_0
    //   45: getfield 189	com/google/android/gms/analytics/internal/zza:zzPW	Lcom/google/android/gms/ads/identifier/AdvertisingIdClient$Info;
    //   48: astore_1
    //   49: aload_0
    //   50: monitorexit
    //   51: aload_1
    //   52: areturn
    //   53: aload_0
    //   54: ldc -63
    //   56: invokevirtual 196	com/google/android/gms/analytics/internal/zza:zzbh	(Ljava/lang/String;)V
    //   59: aload_0
    //   60: new 52	com/google/android/gms/ads/identifier/AdvertisingIdClient$Info
    //   63: dup
    //   64: ldc -58
    //   66: iconst_0
    //   67: invokespecial 201	com/google/android/gms/ads/identifier/AdvertisingIdClient$Info:<init>	(Ljava/lang/String;Z)V
    //   70: putfield 189	com/google/android/gms/analytics/internal/zza:zzPW	Lcom/google/android/gms/ads/identifier/AdvertisingIdClient$Info;
    //   73: goto -29 -> 44
    //   76: astore_1
    //   77: aload_0
    //   78: monitorexit
    //   79: aload_1
    //   80: athrow
    // Local variable table:
    //   start	length	slot	name	signature
    //   0	81	0	this	zza
    //   26	26	1	localInfo	AdvertisingIdClient.Info
    //   76	4	1	localObject	Object
    // Exception table:
    //   from	to	target	type
    //   2	44	76	finally
    //   44	49	76	finally
    //   53	73	76	finally
  }
  
  protected void zziJ() {}
  
  public boolean zziU()
  {
    boolean bool2 = false;
    zzjv();
    AdvertisingIdClient.Info localInfo = zziZ();
    boolean bool1 = bool2;
    if (localInfo != null)
    {
      bool1 = bool2;
      if (!localInfo.isLimitAdTrackingEnabled()) {
        bool1 = true;
      }
    }
    return bool1;
  }
  
  public String zziY()
  {
    zzjv();
    Object localObject = zziZ();
    if (localObject != null) {}
    for (localObject = ((AdvertisingIdClient.Info)localObject).getId();; localObject = null)
    {
      if (TextUtils.isEmpty((CharSequence)localObject)) {
        return null;
      }
      return (String)localObject;
    }
  }
  
  protected AdvertisingIdClient.Info zzja()
  {
    Object localObject = null;
    try
    {
      AdvertisingIdClient.Info localInfo = AdvertisingIdClient.getAdvertisingIdInfo(getContext());
      localObject = localInfo;
    }
    catch (IllegalStateException localIllegalStateException)
    {
      zzbg("IllegalStateException getting Ad Id Info. If you would like to see Audience reports, please ensure that you have added '<meta-data android:name=\"com.google.android.gms.version\" android:value=\"@integer/google_play_services_version\" />' to your application manifest file. See http://goo.gl/naFqQk for details.");
      return null;
    }
    catch (Throwable localThrowable)
    {
      while (zzPV) {}
      zzPV = true;
      zzd("Error getting advertiser id", localThrowable);
    }
    return (AdvertisingIdClient.Info)localObject;
    return null;
  }
  
  protected String zzjb()
  {
    Object localObject1 = null;
    try
    {
      FileInputStream localFileInputStream = getContext().openFileInput("gaClientIdData");
      Object localObject2 = new byte['?'];
      int i = localFileInputStream.read((byte[])localObject2, 0, 128);
      if (localFileInputStream.available() > 0)
      {
        zzbg("Hash file seems corrupted, deleting it.");
        localFileInputStream.close();
        getContext().deleteFile("gaClientIdData");
        return null;
      }
      if (i <= 0)
      {
        zzbd("Hash file is empty.");
        localFileInputStream.close();
        return null;
      }
      localObject2 = new String((byte[])localObject2, 0, i);
      IOException localIOException2;
      return null;
    }
    catch (IOException localIOException1)
    {
      try
      {
        localFileInputStream.close();
        return (String)localObject2;
      }
      catch (IOException localIOException3)
      {
        for (;;)
        {
          localObject1 = localIOException1;
          localIOException2 = localIOException3;
        }
      }
      catch (FileNotFoundException localFileNotFoundException1)
      {
        return localIOException2;
      }
      localIOException1 = localIOException1;
      zzd("Error reading Hash file, deleting it", localIOException1);
      getContext().deleteFile("gaClientIdData");
      return (String)localObject1;
    }
    catch (FileNotFoundException localFileNotFoundException2) {}
  }
}


/* Location:              C:\Users\Genbu Hase\ƒhƒLƒ…ƒƒ“ƒg\Genbu\Tool\Programing\Jad\BlockLauncher 1.13.1.jar!\com\google\android\gms\analytics\internal\zza.class
 * Java compiler version: 6 (50.0)
 * JD-Core Version:       0.7.1-SNAPSHOT-20140817
 */