package com.google.android.gms.gcm;

import android.app.PendingIntent;
import android.content.Context;
import android.content.Intent;
import android.content.pm.PackageInfo;
import android.content.pm.PackageManager;
import android.content.pm.PackageManager.NameNotFoundException;
import android.os.Bundle;
import android.os.Handler;
import android.os.Looper;
import android.os.Message;
import android.os.Messenger;
import android.support.annotation.RequiresPermission;
import android.util.Log;
import com.google.android.gms.iid.InstanceID;
import com.google.android.gms.iid.zzc;
import com.google.android.gms.iid.zzd;
import java.io.IOException;
import java.util.Collections;
import java.util.HashMap;
import java.util.Iterator;
import java.util.Map;
import java.util.Set;
import java.util.concurrent.BlockingQueue;
import java.util.concurrent.LinkedBlockingQueue;
import java.util.concurrent.TimeUnit;
import java.util.concurrent.atomic.AtomicInteger;

public class GoogleCloudMessaging
{
  public static final String ERROR_MAIN_THREAD = "MAIN_THREAD";
  public static final String ERROR_SERVICE_NOT_AVAILABLE = "SERVICE_NOT_AVAILABLE";
  public static final String INSTANCE_ID_SCOPE = "GCM";
  @Deprecated
  public static final String MESSAGE_TYPE_DELETED = "deleted_messages";
  @Deprecated
  public static final String MESSAGE_TYPE_MESSAGE = "gcm";
  @Deprecated
  public static final String MESSAGE_TYPE_SEND_ERROR = "send_error";
  @Deprecated
  public static final String MESSAGE_TYPE_SEND_EVENT = "send_event";
  public static int zzaLM = 5000000;
  public static int zzaLN = 6500000;
  public static int zzaLO = 7000000;
  static GoogleCloudMessaging zzaLP;
  private static final AtomicInteger zzaLS = new AtomicInteger(1);
  private Context context;
  private PendingIntent zzaLQ;
  private Map<String, Handler> zzaLR = Collections.synchronizedMap(new HashMap());
  private final BlockingQueue<Intent> zzaLT = new LinkedBlockingQueue();
  final Messenger zzaLU = new Messenger(new Handler(Looper.getMainLooper())
  {
    public void handleMessage(Message paramAnonymousMessage)
    {
      if ((paramAnonymousMessage == null) || (!(paramAnonymousMessage.obj instanceof Intent))) {
        Log.w("GCM", "Dropping invalid message");
      }
      paramAnonymousMessage = (Intent)paramAnonymousMessage.obj;
      if ("com.google.android.c2dm.intent.REGISTRATION".equals(paramAnonymousMessage.getAction())) {
        GoogleCloudMessaging.zza(GoogleCloudMessaging.this).add(paramAnonymousMessage);
      }
      while (GoogleCloudMessaging.zza(GoogleCloudMessaging.this, paramAnonymousMessage)) {
        return;
      }
      paramAnonymousMessage.setPackage(GoogleCloudMessaging.zzb(GoogleCloudMessaging.this).getPackageName());
      GoogleCloudMessaging.zzb(GoogleCloudMessaging.this).sendBroadcast(paramAnonymousMessage);
    }
  });
  
  public static GoogleCloudMessaging getInstance(Context paramContext)
  {
    try
    {
      if (zzaLP == null)
      {
        zzaLP = new GoogleCloudMessaging();
        zzaLP.context = paramContext.getApplicationContext();
      }
      paramContext = zzaLP;
      return paramContext;
    }
    finally {}
  }
  
  static String zza(Intent paramIntent, String paramString)
    throws IOException
  {
    if (paramIntent == null) {
      throw new IOException("SERVICE_NOT_AVAILABLE");
    }
    paramString = paramIntent.getStringExtra(paramString);
    if (paramString != null) {
      return paramString;
    }
    paramIntent = paramIntent.getStringExtra("error");
    if (paramIntent != null) {
      throw new IOException(paramIntent);
    }
    throw new IOException("SERVICE_NOT_AVAILABLE");
  }
  
  private void zza(String paramString1, String paramString2, long paramLong, int paramInt, Bundle paramBundle)
    throws IOException
  {
    if (paramString1 == null) {
      throw new IllegalArgumentException("Missing 'to'");
    }
    Object localObject1 = new Intent("com.google.android.gcm.intent.SEND");
    if (paramBundle != null) {
      ((Intent)localObject1).putExtras(paramBundle);
    }
    zzs((Intent)localObject1);
    ((Intent)localObject1).setPackage(zzaJ(this.context));
    ((Intent)localObject1).putExtra("google.to", paramString1);
    ((Intent)localObject1).putExtra("google.message_id", paramString2);
    ((Intent)localObject1).putExtra("google.ttl", Long.toString(paramLong));
    ((Intent)localObject1).putExtra("google.delay", Integer.toString(paramInt));
    ((Intent)localObject1).putExtra("google.from", zzdZ(paramString1));
    if (zzaJ(this.context).contains(".gsf"))
    {
      localObject1 = new Bundle();
      Iterator localIterator = paramBundle.keySet().iterator();
      while (localIterator.hasNext())
      {
        String str = (String)localIterator.next();
        Object localObject2 = paramBundle.get(str);
        if ((localObject2 instanceof String)) {
          ((Bundle)localObject1).putString("gcm." + str, (String)localObject2);
        }
      }
      ((Bundle)localObject1).putString("google.to", paramString1);
      ((Bundle)localObject1).putString("google.message_id", paramString2);
      InstanceID.getInstance(this.context).zzc("GCM", "upstream", (Bundle)localObject1);
      return;
    }
    this.context.sendOrderedBroadcast((Intent)localObject1, "com.google.android.gtalkservice.permission.GTALK_SERVICE");
  }
  
  public static String zzaJ(Context paramContext)
  {
    return zzc.zzaN(paramContext);
  }
  
  public static int zzaK(Context paramContext)
  {
    PackageManager localPackageManager = paramContext.getPackageManager();
    try
    {
      int i = localPackageManager.getPackageInfo(zzaJ(paramContext), 0).versionCode;
      return i;
    }
    catch (PackageManager.NameNotFoundException paramContext) {}
    return -1;
  }
  
  private String zzdZ(String paramString)
  {
    int i = paramString.indexOf('@');
    String str = paramString;
    if (i > 0) {
      str = paramString.substring(0, i);
    }
    return InstanceID.getInstance(this.context).zzyB().zzi("", str, "GCM");
  }
  
  private boolean zzr(Intent paramIntent)
  {
    Object localObject2 = paramIntent.getStringExtra("In-Reply-To");
    Object localObject1 = localObject2;
    if (localObject2 == null)
    {
      localObject1 = localObject2;
      if (paramIntent.hasExtra("error")) {
        localObject1 = paramIntent.getStringExtra("google.message_id");
      }
    }
    if (localObject1 != null)
    {
      localObject1 = (Handler)this.zzaLR.remove(localObject1);
      if (localObject1 != null)
      {
        localObject2 = Message.obtain();
        ((Message)localObject2).obj = paramIntent;
        return ((Handler)localObject1).sendMessage((Message)localObject2);
      }
    }
    return false;
  }
  
  private String zzyk()
  {
    return "google.rpc" + String.valueOf(zzaLS.getAndIncrement());
  }
  
  public void close()
  {
    zzaLP = null;
    zzb.zzaLC = null;
    zzyl();
  }
  
  public String getMessageType(Intent paramIntent)
  {
    if (!"com.google.android.c2dm.intent.RECEIVE".equals(paramIntent.getAction())) {
      paramIntent = null;
    }
    String str;
    do
    {
      return paramIntent;
      str = paramIntent.getStringExtra("message_type");
      paramIntent = str;
    } while (str != null);
    return "gcm";
  }
  
  /* Error */
  @Deprecated
  @RequiresPermission("com.google.android.c2dm.permission.RECEIVE")
  public String register(String... paramVarArgs)
    throws IOException
  {
    // Byte code:
    //   0: aload_0
    //   1: monitorenter
    //   2: aload_0
    //   3: aload_1
    //   4: invokevirtual 373	com/google/android/gms/gcm/GoogleCloudMessaging:zzc	([Ljava/lang/String;)Ljava/lang/String;
    //   7: astore_1
    //   8: new 196	android/os/Bundle
    //   11: dup
    //   12: invokespecial 197	android/os/Bundle:<init>	()V
    //   15: astore_2
    //   16: aload_0
    //   17: getfield 116	com/google/android/gms/gcm/GoogleCloudMessaging:context	Landroid/content/Context;
    //   20: invokestatic 154	com/google/android/gms/gcm/GoogleCloudMessaging:zzaJ	(Landroid/content/Context;)Ljava/lang/String;
    //   23: ldc -68
    //   25: invokevirtual 194	java/lang/String:contains	(Ljava/lang/CharSequence;)Z
    //   28: ifeq +30 -> 58
    //   31: aload_2
    //   32: ldc_w 375
    //   35: aload_1
    //   36: invokevirtual 237	android/os/Bundle:putString	(Ljava/lang/String;Ljava/lang/String;)V
    //   39: aload_0
    //   40: getfield 116	com/google/android/gms/gcm/GoogleCloudMessaging:context	Landroid/content/Context;
    //   43: invokestatic 242	com/google/android/gms/iid/InstanceID:getInstance	(Landroid/content/Context;)Lcom/google/android/gms/iid/InstanceID;
    //   46: aload_1
    //   47: ldc 16
    //   49: aload_2
    //   50: invokevirtual 378	com/google/android/gms/iid/InstanceID:getToken	(Ljava/lang/String;Ljava/lang/String;Landroid/os/Bundle;)Ljava/lang/String;
    //   53: astore_1
    //   54: aload_0
    //   55: monitorexit
    //   56: aload_1
    //   57: areturn
    //   58: aload_2
    //   59: ldc_w 380
    //   62: aload_1
    //   63: invokevirtual 237	android/os/Bundle:putString	(Ljava/lang/String;Ljava/lang/String;)V
    //   66: aload_0
    //   67: aload_2
    //   68: invokevirtual 383	com/google/android/gms/gcm/GoogleCloudMessaging:zzE	(Landroid/os/Bundle;)Landroid/content/Intent;
    //   71: ldc_w 385
    //   74: invokestatic 387	com/google/android/gms/gcm/GoogleCloudMessaging:zza	(Landroid/content/Intent;Ljava/lang/String;)Ljava/lang/String;
    //   77: astore_1
    //   78: goto -24 -> 54
    //   81: astore_1
    //   82: aload_0
    //   83: monitorexit
    //   84: aload_1
    //   85: athrow
    // Local variable table:
    //   start	length	slot	name	signature
    //   0	86	0	this	GoogleCloudMessaging
    //   0	86	1	paramVarArgs	String[]
    //   15	53	2	localBundle	Bundle
    // Exception table:
    //   from	to	target	type
    //   2	54	81	finally
    //   58	78	81	finally
  }
  
  @RequiresPermission("com.google.android.c2dm.permission.RECEIVE")
  public void send(String paramString1, String paramString2, long paramLong, Bundle paramBundle)
    throws IOException
  {
    zza(paramString1, paramString2, paramLong, -1, paramBundle);
  }
  
  @RequiresPermission("com.google.android.c2dm.permission.RECEIVE")
  public void send(String paramString1, String paramString2, Bundle paramBundle)
    throws IOException
  {
    send(paramString1, paramString2, -1L, paramBundle);
  }
  
  @Deprecated
  @RequiresPermission("com.google.android.c2dm.permission.RECEIVE")
  public void unregister()
    throws IOException
  {
    try
    {
      if (Looper.getMainLooper() == Looper.myLooper()) {
        throw new IOException("MAIN_THREAD");
      }
    }
    finally {}
    InstanceID.getInstance(this.context).deleteInstanceID();
  }
  
  @Deprecated
  Intent zzE(Bundle paramBundle)
    throws IOException
  {
    if (Looper.getMainLooper() == Looper.myLooper()) {
      throw new IOException("MAIN_THREAD");
    }
    if (zzaK(this.context) < 0) {
      throw new IOException("Google Play Services missing");
    }
    Bundle localBundle = paramBundle;
    if (paramBundle == null) {
      localBundle = new Bundle();
    }
    paramBundle = new Intent("com.google.android.c2dm.intent.REGISTER");
    paramBundle.setPackage(zzaJ(this.context));
    zzs(paramBundle);
    paramBundle.putExtra("google.message_id", zzyk());
    paramBundle.putExtras(localBundle);
    paramBundle.putExtra("google.messenger", this.zzaLU);
    this.context.startService(paramBundle);
    try
    {
      paramBundle = (Intent)this.zzaLT.poll(30000L, TimeUnit.MILLISECONDS);
      return paramBundle;
    }
    catch (InterruptedException paramBundle)
    {
      throw new IOException(paramBundle.getMessage());
    }
  }
  
  String zzc(String... paramVarArgs)
  {
    if ((paramVarArgs == null) || (paramVarArgs.length == 0)) {
      throw new IllegalArgumentException("No senderIds");
    }
    StringBuilder localStringBuilder = new StringBuilder(paramVarArgs[0]);
    int i = 1;
    while (i < paramVarArgs.length)
    {
      localStringBuilder.append(',').append(paramVarArgs[i]);
      i += 1;
    }
    return localStringBuilder.toString();
  }
  
  void zzs(Intent paramIntent)
  {
    try
    {
      if (this.zzaLQ == null)
      {
        Intent localIntent = new Intent();
        localIntent.setPackage("com.google.example.invalidpackage");
        this.zzaLQ = PendingIntent.getBroadcast(this.context, 0, localIntent, 0);
      }
      paramIntent.putExtra("app", this.zzaLQ);
      return;
    }
    finally {}
  }
  
  void zzyl()
  {
    try
    {
      if (this.zzaLQ != null)
      {
        this.zzaLQ.cancel();
        this.zzaLQ = null;
      }
      return;
    }
    finally
    {
      localObject = finally;
      throw ((Throwable)localObject);
    }
  }
}


/* Location:              C:\Users\Genbu Hase\ƒhƒLƒ…ƒƒ“ƒg\Genbu\Tool\Programing\Jad\BlockLauncher 1.12.8.jar!\com\google\android\gms\gcm\GoogleCloudMessaging.class
 * Java compiler version: 6 (50.0)
 * JD-Core Version:       0.7.1-SNAPSHOT-20140817
 */