package com.google.android.gms.nearby.sharing.internal;

import android.os.Binder;
import android.os.IBinder;
import android.os.IInterface;
import android.os.Parcel;
import android.os.Parcelable.Creator;
import android.os.RemoteException;

public abstract interface zzd
  extends IInterface
{
  public abstract void zza(ProvideContentRequest paramProvideContentRequest)
    throws RemoteException;
  
  public abstract void zza(ReceiveContentRequest paramReceiveContentRequest)
    throws RemoteException;
  
  public abstract void zza(StopProvidingContentRequest paramStopProvidingContentRequest)
    throws RemoteException;
  
  public abstract void zza(TrustedDevicesRequest paramTrustedDevicesRequest)
    throws RemoteException;
  
  public abstract void zza(zzc paramzzc)
    throws RemoteException;
  
  public static abstract class zza
    extends Binder
    implements zzd
  {
    public static zzd zzdI(IBinder paramIBinder)
    {
      if (paramIBinder == null) {
        return null;
      }
      IInterface localIInterface = paramIBinder.queryLocalInterface("com.google.android.gms.nearby.sharing.internal.INearbySharingService");
      if ((localIInterface != null) && ((localIInterface instanceof zzd))) {
        return (zzd)localIInterface;
      }
      return new zza(paramIBinder);
    }
    
    public boolean onTransact(int paramInt1, Parcel paramParcel1, Parcel paramParcel2, int paramInt2)
      throws RemoteException
    {
      Object localObject2 = null;
      Object localObject3 = null;
      Object localObject4 = null;
      Object localObject1 = null;
      switch (paramInt1)
      {
      default: 
        return super.onTransact(paramInt1, paramParcel1, paramParcel2, paramInt2);
      case 1598968902: 
        paramParcel2.writeString("com.google.android.gms.nearby.sharing.internal.INearbySharingService");
        return true;
      case 1: 
        paramParcel1.enforceInterface("com.google.android.gms.nearby.sharing.internal.INearbySharingService");
        if (paramParcel1.readInt() != 0) {
          localObject1 = (ProvideContentRequest)ProvideContentRequest.CREATOR.createFromParcel(paramParcel1);
        }
        zza((ProvideContentRequest)localObject1);
        paramParcel2.writeNoException();
        return true;
      case 2: 
        paramParcel1.enforceInterface("com.google.android.gms.nearby.sharing.internal.INearbySharingService");
        localObject1 = localObject2;
        if (paramParcel1.readInt() != 0) {
          localObject1 = (StopProvidingContentRequest)StopProvidingContentRequest.CREATOR.createFromParcel(paramParcel1);
        }
        zza((StopProvidingContentRequest)localObject1);
        paramParcel2.writeNoException();
        return true;
      case 3: 
        paramParcel1.enforceInterface("com.google.android.gms.nearby.sharing.internal.INearbySharingService");
        localObject1 = localObject3;
        if (paramParcel1.readInt() != 0) {
          localObject1 = (TrustedDevicesRequest)TrustedDevicesRequest.CREATOR.createFromParcel(paramParcel1);
        }
        zza((TrustedDevicesRequest)localObject1);
        paramParcel2.writeNoException();
        return true;
      case 4: 
        paramParcel1.enforceInterface("com.google.android.gms.nearby.sharing.internal.INearbySharingService");
        localObject1 = localObject4;
        if (paramParcel1.readInt() != 0) {
          localObject1 = (ReceiveContentRequest)ReceiveContentRequest.CREATOR.createFromParcel(paramParcel1);
        }
        zza((ReceiveContentRequest)localObject1);
        paramParcel2.writeNoException();
        return true;
      }
      paramParcel1.enforceInterface("com.google.android.gms.nearby.sharing.internal.INearbySharingService");
      zza(zzc.zza.zzdH(paramParcel1.readStrongBinder()));
      paramParcel2.writeNoException();
      return true;
    }
    
    private static class zza
      implements zzd
    {
      private IBinder zzoz;
      
      zza(IBinder paramIBinder)
      {
        this.zzoz = paramIBinder;
      }
      
      public IBinder asBinder()
      {
        return this.zzoz;
      }
      
      /* Error */
      public void zza(ProvideContentRequest paramProvideContentRequest)
        throws RemoteException
      {
        // Byte code:
        //   0: invokestatic 30	android/os/Parcel:obtain	()Landroid/os/Parcel;
        //   3: astore_2
        //   4: invokestatic 30	android/os/Parcel:obtain	()Landroid/os/Parcel;
        //   7: astore_3
        //   8: aload_2
        //   9: ldc 32
        //   11: invokevirtual 36	android/os/Parcel:writeInterfaceToken	(Ljava/lang/String;)V
        //   14: aload_1
        //   15: ifnull +41 -> 56
        //   18: aload_2
        //   19: iconst_1
        //   20: invokevirtual 40	android/os/Parcel:writeInt	(I)V
        //   23: aload_1
        //   24: aload_2
        //   25: iconst_0
        //   26: invokevirtual 46	com/google/android/gms/nearby/sharing/internal/ProvideContentRequest:writeToParcel	(Landroid/os/Parcel;I)V
        //   29: aload_0
        //   30: getfield 18	com/google/android/gms/nearby/sharing/internal/zzd$zza$zza:zzoz	Landroid/os/IBinder;
        //   33: iconst_1
        //   34: aload_2
        //   35: aload_3
        //   36: iconst_0
        //   37: invokeinterface 52 5 0
        //   42: pop
        //   43: aload_3
        //   44: invokevirtual 55	android/os/Parcel:readException	()V
        //   47: aload_3
        //   48: invokevirtual 58	android/os/Parcel:recycle	()V
        //   51: aload_2
        //   52: invokevirtual 58	android/os/Parcel:recycle	()V
        //   55: return
        //   56: aload_2
        //   57: iconst_0
        //   58: invokevirtual 40	android/os/Parcel:writeInt	(I)V
        //   61: goto -32 -> 29
        //   64: astore_1
        //   65: aload_3
        //   66: invokevirtual 58	android/os/Parcel:recycle	()V
        //   69: aload_2
        //   70: invokevirtual 58	android/os/Parcel:recycle	()V
        //   73: aload_1
        //   74: athrow
        // Local variable table:
        //   start	length	slot	name	signature
        //   0	75	0	this	zza
        //   0	75	1	paramProvideContentRequest	ProvideContentRequest
        //   3	67	2	localParcel1	Parcel
        //   7	59	3	localParcel2	Parcel
        // Exception table:
        //   from	to	target	type
        //   8	14	64	finally
        //   18	29	64	finally
        //   29	47	64	finally
        //   56	61	64	finally
      }
      
      /* Error */
      public void zza(ReceiveContentRequest paramReceiveContentRequest)
        throws RemoteException
      {
        // Byte code:
        //   0: invokestatic 30	android/os/Parcel:obtain	()Landroid/os/Parcel;
        //   3: astore_2
        //   4: invokestatic 30	android/os/Parcel:obtain	()Landroid/os/Parcel;
        //   7: astore_3
        //   8: aload_2
        //   9: ldc 32
        //   11: invokevirtual 36	android/os/Parcel:writeInterfaceToken	(Ljava/lang/String;)V
        //   14: aload_1
        //   15: ifnull +41 -> 56
        //   18: aload_2
        //   19: iconst_1
        //   20: invokevirtual 40	android/os/Parcel:writeInt	(I)V
        //   23: aload_1
        //   24: aload_2
        //   25: iconst_0
        //   26: invokevirtual 63	com/google/android/gms/nearby/sharing/internal/ReceiveContentRequest:writeToParcel	(Landroid/os/Parcel;I)V
        //   29: aload_0
        //   30: getfield 18	com/google/android/gms/nearby/sharing/internal/zzd$zza$zza:zzoz	Landroid/os/IBinder;
        //   33: iconst_4
        //   34: aload_2
        //   35: aload_3
        //   36: iconst_0
        //   37: invokeinterface 52 5 0
        //   42: pop
        //   43: aload_3
        //   44: invokevirtual 55	android/os/Parcel:readException	()V
        //   47: aload_3
        //   48: invokevirtual 58	android/os/Parcel:recycle	()V
        //   51: aload_2
        //   52: invokevirtual 58	android/os/Parcel:recycle	()V
        //   55: return
        //   56: aload_2
        //   57: iconst_0
        //   58: invokevirtual 40	android/os/Parcel:writeInt	(I)V
        //   61: goto -32 -> 29
        //   64: astore_1
        //   65: aload_3
        //   66: invokevirtual 58	android/os/Parcel:recycle	()V
        //   69: aload_2
        //   70: invokevirtual 58	android/os/Parcel:recycle	()V
        //   73: aload_1
        //   74: athrow
        // Local variable table:
        //   start	length	slot	name	signature
        //   0	75	0	this	zza
        //   0	75	1	paramReceiveContentRequest	ReceiveContentRequest
        //   3	67	2	localParcel1	Parcel
        //   7	59	3	localParcel2	Parcel
        // Exception table:
        //   from	to	target	type
        //   8	14	64	finally
        //   18	29	64	finally
        //   29	47	64	finally
        //   56	61	64	finally
      }
      
      /* Error */
      public void zza(StopProvidingContentRequest paramStopProvidingContentRequest)
        throws RemoteException
      {
        // Byte code:
        //   0: invokestatic 30	android/os/Parcel:obtain	()Landroid/os/Parcel;
        //   3: astore_2
        //   4: invokestatic 30	android/os/Parcel:obtain	()Landroid/os/Parcel;
        //   7: astore_3
        //   8: aload_2
        //   9: ldc 32
        //   11: invokevirtual 36	android/os/Parcel:writeInterfaceToken	(Ljava/lang/String;)V
        //   14: aload_1
        //   15: ifnull +41 -> 56
        //   18: aload_2
        //   19: iconst_1
        //   20: invokevirtual 40	android/os/Parcel:writeInt	(I)V
        //   23: aload_1
        //   24: aload_2
        //   25: iconst_0
        //   26: invokevirtual 67	com/google/android/gms/nearby/sharing/internal/StopProvidingContentRequest:writeToParcel	(Landroid/os/Parcel;I)V
        //   29: aload_0
        //   30: getfield 18	com/google/android/gms/nearby/sharing/internal/zzd$zza$zza:zzoz	Landroid/os/IBinder;
        //   33: iconst_2
        //   34: aload_2
        //   35: aload_3
        //   36: iconst_0
        //   37: invokeinterface 52 5 0
        //   42: pop
        //   43: aload_3
        //   44: invokevirtual 55	android/os/Parcel:readException	()V
        //   47: aload_3
        //   48: invokevirtual 58	android/os/Parcel:recycle	()V
        //   51: aload_2
        //   52: invokevirtual 58	android/os/Parcel:recycle	()V
        //   55: return
        //   56: aload_2
        //   57: iconst_0
        //   58: invokevirtual 40	android/os/Parcel:writeInt	(I)V
        //   61: goto -32 -> 29
        //   64: astore_1
        //   65: aload_3
        //   66: invokevirtual 58	android/os/Parcel:recycle	()V
        //   69: aload_2
        //   70: invokevirtual 58	android/os/Parcel:recycle	()V
        //   73: aload_1
        //   74: athrow
        // Local variable table:
        //   start	length	slot	name	signature
        //   0	75	0	this	zza
        //   0	75	1	paramStopProvidingContentRequest	StopProvidingContentRequest
        //   3	67	2	localParcel1	Parcel
        //   7	59	3	localParcel2	Parcel
        // Exception table:
        //   from	to	target	type
        //   8	14	64	finally
        //   18	29	64	finally
        //   29	47	64	finally
        //   56	61	64	finally
      }
      
      /* Error */
      public void zza(TrustedDevicesRequest paramTrustedDevicesRequest)
        throws RemoteException
      {
        // Byte code:
        //   0: invokestatic 30	android/os/Parcel:obtain	()Landroid/os/Parcel;
        //   3: astore_2
        //   4: invokestatic 30	android/os/Parcel:obtain	()Landroid/os/Parcel;
        //   7: astore_3
        //   8: aload_2
        //   9: ldc 32
        //   11: invokevirtual 36	android/os/Parcel:writeInterfaceToken	(Ljava/lang/String;)V
        //   14: aload_1
        //   15: ifnull +41 -> 56
        //   18: aload_2
        //   19: iconst_1
        //   20: invokevirtual 40	android/os/Parcel:writeInt	(I)V
        //   23: aload_1
        //   24: aload_2
        //   25: iconst_0
        //   26: invokevirtual 71	com/google/android/gms/nearby/sharing/internal/TrustedDevicesRequest:writeToParcel	(Landroid/os/Parcel;I)V
        //   29: aload_0
        //   30: getfield 18	com/google/android/gms/nearby/sharing/internal/zzd$zza$zza:zzoz	Landroid/os/IBinder;
        //   33: iconst_3
        //   34: aload_2
        //   35: aload_3
        //   36: iconst_0
        //   37: invokeinterface 52 5 0
        //   42: pop
        //   43: aload_3
        //   44: invokevirtual 55	android/os/Parcel:readException	()V
        //   47: aload_3
        //   48: invokevirtual 58	android/os/Parcel:recycle	()V
        //   51: aload_2
        //   52: invokevirtual 58	android/os/Parcel:recycle	()V
        //   55: return
        //   56: aload_2
        //   57: iconst_0
        //   58: invokevirtual 40	android/os/Parcel:writeInt	(I)V
        //   61: goto -32 -> 29
        //   64: astore_1
        //   65: aload_3
        //   66: invokevirtual 58	android/os/Parcel:recycle	()V
        //   69: aload_2
        //   70: invokevirtual 58	android/os/Parcel:recycle	()V
        //   73: aload_1
        //   74: athrow
        // Local variable table:
        //   start	length	slot	name	signature
        //   0	75	0	this	zza
        //   0	75	1	paramTrustedDevicesRequest	TrustedDevicesRequest
        //   3	67	2	localParcel1	Parcel
        //   7	59	3	localParcel2	Parcel
        // Exception table:
        //   from	to	target	type
        //   8	14	64	finally
        //   18	29	64	finally
        //   29	47	64	finally
        //   56	61	64	finally
      }
      
      /* Error */
      public void zza(zzc paramzzc)
        throws RemoteException
      {
        // Byte code:
        //   0: invokestatic 30	android/os/Parcel:obtain	()Landroid/os/Parcel;
        //   3: astore_2
        //   4: invokestatic 30	android/os/Parcel:obtain	()Landroid/os/Parcel;
        //   7: astore_3
        //   8: aload_2
        //   9: ldc 32
        //   11: invokevirtual 36	android/os/Parcel:writeInterfaceToken	(Ljava/lang/String;)V
        //   14: aload_1
        //   15: ifnull +42 -> 57
        //   18: aload_1
        //   19: invokeinterface 76 1 0
        //   24: astore_1
        //   25: aload_2
        //   26: aload_1
        //   27: invokevirtual 79	android/os/Parcel:writeStrongBinder	(Landroid/os/IBinder;)V
        //   30: aload_0
        //   31: getfield 18	com/google/android/gms/nearby/sharing/internal/zzd$zza$zza:zzoz	Landroid/os/IBinder;
        //   34: iconst_5
        //   35: aload_2
        //   36: aload_3
        //   37: iconst_0
        //   38: invokeinterface 52 5 0
        //   43: pop
        //   44: aload_3
        //   45: invokevirtual 55	android/os/Parcel:readException	()V
        //   48: aload_3
        //   49: invokevirtual 58	android/os/Parcel:recycle	()V
        //   52: aload_2
        //   53: invokevirtual 58	android/os/Parcel:recycle	()V
        //   56: return
        //   57: aconst_null
        //   58: astore_1
        //   59: goto -34 -> 25
        //   62: astore_1
        //   63: aload_3
        //   64: invokevirtual 58	android/os/Parcel:recycle	()V
        //   67: aload_2
        //   68: invokevirtual 58	android/os/Parcel:recycle	()V
        //   71: aload_1
        //   72: athrow
        // Local variable table:
        //   start	length	slot	name	signature
        //   0	73	0	this	zza
        //   0	73	1	paramzzc	zzc
        //   3	65	2	localParcel1	Parcel
        //   7	57	3	localParcel2	Parcel
        // Exception table:
        //   from	to	target	type
        //   8	14	62	finally
        //   18	25	62	finally
        //   25	48	62	finally
      }
    }
  }
}


/* Location:              C:\Users\Genbu Hase\ÉhÉLÉÖÉÅÉìÉg\Genbu\Tool\Programing\Jad\BlockLauncher 1.12.8.jar!\com\google\android\gms\nearby\sharing\internal\zzd.class
 * Java compiler version: 6 (50.0)
 * JD-Core Version:       0.7.1-SNAPSHOT-20140817
 */